package com.google.android.gms.maps.internal;

import android.os.IBinder;
import android.os.Parcel;
import com.google.android.gms.maps.model.GroundOverlayOptions;
import com.google.android.gms.maps.model.MarkerOptions;
import com.google.android.gms.maps.model.internal.c;
import com.google.android.gms.maps.model.internal.e;
import com.google.android.gms.maps.model.internal.i;
import com.google.android.gms.maps.model.internal.i.a;
import com.google.android.gms.maps.model.internal.j;
import com.google.android.gms.maps.model.internal.j.a;
import com.google.android.gms.maps.model.internal.l;
import com.google.android.gms.maps.model.internal.l.a;
import com.google.android.gms.maps.model.internal.p;

class IGoogleMapDelegate$a$a
  implements IGoogleMapDelegate
{
  private IBinder le;
  
  IGoogleMapDelegate$a$a(IBinder paramIBinder)
  {
    le = paramIBinder;
  }
  
  /* Error */
  public com.google.android.gms.maps.model.internal.h addCircle(com.google.android.gms.maps.model.CircleOptions paramCircleOptions)
  {
    // Byte code:
    //   0: invokestatic 24	android/os/Parcel:obtain	()Landroid/os/Parcel;
    //   3: astore_2
    //   4: invokestatic 24	android/os/Parcel:obtain	()Landroid/os/Parcel;
    //   7: astore_3
    //   8: aload_2
    //   9: ldc 26
    //   11: invokevirtual 30	android/os/Parcel:writeInterfaceToken	(Ljava/lang/String;)V
    //   14: aload_1
    //   15: ifnull +51 -> 66
    //   18: aload_2
    //   19: iconst_1
    //   20: invokevirtual 34	android/os/Parcel:writeInt	(I)V
    //   23: aload_1
    //   24: aload_2
    //   25: iconst_0
    //   26: invokevirtual 40	com/google/android/gms/maps/model/CircleOptions:writeToParcel	(Landroid/os/Parcel;I)V
    //   29: aload_0
    //   30: getfield 15	com/google/android/gms/maps/internal/IGoogleMapDelegate$a$a:le	Landroid/os/IBinder;
    //   33: bipush 35
    //   35: aload_2
    //   36: aload_3
    //   37: iconst_0
    //   38: invokeinterface 46 5 0
    //   43: pop
    //   44: aload_3
    //   45: invokevirtual 49	android/os/Parcel:readException	()V
    //   48: aload_3
    //   49: invokevirtual 53	android/os/Parcel:readStrongBinder	()Landroid/os/IBinder;
    //   52: invokestatic 59	com/google/android/gms/maps/model/internal/h$a:bw	(Landroid/os/IBinder;)Lcom/google/android/gms/maps/model/internal/h;
    //   55: astore_1
    //   56: aload_3
    //   57: invokevirtual 62	android/os/Parcel:recycle	()V
    //   60: aload_2
    //   61: invokevirtual 62	android/os/Parcel:recycle	()V
    //   64: aload_1
    //   65: areturn
    //   66: aload_2
    //   67: iconst_0
    //   68: invokevirtual 34	android/os/Parcel:writeInt	(I)V
    //   71: goto -42 -> 29
    //   74: astore_1
    //   75: aload_3
    //   76: invokevirtual 62	android/os/Parcel:recycle	()V
    //   79: aload_2
    //   80: invokevirtual 62	android/os/Parcel:recycle	()V
    //   83: aload_1
    //   84: athrow
    // Local variable table:
    //   start	length	slot	name	signature
    //   0	85	0	this	a
    //   0	85	1	paramCircleOptions	com.google.android.gms.maps.model.CircleOptions
    //   3	77	2	localParcel1	Parcel
    //   7	69	3	localParcel2	Parcel
    // Exception table:
    //   from	to	target	type
    //   8	14	74	finally
    //   18	29	74	finally
    //   29	56	74	finally
    //   66	71	74	finally
  }
  
  /* Error */
  public i addGroundOverlay(GroundOverlayOptions paramGroundOverlayOptions)
  {
    // Byte code:
    //   0: invokestatic 24	android/os/Parcel:obtain	()Landroid/os/Parcel;
    //   3: astore_2
    //   4: invokestatic 24	android/os/Parcel:obtain	()Landroid/os/Parcel;
    //   7: astore_3
    //   8: aload_2
    //   9: ldc 26
    //   11: invokevirtual 30	android/os/Parcel:writeInterfaceToken	(Ljava/lang/String;)V
    //   14: aload_1
    //   15: ifnull +51 -> 66
    //   18: aload_2
    //   19: iconst_1
    //   20: invokevirtual 34	android/os/Parcel:writeInt	(I)V
    //   23: aload_1
    //   24: aload_2
    //   25: iconst_0
    //   26: invokevirtual 67	com/google/android/gms/maps/model/GroundOverlayOptions:writeToParcel	(Landroid/os/Parcel;I)V
    //   29: aload_0
    //   30: getfield 15	com/google/android/gms/maps/internal/IGoogleMapDelegate$a$a:le	Landroid/os/IBinder;
    //   33: bipush 12
    //   35: aload_2
    //   36: aload_3
    //   37: iconst_0
    //   38: invokeinterface 46 5 0
    //   43: pop
    //   44: aload_3
    //   45: invokevirtual 49	android/os/Parcel:readException	()V
    //   48: aload_3
    //   49: invokevirtual 53	android/os/Parcel:readStrongBinder	()Landroid/os/IBinder;
    //   52: invokestatic 73	com/google/android/gms/maps/model/internal/i$a:bx	(Landroid/os/IBinder;)Lcom/google/android/gms/maps/model/internal/i;
    //   55: astore_1
    //   56: aload_3
    //   57: invokevirtual 62	android/os/Parcel:recycle	()V
    //   60: aload_2
    //   61: invokevirtual 62	android/os/Parcel:recycle	()V
    //   64: aload_1
    //   65: areturn
    //   66: aload_2
    //   67: iconst_0
    //   68: invokevirtual 34	android/os/Parcel:writeInt	(I)V
    //   71: goto -42 -> 29
    //   74: astore_1
    //   75: aload_3
    //   76: invokevirtual 62	android/os/Parcel:recycle	()V
    //   79: aload_2
    //   80: invokevirtual 62	android/os/Parcel:recycle	()V
    //   83: aload_1
    //   84: athrow
    // Local variable table:
    //   start	length	slot	name	signature
    //   0	85	0	this	a
    //   0	85	1	paramGroundOverlayOptions	GroundOverlayOptions
    //   3	77	2	localParcel1	Parcel
    //   7	69	3	localParcel2	Parcel
    // Exception table:
    //   from	to	target	type
    //   8	14	74	finally
    //   18	29	74	finally
    //   29	56	74	finally
    //   66	71	74	finally
  }
  
  public i addGroundOverlay2(GroundOverlayOptions paramGroundOverlayOptions, e parame)
  {
    Parcel localParcel1 = Parcel.obtain();
    Parcel localParcel2 = Parcel.obtain();
    for (;;)
    {
      try
      {
        localParcel1.writeInterfaceToken("com.google.android.gms.maps.internal.IGoogleMapDelegate");
        if (paramGroundOverlayOptions != null)
        {
          localParcel1.writeInt(1);
          paramGroundOverlayOptions.writeToParcel(localParcel1, 0);
          if (parame != null)
          {
            localParcel1.writeInt(1);
            parame.writeToParcel(localParcel1, 0);
            le.transact(70, localParcel1, localParcel2, 0);
            localParcel2.readException();
            paramGroundOverlayOptions = i.a.bx(localParcel2.readStrongBinder());
            return paramGroundOverlayOptions;
          }
        }
        else
        {
          localParcel1.writeInt(0);
          continue;
        }
        localParcel1.writeInt(0);
      }
      finally
      {
        localParcel2.recycle();
        localParcel1.recycle();
      }
    }
  }
  
  /* Error */
  public l addMarker(MarkerOptions paramMarkerOptions)
  {
    // Byte code:
    //   0: invokestatic 24	android/os/Parcel:obtain	()Landroid/os/Parcel;
    //   3: astore_2
    //   4: invokestatic 24	android/os/Parcel:obtain	()Landroid/os/Parcel;
    //   7: astore_3
    //   8: aload_2
    //   9: ldc 26
    //   11: invokevirtual 30	android/os/Parcel:writeInterfaceToken	(Ljava/lang/String;)V
    //   14: aload_1
    //   15: ifnull +51 -> 66
    //   18: aload_2
    //   19: iconst_1
    //   20: invokevirtual 34	android/os/Parcel:writeInt	(I)V
    //   23: aload_1
    //   24: aload_2
    //   25: iconst_0
    //   26: invokevirtual 83	com/google/android/gms/maps/model/MarkerOptions:writeToParcel	(Landroid/os/Parcel;I)V
    //   29: aload_0
    //   30: getfield 15	com/google/android/gms/maps/internal/IGoogleMapDelegate$a$a:le	Landroid/os/IBinder;
    //   33: bipush 11
    //   35: aload_2
    //   36: aload_3
    //   37: iconst_0
    //   38: invokeinterface 46 5 0
    //   43: pop
    //   44: aload_3
    //   45: invokevirtual 49	android/os/Parcel:readException	()V
    //   48: aload_3
    //   49: invokevirtual 53	android/os/Parcel:readStrongBinder	()Landroid/os/IBinder;
    //   52: invokestatic 89	com/google/android/gms/maps/model/internal/l$a:bA	(Landroid/os/IBinder;)Lcom/google/android/gms/maps/model/internal/l;
    //   55: astore_1
    //   56: aload_3
    //   57: invokevirtual 62	android/os/Parcel:recycle	()V
    //   60: aload_2
    //   61: invokevirtual 62	android/os/Parcel:recycle	()V
    //   64: aload_1
    //   65: areturn
    //   66: aload_2
    //   67: iconst_0
    //   68: invokevirtual 34	android/os/Parcel:writeInt	(I)V
    //   71: goto -42 -> 29
    //   74: astore_1
    //   75: aload_3
    //   76: invokevirtual 62	android/os/Parcel:recycle	()V
    //   79: aload_2
    //   80: invokevirtual 62	android/os/Parcel:recycle	()V
    //   83: aload_1
    //   84: athrow
    // Local variable table:
    //   start	length	slot	name	signature
    //   0	85	0	this	a
    //   0	85	1	paramMarkerOptions	MarkerOptions
    //   3	77	2	localParcel1	Parcel
    //   7	69	3	localParcel2	Parcel
    // Exception table:
    //   from	to	target	type
    //   8	14	74	finally
    //   18	29	74	finally
    //   29	56	74	finally
    //   66	71	74	finally
  }
  
  public l addMarker2(MarkerOptions paramMarkerOptions, p paramp)
  {
    Parcel localParcel1 = Parcel.obtain();
    Parcel localParcel2 = Parcel.obtain();
    for (;;)
    {
      try
      {
        localParcel1.writeInterfaceToken("com.google.android.gms.maps.internal.IGoogleMapDelegate");
        if (paramMarkerOptions != null)
        {
          localParcel1.writeInt(1);
          paramMarkerOptions.writeToParcel(localParcel1, 0);
          if (paramp != null)
          {
            localParcel1.writeInt(1);
            paramp.writeToParcel(localParcel1, 0);
            le.transact(68, localParcel1, localParcel2, 0);
            localParcel2.readException();
            paramMarkerOptions = l.a.bA(localParcel2.readStrongBinder());
            return paramMarkerOptions;
          }
        }
        else
        {
          localParcel1.writeInt(0);
          continue;
        }
        localParcel1.writeInt(0);
      }
      finally
      {
        localParcel2.recycle();
        localParcel1.recycle();
      }
    }
  }
  
  /* Error */
  public com.google.android.gms.maps.model.internal.m addPolygon(com.google.android.gms.maps.model.PolygonOptions paramPolygonOptions)
  {
    // Byte code:
    //   0: invokestatic 24	android/os/Parcel:obtain	()Landroid/os/Parcel;
    //   3: astore_2
    //   4: invokestatic 24	android/os/Parcel:obtain	()Landroid/os/Parcel;
    //   7: astore_3
    //   8: aload_2
    //   9: ldc 26
    //   11: invokevirtual 30	android/os/Parcel:writeInterfaceToken	(Ljava/lang/String;)V
    //   14: aload_1
    //   15: ifnull +51 -> 66
    //   18: aload_2
    //   19: iconst_1
    //   20: invokevirtual 34	android/os/Parcel:writeInt	(I)V
    //   23: aload_1
    //   24: aload_2
    //   25: iconst_0
    //   26: invokevirtual 99	com/google/android/gms/maps/model/PolygonOptions:writeToParcel	(Landroid/os/Parcel;I)V
    //   29: aload_0
    //   30: getfield 15	com/google/android/gms/maps/internal/IGoogleMapDelegate$a$a:le	Landroid/os/IBinder;
    //   33: bipush 10
    //   35: aload_2
    //   36: aload_3
    //   37: iconst_0
    //   38: invokeinterface 46 5 0
    //   43: pop
    //   44: aload_3
    //   45: invokevirtual 49	android/os/Parcel:readException	()V
    //   48: aload_3
    //   49: invokevirtual 53	android/os/Parcel:readStrongBinder	()Landroid/os/IBinder;
    //   52: invokestatic 105	com/google/android/gms/maps/model/internal/m$a:bB	(Landroid/os/IBinder;)Lcom/google/android/gms/maps/model/internal/m;
    //   55: astore_1
    //   56: aload_3
    //   57: invokevirtual 62	android/os/Parcel:recycle	()V
    //   60: aload_2
    //   61: invokevirtual 62	android/os/Parcel:recycle	()V
    //   64: aload_1
    //   65: areturn
    //   66: aload_2
    //   67: iconst_0
    //   68: invokevirtual 34	android/os/Parcel:writeInt	(I)V
    //   71: goto -42 -> 29
    //   74: astore_1
    //   75: aload_3
    //   76: invokevirtual 62	android/os/Parcel:recycle	()V
    //   79: aload_2
    //   80: invokevirtual 62	android/os/Parcel:recycle	()V
    //   83: aload_1
    //   84: athrow
    // Local variable table:
    //   start	length	slot	name	signature
    //   0	85	0	this	a
    //   0	85	1	paramPolygonOptions	com.google.android.gms.maps.model.PolygonOptions
    //   3	77	2	localParcel1	Parcel
    //   7	69	3	localParcel2	Parcel
    // Exception table:
    //   from	to	target	type
    //   8	14	74	finally
    //   18	29	74	finally
    //   29	56	74	finally
    //   66	71	74	finally
  }
  
  /* Error */
  public com.google.android.gms.maps.model.internal.IPolylineDelegate addPolyline(com.google.android.gms.maps.model.PolylineOptions paramPolylineOptions)
  {
    // Byte code:
    //   0: invokestatic 24	android/os/Parcel:obtain	()Landroid/os/Parcel;
    //   3: astore_2
    //   4: invokestatic 24	android/os/Parcel:obtain	()Landroid/os/Parcel;
    //   7: astore_3
    //   8: aload_2
    //   9: ldc 26
    //   11: invokevirtual 30	android/os/Parcel:writeInterfaceToken	(Ljava/lang/String;)V
    //   14: aload_1
    //   15: ifnull +51 -> 66
    //   18: aload_2
    //   19: iconst_1
    //   20: invokevirtual 34	android/os/Parcel:writeInt	(I)V
    //   23: aload_1
    //   24: aload_2
    //   25: iconst_0
    //   26: invokevirtual 110	com/google/android/gms/maps/model/PolylineOptions:writeToParcel	(Landroid/os/Parcel;I)V
    //   29: aload_0
    //   30: getfield 15	com/google/android/gms/maps/internal/IGoogleMapDelegate$a$a:le	Landroid/os/IBinder;
    //   33: bipush 9
    //   35: aload_2
    //   36: aload_3
    //   37: iconst_0
    //   38: invokeinterface 46 5 0
    //   43: pop
    //   44: aload_3
    //   45: invokevirtual 49	android/os/Parcel:readException	()V
    //   48: aload_3
    //   49: invokevirtual 53	android/os/Parcel:readStrongBinder	()Landroid/os/IBinder;
    //   52: invokestatic 116	com/google/android/gms/maps/model/internal/IPolylineDelegate$a:bC	(Landroid/os/IBinder;)Lcom/google/android/gms/maps/model/internal/IPolylineDelegate;
    //   55: astore_1
    //   56: aload_3
    //   57: invokevirtual 62	android/os/Parcel:recycle	()V
    //   60: aload_2
    //   61: invokevirtual 62	android/os/Parcel:recycle	()V
    //   64: aload_1
    //   65: areturn
    //   66: aload_2
    //   67: iconst_0
    //   68: invokevirtual 34	android/os/Parcel:writeInt	(I)V
    //   71: goto -42 -> 29
    //   74: astore_1
    //   75: aload_3
    //   76: invokevirtual 62	android/os/Parcel:recycle	()V
    //   79: aload_2
    //   80: invokevirtual 62	android/os/Parcel:recycle	()V
    //   83: aload_1
    //   84: athrow
    // Local variable table:
    //   start	length	slot	name	signature
    //   0	85	0	this	a
    //   0	85	1	paramPolylineOptions	com.google.android.gms.maps.model.PolylineOptions
    //   3	77	2	localParcel1	Parcel
    //   7	69	3	localParcel2	Parcel
    // Exception table:
    //   from	to	target	type
    //   8	14	74	finally
    //   18	29	74	finally
    //   29	56	74	finally
    //   66	71	74	finally
  }
  
  /* Error */
  public com.google.android.gms.maps.model.internal.n addTileOverlay(com.google.android.gms.maps.model.TileOverlayOptions paramTileOverlayOptions)
  {
    // Byte code:
    //   0: invokestatic 24	android/os/Parcel:obtain	()Landroid/os/Parcel;
    //   3: astore_2
    //   4: invokestatic 24	android/os/Parcel:obtain	()Landroid/os/Parcel;
    //   7: astore_3
    //   8: aload_2
    //   9: ldc 26
    //   11: invokevirtual 30	android/os/Parcel:writeInterfaceToken	(Ljava/lang/String;)V
    //   14: aload_1
    //   15: ifnull +51 -> 66
    //   18: aload_2
    //   19: iconst_1
    //   20: invokevirtual 34	android/os/Parcel:writeInt	(I)V
    //   23: aload_1
    //   24: aload_2
    //   25: iconst_0
    //   26: invokevirtual 121	com/google/android/gms/maps/model/TileOverlayOptions:writeToParcel	(Landroid/os/Parcel;I)V
    //   29: aload_0
    //   30: getfield 15	com/google/android/gms/maps/internal/IGoogleMapDelegate$a$a:le	Landroid/os/IBinder;
    //   33: bipush 13
    //   35: aload_2
    //   36: aload_3
    //   37: iconst_0
    //   38: invokeinterface 46 5 0
    //   43: pop
    //   44: aload_3
    //   45: invokevirtual 49	android/os/Parcel:readException	()V
    //   48: aload_3
    //   49: invokevirtual 53	android/os/Parcel:readStrongBinder	()Landroid/os/IBinder;
    //   52: invokestatic 127	com/google/android/gms/maps/model/internal/n$a:bD	(Landroid/os/IBinder;)Lcom/google/android/gms/maps/model/internal/n;
    //   55: astore_1
    //   56: aload_3
    //   57: invokevirtual 62	android/os/Parcel:recycle	()V
    //   60: aload_2
    //   61: invokevirtual 62	android/os/Parcel:recycle	()V
    //   64: aload_1
    //   65: areturn
    //   66: aload_2
    //   67: iconst_0
    //   68: invokevirtual 34	android/os/Parcel:writeInt	(I)V
    //   71: goto -42 -> 29
    //   74: astore_1
    //   75: aload_3
    //   76: invokevirtual 62	android/os/Parcel:recycle	()V
    //   79: aload_2
    //   80: invokevirtual 62	android/os/Parcel:recycle	()V
    //   83: aload_1
    //   84: athrow
    // Local variable table:
    //   start	length	slot	name	signature
    //   0	85	0	this	a
    //   0	85	1	paramTileOverlayOptions	com.google.android.gms.maps.model.TileOverlayOptions
    //   3	77	2	localParcel1	Parcel
    //   7	69	3	localParcel2	Parcel
    // Exception table:
    //   from	to	target	type
    //   8	14	74	finally
    //   18	29	74	finally
    //   29	56	74	finally
    //   66	71	74	finally
  }
  
  /* Error */
  public void animateCamera(com.google.android.gms.dynamic.d paramd)
  {
    // Byte code:
    //   0: invokestatic 24	android/os/Parcel:obtain	()Landroid/os/Parcel;
    //   3: astore_2
    //   4: invokestatic 24	android/os/Parcel:obtain	()Landroid/os/Parcel;
    //   7: astore_3
    //   8: aload_2
    //   9: ldc 26
    //   11: invokevirtual 30	android/os/Parcel:writeInterfaceToken	(Ljava/lang/String;)V
    //   14: aload_1
    //   15: ifnull +42 -> 57
    //   18: aload_1
    //   19: invokeinterface 134 1 0
    //   24: astore_1
    //   25: aload_2
    //   26: aload_1
    //   27: invokevirtual 137	android/os/Parcel:writeStrongBinder	(Landroid/os/IBinder;)V
    //   30: aload_0
    //   31: getfield 15	com/google/android/gms/maps/internal/IGoogleMapDelegate$a$a:le	Landroid/os/IBinder;
    //   34: iconst_5
    //   35: aload_2
    //   36: aload_3
    //   37: iconst_0
    //   38: invokeinterface 46 5 0
    //   43: pop
    //   44: aload_3
    //   45: invokevirtual 49	android/os/Parcel:readException	()V
    //   48: aload_3
    //   49: invokevirtual 62	android/os/Parcel:recycle	()V
    //   52: aload_2
    //   53: invokevirtual 62	android/os/Parcel:recycle	()V
    //   56: return
    //   57: aconst_null
    //   58: astore_1
    //   59: goto -34 -> 25
    //   62: astore_1
    //   63: aload_3
    //   64: invokevirtual 62	android/os/Parcel:recycle	()V
    //   67: aload_2
    //   68: invokevirtual 62	android/os/Parcel:recycle	()V
    //   71: aload_1
    //   72: athrow
    // Local variable table:
    //   start	length	slot	name	signature
    //   0	73	0	this	a
    //   0	73	1	paramd	com.google.android.gms.dynamic.d
    //   3	65	2	localParcel1	Parcel
    //   7	57	3	localParcel2	Parcel
    // Exception table:
    //   from	to	target	type
    //   8	14	62	finally
    //   18	25	62	finally
    //   25	48	62	finally
  }
  
  /* Error */
  public void animateCamera2(c paramc)
  {
    // Byte code:
    //   0: invokestatic 24	android/os/Parcel:obtain	()Landroid/os/Parcel;
    //   3: astore_2
    //   4: invokestatic 24	android/os/Parcel:obtain	()Landroid/os/Parcel;
    //   7: astore_3
    //   8: aload_2
    //   9: ldc 26
    //   11: invokevirtual 30	android/os/Parcel:writeInterfaceToken	(Ljava/lang/String;)V
    //   14: aload_1
    //   15: ifnull +42 -> 57
    //   18: aload_2
    //   19: iconst_1
    //   20: invokevirtual 34	android/os/Parcel:writeInt	(I)V
    //   23: aload_1
    //   24: aload_2
    //   25: iconst_0
    //   26: invokevirtual 142	com/google/android/gms/maps/model/internal/c:writeToParcel	(Landroid/os/Parcel;I)V
    //   29: aload_0
    //   30: getfield 15	com/google/android/gms/maps/internal/IGoogleMapDelegate$a$a:le	Landroid/os/IBinder;
    //   33: bipush 65
    //   35: aload_2
    //   36: aload_3
    //   37: iconst_0
    //   38: invokeinterface 46 5 0
    //   43: pop
    //   44: aload_3
    //   45: invokevirtual 49	android/os/Parcel:readException	()V
    //   48: aload_3
    //   49: invokevirtual 62	android/os/Parcel:recycle	()V
    //   52: aload_2
    //   53: invokevirtual 62	android/os/Parcel:recycle	()V
    //   56: return
    //   57: aload_2
    //   58: iconst_0
    //   59: invokevirtual 34	android/os/Parcel:writeInt	(I)V
    //   62: goto -33 -> 29
    //   65: astore_1
    //   66: aload_3
    //   67: invokevirtual 62	android/os/Parcel:recycle	()V
    //   70: aload_2
    //   71: invokevirtual 62	android/os/Parcel:recycle	()V
    //   74: aload_1
    //   75: athrow
    // Local variable table:
    //   start	length	slot	name	signature
    //   0	76	0	this	a
    //   0	76	1	paramc	c
    //   3	68	2	localParcel1	Parcel
    //   7	60	3	localParcel2	Parcel
    // Exception table:
    //   from	to	target	type
    //   8	14	65	finally
    //   18	29	65	finally
    //   29	48	65	finally
    //   57	62	65	finally
  }
  
  /* Error */
  public void animateCameraWithCallback(com.google.android.gms.dynamic.d paramd, b paramb)
  {
    // Byte code:
    //   0: aconst_null
    //   1: astore_3
    //   2: invokestatic 24	android/os/Parcel:obtain	()Landroid/os/Parcel;
    //   5: astore 4
    //   7: invokestatic 24	android/os/Parcel:obtain	()Landroid/os/Parcel;
    //   10: astore 5
    //   12: aload 4
    //   14: ldc 26
    //   16: invokevirtual 30	android/os/Parcel:writeInterfaceToken	(Ljava/lang/String;)V
    //   19: aload_1
    //   20: ifnull +68 -> 88
    //   23: aload_1
    //   24: invokeinterface 134 1 0
    //   29: astore_1
    //   30: aload 4
    //   32: aload_1
    //   33: invokevirtual 137	android/os/Parcel:writeStrongBinder	(Landroid/os/IBinder;)V
    //   36: aload_3
    //   37: astore_1
    //   38: aload_2
    //   39: ifnull +10 -> 49
    //   42: aload_2
    //   43: invokeinterface 147 1 0
    //   48: astore_1
    //   49: aload 4
    //   51: aload_1
    //   52: invokevirtual 137	android/os/Parcel:writeStrongBinder	(Landroid/os/IBinder;)V
    //   55: aload_0
    //   56: getfield 15	com/google/android/gms/maps/internal/IGoogleMapDelegate$a$a:le	Landroid/os/IBinder;
    //   59: bipush 6
    //   61: aload 4
    //   63: aload 5
    //   65: iconst_0
    //   66: invokeinterface 46 5 0
    //   71: pop
    //   72: aload 5
    //   74: invokevirtual 49	android/os/Parcel:readException	()V
    //   77: aload 5
    //   79: invokevirtual 62	android/os/Parcel:recycle	()V
    //   82: aload 4
    //   84: invokevirtual 62	android/os/Parcel:recycle	()V
    //   87: return
    //   88: aconst_null
    //   89: astore_1
    //   90: goto -60 -> 30
    //   93: astore_1
    //   94: aload 5
    //   96: invokevirtual 62	android/os/Parcel:recycle	()V
    //   99: aload 4
    //   101: invokevirtual 62	android/os/Parcel:recycle	()V
    //   104: aload_1
    //   105: athrow
    // Local variable table:
    //   start	length	slot	name	signature
    //   0	106	0	this	a
    //   0	106	1	paramd	com.google.android.gms.dynamic.d
    //   0	106	2	paramb	b
    //   1	36	3	localObject	Object
    //   5	95	4	localParcel1	Parcel
    //   10	85	5	localParcel2	Parcel
    // Exception table:
    //   from	to	target	type
    //   12	19	93	finally
    //   23	30	93	finally
    //   30	36	93	finally
    //   42	49	93	finally
    //   49	77	93	finally
  }
  
  public void animateCameraWithCallback2(c paramc, b paramb)
  {
    Parcel localParcel1 = Parcel.obtain();
    Parcel localParcel2 = Parcel.obtain();
    for (;;)
    {
      try
      {
        localParcel1.writeInterfaceToken("com.google.android.gms.maps.internal.IGoogleMapDelegate");
        if (paramc != null)
        {
          localParcel1.writeInt(1);
          paramc.writeToParcel(localParcel1, 0);
          if (paramb != null)
          {
            paramc = paramb.asBinder();
            localParcel1.writeStrongBinder(paramc);
            le.transact(66, localParcel1, localParcel2, 0);
            localParcel2.readException();
          }
        }
        else
        {
          localParcel1.writeInt(0);
          continue;
        }
        paramc = null;
      }
      finally
      {
        localParcel2.recycle();
        localParcel1.recycle();
      }
    }
  }
  
  /* Error */
  public void animateCameraWithDurationAndCallback(com.google.android.gms.dynamic.d paramd, int paramInt, b paramb)
  {
    // Byte code:
    //   0: aconst_null
    //   1: astore 4
    //   3: invokestatic 24	android/os/Parcel:obtain	()Landroid/os/Parcel;
    //   6: astore 5
    //   8: invokestatic 24	android/os/Parcel:obtain	()Landroid/os/Parcel;
    //   11: astore 6
    //   13: aload 5
    //   15: ldc 26
    //   17: invokevirtual 30	android/os/Parcel:writeInterfaceToken	(Ljava/lang/String;)V
    //   20: aload_1
    //   21: ifnull +75 -> 96
    //   24: aload_1
    //   25: invokeinterface 134 1 0
    //   30: astore_1
    //   31: aload 5
    //   33: aload_1
    //   34: invokevirtual 137	android/os/Parcel:writeStrongBinder	(Landroid/os/IBinder;)V
    //   37: aload 5
    //   39: iload_2
    //   40: invokevirtual 34	android/os/Parcel:writeInt	(I)V
    //   43: aload 4
    //   45: astore_1
    //   46: aload_3
    //   47: ifnull +10 -> 57
    //   50: aload_3
    //   51: invokeinterface 147 1 0
    //   56: astore_1
    //   57: aload 5
    //   59: aload_1
    //   60: invokevirtual 137	android/os/Parcel:writeStrongBinder	(Landroid/os/IBinder;)V
    //   63: aload_0
    //   64: getfield 15	com/google/android/gms/maps/internal/IGoogleMapDelegate$a$a:le	Landroid/os/IBinder;
    //   67: bipush 7
    //   69: aload 5
    //   71: aload 6
    //   73: iconst_0
    //   74: invokeinterface 46 5 0
    //   79: pop
    //   80: aload 6
    //   82: invokevirtual 49	android/os/Parcel:readException	()V
    //   85: aload 6
    //   87: invokevirtual 62	android/os/Parcel:recycle	()V
    //   90: aload 5
    //   92: invokevirtual 62	android/os/Parcel:recycle	()V
    //   95: return
    //   96: aconst_null
    //   97: astore_1
    //   98: goto -67 -> 31
    //   101: astore_1
    //   102: aload 6
    //   104: invokevirtual 62	android/os/Parcel:recycle	()V
    //   107: aload 5
    //   109: invokevirtual 62	android/os/Parcel:recycle	()V
    //   112: aload_1
    //   113: athrow
    // Local variable table:
    //   start	length	slot	name	signature
    //   0	114	0	this	a
    //   0	114	1	paramd	com.google.android.gms.dynamic.d
    //   0	114	2	paramInt	int
    //   0	114	3	paramb	b
    //   1	43	4	localObject	Object
    //   6	102	5	localParcel1	Parcel
    //   11	92	6	localParcel2	Parcel
    // Exception table:
    //   from	to	target	type
    //   13	20	101	finally
    //   24	31	101	finally
    //   31	43	101	finally
    //   50	57	101	finally
    //   57	85	101	finally
  }
  
  public void animateCameraWithDurationAndCallback2(c paramc, int paramInt, b paramb)
  {
    Parcel localParcel1 = Parcel.obtain();
    Parcel localParcel2 = Parcel.obtain();
    for (;;)
    {
      try
      {
        localParcel1.writeInterfaceToken("com.google.android.gms.maps.internal.IGoogleMapDelegate");
        if (paramc != null)
        {
          localParcel1.writeInt(1);
          paramc.writeToParcel(localParcel1, 0);
          localParcel1.writeInt(paramInt);
          if (paramb != null)
          {
            paramc = paramb.asBinder();
            localParcel1.writeStrongBinder(paramc);
            le.transact(67, localParcel1, localParcel2, 0);
            localParcel2.readException();
          }
        }
        else
        {
          localParcel1.writeInt(0);
          continue;
        }
        paramc = null;
      }
      finally
      {
        localParcel2.recycle();
        localParcel1.recycle();
      }
    }
  }
  
  public IBinder asBinder()
  {
    return le;
  }
  
  public void clear()
  {
    Parcel localParcel1 = Parcel.obtain();
    Parcel localParcel2 = Parcel.obtain();
    try
    {
      localParcel1.writeInterfaceToken("com.google.android.gms.maps.internal.IGoogleMapDelegate");
      le.transact(14, localParcel1, localParcel2, 0);
      localParcel2.readException();
      return;
    }
    finally
    {
      localParcel2.recycle();
      localParcel1.recycle();
    }
  }
  
  /* Error */
  public com.google.android.gms.maps.model.CameraPosition getCameraPosition()
  {
    // Byte code:
    //   0: invokestatic 24	android/os/Parcel:obtain	()Landroid/os/Parcel;
    //   3: astore_2
    //   4: invokestatic 24	android/os/Parcel:obtain	()Landroid/os/Parcel;
    //   7: astore_3
    //   8: aload_2
    //   9: ldc 26
    //   11: invokevirtual 30	android/os/Parcel:writeInterfaceToken	(Ljava/lang/String;)V
    //   14: aload_0
    //   15: getfield 15	com/google/android/gms/maps/internal/IGoogleMapDelegate$a$a:le	Landroid/os/IBinder;
    //   18: iconst_1
    //   19: aload_2
    //   20: aload_3
    //   21: iconst_0
    //   22: invokeinterface 46 5 0
    //   27: pop
    //   28: aload_3
    //   29: invokevirtual 49	android/os/Parcel:readException	()V
    //   32: aload_3
    //   33: invokevirtual 160	android/os/Parcel:readInt	()I
    //   36: ifeq +21 -> 57
    //   39: getstatic 166	com/google/android/gms/maps/model/CameraPosition:CREATOR	Lcom/google/android/gms/maps/model/a;
    //   42: aload_3
    //   43: invokevirtual 172	com/google/android/gms/maps/model/a:da	(Landroid/os/Parcel;)Lcom/google/android/gms/maps/model/CameraPosition;
    //   46: astore_1
    //   47: aload_3
    //   48: invokevirtual 62	android/os/Parcel:recycle	()V
    //   51: aload_2
    //   52: invokevirtual 62	android/os/Parcel:recycle	()V
    //   55: aload_1
    //   56: areturn
    //   57: aconst_null
    //   58: astore_1
    //   59: goto -12 -> 47
    //   62: astore_1
    //   63: aload_3
    //   64: invokevirtual 62	android/os/Parcel:recycle	()V
    //   67: aload_2
    //   68: invokevirtual 62	android/os/Parcel:recycle	()V
    //   71: aload_1
    //   72: athrow
    // Local variable table:
    //   start	length	slot	name	signature
    //   0	73	0	this	a
    //   46	13	1	localCameraPosition	com.google.android.gms.maps.model.CameraPosition
    //   62	10	1	localObject	Object
    //   3	65	2	localParcel1	Parcel
    //   7	57	3	localParcel2	Parcel
    // Exception table:
    //   from	to	target	type
    //   8	47	62	finally
  }
  
  public j getFocusedBuilding()
  {
    Parcel localParcel1 = Parcel.obtain();
    Parcel localParcel2 = Parcel.obtain();
    try
    {
      localParcel1.writeInterfaceToken("com.google.android.gms.maps.internal.IGoogleMapDelegate");
      le.transact(44, localParcel1, localParcel2, 0);
      localParcel2.readException();
      j localj = j.a.by(localParcel2.readStrongBinder());
      return localj;
    }
    finally
    {
      localParcel2.recycle();
      localParcel1.recycle();
    }
  }
  
  /* Error */
  public void getMapAsync(m paramm)
  {
    // Byte code:
    //   0: invokestatic 24	android/os/Parcel:obtain	()Landroid/os/Parcel;
    //   3: astore_2
    //   4: invokestatic 24	android/os/Parcel:obtain	()Landroid/os/Parcel;
    //   7: astore_3
    //   8: aload_2
    //   9: ldc 26
    //   11: invokevirtual 30	android/os/Parcel:writeInterfaceToken	(Ljava/lang/String;)V
    //   14: aload_1
    //   15: ifnull +43 -> 58
    //   18: aload_1
    //   19: invokeinterface 185 1 0
    //   24: astore_1
    //   25: aload_2
    //   26: aload_1
    //   27: invokevirtual 137	android/os/Parcel:writeStrongBinder	(Landroid/os/IBinder;)V
    //   30: aload_0
    //   31: getfield 15	com/google/android/gms/maps/internal/IGoogleMapDelegate$a$a:le	Landroid/os/IBinder;
    //   34: bipush 53
    //   36: aload_2
    //   37: aload_3
    //   38: iconst_0
    //   39: invokeinterface 46 5 0
    //   44: pop
    //   45: aload_3
    //   46: invokevirtual 49	android/os/Parcel:readException	()V
    //   49: aload_3
    //   50: invokevirtual 62	android/os/Parcel:recycle	()V
    //   53: aload_2
    //   54: invokevirtual 62	android/os/Parcel:recycle	()V
    //   57: return
    //   58: aconst_null
    //   59: astore_1
    //   60: goto -35 -> 25
    //   63: astore_1
    //   64: aload_3
    //   65: invokevirtual 62	android/os/Parcel:recycle	()V
    //   68: aload_2
    //   69: invokevirtual 62	android/os/Parcel:recycle	()V
    //   72: aload_1
    //   73: athrow
    // Local variable table:
    //   start	length	slot	name	signature
    //   0	74	0	this	a
    //   0	74	1	paramm	m
    //   3	66	2	localParcel1	Parcel
    //   7	58	3	localParcel2	Parcel
    // Exception table:
    //   from	to	target	type
    //   8	14	63	finally
    //   18	25	63	finally
    //   25	49	63	finally
  }
  
  public int getMapType()
  {
    Parcel localParcel1 = Parcel.obtain();
    Parcel localParcel2 = Parcel.obtain();
    try
    {
      localParcel1.writeInterfaceToken("com.google.android.gms.maps.internal.IGoogleMapDelegate");
      le.transact(15, localParcel1, localParcel2, 0);
      localParcel2.readException();
      int i = localParcel2.readInt();
      return i;
    }
    finally
    {
      localParcel2.recycle();
      localParcel1.recycle();
    }
  }
  
  public float getMaxZoomLevel()
  {
    Parcel localParcel1 = Parcel.obtain();
    Parcel localParcel2 = Parcel.obtain();
    try
    {
      localParcel1.writeInterfaceToken("com.google.android.gms.maps.internal.IGoogleMapDelegate");
      le.transact(2, localParcel1, localParcel2, 0);
      localParcel2.readException();
      float f = localParcel2.readFloat();
      return f;
    }
    finally
    {
      localParcel2.recycle();
      localParcel1.recycle();
    }
  }
  
  public float getMinZoomLevel()
  {
    Parcel localParcel1 = Parcel.obtain();
    Parcel localParcel2 = Parcel.obtain();
    try
    {
      localParcel1.writeInterfaceToken("com.google.android.gms.maps.internal.IGoogleMapDelegate");
      le.transact(3, localParcel1, localParcel2, 0);
      localParcel2.readException();
      float f = localParcel2.readFloat();
      return f;
    }
    finally
    {
      localParcel2.recycle();
      localParcel1.recycle();
    }
  }
  
  /* Error */
  public android.location.Location getMyLocation()
  {
    // Byte code:
    //   0: invokestatic 24	android/os/Parcel:obtain	()Landroid/os/Parcel;
    //   3: astore_2
    //   4: invokestatic 24	android/os/Parcel:obtain	()Landroid/os/Parcel;
    //   7: astore_3
    //   8: aload_2
    //   9: ldc 26
    //   11: invokevirtual 30	android/os/Parcel:writeInterfaceToken	(Ljava/lang/String;)V
    //   14: aload_0
    //   15: getfield 15	com/google/android/gms/maps/internal/IGoogleMapDelegate$a$a:le	Landroid/os/IBinder;
    //   18: bipush 23
    //   20: aload_2
    //   21: aload_3
    //   22: iconst_0
    //   23: invokeinterface 46 5 0
    //   28: pop
    //   29: aload_3
    //   30: invokevirtual 49	android/os/Parcel:readException	()V
    //   33: aload_3
    //   34: invokevirtual 160	android/os/Parcel:readInt	()I
    //   37: ifeq +26 -> 63
    //   40: getstatic 199	android/location/Location:CREATOR	Landroid/os/Parcelable$Creator;
    //   43: aload_3
    //   44: invokeinterface 205 2 0
    //   49: checkcast 196	android/location/Location
    //   52: astore_1
    //   53: aload_3
    //   54: invokevirtual 62	android/os/Parcel:recycle	()V
    //   57: aload_2
    //   58: invokevirtual 62	android/os/Parcel:recycle	()V
    //   61: aload_1
    //   62: areturn
    //   63: aconst_null
    //   64: astore_1
    //   65: goto -12 -> 53
    //   68: astore_1
    //   69: aload_3
    //   70: invokevirtual 62	android/os/Parcel:recycle	()V
    //   73: aload_2
    //   74: invokevirtual 62	android/os/Parcel:recycle	()V
    //   77: aload_1
    //   78: athrow
    // Local variable table:
    //   start	length	slot	name	signature
    //   0	79	0	this	a
    //   52	13	1	localLocation	android.location.Location
    //   68	10	1	localObject	Object
    //   3	71	2	localParcel1	Parcel
    //   7	63	3	localParcel2	Parcel
    // Exception table:
    //   from	to	target	type
    //   8	53	68	finally
  }
  
  public IProjectionDelegate getProjection()
  {
    Parcel localParcel1 = Parcel.obtain();
    Parcel localParcel2 = Parcel.obtain();
    try
    {
      localParcel1.writeInterfaceToken("com.google.android.gms.maps.internal.IGoogleMapDelegate");
      le.transact(26, localParcel1, localParcel2, 0);
      localParcel2.readException();
      IProjectionDelegate localIProjectionDelegate = IProjectionDelegate.a.bp(localParcel2.readStrongBinder());
      return localIProjectionDelegate;
    }
    finally
    {
      localParcel2.recycle();
      localParcel1.recycle();
    }
  }
  
  public IUiSettingsDelegate getUiSettings()
  {
    Parcel localParcel1 = Parcel.obtain();
    Parcel localParcel2 = Parcel.obtain();
    try
    {
      localParcel1.writeInterfaceToken("com.google.android.gms.maps.internal.IGoogleMapDelegate");
      le.transact(25, localParcel1, localParcel2, 0);
      localParcel2.readException();
      IUiSettingsDelegate localIUiSettingsDelegate = IUiSettingsDelegate.a.bu(localParcel2.readStrongBinder());
      return localIUiSettingsDelegate;
    }
    finally
    {
      localParcel2.recycle();
      localParcel1.recycle();
    }
  }
  
  public boolean isBuildingsEnabled()
  {
    boolean bool = false;
    Parcel localParcel1 = Parcel.obtain();
    Parcel localParcel2 = Parcel.obtain();
    try
    {
      localParcel1.writeInterfaceToken("com.google.android.gms.maps.internal.IGoogleMapDelegate");
      le.transact(40, localParcel1, localParcel2, 0);
      localParcel2.readException();
      int i = localParcel2.readInt();
      if (i != 0) {
        bool = true;
      }
      return bool;
    }
    finally
    {
      localParcel2.recycle();
      localParcel1.recycle();
    }
  }
  
  public boolean isIndoorEnabled()
  {
    boolean bool = false;
    Parcel localParcel1 = Parcel.obtain();
    Parcel localParcel2 = Parcel.obtain();
    try
    {
      localParcel1.writeInterfaceToken("com.google.android.gms.maps.internal.IGoogleMapDelegate");
      le.transact(19, localParcel1, localParcel2, 0);
      localParcel2.readException();
      int i = localParcel2.readInt();
      if (i != 0) {
        bool = true;
      }
      return bool;
    }
    finally
    {
      localParcel2.recycle();
      localParcel1.recycle();
    }
  }
  
  public boolean isMyLocationEnabled()
  {
    boolean bool = false;
    Parcel localParcel1 = Parcel.obtain();
    Parcel localParcel2 = Parcel.obtain();
    try
    {
      localParcel1.writeInterfaceToken("com.google.android.gms.maps.internal.IGoogleMapDelegate");
      le.transact(21, localParcel1, localParcel2, 0);
      localParcel2.readException();
      int i = localParcel2.readInt();
      if (i != 0) {
        bool = true;
      }
      return bool;
    }
    finally
    {
      localParcel2.recycle();
      localParcel1.recycle();
    }
  }
  
  public boolean isTrafficEnabled()
  {
    boolean bool = false;
    Parcel localParcel1 = Parcel.obtain();
    Parcel localParcel2 = Parcel.obtain();
    try
    {
      localParcel1.writeInterfaceToken("com.google.android.gms.maps.internal.IGoogleMapDelegate");
      le.transact(17, localParcel1, localParcel2, 0);
      localParcel2.readException();
      int i = localParcel2.readInt();
      if (i != 0) {
        bool = true;
      }
      return bool;
    }
    finally
    {
      localParcel2.recycle();
      localParcel1.recycle();
    }
  }
  
  /* Error */
  public void moveCamera(com.google.android.gms.dynamic.d paramd)
  {
    // Byte code:
    //   0: invokestatic 24	android/os/Parcel:obtain	()Landroid/os/Parcel;
    //   3: astore_2
    //   4: invokestatic 24	android/os/Parcel:obtain	()Landroid/os/Parcel;
    //   7: astore_3
    //   8: aload_2
    //   9: ldc 26
    //   11: invokevirtual 30	android/os/Parcel:writeInterfaceToken	(Ljava/lang/String;)V
    //   14: aload_1
    //   15: ifnull +42 -> 57
    //   18: aload_1
    //   19: invokeinterface 134 1 0
    //   24: astore_1
    //   25: aload_2
    //   26: aload_1
    //   27: invokevirtual 137	android/os/Parcel:writeStrongBinder	(Landroid/os/IBinder;)V
    //   30: aload_0
    //   31: getfield 15	com/google/android/gms/maps/internal/IGoogleMapDelegate$a$a:le	Landroid/os/IBinder;
    //   34: iconst_4
    //   35: aload_2
    //   36: aload_3
    //   37: iconst_0
    //   38: invokeinterface 46 5 0
    //   43: pop
    //   44: aload_3
    //   45: invokevirtual 49	android/os/Parcel:readException	()V
    //   48: aload_3
    //   49: invokevirtual 62	android/os/Parcel:recycle	()V
    //   52: aload_2
    //   53: invokevirtual 62	android/os/Parcel:recycle	()V
    //   56: return
    //   57: aconst_null
    //   58: astore_1
    //   59: goto -34 -> 25
    //   62: astore_1
    //   63: aload_3
    //   64: invokevirtual 62	android/os/Parcel:recycle	()V
    //   67: aload_2
    //   68: invokevirtual 62	android/os/Parcel:recycle	()V
    //   71: aload_1
    //   72: athrow
    // Local variable table:
    //   start	length	slot	name	signature
    //   0	73	0	this	a
    //   0	73	1	paramd	com.google.android.gms.dynamic.d
    //   3	65	2	localParcel1	Parcel
    //   7	57	3	localParcel2	Parcel
    // Exception table:
    //   from	to	target	type
    //   8	14	62	finally
    //   18	25	62	finally
    //   25	48	62	finally
  }
  
  /* Error */
  public void moveCamera2(c paramc)
  {
    // Byte code:
    //   0: invokestatic 24	android/os/Parcel:obtain	()Landroid/os/Parcel;
    //   3: astore_2
    //   4: invokestatic 24	android/os/Parcel:obtain	()Landroid/os/Parcel;
    //   7: astore_3
    //   8: aload_2
    //   9: ldc 26
    //   11: invokevirtual 30	android/os/Parcel:writeInterfaceToken	(Ljava/lang/String;)V
    //   14: aload_1
    //   15: ifnull +42 -> 57
    //   18: aload_2
    //   19: iconst_1
    //   20: invokevirtual 34	android/os/Parcel:writeInt	(I)V
    //   23: aload_1
    //   24: aload_2
    //   25: iconst_0
    //   26: invokevirtual 142	com/google/android/gms/maps/model/internal/c:writeToParcel	(Landroid/os/Parcel;I)V
    //   29: aload_0
    //   30: getfield 15	com/google/android/gms/maps/internal/IGoogleMapDelegate$a$a:le	Landroid/os/IBinder;
    //   33: bipush 64
    //   35: aload_2
    //   36: aload_3
    //   37: iconst_0
    //   38: invokeinterface 46 5 0
    //   43: pop
    //   44: aload_3
    //   45: invokevirtual 49	android/os/Parcel:readException	()V
    //   48: aload_3
    //   49: invokevirtual 62	android/os/Parcel:recycle	()V
    //   52: aload_2
    //   53: invokevirtual 62	android/os/Parcel:recycle	()V
    //   56: return
    //   57: aload_2
    //   58: iconst_0
    //   59: invokevirtual 34	android/os/Parcel:writeInt	(I)V
    //   62: goto -33 -> 29
    //   65: astore_1
    //   66: aload_3
    //   67: invokevirtual 62	android/os/Parcel:recycle	()V
    //   70: aload_2
    //   71: invokevirtual 62	android/os/Parcel:recycle	()V
    //   74: aload_1
    //   75: athrow
    // Local variable table:
    //   start	length	slot	name	signature
    //   0	76	0	this	a
    //   0	76	1	paramc	c
    //   3	68	2	localParcel1	Parcel
    //   7	60	3	localParcel2	Parcel
    // Exception table:
    //   from	to	target	type
    //   8	14	65	finally
    //   18	29	65	finally
    //   29	48	65	finally
    //   57	62	65	finally
  }
  
  /* Error */
  public void onCreate(android.os.Bundle paramBundle)
  {
    // Byte code:
    //   0: invokestatic 24	android/os/Parcel:obtain	()Landroid/os/Parcel;
    //   3: astore_2
    //   4: invokestatic 24	android/os/Parcel:obtain	()Landroid/os/Parcel;
    //   7: astore_3
    //   8: aload_2
    //   9: ldc 26
    //   11: invokevirtual 30	android/os/Parcel:writeInterfaceToken	(Ljava/lang/String;)V
    //   14: aload_1
    //   15: ifnull +42 -> 57
    //   18: aload_2
    //   19: iconst_1
    //   20: invokevirtual 34	android/os/Parcel:writeInt	(I)V
    //   23: aload_1
    //   24: aload_2
    //   25: iconst_0
    //   26: invokevirtual 233	android/os/Bundle:writeToParcel	(Landroid/os/Parcel;I)V
    //   29: aload_0
    //   30: getfield 15	com/google/android/gms/maps/internal/IGoogleMapDelegate$a$a:le	Landroid/os/IBinder;
    //   33: bipush 54
    //   35: aload_2
    //   36: aload_3
    //   37: iconst_0
    //   38: invokeinterface 46 5 0
    //   43: pop
    //   44: aload_3
    //   45: invokevirtual 49	android/os/Parcel:readException	()V
    //   48: aload_3
    //   49: invokevirtual 62	android/os/Parcel:recycle	()V
    //   52: aload_2
    //   53: invokevirtual 62	android/os/Parcel:recycle	()V
    //   56: return
    //   57: aload_2
    //   58: iconst_0
    //   59: invokevirtual 34	android/os/Parcel:writeInt	(I)V
    //   62: goto -33 -> 29
    //   65: astore_1
    //   66: aload_3
    //   67: invokevirtual 62	android/os/Parcel:recycle	()V
    //   70: aload_2
    //   71: invokevirtual 62	android/os/Parcel:recycle	()V
    //   74: aload_1
    //   75: athrow
    // Local variable table:
    //   start	length	slot	name	signature
    //   0	76	0	this	a
    //   0	76	1	paramBundle	android.os.Bundle
    //   3	68	2	localParcel1	Parcel
    //   7	60	3	localParcel2	Parcel
    // Exception table:
    //   from	to	target	type
    //   8	14	65	finally
    //   18	29	65	finally
    //   29	48	65	finally
    //   57	62	65	finally
  }
  
  public void onDestroy()
  {
    Parcel localParcel1 = Parcel.obtain();
    Parcel localParcel2 = Parcel.obtain();
    try
    {
      localParcel1.writeInterfaceToken("com.google.android.gms.maps.internal.IGoogleMapDelegate");
      le.transact(57, localParcel1, localParcel2, 0);
      localParcel2.readException();
      return;
    }
    finally
    {
      localParcel2.recycle();
      localParcel1.recycle();
    }
  }
  
  public void onLowMemory()
  {
    Parcel localParcel1 = Parcel.obtain();
    Parcel localParcel2 = Parcel.obtain();
    try
    {
      localParcel1.writeInterfaceToken("com.google.android.gms.maps.internal.IGoogleMapDelegate");
      le.transact(58, localParcel1, localParcel2, 0);
      localParcel2.readException();
      return;
    }
    finally
    {
      localParcel2.recycle();
      localParcel1.recycle();
    }
  }
  
  public void onPause()
  {
    Parcel localParcel1 = Parcel.obtain();
    Parcel localParcel2 = Parcel.obtain();
    try
    {
      localParcel1.writeInterfaceToken("com.google.android.gms.maps.internal.IGoogleMapDelegate");
      le.transact(56, localParcel1, localParcel2, 0);
      localParcel2.readException();
      return;
    }
    finally
    {
      localParcel2.recycle();
      localParcel1.recycle();
    }
  }
  
  public void onResume()
  {
    Parcel localParcel1 = Parcel.obtain();
    Parcel localParcel2 = Parcel.obtain();
    try
    {
      localParcel1.writeInterfaceToken("com.google.android.gms.maps.internal.IGoogleMapDelegate");
      le.transact(55, localParcel1, localParcel2, 0);
      localParcel2.readException();
      return;
    }
    finally
    {
      localParcel2.recycle();
      localParcel1.recycle();
    }
  }
  
  /* Error */
  public void onSaveInstanceState(android.os.Bundle paramBundle)
  {
    // Byte code:
    //   0: invokestatic 24	android/os/Parcel:obtain	()Landroid/os/Parcel;
    //   3: astore_2
    //   4: invokestatic 24	android/os/Parcel:obtain	()Landroid/os/Parcel;
    //   7: astore_3
    //   8: aload_2
    //   9: ldc 26
    //   11: invokevirtual 30	android/os/Parcel:writeInterfaceToken	(Ljava/lang/String;)V
    //   14: aload_1
    //   15: ifnull +54 -> 69
    //   18: aload_2
    //   19: iconst_1
    //   20: invokevirtual 34	android/os/Parcel:writeInt	(I)V
    //   23: aload_1
    //   24: aload_2
    //   25: iconst_0
    //   26: invokevirtual 233	android/os/Bundle:writeToParcel	(Landroid/os/Parcel;I)V
    //   29: aload_0
    //   30: getfield 15	com/google/android/gms/maps/internal/IGoogleMapDelegate$a$a:le	Landroid/os/IBinder;
    //   33: bipush 60
    //   35: aload_2
    //   36: aload_3
    //   37: iconst_0
    //   38: invokeinterface 46 5 0
    //   43: pop
    //   44: aload_3
    //   45: invokevirtual 49	android/os/Parcel:readException	()V
    //   48: aload_3
    //   49: invokevirtual 160	android/os/Parcel:readInt	()I
    //   52: ifeq +8 -> 60
    //   55: aload_1
    //   56: aload_3
    //   57: invokevirtual 242	android/os/Bundle:readFromParcel	(Landroid/os/Parcel;)V
    //   60: aload_3
    //   61: invokevirtual 62	android/os/Parcel:recycle	()V
    //   64: aload_2
    //   65: invokevirtual 62	android/os/Parcel:recycle	()V
    //   68: return
    //   69: aload_2
    //   70: iconst_0
    //   71: invokevirtual 34	android/os/Parcel:writeInt	(I)V
    //   74: goto -45 -> 29
    //   77: astore_1
    //   78: aload_3
    //   79: invokevirtual 62	android/os/Parcel:recycle	()V
    //   82: aload_2
    //   83: invokevirtual 62	android/os/Parcel:recycle	()V
    //   86: aload_1
    //   87: athrow
    // Local variable table:
    //   start	length	slot	name	signature
    //   0	88	0	this	a
    //   0	88	1	paramBundle	android.os.Bundle
    //   3	80	2	localParcel1	Parcel
    //   7	72	3	localParcel2	Parcel
    // Exception table:
    //   from	to	target	type
    //   8	14	77	finally
    //   18	29	77	finally
    //   29	60	77	finally
    //   69	74	77	finally
  }
  
  public void setBuildingsEnabled(boolean paramBoolean)
  {
    int i = 0;
    Parcel localParcel1 = Parcel.obtain();
    Parcel localParcel2 = Parcel.obtain();
    try
    {
      localParcel1.writeInterfaceToken("com.google.android.gms.maps.internal.IGoogleMapDelegate");
      if (paramBoolean) {
        i = 1;
      }
      localParcel1.writeInt(i);
      le.transact(41, localParcel1, localParcel2, 0);
      localParcel2.readException();
      return;
    }
    finally
    {
      localParcel2.recycle();
      localParcel1.recycle();
    }
  }
  
  public void setContentDescription(String paramString)
  {
    Parcel localParcel1 = Parcel.obtain();
    Parcel localParcel2 = Parcel.obtain();
    try
    {
      localParcel1.writeInterfaceToken("com.google.android.gms.maps.internal.IGoogleMapDelegate");
      localParcel1.writeString(paramString);
      le.transact(61, localParcel1, localParcel2, 0);
      localParcel2.readException();
      return;
    }
    finally
    {
      localParcel2.recycle();
      localParcel1.recycle();
    }
  }
  
  /* Error */
  public boolean setIndoorEnabled(boolean paramBoolean)
  {
    // Byte code:
    //   0: iconst_1
    //   1: istore_3
    //   2: invokestatic 24	android/os/Parcel:obtain	()Landroid/os/Parcel;
    //   5: astore 4
    //   7: invokestatic 24	android/os/Parcel:obtain	()Landroid/os/Parcel;
    //   10: astore 5
    //   12: aload 4
    //   14: ldc 26
    //   16: invokevirtual 30	android/os/Parcel:writeInterfaceToken	(Ljava/lang/String;)V
    //   19: iload_1
    //   20: ifeq +57 -> 77
    //   23: iconst_1
    //   24: istore_2
    //   25: aload 4
    //   27: iload_2
    //   28: invokevirtual 34	android/os/Parcel:writeInt	(I)V
    //   31: aload_0
    //   32: getfield 15	com/google/android/gms/maps/internal/IGoogleMapDelegate$a$a:le	Landroid/os/IBinder;
    //   35: bipush 20
    //   37: aload 4
    //   39: aload 5
    //   41: iconst_0
    //   42: invokeinterface 46 5 0
    //   47: pop
    //   48: aload 5
    //   50: invokevirtual 49	android/os/Parcel:readException	()V
    //   53: aload 5
    //   55: invokevirtual 160	android/os/Parcel:readInt	()I
    //   58: istore_2
    //   59: iload_2
    //   60: ifeq +22 -> 82
    //   63: iload_3
    //   64: istore_1
    //   65: aload 5
    //   67: invokevirtual 62	android/os/Parcel:recycle	()V
    //   70: aload 4
    //   72: invokevirtual 62	android/os/Parcel:recycle	()V
    //   75: iload_1
    //   76: ireturn
    //   77: iconst_0
    //   78: istore_2
    //   79: goto -54 -> 25
    //   82: iconst_0
    //   83: istore_1
    //   84: goto -19 -> 65
    //   87: astore 6
    //   89: aload 5
    //   91: invokevirtual 62	android/os/Parcel:recycle	()V
    //   94: aload 4
    //   96: invokevirtual 62	android/os/Parcel:recycle	()V
    //   99: aload 6
    //   101: athrow
    // Local variable table:
    //   start	length	slot	name	signature
    //   0	102	0	this	a
    //   0	102	1	paramBoolean	boolean
    //   24	55	2	i	int
    //   1	63	3	bool	boolean
    //   5	90	4	localParcel1	Parcel
    //   10	80	5	localParcel2	Parcel
    //   87	13	6	localObject	Object
    // Exception table:
    //   from	to	target	type
    //   12	19	87	finally
    //   25	59	87	finally
  }
  
  /* Error */
  public void setInfoWindowAdapter(d paramd)
  {
    // Byte code:
    //   0: invokestatic 24	android/os/Parcel:obtain	()Landroid/os/Parcel;
    //   3: astore_2
    //   4: invokestatic 24	android/os/Parcel:obtain	()Landroid/os/Parcel;
    //   7: astore_3
    //   8: aload_2
    //   9: ldc 26
    //   11: invokevirtual 30	android/os/Parcel:writeInterfaceToken	(Ljava/lang/String;)V
    //   14: aload_1
    //   15: ifnull +43 -> 58
    //   18: aload_1
    //   19: invokeinterface 255 1 0
    //   24: astore_1
    //   25: aload_2
    //   26: aload_1
    //   27: invokevirtual 137	android/os/Parcel:writeStrongBinder	(Landroid/os/IBinder;)V
    //   30: aload_0
    //   31: getfield 15	com/google/android/gms/maps/internal/IGoogleMapDelegate$a$a:le	Landroid/os/IBinder;
    //   34: bipush 33
    //   36: aload_2
    //   37: aload_3
    //   38: iconst_0
    //   39: invokeinterface 46 5 0
    //   44: pop
    //   45: aload_3
    //   46: invokevirtual 49	android/os/Parcel:readException	()V
    //   49: aload_3
    //   50: invokevirtual 62	android/os/Parcel:recycle	()V
    //   53: aload_2
    //   54: invokevirtual 62	android/os/Parcel:recycle	()V
    //   57: return
    //   58: aconst_null
    //   59: astore_1
    //   60: goto -35 -> 25
    //   63: astore_1
    //   64: aload_3
    //   65: invokevirtual 62	android/os/Parcel:recycle	()V
    //   68: aload_2
    //   69: invokevirtual 62	android/os/Parcel:recycle	()V
    //   72: aload_1
    //   73: athrow
    // Local variable table:
    //   start	length	slot	name	signature
    //   0	74	0	this	a
    //   0	74	1	paramd	d
    //   3	66	2	localParcel1	Parcel
    //   7	58	3	localParcel2	Parcel
    // Exception table:
    //   from	to	target	type
    //   8	14	63	finally
    //   18	25	63	finally
    //   25	49	63	finally
  }
  
  /* Error */
  public void setInfoWindowRenderer(e parame)
  {
    // Byte code:
    //   0: invokestatic 24	android/os/Parcel:obtain	()Landroid/os/Parcel;
    //   3: astore_2
    //   4: invokestatic 24	android/os/Parcel:obtain	()Landroid/os/Parcel;
    //   7: astore_3
    //   8: aload_2
    //   9: ldc 26
    //   11: invokevirtual 30	android/os/Parcel:writeInterfaceToken	(Ljava/lang/String;)V
    //   14: aload_1
    //   15: ifnull +43 -> 58
    //   18: aload_1
    //   19: invokeinterface 260 1 0
    //   24: astore_1
    //   25: aload_2
    //   26: aload_1
    //   27: invokevirtual 137	android/os/Parcel:writeStrongBinder	(Landroid/os/IBinder;)V
    //   30: aload_0
    //   31: getfield 15	com/google/android/gms/maps/internal/IGoogleMapDelegate$a$a:le	Landroid/os/IBinder;
    //   34: bipush 69
    //   36: aload_2
    //   37: aload_3
    //   38: iconst_0
    //   39: invokeinterface 46 5 0
    //   44: pop
    //   45: aload_3
    //   46: invokevirtual 49	android/os/Parcel:readException	()V
    //   49: aload_3
    //   50: invokevirtual 62	android/os/Parcel:recycle	()V
    //   53: aload_2
    //   54: invokevirtual 62	android/os/Parcel:recycle	()V
    //   57: return
    //   58: aconst_null
    //   59: astore_1
    //   60: goto -35 -> 25
    //   63: astore_1
    //   64: aload_3
    //   65: invokevirtual 62	android/os/Parcel:recycle	()V
    //   68: aload_2
    //   69: invokevirtual 62	android/os/Parcel:recycle	()V
    //   72: aload_1
    //   73: athrow
    // Local variable table:
    //   start	length	slot	name	signature
    //   0	74	0	this	a
    //   0	74	1	parame	e
    //   3	66	2	localParcel1	Parcel
    //   7	58	3	localParcel2	Parcel
    // Exception table:
    //   from	to	target	type
    //   8	14	63	finally
    //   18	25	63	finally
    //   25	49	63	finally
  }
  
  /* Error */
  public void setLocationSource(ILocationSourceDelegate paramILocationSourceDelegate)
  {
    // Byte code:
    //   0: invokestatic 24	android/os/Parcel:obtain	()Landroid/os/Parcel;
    //   3: astore_2
    //   4: invokestatic 24	android/os/Parcel:obtain	()Landroid/os/Parcel;
    //   7: astore_3
    //   8: aload_2
    //   9: ldc 26
    //   11: invokevirtual 30	android/os/Parcel:writeInterfaceToken	(Ljava/lang/String;)V
    //   14: aload_1
    //   15: ifnull +43 -> 58
    //   18: aload_1
    //   19: invokeinterface 265 1 0
    //   24: astore_1
    //   25: aload_2
    //   26: aload_1
    //   27: invokevirtual 137	android/os/Parcel:writeStrongBinder	(Landroid/os/IBinder;)V
    //   30: aload_0
    //   31: getfield 15	com/google/android/gms/maps/internal/IGoogleMapDelegate$a$a:le	Landroid/os/IBinder;
    //   34: bipush 24
    //   36: aload_2
    //   37: aload_3
    //   38: iconst_0
    //   39: invokeinterface 46 5 0
    //   44: pop
    //   45: aload_3
    //   46: invokevirtual 49	android/os/Parcel:readException	()V
    //   49: aload_3
    //   50: invokevirtual 62	android/os/Parcel:recycle	()V
    //   53: aload_2
    //   54: invokevirtual 62	android/os/Parcel:recycle	()V
    //   57: return
    //   58: aconst_null
    //   59: astore_1
    //   60: goto -35 -> 25
    //   63: astore_1
    //   64: aload_3
    //   65: invokevirtual 62	android/os/Parcel:recycle	()V
    //   68: aload_2
    //   69: invokevirtual 62	android/os/Parcel:recycle	()V
    //   72: aload_1
    //   73: athrow
    // Local variable table:
    //   start	length	slot	name	signature
    //   0	74	0	this	a
    //   0	74	1	paramILocationSourceDelegate	ILocationSourceDelegate
    //   3	66	2	localParcel1	Parcel
    //   7	58	3	localParcel2	Parcel
    // Exception table:
    //   from	to	target	type
    //   8	14	63	finally
    //   18	25	63	finally
    //   25	49	63	finally
  }
  
  public void setMapType(int paramInt)
  {
    Parcel localParcel1 = Parcel.obtain();
    Parcel localParcel2 = Parcel.obtain();
    try
    {
      localParcel1.writeInterfaceToken("com.google.android.gms.maps.internal.IGoogleMapDelegate");
      localParcel1.writeInt(paramInt);
      le.transact(16, localParcel1, localParcel2, 0);
      localParcel2.readException();
      return;
    }
    finally
    {
      localParcel2.recycle();
      localParcel1.recycle();
    }
  }
  
  public void setMyLocationEnabled(boolean paramBoolean)
  {
    int i = 0;
    Parcel localParcel1 = Parcel.obtain();
    Parcel localParcel2 = Parcel.obtain();
    try
    {
      localParcel1.writeInterfaceToken("com.google.android.gms.maps.internal.IGoogleMapDelegate");
      if (paramBoolean) {
        i = 1;
      }
      localParcel1.writeInt(i);
      le.transact(22, localParcel1, localParcel2, 0);
      localParcel2.readException();
      return;
    }
    finally
    {
      localParcel2.recycle();
      localParcel1.recycle();
    }
  }
  
  /* Error */
  public void setOnCameraChangeListener(f paramf)
  {
    // Byte code:
    //   0: invokestatic 24	android/os/Parcel:obtain	()Landroid/os/Parcel;
    //   3: astore_2
    //   4: invokestatic 24	android/os/Parcel:obtain	()Landroid/os/Parcel;
    //   7: astore_3
    //   8: aload_2
    //   9: ldc 26
    //   11: invokevirtual 30	android/os/Parcel:writeInterfaceToken	(Ljava/lang/String;)V
    //   14: aload_1
    //   15: ifnull +43 -> 58
    //   18: aload_1
    //   19: invokeinterface 272 1 0
    //   24: astore_1
    //   25: aload_2
    //   26: aload_1
    //   27: invokevirtual 137	android/os/Parcel:writeStrongBinder	(Landroid/os/IBinder;)V
    //   30: aload_0
    //   31: getfield 15	com/google/android/gms/maps/internal/IGoogleMapDelegate$a$a:le	Landroid/os/IBinder;
    //   34: bipush 27
    //   36: aload_2
    //   37: aload_3
    //   38: iconst_0
    //   39: invokeinterface 46 5 0
    //   44: pop
    //   45: aload_3
    //   46: invokevirtual 49	android/os/Parcel:readException	()V
    //   49: aload_3
    //   50: invokevirtual 62	android/os/Parcel:recycle	()V
    //   53: aload_2
    //   54: invokevirtual 62	android/os/Parcel:recycle	()V
    //   57: return
    //   58: aconst_null
    //   59: astore_1
    //   60: goto -35 -> 25
    //   63: astore_1
    //   64: aload_3
    //   65: invokevirtual 62	android/os/Parcel:recycle	()V
    //   68: aload_2
    //   69: invokevirtual 62	android/os/Parcel:recycle	()V
    //   72: aload_1
    //   73: athrow
    // Local variable table:
    //   start	length	slot	name	signature
    //   0	74	0	this	a
    //   0	74	1	paramf	f
    //   3	66	2	localParcel1	Parcel
    //   7	58	3	localParcel2	Parcel
    // Exception table:
    //   from	to	target	type
    //   8	14	63	finally
    //   18	25	63	finally
    //   25	49	63	finally
  }
  
  /* Error */
  public void setOnIndoorStateChangeListener(g paramg)
  {
    // Byte code:
    //   0: invokestatic 24	android/os/Parcel:obtain	()Landroid/os/Parcel;
    //   3: astore_2
    //   4: invokestatic 24	android/os/Parcel:obtain	()Landroid/os/Parcel;
    //   7: astore_3
    //   8: aload_2
    //   9: ldc 26
    //   11: invokevirtual 30	android/os/Parcel:writeInterfaceToken	(Ljava/lang/String;)V
    //   14: aload_1
    //   15: ifnull +43 -> 58
    //   18: aload_1
    //   19: invokeinterface 277 1 0
    //   24: astore_1
    //   25: aload_2
    //   26: aload_1
    //   27: invokevirtual 137	android/os/Parcel:writeStrongBinder	(Landroid/os/IBinder;)V
    //   30: aload_0
    //   31: getfield 15	com/google/android/gms/maps/internal/IGoogleMapDelegate$a$a:le	Landroid/os/IBinder;
    //   34: bipush 45
    //   36: aload_2
    //   37: aload_3
    //   38: iconst_0
    //   39: invokeinterface 46 5 0
    //   44: pop
    //   45: aload_3
    //   46: invokevirtual 49	android/os/Parcel:readException	()V
    //   49: aload_3
    //   50: invokevirtual 62	android/os/Parcel:recycle	()V
    //   53: aload_2
    //   54: invokevirtual 62	android/os/Parcel:recycle	()V
    //   57: return
    //   58: aconst_null
    //   59: astore_1
    //   60: goto -35 -> 25
    //   63: astore_1
    //   64: aload_3
    //   65: invokevirtual 62	android/os/Parcel:recycle	()V
    //   68: aload_2
    //   69: invokevirtual 62	android/os/Parcel:recycle	()V
    //   72: aload_1
    //   73: athrow
    // Local variable table:
    //   start	length	slot	name	signature
    //   0	74	0	this	a
    //   0	74	1	paramg	g
    //   3	66	2	localParcel1	Parcel
    //   7	58	3	localParcel2	Parcel
    // Exception table:
    //   from	to	target	type
    //   8	14	63	finally
    //   18	25	63	finally
    //   25	49	63	finally
  }
  
  /* Error */
  public void setOnInfoWindowClickListener(h paramh)
  {
    // Byte code:
    //   0: invokestatic 24	android/os/Parcel:obtain	()Landroid/os/Parcel;
    //   3: astore_2
    //   4: invokestatic 24	android/os/Parcel:obtain	()Landroid/os/Parcel;
    //   7: astore_3
    //   8: aload_2
    //   9: ldc 26
    //   11: invokevirtual 30	android/os/Parcel:writeInterfaceToken	(Ljava/lang/String;)V
    //   14: aload_1
    //   15: ifnull +43 -> 58
    //   18: aload_1
    //   19: invokeinterface 282 1 0
    //   24: astore_1
    //   25: aload_2
    //   26: aload_1
    //   27: invokevirtual 137	android/os/Parcel:writeStrongBinder	(Landroid/os/IBinder;)V
    //   30: aload_0
    //   31: getfield 15	com/google/android/gms/maps/internal/IGoogleMapDelegate$a$a:le	Landroid/os/IBinder;
    //   34: bipush 32
    //   36: aload_2
    //   37: aload_3
    //   38: iconst_0
    //   39: invokeinterface 46 5 0
    //   44: pop
    //   45: aload_3
    //   46: invokevirtual 49	android/os/Parcel:readException	()V
    //   49: aload_3
    //   50: invokevirtual 62	android/os/Parcel:recycle	()V
    //   53: aload_2
    //   54: invokevirtual 62	android/os/Parcel:recycle	()V
    //   57: return
    //   58: aconst_null
    //   59: astore_1
    //   60: goto -35 -> 25
    //   63: astore_1
    //   64: aload_3
    //   65: invokevirtual 62	android/os/Parcel:recycle	()V
    //   68: aload_2
    //   69: invokevirtual 62	android/os/Parcel:recycle	()V
    //   72: aload_1
    //   73: athrow
    // Local variable table:
    //   start	length	slot	name	signature
    //   0	74	0	this	a
    //   0	74	1	paramh	h
    //   3	66	2	localParcel1	Parcel
    //   7	58	3	localParcel2	Parcel
    // Exception table:
    //   from	to	target	type
    //   8	14	63	finally
    //   18	25	63	finally
    //   25	49	63	finally
  }
  
  /* Error */
  public void setOnMapClickListener(j paramj)
  {
    // Byte code:
    //   0: invokestatic 24	android/os/Parcel:obtain	()Landroid/os/Parcel;
    //   3: astore_2
    //   4: invokestatic 24	android/os/Parcel:obtain	()Landroid/os/Parcel;
    //   7: astore_3
    //   8: aload_2
    //   9: ldc 26
    //   11: invokevirtual 30	android/os/Parcel:writeInterfaceToken	(Ljava/lang/String;)V
    //   14: aload_1
    //   15: ifnull +43 -> 58
    //   18: aload_1
    //   19: invokeinterface 287 1 0
    //   24: astore_1
    //   25: aload_2
    //   26: aload_1
    //   27: invokevirtual 137	android/os/Parcel:writeStrongBinder	(Landroid/os/IBinder;)V
    //   30: aload_0
    //   31: getfield 15	com/google/android/gms/maps/internal/IGoogleMapDelegate$a$a:le	Landroid/os/IBinder;
    //   34: bipush 28
    //   36: aload_2
    //   37: aload_3
    //   38: iconst_0
    //   39: invokeinterface 46 5 0
    //   44: pop
    //   45: aload_3
    //   46: invokevirtual 49	android/os/Parcel:readException	()V
    //   49: aload_3
    //   50: invokevirtual 62	android/os/Parcel:recycle	()V
    //   53: aload_2
    //   54: invokevirtual 62	android/os/Parcel:recycle	()V
    //   57: return
    //   58: aconst_null
    //   59: astore_1
    //   60: goto -35 -> 25
    //   63: astore_1
    //   64: aload_3
    //   65: invokevirtual 62	android/os/Parcel:recycle	()V
    //   68: aload_2
    //   69: invokevirtual 62	android/os/Parcel:recycle	()V
    //   72: aload_1
    //   73: athrow
    // Local variable table:
    //   start	length	slot	name	signature
    //   0	74	0	this	a
    //   0	74	1	paramj	j
    //   3	66	2	localParcel1	Parcel
    //   7	58	3	localParcel2	Parcel
    // Exception table:
    //   from	to	target	type
    //   8	14	63	finally
    //   18	25	63	finally
    //   25	49	63	finally
  }
  
  /* Error */
  public void setOnMapLoadedCallback(k paramk)
  {
    // Byte code:
    //   0: invokestatic 24	android/os/Parcel:obtain	()Landroid/os/Parcel;
    //   3: astore_2
    //   4: invokestatic 24	android/os/Parcel:obtain	()Landroid/os/Parcel;
    //   7: astore_3
    //   8: aload_2
    //   9: ldc 26
    //   11: invokevirtual 30	android/os/Parcel:writeInterfaceToken	(Ljava/lang/String;)V
    //   14: aload_1
    //   15: ifnull +43 -> 58
    //   18: aload_1
    //   19: invokeinterface 292 1 0
    //   24: astore_1
    //   25: aload_2
    //   26: aload_1
    //   27: invokevirtual 137	android/os/Parcel:writeStrongBinder	(Landroid/os/IBinder;)V
    //   30: aload_0
    //   31: getfield 15	com/google/android/gms/maps/internal/IGoogleMapDelegate$a$a:le	Landroid/os/IBinder;
    //   34: bipush 42
    //   36: aload_2
    //   37: aload_3
    //   38: iconst_0
    //   39: invokeinterface 46 5 0
    //   44: pop
    //   45: aload_3
    //   46: invokevirtual 49	android/os/Parcel:readException	()V
    //   49: aload_3
    //   50: invokevirtual 62	android/os/Parcel:recycle	()V
    //   53: aload_2
    //   54: invokevirtual 62	android/os/Parcel:recycle	()V
    //   57: return
    //   58: aconst_null
    //   59: astore_1
    //   60: goto -35 -> 25
    //   63: astore_1
    //   64: aload_3
    //   65: invokevirtual 62	android/os/Parcel:recycle	()V
    //   68: aload_2
    //   69: invokevirtual 62	android/os/Parcel:recycle	()V
    //   72: aload_1
    //   73: athrow
    // Local variable table:
    //   start	length	slot	name	signature
    //   0	74	0	this	a
    //   0	74	1	paramk	k
    //   3	66	2	localParcel1	Parcel
    //   7	58	3	localParcel2	Parcel
    // Exception table:
    //   from	to	target	type
    //   8	14	63	finally
    //   18	25	63	finally
    //   25	49	63	finally
  }
  
  /* Error */
  public void setOnMapLongClickListener(l paraml)
  {
    // Byte code:
    //   0: invokestatic 24	android/os/Parcel:obtain	()Landroid/os/Parcel;
    //   3: astore_2
    //   4: invokestatic 24	android/os/Parcel:obtain	()Landroid/os/Parcel;
    //   7: astore_3
    //   8: aload_2
    //   9: ldc 26
    //   11: invokevirtual 30	android/os/Parcel:writeInterfaceToken	(Ljava/lang/String;)V
    //   14: aload_1
    //   15: ifnull +43 -> 58
    //   18: aload_1
    //   19: invokeinterface 297 1 0
    //   24: astore_1
    //   25: aload_2
    //   26: aload_1
    //   27: invokevirtual 137	android/os/Parcel:writeStrongBinder	(Landroid/os/IBinder;)V
    //   30: aload_0
    //   31: getfield 15	com/google/android/gms/maps/internal/IGoogleMapDelegate$a$a:le	Landroid/os/IBinder;
    //   34: bipush 29
    //   36: aload_2
    //   37: aload_3
    //   38: iconst_0
    //   39: invokeinterface 46 5 0
    //   44: pop
    //   45: aload_3
    //   46: invokevirtual 49	android/os/Parcel:readException	()V
    //   49: aload_3
    //   50: invokevirtual 62	android/os/Parcel:recycle	()V
    //   53: aload_2
    //   54: invokevirtual 62	android/os/Parcel:recycle	()V
    //   57: return
    //   58: aconst_null
    //   59: astore_1
    //   60: goto -35 -> 25
    //   63: astore_1
    //   64: aload_3
    //   65: invokevirtual 62	android/os/Parcel:recycle	()V
    //   68: aload_2
    //   69: invokevirtual 62	android/os/Parcel:recycle	()V
    //   72: aload_1
    //   73: athrow
    // Local variable table:
    //   start	length	slot	name	signature
    //   0	74	0	this	a
    //   0	74	1	paraml	l
    //   3	66	2	localParcel1	Parcel
    //   7	58	3	localParcel2	Parcel
    // Exception table:
    //   from	to	target	type
    //   8	14	63	finally
    //   18	25	63	finally
    //   25	49	63	finally
  }
  
  /* Error */
  public void setOnMarkerClickListener(n paramn)
  {
    // Byte code:
    //   0: invokestatic 24	android/os/Parcel:obtain	()Landroid/os/Parcel;
    //   3: astore_2
    //   4: invokestatic 24	android/os/Parcel:obtain	()Landroid/os/Parcel;
    //   7: astore_3
    //   8: aload_2
    //   9: ldc 26
    //   11: invokevirtual 30	android/os/Parcel:writeInterfaceToken	(Ljava/lang/String;)V
    //   14: aload_1
    //   15: ifnull +43 -> 58
    //   18: aload_1
    //   19: invokeinterface 302 1 0
    //   24: astore_1
    //   25: aload_2
    //   26: aload_1
    //   27: invokevirtual 137	android/os/Parcel:writeStrongBinder	(Landroid/os/IBinder;)V
    //   30: aload_0
    //   31: getfield 15	com/google/android/gms/maps/internal/IGoogleMapDelegate$a$a:le	Landroid/os/IBinder;
    //   34: bipush 30
    //   36: aload_2
    //   37: aload_3
    //   38: iconst_0
    //   39: invokeinterface 46 5 0
    //   44: pop
    //   45: aload_3
    //   46: invokevirtual 49	android/os/Parcel:readException	()V
    //   49: aload_3
    //   50: invokevirtual 62	android/os/Parcel:recycle	()V
    //   53: aload_2
    //   54: invokevirtual 62	android/os/Parcel:recycle	()V
    //   57: return
    //   58: aconst_null
    //   59: astore_1
    //   60: goto -35 -> 25
    //   63: astore_1
    //   64: aload_3
    //   65: invokevirtual 62	android/os/Parcel:recycle	()V
    //   68: aload_2
    //   69: invokevirtual 62	android/os/Parcel:recycle	()V
    //   72: aload_1
    //   73: athrow
    // Local variable table:
    //   start	length	slot	name	signature
    //   0	74	0	this	a
    //   0	74	1	paramn	n
    //   3	66	2	localParcel1	Parcel
    //   7	58	3	localParcel2	Parcel
    // Exception table:
    //   from	to	target	type
    //   8	14	63	finally
    //   18	25	63	finally
    //   25	49	63	finally
  }
  
  /* Error */
  public void setOnMarkerDragListener(o paramo)
  {
    // Byte code:
    //   0: invokestatic 24	android/os/Parcel:obtain	()Landroid/os/Parcel;
    //   3: astore_2
    //   4: invokestatic 24	android/os/Parcel:obtain	()Landroid/os/Parcel;
    //   7: astore_3
    //   8: aload_2
    //   9: ldc 26
    //   11: invokevirtual 30	android/os/Parcel:writeInterfaceToken	(Ljava/lang/String;)V
    //   14: aload_1
    //   15: ifnull +43 -> 58
    //   18: aload_1
    //   19: invokeinterface 307 1 0
    //   24: astore_1
    //   25: aload_2
    //   26: aload_1
    //   27: invokevirtual 137	android/os/Parcel:writeStrongBinder	(Landroid/os/IBinder;)V
    //   30: aload_0
    //   31: getfield 15	com/google/android/gms/maps/internal/IGoogleMapDelegate$a$a:le	Landroid/os/IBinder;
    //   34: bipush 31
    //   36: aload_2
    //   37: aload_3
    //   38: iconst_0
    //   39: invokeinterface 46 5 0
    //   44: pop
    //   45: aload_3
    //   46: invokevirtual 49	android/os/Parcel:readException	()V
    //   49: aload_3
    //   50: invokevirtual 62	android/os/Parcel:recycle	()V
    //   53: aload_2
    //   54: invokevirtual 62	android/os/Parcel:recycle	()V
    //   57: return
    //   58: aconst_null
    //   59: astore_1
    //   60: goto -35 -> 25
    //   63: astore_1
    //   64: aload_3
    //   65: invokevirtual 62	android/os/Parcel:recycle	()V
    //   68: aload_2
    //   69: invokevirtual 62	android/os/Parcel:recycle	()V
    //   72: aload_1
    //   73: athrow
    // Local variable table:
    //   start	length	slot	name	signature
    //   0	74	0	this	a
    //   0	74	1	paramo	o
    //   3	66	2	localParcel1	Parcel
    //   7	58	3	localParcel2	Parcel
    // Exception table:
    //   from	to	target	type
    //   8	14	63	finally
    //   18	25	63	finally
    //   25	49	63	finally
  }
  
  /* Error */
  public void setOnMyLocationButtonClickListener(p paramp)
  {
    // Byte code:
    //   0: invokestatic 24	android/os/Parcel:obtain	()Landroid/os/Parcel;
    //   3: astore_2
    //   4: invokestatic 24	android/os/Parcel:obtain	()Landroid/os/Parcel;
    //   7: astore_3
    //   8: aload_2
    //   9: ldc 26
    //   11: invokevirtual 30	android/os/Parcel:writeInterfaceToken	(Ljava/lang/String;)V
    //   14: aload_1
    //   15: ifnull +43 -> 58
    //   18: aload_1
    //   19: invokeinterface 312 1 0
    //   24: astore_1
    //   25: aload_2
    //   26: aload_1
    //   27: invokevirtual 137	android/os/Parcel:writeStrongBinder	(Landroid/os/IBinder;)V
    //   30: aload_0
    //   31: getfield 15	com/google/android/gms/maps/internal/IGoogleMapDelegate$a$a:le	Landroid/os/IBinder;
    //   34: bipush 37
    //   36: aload_2
    //   37: aload_3
    //   38: iconst_0
    //   39: invokeinterface 46 5 0
    //   44: pop
    //   45: aload_3
    //   46: invokevirtual 49	android/os/Parcel:readException	()V
    //   49: aload_3
    //   50: invokevirtual 62	android/os/Parcel:recycle	()V
    //   53: aload_2
    //   54: invokevirtual 62	android/os/Parcel:recycle	()V
    //   57: return
    //   58: aconst_null
    //   59: astore_1
    //   60: goto -35 -> 25
    //   63: astore_1
    //   64: aload_3
    //   65: invokevirtual 62	android/os/Parcel:recycle	()V
    //   68: aload_2
    //   69: invokevirtual 62	android/os/Parcel:recycle	()V
    //   72: aload_1
    //   73: athrow
    // Local variable table:
    //   start	length	slot	name	signature
    //   0	74	0	this	a
    //   0	74	1	paramp	p
    //   3	66	2	localParcel1	Parcel
    //   7	58	3	localParcel2	Parcel
    // Exception table:
    //   from	to	target	type
    //   8	14	63	finally
    //   18	25	63	finally
    //   25	49	63	finally
  }
  
  /* Error */
  public void setOnMyLocationChangeListener(q paramq)
  {
    // Byte code:
    //   0: invokestatic 24	android/os/Parcel:obtain	()Landroid/os/Parcel;
    //   3: astore_2
    //   4: invokestatic 24	android/os/Parcel:obtain	()Landroid/os/Parcel;
    //   7: astore_3
    //   8: aload_2
    //   9: ldc 26
    //   11: invokevirtual 30	android/os/Parcel:writeInterfaceToken	(Ljava/lang/String;)V
    //   14: aload_1
    //   15: ifnull +43 -> 58
    //   18: aload_1
    //   19: invokeinterface 317 1 0
    //   24: astore_1
    //   25: aload_2
    //   26: aload_1
    //   27: invokevirtual 137	android/os/Parcel:writeStrongBinder	(Landroid/os/IBinder;)V
    //   30: aload_0
    //   31: getfield 15	com/google/android/gms/maps/internal/IGoogleMapDelegate$a$a:le	Landroid/os/IBinder;
    //   34: bipush 36
    //   36: aload_2
    //   37: aload_3
    //   38: iconst_0
    //   39: invokeinterface 46 5 0
    //   44: pop
    //   45: aload_3
    //   46: invokevirtual 49	android/os/Parcel:readException	()V
    //   49: aload_3
    //   50: invokevirtual 62	android/os/Parcel:recycle	()V
    //   53: aload_2
    //   54: invokevirtual 62	android/os/Parcel:recycle	()V
    //   57: return
    //   58: aconst_null
    //   59: astore_1
    //   60: goto -35 -> 25
    //   63: astore_1
    //   64: aload_3
    //   65: invokevirtual 62	android/os/Parcel:recycle	()V
    //   68: aload_2
    //   69: invokevirtual 62	android/os/Parcel:recycle	()V
    //   72: aload_1
    //   73: athrow
    // Local variable table:
    //   start	length	slot	name	signature
    //   0	74	0	this	a
    //   0	74	1	paramq	q
    //   3	66	2	localParcel1	Parcel
    //   7	58	3	localParcel2	Parcel
    // Exception table:
    //   from	to	target	type
    //   8	14	63	finally
    //   18	25	63	finally
    //   25	49	63	finally
  }
  
  public void setPadding(int paramInt1, int paramInt2, int paramInt3, int paramInt4)
  {
    Parcel localParcel1 = Parcel.obtain();
    Parcel localParcel2 = Parcel.obtain();
    try
    {
      localParcel1.writeInterfaceToken("com.google.android.gms.maps.internal.IGoogleMapDelegate");
      localParcel1.writeInt(paramInt1);
      localParcel1.writeInt(paramInt2);
      localParcel1.writeInt(paramInt3);
      localParcel1.writeInt(paramInt4);
      le.transact(39, localParcel1, localParcel2, 0);
      localParcel2.readException();
      return;
    }
    finally
    {
      localParcel2.recycle();
      localParcel1.recycle();
    }
  }
  
  public void setTrafficEnabled(boolean paramBoolean)
  {
    int i = 0;
    Parcel localParcel1 = Parcel.obtain();
    Parcel localParcel2 = Parcel.obtain();
    try
    {
      localParcel1.writeInterfaceToken("com.google.android.gms.maps.internal.IGoogleMapDelegate");
      if (paramBoolean) {
        i = 1;
      }
      localParcel1.writeInt(i);
      le.transact(18, localParcel1, localParcel2, 0);
      localParcel2.readException();
      return;
    }
    finally
    {
      localParcel2.recycle();
      localParcel1.recycle();
    }
  }
  
  /* Error */
  public void snapshot(v paramv, com.google.android.gms.dynamic.d paramd)
  {
    // Byte code:
    //   0: aconst_null
    //   1: astore_3
    //   2: invokestatic 24	android/os/Parcel:obtain	()Landroid/os/Parcel;
    //   5: astore 4
    //   7: invokestatic 24	android/os/Parcel:obtain	()Landroid/os/Parcel;
    //   10: astore 5
    //   12: aload 4
    //   14: ldc 26
    //   16: invokevirtual 30	android/os/Parcel:writeInterfaceToken	(Ljava/lang/String;)V
    //   19: aload_1
    //   20: ifnull +68 -> 88
    //   23: aload_1
    //   24: invokeinterface 325 1 0
    //   29: astore_1
    //   30: aload 4
    //   32: aload_1
    //   33: invokevirtual 137	android/os/Parcel:writeStrongBinder	(Landroid/os/IBinder;)V
    //   36: aload_3
    //   37: astore_1
    //   38: aload_2
    //   39: ifnull +10 -> 49
    //   42: aload_2
    //   43: invokeinterface 134 1 0
    //   48: astore_1
    //   49: aload 4
    //   51: aload_1
    //   52: invokevirtual 137	android/os/Parcel:writeStrongBinder	(Landroid/os/IBinder;)V
    //   55: aload_0
    //   56: getfield 15	com/google/android/gms/maps/internal/IGoogleMapDelegate$a$a:le	Landroid/os/IBinder;
    //   59: bipush 38
    //   61: aload 4
    //   63: aload 5
    //   65: iconst_0
    //   66: invokeinterface 46 5 0
    //   71: pop
    //   72: aload 5
    //   74: invokevirtual 49	android/os/Parcel:readException	()V
    //   77: aload 5
    //   79: invokevirtual 62	android/os/Parcel:recycle	()V
    //   82: aload 4
    //   84: invokevirtual 62	android/os/Parcel:recycle	()V
    //   87: return
    //   88: aconst_null
    //   89: astore_1
    //   90: goto -60 -> 30
    //   93: astore_1
    //   94: aload 5
    //   96: invokevirtual 62	android/os/Parcel:recycle	()V
    //   99: aload 4
    //   101: invokevirtual 62	android/os/Parcel:recycle	()V
    //   104: aload_1
    //   105: athrow
    // Local variable table:
    //   start	length	slot	name	signature
    //   0	106	0	this	a
    //   0	106	1	paramv	v
    //   0	106	2	paramd	com.google.android.gms.dynamic.d
    //   1	36	3	localObject	Object
    //   5	95	4	localParcel1	Parcel
    //   10	85	5	localParcel2	Parcel
    // Exception table:
    //   from	to	target	type
    //   12	19	93	finally
    //   23	30	93	finally
    //   30	36	93	finally
    //   42	49	93	finally
    //   49	77	93	finally
  }
  
  public void stopAnimation()
  {
    Parcel localParcel1 = Parcel.obtain();
    Parcel localParcel2 = Parcel.obtain();
    try
    {
      localParcel1.writeInterfaceToken("com.google.android.gms.maps.internal.IGoogleMapDelegate");
      le.transact(8, localParcel1, localParcel2, 0);
      localParcel2.readException();
      return;
    }
    finally
    {
      localParcel2.recycle();
      localParcel1.recycle();
    }
  }
  
  public boolean useViewLifecycleWhenInFragment()
  {
    boolean bool = false;
    Parcel localParcel1 = Parcel.obtain();
    Parcel localParcel2 = Parcel.obtain();
    try
    {
      localParcel1.writeInterfaceToken("com.google.android.gms.maps.internal.IGoogleMapDelegate");
      le.transact(59, localParcel1, localParcel2, 0);
      localParcel2.readException();
      int i = localParcel2.readInt();
      if (i != 0) {
        bool = true;
      }
      return bool;
    }
    finally
    {
      localParcel2.recycle();
      localParcel1.recycle();
    }
  }
}

/* Location:
 * Qualified Name:     com.google.android.gms.maps.internal.IGoogleMapDelegate.a.a
 * Java Class Version: 6 (50.0)
 * JD-Core Version:    0.7.1
 */