package com.yelp.android.ui.util;

import android.view.View.OnClickListener;
import java.lang.reflect.Method;

class SlightlyLessBrokenLinearLayout$1
  implements View.OnClickListener
{
  private Method c;
  
  SlightlyLessBrokenLinearLayout$1(SlightlyLessBrokenLinearLayout paramSlightlyLessBrokenLinearLayout, String paramString) {}
  
  /* Error */
  public void onClick(android.view.View paramView)
  {
    // Byte code:
    //   0: aload_0
    //   1: getfield 36	com/yelp/android/ui/util/SlightlyLessBrokenLinearLayout$1:c	Ljava/lang/reflect/Method;
    //   4: ifnonnull +33 -> 37
    //   7: aload_0
    //   8: aload_0
    //   9: getfield 20	com/yelp/android/ui/util/SlightlyLessBrokenLinearLayout$1:b	Lcom/yelp/android/ui/util/SlightlyLessBrokenLinearLayout;
    //   12: invokevirtual 40	com/yelp/android/ui/util/SlightlyLessBrokenLinearLayout:getContext	()Landroid/content/Context;
    //   15: invokevirtual 44	java/lang/Object:getClass	()Ljava/lang/Class;
    //   18: aload_0
    //   19: getfield 22	com/yelp/android/ui/util/SlightlyLessBrokenLinearLayout$1:a	Ljava/lang/String;
    //   22: iconst_1
    //   23: anewarray 46	java/lang/Class
    //   26: dup
    //   27: iconst_0
    //   28: ldc 48
    //   30: aastore
    //   31: invokevirtual 52	java/lang/Class:getMethod	(Ljava/lang/String;[Ljava/lang/Class;)Ljava/lang/reflect/Method;
    //   34: putfield 36	com/yelp/android/ui/util/SlightlyLessBrokenLinearLayout$1:c	Ljava/lang/reflect/Method;
    //   37: aload_0
    //   38: getfield 36	com/yelp/android/ui/util/SlightlyLessBrokenLinearLayout$1:c	Ljava/lang/reflect/Method;
    //   41: aload_0
    //   42: getfield 20	com/yelp/android/ui/util/SlightlyLessBrokenLinearLayout$1:b	Lcom/yelp/android/ui/util/SlightlyLessBrokenLinearLayout;
    //   45: invokevirtual 40	com/yelp/android/ui/util/SlightlyLessBrokenLinearLayout:getContext	()Landroid/content/Context;
    //   48: iconst_1
    //   49: anewarray 4	java/lang/Object
    //   52: dup
    //   53: iconst_0
    //   54: aload_0
    //   55: aastore
    //   56: invokevirtual 58	java/lang/reflect/Method:invoke	(Ljava/lang/Object;[Ljava/lang/Object;)Ljava/lang/Object;
    //   59: pop
    //   60: return
    //   61: astore_3
    //   62: aload_0
    //   63: getfield 20	com/yelp/android/ui/util/SlightlyLessBrokenLinearLayout$1:b	Lcom/yelp/android/ui/util/SlightlyLessBrokenLinearLayout;
    //   66: invokevirtual 62	com/yelp/android/ui/util/SlightlyLessBrokenLinearLayout:getId	()I
    //   69: istore_2
    //   70: iload_2
    //   71: iconst_m1
    //   72: if_icmpne +76 -> 148
    //   75: ldc 64
    //   77: astore_1
    //   78: new 66	java/lang/IllegalStateException
    //   81: dup
    //   82: new 68	java/lang/StringBuilder
    //   85: dup
    //   86: invokespecial 69	java/lang/StringBuilder:<init>	()V
    //   89: ldc 71
    //   91: invokevirtual 75	java/lang/StringBuilder:append	(Ljava/lang/String;)Ljava/lang/StringBuilder;
    //   94: aload_0
    //   95: getfield 22	com/yelp/android/ui/util/SlightlyLessBrokenLinearLayout$1:a	Ljava/lang/String;
    //   98: invokevirtual 75	java/lang/StringBuilder:append	(Ljava/lang/String;)Ljava/lang/StringBuilder;
    //   101: ldc 77
    //   103: invokevirtual 75	java/lang/StringBuilder:append	(Ljava/lang/String;)Ljava/lang/StringBuilder;
    //   106: aload_0
    //   107: getfield 20	com/yelp/android/ui/util/SlightlyLessBrokenLinearLayout$1:b	Lcom/yelp/android/ui/util/SlightlyLessBrokenLinearLayout;
    //   110: invokevirtual 40	com/yelp/android/ui/util/SlightlyLessBrokenLinearLayout:getContext	()Landroid/content/Context;
    //   113: invokevirtual 44	java/lang/Object:getClass	()Ljava/lang/Class;
    //   116: invokevirtual 80	java/lang/StringBuilder:append	(Ljava/lang/Object;)Ljava/lang/StringBuilder;
    //   119: ldc 82
    //   121: invokevirtual 75	java/lang/StringBuilder:append	(Ljava/lang/String;)Ljava/lang/StringBuilder;
    //   124: ldc 84
    //   126: invokevirtual 75	java/lang/StringBuilder:append	(Ljava/lang/String;)Ljava/lang/StringBuilder;
    //   129: aload_0
    //   130: invokevirtual 44	java/lang/Object:getClass	()Ljava/lang/Class;
    //   133: invokevirtual 80	java/lang/StringBuilder:append	(Ljava/lang/Object;)Ljava/lang/StringBuilder;
    //   136: aload_1
    //   137: invokevirtual 75	java/lang/StringBuilder:append	(Ljava/lang/String;)Ljava/lang/StringBuilder;
    //   140: invokevirtual 88	java/lang/StringBuilder:toString	()Ljava/lang/String;
    //   143: aload_3
    //   144: invokespecial 91	java/lang/IllegalStateException:<init>	(Ljava/lang/String;Ljava/lang/Throwable;)V
    //   147: athrow
    //   148: new 68	java/lang/StringBuilder
    //   151: dup
    //   152: invokespecial 69	java/lang/StringBuilder:<init>	()V
    //   155: ldc 93
    //   157: invokevirtual 75	java/lang/StringBuilder:append	(Ljava/lang/String;)Ljava/lang/StringBuilder;
    //   160: aload_0
    //   161: getfield 20	com/yelp/android/ui/util/SlightlyLessBrokenLinearLayout$1:b	Lcom/yelp/android/ui/util/SlightlyLessBrokenLinearLayout;
    //   164: invokevirtual 40	com/yelp/android/ui/util/SlightlyLessBrokenLinearLayout:getContext	()Landroid/content/Context;
    //   167: invokevirtual 99	android/content/Context:getResources	()Landroid/content/res/Resources;
    //   170: iload_2
    //   171: invokevirtual 105	android/content/res/Resources:getResourceEntryName	(I)Ljava/lang/String;
    //   174: invokevirtual 75	java/lang/StringBuilder:append	(Ljava/lang/String;)Ljava/lang/StringBuilder;
    //   177: ldc 107
    //   179: invokevirtual 75	java/lang/StringBuilder:append	(Ljava/lang/String;)Ljava/lang/StringBuilder;
    //   182: invokevirtual 88	java/lang/StringBuilder:toString	()Ljava/lang/String;
    //   185: astore_1
    //   186: goto -108 -> 78
    //   189: astore_1
    //   190: new 66	java/lang/IllegalStateException
    //   193: dup
    //   194: ldc 109
    //   196: aload_1
    //   197: invokespecial 91	java/lang/IllegalStateException:<init>	(Ljava/lang/String;Ljava/lang/Throwable;)V
    //   200: athrow
    //   201: astore_1
    //   202: new 66	java/lang/IllegalStateException
    //   205: dup
    //   206: ldc 111
    //   208: aload_1
    //   209: invokespecial 91	java/lang/IllegalStateException:<init>	(Ljava/lang/String;Ljava/lang/Throwable;)V
    //   212: athrow
    // Local variable table:
    //   start	length	slot	name	signature
    //   0	213	0	this	1
    //   0	213	1	paramView	android.view.View
    //   69	102	2	i	int
    //   61	83	3	localNoSuchMethodException	NoSuchMethodException
    // Exception table:
    //   from	to	target	type
    //   7	37	61	java/lang/NoSuchMethodException
    //   37	60	189	java/lang/IllegalAccessException
    //   37	60	201	java/lang/reflect/InvocationTargetException
  }
}

/* Location:
 * Qualified Name:     com.yelp.android.ui.util.SlightlyLessBrokenLinearLayout.1
 * Java Class Version: 6 (50.0)
 * JD-Core Version:    0.7.1
 */