package com.google.android.gms.measurement.internal;

import com.google.android.gms.common.internal.zzx;
import java.net.URL;
import java.util.Map;

class aa$c
  implements Runnable
{
  private final URL b;
  private final byte[] c;
  private final aa.a d;
  private final String e;
  private final Map<String, String> f;
  
  public aa$c(String paramString, URL paramURL, byte[] paramArrayOfByte, Map<String, String> paramMap, aa.a parama)
  {
    zzx.zzcM(paramURL);
    zzx.zzz(paramArrayOfByte);
    Object localObject;
    zzx.zzz(localObject);
    b = paramArrayOfByte;
    c = paramMap;
    d = ((aa.a)localObject);
    e = paramURL;
    f = parama;
  }
  
  /* Error */
  public void run()
  {
    // Byte code:
    //   0: aload_0
    //   1: getfield 25	com/google/android/gms/measurement/internal/aa$c:a	Lcom/google/android/gms/measurement/internal/aa;
    //   4: invokevirtual 56	com/google/android/gms/measurement/internal/aa:e	()V
    //   7: iconst_0
    //   8: istore_3
    //   9: iconst_0
    //   10: istore 4
    //   12: iconst_0
    //   13: istore 5
    //   15: aload_0
    //   16: getfield 25	com/google/android/gms/measurement/internal/aa$c:a	Lcom/google/android/gms/measurement/internal/aa;
    //   19: aload_0
    //   20: getfield 40	com/google/android/gms/measurement/internal/aa$c:b	Ljava/net/URL;
    //   23: invokevirtual 59	com/google/android/gms/measurement/internal/aa:a	(Ljava/net/URL;)Ljava/net/HttpURLConnection;
    //   26: astore 6
    //   28: iload 5
    //   30: istore_2
    //   31: iload 4
    //   33: istore_1
    //   34: aload_0
    //   35: getfield 48	com/google/android/gms/measurement/internal/aa$c:f	Ljava/util/Map;
    //   38: ifnull +159 -> 197
    //   41: iload 5
    //   43: istore_2
    //   44: iload 4
    //   46: istore_1
    //   47: aload_0
    //   48: getfield 48	com/google/android/gms/measurement/internal/aa$c:f	Ljava/util/Map;
    //   51: invokeinterface 65 1 0
    //   56: invokeinterface 71 1 0
    //   61: astore 7
    //   63: iload 5
    //   65: istore_2
    //   66: iload 4
    //   68: istore_1
    //   69: aload 7
    //   71: invokeinterface 77 1 0
    //   76: ifeq +121 -> 197
    //   79: iload 5
    //   81: istore_2
    //   82: iload 4
    //   84: istore_1
    //   85: aload 7
    //   87: invokeinterface 81 1 0
    //   92: checkcast 83	java/util/Map$Entry
    //   95: astore 8
    //   97: iload 5
    //   99: istore_2
    //   100: iload 4
    //   102: istore_1
    //   103: aload 6
    //   105: aload 8
    //   107: invokeinterface 86 1 0
    //   112: checkcast 88	java/lang/String
    //   115: aload 8
    //   117: invokeinterface 91 1 0
    //   122: checkcast 88	java/lang/String
    //   125: invokevirtual 97	java/net/HttpURLConnection:addRequestProperty	(Ljava/lang/String;Ljava/lang/String;)V
    //   128: goto -65 -> 63
    //   131: astore 8
    //   133: iload_2
    //   134: istore_1
    //   135: aconst_null
    //   136: astore 9
    //   138: aload 6
    //   140: astore 7
    //   142: aload 9
    //   144: astore 6
    //   146: aload 6
    //   148: ifnull +8 -> 156
    //   151: aload 6
    //   153: invokevirtual 102	java/io/OutputStream:close	()V
    //   156: aload 7
    //   158: ifnull +8 -> 166
    //   161: aload 7
    //   163: invokevirtual 105	java/net/HttpURLConnection:disconnect	()V
    //   166: aload_0
    //   167: getfield 25	com/google/android/gms/measurement/internal/aa$c:a	Lcom/google/android/gms/measurement/internal/aa;
    //   170: invokevirtual 109	com/google/android/gms/measurement/internal/aa:r	()Lcom/google/android/gms/measurement/internal/af;
    //   173: new 111	com/google/android/gms/measurement/internal/aa$b
    //   176: dup
    //   177: aload_0
    //   178: getfield 46	com/google/android/gms/measurement/internal/aa$c:e	Ljava/lang/String;
    //   181: aload_0
    //   182: getfield 44	com/google/android/gms/measurement/internal/aa$c:d	Lcom/google/android/gms/measurement/internal/aa$a;
    //   185: iload_1
    //   186: aload 8
    //   188: aconst_null
    //   189: aconst_null
    //   190: invokespecial 114	com/google/android/gms/measurement/internal/aa$b:<init>	(Ljava/lang/String;Lcom/google/android/gms/measurement/internal/aa$a;ILjava/lang/Throwable;[BLcom/google/android/gms/measurement/internal/aa$1;)V
    //   193: invokevirtual 119	com/google/android/gms/measurement/internal/af:a	(Ljava/lang/Runnable;)V
    //   196: return
    //   197: iload 5
    //   199: istore_2
    //   200: iload 4
    //   202: istore_1
    //   203: aload_0
    //   204: getfield 42	com/google/android/gms/measurement/internal/aa$c:c	[B
    //   207: ifnull +404 -> 611
    //   210: iload 5
    //   212: istore_2
    //   213: iload 4
    //   215: istore_1
    //   216: aload_0
    //   217: getfield 25	com/google/android/gms/measurement/internal/aa$c:a	Lcom/google/android/gms/measurement/internal/aa;
    //   220: invokevirtual 123	com/google/android/gms/measurement/internal/aa:o	()Lcom/google/android/gms/measurement/internal/k;
    //   223: aload_0
    //   224: getfield 42	com/google/android/gms/measurement/internal/aa$c:c	[B
    //   227: invokevirtual 128	com/google/android/gms/measurement/internal/k:a	([B)[B
    //   230: astore 8
    //   232: iload 5
    //   234: istore_2
    //   235: iload 4
    //   237: istore_1
    //   238: aload_0
    //   239: getfield 25	com/google/android/gms/measurement/internal/aa$c:a	Lcom/google/android/gms/measurement/internal/aa;
    //   242: invokevirtual 132	com/google/android/gms/measurement/internal/aa:s	()Lcom/google/android/gms/measurement/internal/z;
    //   245: invokevirtual 138	com/google/android/gms/measurement/internal/z:z	()Lcom/google/android/gms/measurement/internal/z$a;
    //   248: ldc -116
    //   250: aload 8
    //   252: arraylength
    //   253: invokestatic 146	java/lang/Integer:valueOf	(I)Ljava/lang/Integer;
    //   256: invokevirtual 151	com/google/android/gms/measurement/internal/z$a:a	(Ljava/lang/String;Ljava/lang/Object;)V
    //   259: iload 5
    //   261: istore_2
    //   262: iload 4
    //   264: istore_1
    //   265: aload 6
    //   267: iconst_1
    //   268: invokevirtual 155	java/net/HttpURLConnection:setDoOutput	(Z)V
    //   271: iload 5
    //   273: istore_2
    //   274: iload 4
    //   276: istore_1
    //   277: aload 6
    //   279: ldc -99
    //   281: ldc -97
    //   283: invokevirtual 97	java/net/HttpURLConnection:addRequestProperty	(Ljava/lang/String;Ljava/lang/String;)V
    //   286: iload 5
    //   288: istore_2
    //   289: iload 4
    //   291: istore_1
    //   292: aload 6
    //   294: aload 8
    //   296: arraylength
    //   297: invokevirtual 163	java/net/HttpURLConnection:setFixedLengthStreamingMode	(I)V
    //   300: iload 5
    //   302: istore_2
    //   303: iload 4
    //   305: istore_1
    //   306: aload 6
    //   308: invokevirtual 166	java/net/HttpURLConnection:connect	()V
    //   311: iload 5
    //   313: istore_2
    //   314: iload 4
    //   316: istore_1
    //   317: aload 6
    //   319: invokevirtual 170	java/net/HttpURLConnection:getOutputStream	()Ljava/io/OutputStream;
    //   322: astore 7
    //   324: aload 7
    //   326: aload 8
    //   328: invokevirtual 174	java/io/OutputStream:write	([B)V
    //   331: aload 7
    //   333: invokevirtual 102	java/io/OutputStream:close	()V
    //   336: iload 5
    //   338: istore_2
    //   339: iload 4
    //   341: istore_1
    //   342: aload 6
    //   344: invokevirtual 178	java/net/HttpURLConnection:getResponseCode	()I
    //   347: istore_3
    //   348: iload_3
    //   349: istore_2
    //   350: iload_3
    //   351: istore_1
    //   352: aload_0
    //   353: getfield 25	com/google/android/gms/measurement/internal/aa$c:a	Lcom/google/android/gms/measurement/internal/aa;
    //   356: aload 6
    //   358: invokestatic 181	com/google/android/gms/measurement/internal/aa:a	(Lcom/google/android/gms/measurement/internal/aa;Ljava/net/HttpURLConnection;)[B
    //   361: astore 8
    //   363: iconst_0
    //   364: ifeq +11 -> 375
    //   367: new 183	java/lang/NullPointerException
    //   370: dup
    //   371: invokespecial 184	java/lang/NullPointerException:<init>	()V
    //   374: athrow
    //   375: aload 6
    //   377: ifnull +8 -> 385
    //   380: aload 6
    //   382: invokevirtual 105	java/net/HttpURLConnection:disconnect	()V
    //   385: aload_0
    //   386: getfield 25	com/google/android/gms/measurement/internal/aa$c:a	Lcom/google/android/gms/measurement/internal/aa;
    //   389: invokevirtual 109	com/google/android/gms/measurement/internal/aa:r	()Lcom/google/android/gms/measurement/internal/af;
    //   392: new 111	com/google/android/gms/measurement/internal/aa$b
    //   395: dup
    //   396: aload_0
    //   397: getfield 46	com/google/android/gms/measurement/internal/aa$c:e	Ljava/lang/String;
    //   400: aload_0
    //   401: getfield 44	com/google/android/gms/measurement/internal/aa$c:d	Lcom/google/android/gms/measurement/internal/aa$a;
    //   404: iload_3
    //   405: aconst_null
    //   406: aload 8
    //   408: aconst_null
    //   409: invokespecial 114	com/google/android/gms/measurement/internal/aa$b:<init>	(Ljava/lang/String;Lcom/google/android/gms/measurement/internal/aa$a;ILjava/lang/Throwable;[BLcom/google/android/gms/measurement/internal/aa$1;)V
    //   412: invokevirtual 119	com/google/android/gms/measurement/internal/af:a	(Ljava/lang/Runnable;)V
    //   415: return
    //   416: astore 7
    //   418: aload_0
    //   419: getfield 25	com/google/android/gms/measurement/internal/aa$c:a	Lcom/google/android/gms/measurement/internal/aa;
    //   422: invokevirtual 132	com/google/android/gms/measurement/internal/aa:s	()Lcom/google/android/gms/measurement/internal/z;
    //   425: invokevirtual 186	com/google/android/gms/measurement/internal/z:b	()Lcom/google/android/gms/measurement/internal/z$a;
    //   428: ldc -68
    //   430: aload 7
    //   432: invokevirtual 151	com/google/android/gms/measurement/internal/z$a:a	(Ljava/lang/String;Ljava/lang/Object;)V
    //   435: goto -60 -> 375
    //   438: astore 6
    //   440: aload_0
    //   441: getfield 25	com/google/android/gms/measurement/internal/aa$c:a	Lcom/google/android/gms/measurement/internal/aa;
    //   444: invokevirtual 132	com/google/android/gms/measurement/internal/aa:s	()Lcom/google/android/gms/measurement/internal/z;
    //   447: invokevirtual 186	com/google/android/gms/measurement/internal/z:b	()Lcom/google/android/gms/measurement/internal/z$a;
    //   450: ldc -68
    //   452: aload 6
    //   454: invokevirtual 151	com/google/android/gms/measurement/internal/z$a:a	(Ljava/lang/String;Ljava/lang/Object;)V
    //   457: goto -301 -> 156
    //   460: astore 6
    //   462: aconst_null
    //   463: astore 8
    //   465: aconst_null
    //   466: astore 7
    //   468: iload_3
    //   469: istore_1
    //   470: aload 7
    //   472: ifnull +8 -> 480
    //   475: aload 7
    //   477: invokevirtual 102	java/io/OutputStream:close	()V
    //   480: aload 8
    //   482: ifnull +8 -> 490
    //   485: aload 8
    //   487: invokevirtual 105	java/net/HttpURLConnection:disconnect	()V
    //   490: aload_0
    //   491: getfield 25	com/google/android/gms/measurement/internal/aa$c:a	Lcom/google/android/gms/measurement/internal/aa;
    //   494: invokevirtual 109	com/google/android/gms/measurement/internal/aa:r	()Lcom/google/android/gms/measurement/internal/af;
    //   497: new 111	com/google/android/gms/measurement/internal/aa$b
    //   500: dup
    //   501: aload_0
    //   502: getfield 46	com/google/android/gms/measurement/internal/aa$c:e	Ljava/lang/String;
    //   505: aload_0
    //   506: getfield 44	com/google/android/gms/measurement/internal/aa$c:d	Lcom/google/android/gms/measurement/internal/aa$a;
    //   509: iload_1
    //   510: aconst_null
    //   511: aconst_null
    //   512: aconst_null
    //   513: invokespecial 114	com/google/android/gms/measurement/internal/aa$b:<init>	(Ljava/lang/String;Lcom/google/android/gms/measurement/internal/aa$a;ILjava/lang/Throwable;[BLcom/google/android/gms/measurement/internal/aa$1;)V
    //   516: invokevirtual 119	com/google/android/gms/measurement/internal/af:a	(Ljava/lang/Runnable;)V
    //   519: aload 6
    //   521: athrow
    //   522: astore 7
    //   524: aload_0
    //   525: getfield 25	com/google/android/gms/measurement/internal/aa$c:a	Lcom/google/android/gms/measurement/internal/aa;
    //   528: invokevirtual 132	com/google/android/gms/measurement/internal/aa:s	()Lcom/google/android/gms/measurement/internal/z;
    //   531: invokevirtual 186	com/google/android/gms/measurement/internal/z:b	()Lcom/google/android/gms/measurement/internal/z$a;
    //   534: ldc -68
    //   536: aload 7
    //   538: invokevirtual 151	com/google/android/gms/measurement/internal/z$a:a	(Ljava/lang/String;Ljava/lang/Object;)V
    //   541: goto -61 -> 480
    //   544: astore 9
    //   546: aconst_null
    //   547: astore 7
    //   549: aload 6
    //   551: astore 8
    //   553: aload 9
    //   555: astore 6
    //   557: goto -87 -> 470
    //   560: astore 9
    //   562: aload 6
    //   564: astore 8
    //   566: iload_3
    //   567: istore_1
    //   568: aload 9
    //   570: astore 6
    //   572: goto -102 -> 470
    //   575: astore 8
    //   577: iconst_0
    //   578: istore_1
    //   579: aconst_null
    //   580: astore 6
    //   582: aconst_null
    //   583: astore 7
    //   585: goto -439 -> 146
    //   588: astore 9
    //   590: iconst_0
    //   591: istore_1
    //   592: aload 6
    //   594: astore 8
    //   596: aload 7
    //   598: astore 6
    //   600: aload 8
    //   602: astore 7
    //   604: aload 9
    //   606: astore 8
    //   608: goto -462 -> 146
    //   611: goto -275 -> 336
    // Local variable table:
    //   start	length	slot	name	signature
    //   0	614	0	this	c
    //   33	559	1	i	int
    //   30	320	2	j	int
    //   8	559	3	k	int
    //   10	330	4	m	int
    //   13	324	5	n	int
    //   26	355	6	localObject1	Object
    //   438	15	6	localIOException1	java.io.IOException
    //   460	90	6	localObject2	Object
    //   555	44	6	localObject3	Object
    //   61	271	7	localObject4	Object
    //   416	15	7	localIOException2	java.io.IOException
    //   466	10	7	localObject5	Object
    //   522	15	7	localIOException3	java.io.IOException
    //   547	56	7	localObject6	Object
    //   95	21	8	localEntry	java.util.Map.Entry
    //   131	56	8	localIOException4	java.io.IOException
    //   230	335	8	localObject7	Object
    //   575	1	8	localIOException5	java.io.IOException
    //   594	13	8	localObject8	Object
    //   136	7	9	localObject9	Object
    //   544	10	9	localObject10	Object
    //   560	9	9	localObject11	Object
    //   588	17	9	localIOException6	java.io.IOException
    // Exception table:
    //   from	to	target	type
    //   34	41	131	java/io/IOException
    //   47	63	131	java/io/IOException
    //   69	79	131	java/io/IOException
    //   85	97	131	java/io/IOException
    //   103	128	131	java/io/IOException
    //   203	210	131	java/io/IOException
    //   216	232	131	java/io/IOException
    //   238	259	131	java/io/IOException
    //   265	271	131	java/io/IOException
    //   277	286	131	java/io/IOException
    //   292	300	131	java/io/IOException
    //   306	311	131	java/io/IOException
    //   317	324	131	java/io/IOException
    //   342	348	131	java/io/IOException
    //   352	363	131	java/io/IOException
    //   367	375	416	java/io/IOException
    //   151	156	438	java/io/IOException
    //   15	28	460	finally
    //   475	480	522	java/io/IOException
    //   34	41	544	finally
    //   47	63	544	finally
    //   69	79	544	finally
    //   85	97	544	finally
    //   103	128	544	finally
    //   203	210	544	finally
    //   216	232	544	finally
    //   238	259	544	finally
    //   265	271	544	finally
    //   277	286	544	finally
    //   292	300	544	finally
    //   306	311	544	finally
    //   317	324	544	finally
    //   342	348	544	finally
    //   352	363	544	finally
    //   324	336	560	finally
    //   15	28	575	java/io/IOException
    //   324	336	588	java/io/IOException
  }
}

/* Location:
 * Qualified Name:     com.google.android.gms.measurement.internal.aa.c
 * Java Class Version: 6 (50.0)
 * JD-Core Version:    0.7.1
 */