package com.yelp.android.cx;

public final class k
  extends a<String>
{
  protected k()
  {
    super(true);
  }
  
  /* Error */
  protected final void a(java.net.HttpURLConnection paramHttpURLConnection, com.yelp.android.cw.c paramc, com.yelp.android.cw.d<String> paramd)
    throws java.lang.Exception
  {
    // Byte code:
    //   0: aload_2
    //   1: invokevirtual 21	com/yelp/android/cw/c:g	()Ljava/lang/String;
    //   4: astore 13
    //   6: aload 13
    //   8: ifnull +11 -> 19
    //   11: aload 13
    //   13: invokevirtual 27	java/lang/String:length	()I
    //   16: ifne +31 -> 47
    //   19: new 29	java/io/FileNotFoundException
    //   22: dup
    //   23: new 31	java/lang/StringBuilder
    //   26: dup
    //   27: invokespecial 33	java/lang/StringBuilder:<init>	()V
    //   30: aload 13
    //   32: invokevirtual 37	java/lang/StringBuilder:append	(Ljava/lang/String;)Ljava/lang/StringBuilder;
    //   35: ldc 39
    //   37: invokevirtual 37	java/lang/StringBuilder:append	(Ljava/lang/String;)Ljava/lang/StringBuilder;
    //   40: invokevirtual 42	java/lang/StringBuilder:toString	()Ljava/lang/String;
    //   43: invokespecial 45	java/io/FileNotFoundException:<init>	(Ljava/lang/String;)V
    //   46: athrow
    //   47: aload 13
    //   49: ldc 47
    //   51: invokevirtual 51	java/lang/String:startsWith	(Ljava/lang/String;)Z
    //   54: ifeq +107 -> 161
    //   57: aload 13
    //   59: bipush 7
    //   61: invokevirtual 55	java/lang/String:substring	(I)Ljava/lang/String;
    //   64: astore 12
    //   66: invokestatic 60	jp/line/android/sdk/c:a	()Ljp/line/android/sdk/a;
    //   69: invokeinterface 65 1 0
    //   74: invokevirtual 71	android/content/Context:getAssets	()Landroid/content/res/AssetManager;
    //   77: astore_2
    //   78: aload_2
    //   79: aload 12
    //   81: invokevirtual 77	android/content/res/AssetManager:openFd	(Ljava/lang/String;)Landroid/content/res/AssetFileDescriptor;
    //   84: invokevirtual 83	android/content/res/AssetFileDescriptor:getLength	()J
    //   87: lstore 7
    //   89: aload_2
    //   90: aload 12
    //   92: invokevirtual 87	android/content/res/AssetManager:open	(Ljava/lang/String;)Ljava/io/InputStream;
    //   95: astore_2
    //   96: aload 12
    //   98: ldc 89
    //   100: invokevirtual 93	java/lang/String:lastIndexOf	(Ljava/lang/String;)I
    //   103: istore 4
    //   105: iload 4
    //   107: ifle +51 -> 158
    //   110: aload 12
    //   112: iload 4
    //   114: invokevirtual 55	java/lang/String:substring	(I)Ljava/lang/String;
    //   117: astore 12
    //   119: aload_2
    //   120: ifnull +10 -> 130
    //   123: lload 7
    //   125: lconst_0
    //   126: lcmp
    //   127: ifge +87 -> 214
    //   130: new 29	java/io/FileNotFoundException
    //   133: dup
    //   134: new 31	java/lang/StringBuilder
    //   137: dup
    //   138: invokespecial 33	java/lang/StringBuilder:<init>	()V
    //   141: aload 13
    //   143: invokevirtual 37	java/lang/StringBuilder:append	(Ljava/lang/String;)Ljava/lang/StringBuilder;
    //   146: ldc 39
    //   148: invokevirtual 37	java/lang/StringBuilder:append	(Ljava/lang/String;)Ljava/lang/StringBuilder;
    //   151: invokevirtual 42	java/lang/StringBuilder:toString	()Ljava/lang/String;
    //   154: invokespecial 45	java/io/FileNotFoundException:<init>	(Ljava/lang/String;)V
    //   157: athrow
    //   158: goto -39 -> 119
    //   161: new 95	java/io/File
    //   164: dup
    //   165: aload 13
    //   167: invokespecial 96	java/io/File:<init>	(Ljava/lang/String;)V
    //   170: astore 12
    //   172: aload 12
    //   174: invokevirtual 100	java/io/File:isFile	()Z
    //   177: ifeq +331 -> 508
    //   180: aload 12
    //   182: invokevirtual 102	java/io/File:length	()J
    //   185: lstore 7
    //   187: new 104	java/io/BufferedInputStream
    //   190: dup
    //   191: new 106	java/io/FileInputStream
    //   194: dup
    //   195: aload 12
    //   197: invokespecial 109	java/io/FileInputStream:<init>	(Ljava/io/File;)V
    //   200: invokespecial 112	java/io/BufferedInputStream:<init>	(Ljava/io/InputStream;)V
    //   203: astore_2
    //   204: aload 12
    //   206: invokevirtual 115	java/io/File:getName	()Ljava/lang/String;
    //   209: astore 12
    //   211: goto -92 -> 119
    //   214: new 31	java/lang/StringBuilder
    //   217: dup
    //   218: invokespecial 33	java/lang/StringBuilder:<init>	()V
    //   221: astore 13
    //   223: aload 13
    //   225: ldc 117
    //   227: invokevirtual 37	java/lang/StringBuilder:append	(Ljava/lang/String;)Ljava/lang/StringBuilder;
    //   230: aload 12
    //   232: invokevirtual 37	java/lang/StringBuilder:append	(Ljava/lang/String;)Ljava/lang/StringBuilder;
    //   235: ldc 119
    //   237: invokevirtual 37	java/lang/StringBuilder:append	(Ljava/lang/String;)Ljava/lang/StringBuilder;
    //   240: pop
    //   241: aload 13
    //   243: invokevirtual 42	java/lang/StringBuilder:toString	()Ljava/lang/String;
    //   246: ldc 121
    //   248: invokevirtual 125	java/lang/String:getBytes	(Ljava/lang/String;)[B
    //   251: astore 13
    //   253: new 31	java/lang/StringBuilder
    //   256: dup
    //   257: invokespecial 33	java/lang/StringBuilder:<init>	()V
    //   260: astore 12
    //   262: aload 12
    //   264: ldc 127
    //   266: invokevirtual 37	java/lang/StringBuilder:append	(Ljava/lang/String;)Ljava/lang/StringBuilder;
    //   269: pop
    //   270: aload 12
    //   272: invokevirtual 42	java/lang/StringBuilder:toString	()Ljava/lang/String;
    //   275: ldc 121
    //   277: invokevirtual 125	java/lang/String:getBytes	(Ljava/lang/String;)[B
    //   280: astore 14
    //   282: aload_1
    //   283: ldc -127
    //   285: invokevirtual 134	java/net/HttpURLConnection:setRequestMethod	(Ljava/lang/String;)V
    //   288: aload_1
    //   289: iconst_1
    //   290: invokevirtual 137	java/net/HttpURLConnection:setDoOutput	(Z)V
    //   293: aload_1
    //   294: ldc -117
    //   296: ldc -115
    //   298: invokevirtual 145	java/net/HttpURLConnection:setRequestProperty	(Ljava/lang/String;Ljava/lang/String;)V
    //   301: aload_1
    //   302: ldc -109
    //   304: aload 13
    //   306: arraylength
    //   307: i2l
    //   308: lload 7
    //   310: ladd
    //   311: aload 14
    //   313: arraylength
    //   314: i2l
    //   315: ladd
    //   316: invokestatic 151	java/lang/String:valueOf	(J)Ljava/lang/String;
    //   319: invokevirtual 145	java/net/HttpURLConnection:setRequestProperty	(Ljava/lang/String;Ljava/lang/String;)V
    //   322: aload_1
    //   323: invokestatic 155	com/yelp/android/cx/k:b	(Ljava/net/HttpURLConnection;)V
    //   326: aconst_null
    //   327: astore 12
    //   329: new 157	java/io/BufferedOutputStream
    //   332: dup
    //   333: aload_1
    //   334: invokevirtual 161	java/net/HttpURLConnection:getOutputStream	()Ljava/io/OutputStream;
    //   337: invokespecial 164	java/io/BufferedOutputStream:<init>	(Ljava/io/OutputStream;)V
    //   340: astore_1
    //   341: aload_1
    //   342: aload 13
    //   344: invokevirtual 168	java/io/BufferedOutputStream:write	([B)V
    //   347: sipush 1024
    //   350: newarray <illegal type>
    //   352: astore 12
    //   354: lconst_0
    //   355: lstore 9
    //   357: iconst_0
    //   358: istore 4
    //   360: aload_3
    //   361: ifnull +62 -> 423
    //   364: iconst_1
    //   365: istore 5
    //   367: aload_2
    //   368: aload 12
    //   370: iconst_0
    //   371: aload 12
    //   373: arraylength
    //   374: invokevirtual 174	java/io/InputStream:read	([BII)I
    //   377: istore 6
    //   379: iload 6
    //   381: iconst_m1
    //   382: if_icmpeq +86 -> 468
    //   385: aload_1
    //   386: aload 12
    //   388: iconst_0
    //   389: iload 6
    //   391: invokevirtual 177	java/io/BufferedOutputStream:write	([BII)V
    //   394: lload 9
    //   396: iload 6
    //   398: i2l
    //   399: ladd
    //   400: lstore 9
    //   402: iload 5
    //   404: ifeq +25 -> 429
    //   407: aload_3
    //   408: invokevirtual 181	com/yelp/android/cw/d:a	()Z
    //   411: istore 11
    //   413: iload 11
    //   415: ifeq +14 -> 429
    //   418: aload_1
    //   419: invokevirtual 184	java/io/BufferedOutputStream:close	()V
    //   422: return
    //   423: iconst_0
    //   424: istore 5
    //   426: goto -59 -> 367
    //   429: ldc2_w 185
    //   432: lload 9
    //   434: lmul
    //   435: lload 7
    //   437: ldiv
    //   438: l2i
    //   439: istore 6
    //   441: iload 4
    //   443: iload 6
    //   445: if_icmpge +60 -> 505
    //   448: iload 5
    //   450: ifeq +11 -> 461
    //   453: aload_3
    //   454: lload 9
    //   456: lload 7
    //   458: invokevirtual 189	com/yelp/android/cw/d:a	(JJ)V
    //   461: iload 6
    //   463: istore 4
    //   465: goto +54 -> 519
    //   468: aload_1
    //   469: aload 14
    //   471: invokevirtual 168	java/io/BufferedOutputStream:write	([B)V
    //   474: aload_1
    //   475: invokevirtual 192	java/io/BufferedOutputStream:flush	()V
    //   478: aload_1
    //   479: invokevirtual 184	java/io/BufferedOutputStream:close	()V
    //   482: return
    //   483: astore_1
    //   484: aload 12
    //   486: astore_2
    //   487: aload_2
    //   488: ifnull +7 -> 495
    //   491: aload_2
    //   492: invokevirtual 184	java/io/BufferedOutputStream:close	()V
    //   495: aload_1
    //   496: athrow
    //   497: astore_3
    //   498: aload_1
    //   499: astore_2
    //   500: aload_3
    //   501: astore_1
    //   502: goto -15 -> 487
    //   505: goto +14 -> 519
    //   508: lconst_0
    //   509: lstore 7
    //   511: aconst_null
    //   512: astore_2
    //   513: aconst_null
    //   514: astore 12
    //   516: goto -397 -> 119
    //   519: goto -152 -> 367
    // Local variable table:
    //   start	length	slot	name	signature
    //   0	522	0	this	k
    //   0	522	1	paramHttpURLConnection	java.net.HttpURLConnection
    //   0	522	2	paramc	com.yelp.android.cw.c
    //   0	522	3	paramd	com.yelp.android.cw.d<String>
    //   103	361	4	i	int
    //   365	84	5	j	int
    //   377	85	6	k	int
    //   87	423	7	l1	long
    //   355	100	9	l2	long
    //   411	3	11	bool	boolean
    //   64	451	12	localObject1	Object
    //   4	339	13	localObject2	Object
    //   280	190	14	arrayOfByte	byte[]
    // Exception table:
    //   from	to	target	type
    //   329	341	483	finally
    //   341	354	497	finally
    //   367	379	497	finally
    //   385	394	497	finally
    //   407	413	497	finally
    //   429	441	497	finally
    //   453	461	497	finally
    //   468	478	497	finally
  }
}

/* Location:
 * Qualified Name:     com.yelp.android.cx.k
 * Java Class Version: 6 (50.0)
 * JD-Core Version:    0.7.1
 */