package com.yelp.android.bj;

import android.location.Location;
import android.os.Binder;
import android.os.Bundle;
import android.os.IBinder;
import android.os.IInterface;
import android.os.Parcel;
import android.os.Parcelable.Creator;
import android.os.RemoteException;
import com.google.android.gms.maps.model.CameraPosition;
import com.google.android.gms.maps.model.CircleOptions;
import com.google.android.gms.maps.model.GroundOverlayOptions;
import com.google.android.gms.maps.model.MarkerOptions;
import com.google.android.gms.maps.model.PolygonOptions;
import com.google.android.gms.maps.model.PolylineOptions;
import com.google.android.gms.maps.model.TileOverlayOptions;
import com.google.android.gms.maps.model.l;
import com.google.android.gms.maps.model.m;
import com.google.android.gms.maps.model.s;
import com.yelp.android.bk.a;
import com.yelp.android.bk.d;
import com.yelp.android.bk.e;
import com.yelp.android.bk.e.a;
import com.yelp.android.bk.h;

public abstract interface b
  extends IInterface
{
  public abstract CameraPosition a()
    throws RemoteException;
  
  public abstract a a(PolylineOptions paramPolylineOptions)
    throws RemoteException;
  
  public abstract com.yelp.android.bk.c a(CircleOptions paramCircleOptions)
    throws RemoteException;
  
  public abstract d a(GroundOverlayOptions paramGroundOverlayOptions)
    throws RemoteException;
  
  public abstract com.yelp.android.bk.f a(MarkerOptions paramMarkerOptions)
    throws RemoteException;
  
  public abstract com.yelp.android.bk.g a(PolygonOptions paramPolygonOptions)
    throws RemoteException;
  
  public abstract h a(TileOverlayOptions paramTileOverlayOptions)
    throws RemoteException;
  
  public abstract void a(int paramInt)
    throws RemoteException;
  
  public abstract void a(int paramInt1, int paramInt2, int paramInt3, int paramInt4)
    throws RemoteException;
  
  public abstract void a(Bundle paramBundle)
    throws RemoteException;
  
  public abstract void a(com.google.android.gms.dynamic.c paramc)
    throws RemoteException;
  
  public abstract void a(com.google.android.gms.dynamic.c paramc, int paramInt, r paramr)
    throws RemoteException;
  
  public abstract void a(com.google.android.gms.dynamic.c paramc, r paramr)
    throws RemoteException;
  
  public abstract void a(ab paramab)
    throws RemoteException;
  
  public abstract void a(ac paramac)
    throws RemoteException;
  
  public abstract void a(ad paramad)
    throws RemoteException;
  
  public abstract void a(ae paramae)
    throws RemoteException;
  
  public abstract void a(af paramaf)
    throws RemoteException;
  
  public abstract void a(ag paramag)
    throws RemoteException;
  
  public abstract void a(ah paramah)
    throws RemoteException;
  
  public abstract void a(ai paramai)
    throws RemoteException;
  
  public abstract void a(aj paramaj)
    throws RemoteException;
  
  public abstract void a(ak paramak)
    throws RemoteException;
  
  public abstract void a(al paramal)
    throws RemoteException;
  
  public abstract void a(c paramc)
    throws RemoteException;
  
  public abstract void a(o paramo, com.google.android.gms.dynamic.c paramc)
    throws RemoteException;
  
  public abstract void a(t paramt)
    throws RemoteException;
  
  public abstract void a(u paramu)
    throws RemoteException;
  
  public abstract void a(v paramv)
    throws RemoteException;
  
  public abstract void a(w paramw)
    throws RemoteException;
  
  public abstract void a(x paramx)
    throws RemoteException;
  
  public abstract void a(y paramy)
    throws RemoteException;
  
  public abstract void a(z paramz)
    throws RemoteException;
  
  public abstract void a(String paramString)
    throws RemoteException;
  
  public abstract void a(boolean paramBoolean)
    throws RemoteException;
  
  public abstract float b()
    throws RemoteException;
  
  public abstract void b(Bundle paramBundle)
    throws RemoteException;
  
  public abstract void b(com.google.android.gms.dynamic.c paramc)
    throws RemoteException;
  
  public abstract boolean b(boolean paramBoolean)
    throws RemoteException;
  
  public abstract float c()
    throws RemoteException;
  
  public abstract void c(Bundle paramBundle)
    throws RemoteException;
  
  public abstract void c(boolean paramBoolean)
    throws RemoteException;
  
  public abstract void d()
    throws RemoteException;
  
  public abstract void d(boolean paramBoolean)
    throws RemoteException;
  
  public abstract void e()
    throws RemoteException;
  
  public abstract int f()
    throws RemoteException;
  
  public abstract boolean g()
    throws RemoteException;
  
  public abstract boolean h()
    throws RemoteException;
  
  public abstract boolean i()
    throws RemoteException;
  
  public abstract Location j()
    throws RemoteException;
  
  public abstract j k()
    throws RemoteException;
  
  public abstract f l()
    throws RemoteException;
  
  public abstract boolean m()
    throws RemoteException;
  
  public abstract e n()
    throws RemoteException;
  
  public abstract void o()
    throws RemoteException;
  
  public abstract void p()
    throws RemoteException;
  
  public abstract void q()
    throws RemoteException;
  
  public abstract void r()
    throws RemoteException;
  
  public abstract boolean s()
    throws RemoteException;
  
  public abstract void t()
    throws RemoteException;
  
  public static abstract class a
    extends Binder
    implements b
  {
    public static b a(IBinder paramIBinder)
    {
      if (paramIBinder == null) {
        return null;
      }
      IInterface localIInterface = paramIBinder.queryLocalInterface("com.google.android.gms.maps.internal.IGoogleMapDelegate");
      if ((localIInterface != null) && ((localIInterface instanceof b))) {
        return (b)localIInterface;
      }
      return new a(paramIBinder);
    }
    
    public boolean onTransact(int paramInt1, Parcel paramParcel1, Parcel paramParcel2, int paramInt2)
      throws RemoteException
    {
      int i = 0;
      int j = 0;
      int k = 0;
      boolean bool2 = false;
      int m = 0;
      boolean bool3 = false;
      int n = 0;
      boolean bool1 = false;
      a locala = null;
      Object localObject2 = null;
      Object localObject3 = null;
      Object localObject4 = null;
      Object localObject6 = null;
      Object localObject7 = null;
      Object localObject5 = null;
      Object localObject8 = null;
      Object localObject1 = null;
      float f;
      switch (paramInt1)
      {
      default: 
        return super.onTransact(paramInt1, paramParcel1, paramParcel2, paramInt2);
      case 1598968902: 
        paramParcel2.writeString("com.google.android.gms.maps.internal.IGoogleMapDelegate");
        return true;
      case 1: 
        paramParcel1.enforceInterface("com.google.android.gms.maps.internal.IGoogleMapDelegate");
        paramParcel1 = a();
        paramParcel2.writeNoException();
        if (paramParcel1 != null)
        {
          paramParcel2.writeInt(1);
          paramParcel1.writeToParcel(paramParcel2, 1);
          return true;
        }
        paramParcel2.writeInt(0);
        return true;
      case 2: 
        paramParcel1.enforceInterface("com.google.android.gms.maps.internal.IGoogleMapDelegate");
        f = b();
        paramParcel2.writeNoException();
        paramParcel2.writeFloat(f);
        return true;
      case 3: 
        paramParcel1.enforceInterface("com.google.android.gms.maps.internal.IGoogleMapDelegate");
        f = c();
        paramParcel2.writeNoException();
        paramParcel2.writeFloat(f);
        return true;
      case 4: 
        paramParcel1.enforceInterface("com.google.android.gms.maps.internal.IGoogleMapDelegate");
        a(com.google.android.gms.dynamic.c.a.a(paramParcel1.readStrongBinder()));
        paramParcel2.writeNoException();
        return true;
      case 5: 
        paramParcel1.enforceInterface("com.google.android.gms.maps.internal.IGoogleMapDelegate");
        b(com.google.android.gms.dynamic.c.a.a(paramParcel1.readStrongBinder()));
        paramParcel2.writeNoException();
        return true;
      case 6: 
        paramParcel1.enforceInterface("com.google.android.gms.maps.internal.IGoogleMapDelegate");
        a(com.google.android.gms.dynamic.c.a.a(paramParcel1.readStrongBinder()), r.a.a(paramParcel1.readStrongBinder()));
        paramParcel2.writeNoException();
        return true;
      case 7: 
        paramParcel1.enforceInterface("com.google.android.gms.maps.internal.IGoogleMapDelegate");
        a(com.google.android.gms.dynamic.c.a.a(paramParcel1.readStrongBinder()), paramParcel1.readInt(), r.a.a(paramParcel1.readStrongBinder()));
        paramParcel2.writeNoException();
        return true;
      case 8: 
        paramParcel1.enforceInterface("com.google.android.gms.maps.internal.IGoogleMapDelegate");
        d();
        paramParcel2.writeNoException();
        return true;
      case 9: 
        paramParcel1.enforceInterface("com.google.android.gms.maps.internal.IGoogleMapDelegate");
        if (paramParcel1.readInt() != 0) {}
        for (paramParcel1 = PolylineOptions.CREATOR.a(paramParcel1);; paramParcel1 = null)
        {
          locala = a(paramParcel1);
          paramParcel2.writeNoException();
          paramParcel1 = (Parcel)localObject1;
          if (locala != null) {
            paramParcel1 = locala.asBinder();
          }
          paramParcel2.writeStrongBinder(paramParcel1);
          return true;
        }
      case 10: 
        paramParcel1.enforceInterface("com.google.android.gms.maps.internal.IGoogleMapDelegate");
        if (paramParcel1.readInt() != 0) {}
        for (paramParcel1 = PolygonOptions.CREATOR.a(paramParcel1);; paramParcel1 = null)
        {
          localObject1 = a(paramParcel1);
          paramParcel2.writeNoException();
          paramParcel1 = locala;
          if (localObject1 != null) {
            paramParcel1 = ((com.yelp.android.bk.g)localObject1).asBinder();
          }
          paramParcel2.writeStrongBinder(paramParcel1);
          return true;
        }
      case 11: 
        paramParcel1.enforceInterface("com.google.android.gms.maps.internal.IGoogleMapDelegate");
        if (paramParcel1.readInt() != 0) {}
        for (paramParcel1 = MarkerOptions.CREATOR.a(paramParcel1);; paramParcel1 = null)
        {
          localObject1 = a(paramParcel1);
          paramParcel2.writeNoException();
          paramParcel1 = (Parcel)localObject2;
          if (localObject1 != null) {
            paramParcel1 = ((com.yelp.android.bk.f)localObject1).asBinder();
          }
          paramParcel2.writeStrongBinder(paramParcel1);
          return true;
        }
      case 12: 
        paramParcel1.enforceInterface("com.google.android.gms.maps.internal.IGoogleMapDelegate");
        if (paramParcel1.readInt() != 0) {}
        for (paramParcel1 = GroundOverlayOptions.CREATOR.a(paramParcel1);; paramParcel1 = null)
        {
          localObject1 = a(paramParcel1);
          paramParcel2.writeNoException();
          paramParcel1 = (Parcel)localObject3;
          if (localObject1 != null) {
            paramParcel1 = ((d)localObject1).asBinder();
          }
          paramParcel2.writeStrongBinder(paramParcel1);
          return true;
        }
      case 13: 
        paramParcel1.enforceInterface("com.google.android.gms.maps.internal.IGoogleMapDelegate");
        if (paramParcel1.readInt() != 0) {}
        for (paramParcel1 = TileOverlayOptions.CREATOR.a(paramParcel1);; paramParcel1 = null)
        {
          localObject1 = a(paramParcel1);
          paramParcel2.writeNoException();
          paramParcel1 = (Parcel)localObject4;
          if (localObject1 != null) {
            paramParcel1 = ((h)localObject1).asBinder();
          }
          paramParcel2.writeStrongBinder(paramParcel1);
          return true;
        }
      case 14: 
        paramParcel1.enforceInterface("com.google.android.gms.maps.internal.IGoogleMapDelegate");
        e();
        paramParcel2.writeNoException();
        return true;
      case 15: 
        paramParcel1.enforceInterface("com.google.android.gms.maps.internal.IGoogleMapDelegate");
        paramInt1 = f();
        paramParcel2.writeNoException();
        paramParcel2.writeInt(paramInt1);
        return true;
      case 16: 
        paramParcel1.enforceInterface("com.google.android.gms.maps.internal.IGoogleMapDelegate");
        a(paramParcel1.readInt());
        paramParcel2.writeNoException();
        return true;
      case 17: 
        paramParcel1.enforceInterface("com.google.android.gms.maps.internal.IGoogleMapDelegate");
        bool1 = g();
        paramParcel2.writeNoException();
        if (bool1) {}
        for (paramInt1 = 1;; paramInt1 = 0)
        {
          paramParcel2.writeInt(paramInt1);
          return true;
        }
      case 18: 
        paramParcel1.enforceInterface("com.google.android.gms.maps.internal.IGoogleMapDelegate");
        if (paramParcel1.readInt() != 0) {
          bool1 = true;
        }
        a(bool1);
        paramParcel2.writeNoException();
        return true;
      case 19: 
        paramParcel1.enforceInterface("com.google.android.gms.maps.internal.IGoogleMapDelegate");
        bool1 = h();
        paramParcel2.writeNoException();
        paramInt1 = i;
        if (bool1) {
          paramInt1 = 1;
        }
        paramParcel2.writeInt(paramInt1);
        return true;
      case 20: 
        paramParcel1.enforceInterface("com.google.android.gms.maps.internal.IGoogleMapDelegate");
        if (paramParcel1.readInt() != 0) {}
        for (bool1 = true;; bool1 = false)
        {
          bool1 = b(bool1);
          paramParcel2.writeNoException();
          paramInt1 = j;
          if (bool1) {
            paramInt1 = 1;
          }
          paramParcel2.writeInt(paramInt1);
          return true;
        }
      case 21: 
        paramParcel1.enforceInterface("com.google.android.gms.maps.internal.IGoogleMapDelegate");
        bool1 = i();
        paramParcel2.writeNoException();
        paramInt1 = k;
        if (bool1) {
          paramInt1 = 1;
        }
        paramParcel2.writeInt(paramInt1);
        return true;
      case 22: 
        paramParcel1.enforceInterface("com.google.android.gms.maps.internal.IGoogleMapDelegate");
        bool1 = bool2;
        if (paramParcel1.readInt() != 0) {
          bool1 = true;
        }
        c(bool1);
        paramParcel2.writeNoException();
        return true;
      case 23: 
        paramParcel1.enforceInterface("com.google.android.gms.maps.internal.IGoogleMapDelegate");
        paramParcel1 = j();
        paramParcel2.writeNoException();
        if (paramParcel1 != null)
        {
          paramParcel2.writeInt(1);
          paramParcel1.writeToParcel(paramParcel2, 1);
          return true;
        }
        paramParcel2.writeInt(0);
        return true;
      case 24: 
        paramParcel1.enforceInterface("com.google.android.gms.maps.internal.IGoogleMapDelegate");
        a(c.a.a(paramParcel1.readStrongBinder()));
        paramParcel2.writeNoException();
        return true;
      case 25: 
        paramParcel1.enforceInterface("com.google.android.gms.maps.internal.IGoogleMapDelegate");
        localObject1 = k();
        paramParcel2.writeNoException();
        paramParcel1 = (Parcel)localObject6;
        if (localObject1 != null) {
          paramParcel1 = ((j)localObject1).asBinder();
        }
        paramParcel2.writeStrongBinder(paramParcel1);
        return true;
      case 26: 
        paramParcel1.enforceInterface("com.google.android.gms.maps.internal.IGoogleMapDelegate");
        localObject1 = l();
        paramParcel2.writeNoException();
        paramParcel1 = (Parcel)localObject7;
        if (localObject1 != null) {
          paramParcel1 = ((f)localObject1).asBinder();
        }
        paramParcel2.writeStrongBinder(paramParcel1);
        return true;
      case 27: 
        paramParcel1.enforceInterface("com.google.android.gms.maps.internal.IGoogleMapDelegate");
        a(u.a.a(paramParcel1.readStrongBinder()));
        paramParcel2.writeNoException();
        return true;
      case 28: 
        paramParcel1.enforceInterface("com.google.android.gms.maps.internal.IGoogleMapDelegate");
        a(ab.a.a(paramParcel1.readStrongBinder()));
        paramParcel2.writeNoException();
        return true;
      case 29: 
        paramParcel1.enforceInterface("com.google.android.gms.maps.internal.IGoogleMapDelegate");
        a(ad.a.a(paramParcel1.readStrongBinder()));
        paramParcel2.writeNoException();
        return true;
      case 30: 
        paramParcel1.enforceInterface("com.google.android.gms.maps.internal.IGoogleMapDelegate");
        a(af.a.a(paramParcel1.readStrongBinder()));
        paramParcel2.writeNoException();
        return true;
      case 31: 
        paramParcel1.enforceInterface("com.google.android.gms.maps.internal.IGoogleMapDelegate");
        a(ag.a.a(paramParcel1.readStrongBinder()));
        paramParcel2.writeNoException();
        return true;
      case 32: 
        paramParcel1.enforceInterface("com.google.android.gms.maps.internal.IGoogleMapDelegate");
        a(x.a.a(paramParcel1.readStrongBinder()));
        paramParcel2.writeNoException();
        return true;
      case 33: 
        paramParcel1.enforceInterface("com.google.android.gms.maps.internal.IGoogleMapDelegate");
        a(t.a.a(paramParcel1.readStrongBinder()));
        paramParcel2.writeNoException();
        return true;
      case 35: 
        paramParcel1.enforceInterface("com.google.android.gms.maps.internal.IGoogleMapDelegate");
        if (paramParcel1.readInt() != 0) {}
        for (paramParcel1 = CircleOptions.CREATOR.a(paramParcel1);; paramParcel1 = null)
        {
          localObject1 = a(paramParcel1);
          paramParcel2.writeNoException();
          paramParcel1 = (Parcel)localObject5;
          if (localObject1 != null) {
            paramParcel1 = ((com.yelp.android.bk.c)localObject1).asBinder();
          }
          paramParcel2.writeStrongBinder(paramParcel1);
          return true;
        }
      case 36: 
        paramParcel1.enforceInterface("com.google.android.gms.maps.internal.IGoogleMapDelegate");
        a(ai.a.a(paramParcel1.readStrongBinder()));
        paramParcel2.writeNoException();
        return true;
      case 37: 
        paramParcel1.enforceInterface("com.google.android.gms.maps.internal.IGoogleMapDelegate");
        a(ah.a.a(paramParcel1.readStrongBinder()));
        paramParcel2.writeNoException();
        return true;
      case 38: 
        paramParcel1.enforceInterface("com.google.android.gms.maps.internal.IGoogleMapDelegate");
        a(o.a.a(paramParcel1.readStrongBinder()), com.google.android.gms.dynamic.c.a.a(paramParcel1.readStrongBinder()));
        paramParcel2.writeNoException();
        return true;
      case 39: 
        paramParcel1.enforceInterface("com.google.android.gms.maps.internal.IGoogleMapDelegate");
        a(paramParcel1.readInt(), paramParcel1.readInt(), paramParcel1.readInt(), paramParcel1.readInt());
        paramParcel2.writeNoException();
        return true;
      case 40: 
        paramParcel1.enforceInterface("com.google.android.gms.maps.internal.IGoogleMapDelegate");
        bool1 = m();
        paramParcel2.writeNoException();
        paramInt1 = m;
        if (bool1) {
          paramInt1 = 1;
        }
        paramParcel2.writeInt(paramInt1);
        return true;
      case 41: 
        paramParcel1.enforceInterface("com.google.android.gms.maps.internal.IGoogleMapDelegate");
        bool1 = bool3;
        if (paramParcel1.readInt() != 0) {
          bool1 = true;
        }
        d(bool1);
        paramParcel2.writeNoException();
        return true;
      case 42: 
        paramParcel1.enforceInterface("com.google.android.gms.maps.internal.IGoogleMapDelegate");
        a(ac.a.a(paramParcel1.readStrongBinder()));
        paramParcel2.writeNoException();
        return true;
      case 44: 
        paramParcel1.enforceInterface("com.google.android.gms.maps.internal.IGoogleMapDelegate");
        localObject1 = n();
        paramParcel2.writeNoException();
        paramParcel1 = (Parcel)localObject8;
        if (localObject1 != null) {
          paramParcel1 = ((e)localObject1).asBinder();
        }
        paramParcel2.writeStrongBinder(paramParcel1);
        return true;
      case 45: 
        paramParcel1.enforceInterface("com.google.android.gms.maps.internal.IGoogleMapDelegate");
        a(w.a.a(paramParcel1.readStrongBinder()));
        paramParcel2.writeNoException();
        return true;
      case 53: 
        paramParcel1.enforceInterface("com.google.android.gms.maps.internal.IGoogleMapDelegate");
        a(ae.a.a(paramParcel1.readStrongBinder()));
        paramParcel2.writeNoException();
        return true;
      case 54: 
        paramParcel1.enforceInterface("com.google.android.gms.maps.internal.IGoogleMapDelegate");
        if (paramParcel1.readInt() != 0) {}
        for (paramParcel1 = (Bundle)Bundle.CREATOR.createFromParcel(paramParcel1);; paramParcel1 = null)
        {
          a(paramParcel1);
          paramParcel2.writeNoException();
          return true;
        }
      case 55: 
        paramParcel1.enforceInterface("com.google.android.gms.maps.internal.IGoogleMapDelegate");
        o();
        paramParcel2.writeNoException();
        return true;
      case 56: 
        paramParcel1.enforceInterface("com.google.android.gms.maps.internal.IGoogleMapDelegate");
        p();
        paramParcel2.writeNoException();
        return true;
      case 57: 
        paramParcel1.enforceInterface("com.google.android.gms.maps.internal.IGoogleMapDelegate");
        q();
        paramParcel2.writeNoException();
        return true;
      case 58: 
        paramParcel1.enforceInterface("com.google.android.gms.maps.internal.IGoogleMapDelegate");
        r();
        paramParcel2.writeNoException();
        return true;
      case 59: 
        paramParcel1.enforceInterface("com.google.android.gms.maps.internal.IGoogleMapDelegate");
        bool1 = s();
        paramParcel2.writeNoException();
        paramInt1 = n;
        if (bool1) {
          paramInt1 = 1;
        }
        paramParcel2.writeInt(paramInt1);
        return true;
      case 60: 
        paramParcel1.enforceInterface("com.google.android.gms.maps.internal.IGoogleMapDelegate");
        if (paramParcel1.readInt() != 0) {}
        for (paramParcel1 = (Bundle)Bundle.CREATOR.createFromParcel(paramParcel1);; paramParcel1 = null)
        {
          b(paramParcel1);
          paramParcel2.writeNoException();
          if (paramParcel1 == null) {
            break;
          }
          paramParcel2.writeInt(1);
          paramParcel1.writeToParcel(paramParcel2, 1);
          return true;
        }
        paramParcel2.writeInt(0);
        return true;
      case 61: 
        paramParcel1.enforceInterface("com.google.android.gms.maps.internal.IGoogleMapDelegate");
        a(paramParcel1.readString());
        paramParcel2.writeNoException();
        return true;
      case 80: 
        paramParcel1.enforceInterface("com.google.android.gms.maps.internal.IGoogleMapDelegate");
        a(aj.a.a(paramParcel1.readStrongBinder()));
        paramParcel2.writeNoException();
        return true;
      case 81: 
        paramParcel1.enforceInterface("com.google.android.gms.maps.internal.IGoogleMapDelegate");
        if (paramParcel1.readInt() != 0) {}
        for (paramParcel1 = (Bundle)Bundle.CREATOR.createFromParcel(paramParcel1);; paramParcel1 = null)
        {
          c(paramParcel1);
          paramParcel2.writeNoException();
          return true;
        }
      case 82: 
        paramParcel1.enforceInterface("com.google.android.gms.maps.internal.IGoogleMapDelegate");
        t();
        paramParcel2.writeNoException();
        return true;
      case 83: 
        paramParcel1.enforceInterface("com.google.android.gms.maps.internal.IGoogleMapDelegate");
        a(v.a.a(paramParcel1.readStrongBinder()));
        paramParcel2.writeNoException();
        return true;
      case 84: 
        paramParcel1.enforceInterface("com.google.android.gms.maps.internal.IGoogleMapDelegate");
        a(z.a.a(paramParcel1.readStrongBinder()));
        paramParcel2.writeNoException();
        return true;
      case 85: 
        paramParcel1.enforceInterface("com.google.android.gms.maps.internal.IGoogleMapDelegate");
        a(ak.a.a(paramParcel1.readStrongBinder()));
        paramParcel2.writeNoException();
        return true;
      case 86: 
        paramParcel1.enforceInterface("com.google.android.gms.maps.internal.IGoogleMapDelegate");
        a(y.a.a(paramParcel1.readStrongBinder()));
        paramParcel2.writeNoException();
        return true;
      }
      paramParcel1.enforceInterface("com.google.android.gms.maps.internal.IGoogleMapDelegate");
      a(al.a.a(paramParcel1.readStrongBinder()));
      paramParcel2.writeNoException();
      return true;
    }
    
    private static class a
      implements b
    {
      private IBinder a;
      
      a(IBinder paramIBinder)
      {
        a = paramIBinder;
      }
      
      /* Error */
      public CameraPosition a()
        throws RemoteException
      {
        // Byte code:
        //   0: invokestatic 27	android/os/Parcel:obtain	()Landroid/os/Parcel;
        //   3: astore_2
        //   4: invokestatic 27	android/os/Parcel:obtain	()Landroid/os/Parcel;
        //   7: astore_3
        //   8: aload_2
        //   9: ldc 29
        //   11: invokevirtual 33	android/os/Parcel:writeInterfaceToken	(Ljava/lang/String;)V
        //   14: aload_0
        //   15: getfield 17	com/yelp/android/bj/b$a$a:a	Landroid/os/IBinder;
        //   18: iconst_1
        //   19: aload_2
        //   20: aload_3
        //   21: iconst_0
        //   22: invokeinterface 39 5 0
        //   27: pop
        //   28: aload_3
        //   29: invokevirtual 42	android/os/Parcel:readException	()V
        //   32: aload_3
        //   33: invokevirtual 46	android/os/Parcel:readInt	()I
        //   36: ifeq +21 -> 57
        //   39: getstatic 52	com/google/android/gms/maps/model/CameraPosition:CREATOR	Lcom/google/android/gms/maps/model/e;
        //   42: aload_3
        //   43: invokevirtual 57	com/google/android/gms/maps/model/e:a	(Landroid/os/Parcel;)Lcom/google/android/gms/maps/model/CameraPosition;
        //   46: astore_1
        //   47: aload_3
        //   48: invokevirtual 60	android/os/Parcel:recycle	()V
        //   51: aload_2
        //   52: invokevirtual 60	android/os/Parcel:recycle	()V
        //   55: aload_1
        //   56: areturn
        //   57: aconst_null
        //   58: astore_1
        //   59: goto -12 -> 47
        //   62: astore_1
        //   63: aload_3
        //   64: invokevirtual 60	android/os/Parcel:recycle	()V
        //   67: aload_2
        //   68: invokevirtual 60	android/os/Parcel:recycle	()V
        //   71: aload_1
        //   72: athrow
        // Local variable table:
        //   start	length	slot	name	signature
        //   0	73	0	this	a
        //   46	13	1	localCameraPosition	CameraPosition
        //   62	10	1	localObject	Object
        //   3	65	2	localParcel1	Parcel
        //   7	57	3	localParcel2	Parcel
        // Exception table:
        //   from	to	target	type
        //   8	47	62	finally
      }
      
      /* Error */
      public a a(PolylineOptions paramPolylineOptions)
        throws RemoteException
      {
        // Byte code:
        //   0: invokestatic 27	android/os/Parcel:obtain	()Landroid/os/Parcel;
        //   3: astore_2
        //   4: invokestatic 27	android/os/Parcel:obtain	()Landroid/os/Parcel;
        //   7: astore_3
        //   8: aload_2
        //   9: ldc 29
        //   11: invokevirtual 33	android/os/Parcel:writeInterfaceToken	(Ljava/lang/String;)V
        //   14: aload_1
        //   15: ifnull +51 -> 66
        //   18: aload_2
        //   19: iconst_1
        //   20: invokevirtual 66	android/os/Parcel:writeInt	(I)V
        //   23: aload_1
        //   24: aload_2
        //   25: iconst_0
        //   26: invokevirtual 72	com/google/android/gms/maps/model/PolylineOptions:writeToParcel	(Landroid/os/Parcel;I)V
        //   29: aload_0
        //   30: getfield 17	com/yelp/android/bj/b$a$a:a	Landroid/os/IBinder;
        //   33: bipush 9
        //   35: aload_2
        //   36: aload_3
        //   37: iconst_0
        //   38: invokeinterface 39 5 0
        //   43: pop
        //   44: aload_3
        //   45: invokevirtual 42	android/os/Parcel:readException	()V
        //   48: aload_3
        //   49: invokevirtual 76	android/os/Parcel:readStrongBinder	()Landroid/os/IBinder;
        //   52: invokestatic 81	com/yelp/android/bk/a$a:a	(Landroid/os/IBinder;)Lcom/yelp/android/bk/a;
        //   55: astore_1
        //   56: aload_3
        //   57: invokevirtual 60	android/os/Parcel:recycle	()V
        //   60: aload_2
        //   61: invokevirtual 60	android/os/Parcel:recycle	()V
        //   64: aload_1
        //   65: areturn
        //   66: aload_2
        //   67: iconst_0
        //   68: invokevirtual 66	android/os/Parcel:writeInt	(I)V
        //   71: goto -42 -> 29
        //   74: astore_1
        //   75: aload_3
        //   76: invokevirtual 60	android/os/Parcel:recycle	()V
        //   79: aload_2
        //   80: invokevirtual 60	android/os/Parcel:recycle	()V
        //   83: aload_1
        //   84: athrow
        // Local variable table:
        //   start	length	slot	name	signature
        //   0	85	0	this	a
        //   0	85	1	paramPolylineOptions	PolylineOptions
        //   3	77	2	localParcel1	Parcel
        //   7	69	3	localParcel2	Parcel
        // Exception table:
        //   from	to	target	type
        //   8	14	74	finally
        //   18	29	74	finally
        //   29	56	74	finally
        //   66	71	74	finally
      }
      
      /* Error */
      public com.yelp.android.bk.c a(CircleOptions paramCircleOptions)
        throws RemoteException
      {
        // Byte code:
        //   0: invokestatic 27	android/os/Parcel:obtain	()Landroid/os/Parcel;
        //   3: astore_2
        //   4: invokestatic 27	android/os/Parcel:obtain	()Landroid/os/Parcel;
        //   7: astore_3
        //   8: aload_2
        //   9: ldc 29
        //   11: invokevirtual 33	android/os/Parcel:writeInterfaceToken	(Ljava/lang/String;)V
        //   14: aload_1
        //   15: ifnull +51 -> 66
        //   18: aload_2
        //   19: iconst_1
        //   20: invokevirtual 66	android/os/Parcel:writeInt	(I)V
        //   23: aload_1
        //   24: aload_2
        //   25: iconst_0
        //   26: invokevirtual 85	com/google/android/gms/maps/model/CircleOptions:writeToParcel	(Landroid/os/Parcel;I)V
        //   29: aload_0
        //   30: getfield 17	com/yelp/android/bj/b$a$a:a	Landroid/os/IBinder;
        //   33: bipush 35
        //   35: aload_2
        //   36: aload_3
        //   37: iconst_0
        //   38: invokeinterface 39 5 0
        //   43: pop
        //   44: aload_3
        //   45: invokevirtual 42	android/os/Parcel:readException	()V
        //   48: aload_3
        //   49: invokevirtual 76	android/os/Parcel:readStrongBinder	()Landroid/os/IBinder;
        //   52: invokestatic 90	com/yelp/android/bk/c$a:a	(Landroid/os/IBinder;)Lcom/yelp/android/bk/c;
        //   55: astore_1
        //   56: aload_3
        //   57: invokevirtual 60	android/os/Parcel:recycle	()V
        //   60: aload_2
        //   61: invokevirtual 60	android/os/Parcel:recycle	()V
        //   64: aload_1
        //   65: areturn
        //   66: aload_2
        //   67: iconst_0
        //   68: invokevirtual 66	android/os/Parcel:writeInt	(I)V
        //   71: goto -42 -> 29
        //   74: astore_1
        //   75: aload_3
        //   76: invokevirtual 60	android/os/Parcel:recycle	()V
        //   79: aload_2
        //   80: invokevirtual 60	android/os/Parcel:recycle	()V
        //   83: aload_1
        //   84: athrow
        // Local variable table:
        //   start	length	slot	name	signature
        //   0	85	0	this	a
        //   0	85	1	paramCircleOptions	CircleOptions
        //   3	77	2	localParcel1	Parcel
        //   7	69	3	localParcel2	Parcel
        // Exception table:
        //   from	to	target	type
        //   8	14	74	finally
        //   18	29	74	finally
        //   29	56	74	finally
        //   66	71	74	finally
      }
      
      /* Error */
      public d a(GroundOverlayOptions paramGroundOverlayOptions)
        throws RemoteException
      {
        // Byte code:
        //   0: invokestatic 27	android/os/Parcel:obtain	()Landroid/os/Parcel;
        //   3: astore_2
        //   4: invokestatic 27	android/os/Parcel:obtain	()Landroid/os/Parcel;
        //   7: astore_3
        //   8: aload_2
        //   9: ldc 29
        //   11: invokevirtual 33	android/os/Parcel:writeInterfaceToken	(Ljava/lang/String;)V
        //   14: aload_1
        //   15: ifnull +51 -> 66
        //   18: aload_2
        //   19: iconst_1
        //   20: invokevirtual 66	android/os/Parcel:writeInt	(I)V
        //   23: aload_1
        //   24: aload_2
        //   25: iconst_0
        //   26: invokevirtual 94	com/google/android/gms/maps/model/GroundOverlayOptions:writeToParcel	(Landroid/os/Parcel;I)V
        //   29: aload_0
        //   30: getfield 17	com/yelp/android/bj/b$a$a:a	Landroid/os/IBinder;
        //   33: bipush 12
        //   35: aload_2
        //   36: aload_3
        //   37: iconst_0
        //   38: invokeinterface 39 5 0
        //   43: pop
        //   44: aload_3
        //   45: invokevirtual 42	android/os/Parcel:readException	()V
        //   48: aload_3
        //   49: invokevirtual 76	android/os/Parcel:readStrongBinder	()Landroid/os/IBinder;
        //   52: invokestatic 99	com/yelp/android/bk/d$a:a	(Landroid/os/IBinder;)Lcom/yelp/android/bk/d;
        //   55: astore_1
        //   56: aload_3
        //   57: invokevirtual 60	android/os/Parcel:recycle	()V
        //   60: aload_2
        //   61: invokevirtual 60	android/os/Parcel:recycle	()V
        //   64: aload_1
        //   65: areturn
        //   66: aload_2
        //   67: iconst_0
        //   68: invokevirtual 66	android/os/Parcel:writeInt	(I)V
        //   71: goto -42 -> 29
        //   74: astore_1
        //   75: aload_3
        //   76: invokevirtual 60	android/os/Parcel:recycle	()V
        //   79: aload_2
        //   80: invokevirtual 60	android/os/Parcel:recycle	()V
        //   83: aload_1
        //   84: athrow
        // Local variable table:
        //   start	length	slot	name	signature
        //   0	85	0	this	a
        //   0	85	1	paramGroundOverlayOptions	GroundOverlayOptions
        //   3	77	2	localParcel1	Parcel
        //   7	69	3	localParcel2	Parcel
        // Exception table:
        //   from	to	target	type
        //   8	14	74	finally
        //   18	29	74	finally
        //   29	56	74	finally
        //   66	71	74	finally
      }
      
      /* Error */
      public com.yelp.android.bk.f a(MarkerOptions paramMarkerOptions)
        throws RemoteException
      {
        // Byte code:
        //   0: invokestatic 27	android/os/Parcel:obtain	()Landroid/os/Parcel;
        //   3: astore_2
        //   4: invokestatic 27	android/os/Parcel:obtain	()Landroid/os/Parcel;
        //   7: astore_3
        //   8: aload_2
        //   9: ldc 29
        //   11: invokevirtual 33	android/os/Parcel:writeInterfaceToken	(Ljava/lang/String;)V
        //   14: aload_1
        //   15: ifnull +51 -> 66
        //   18: aload_2
        //   19: iconst_1
        //   20: invokevirtual 66	android/os/Parcel:writeInt	(I)V
        //   23: aload_1
        //   24: aload_2
        //   25: iconst_0
        //   26: invokevirtual 103	com/google/android/gms/maps/model/MarkerOptions:writeToParcel	(Landroid/os/Parcel;I)V
        //   29: aload_0
        //   30: getfield 17	com/yelp/android/bj/b$a$a:a	Landroid/os/IBinder;
        //   33: bipush 11
        //   35: aload_2
        //   36: aload_3
        //   37: iconst_0
        //   38: invokeinterface 39 5 0
        //   43: pop
        //   44: aload_3
        //   45: invokevirtual 42	android/os/Parcel:readException	()V
        //   48: aload_3
        //   49: invokevirtual 76	android/os/Parcel:readStrongBinder	()Landroid/os/IBinder;
        //   52: invokestatic 108	com/yelp/android/bk/f$a:a	(Landroid/os/IBinder;)Lcom/yelp/android/bk/f;
        //   55: astore_1
        //   56: aload_3
        //   57: invokevirtual 60	android/os/Parcel:recycle	()V
        //   60: aload_2
        //   61: invokevirtual 60	android/os/Parcel:recycle	()V
        //   64: aload_1
        //   65: areturn
        //   66: aload_2
        //   67: iconst_0
        //   68: invokevirtual 66	android/os/Parcel:writeInt	(I)V
        //   71: goto -42 -> 29
        //   74: astore_1
        //   75: aload_3
        //   76: invokevirtual 60	android/os/Parcel:recycle	()V
        //   79: aload_2
        //   80: invokevirtual 60	android/os/Parcel:recycle	()V
        //   83: aload_1
        //   84: athrow
        // Local variable table:
        //   start	length	slot	name	signature
        //   0	85	0	this	a
        //   0	85	1	paramMarkerOptions	MarkerOptions
        //   3	77	2	localParcel1	Parcel
        //   7	69	3	localParcel2	Parcel
        // Exception table:
        //   from	to	target	type
        //   8	14	74	finally
        //   18	29	74	finally
        //   29	56	74	finally
        //   66	71	74	finally
      }
      
      /* Error */
      public com.yelp.android.bk.g a(PolygonOptions paramPolygonOptions)
        throws RemoteException
      {
        // Byte code:
        //   0: invokestatic 27	android/os/Parcel:obtain	()Landroid/os/Parcel;
        //   3: astore_2
        //   4: invokestatic 27	android/os/Parcel:obtain	()Landroid/os/Parcel;
        //   7: astore_3
        //   8: aload_2
        //   9: ldc 29
        //   11: invokevirtual 33	android/os/Parcel:writeInterfaceToken	(Ljava/lang/String;)V
        //   14: aload_1
        //   15: ifnull +51 -> 66
        //   18: aload_2
        //   19: iconst_1
        //   20: invokevirtual 66	android/os/Parcel:writeInt	(I)V
        //   23: aload_1
        //   24: aload_2
        //   25: iconst_0
        //   26: invokevirtual 112	com/google/android/gms/maps/model/PolygonOptions:writeToParcel	(Landroid/os/Parcel;I)V
        //   29: aload_0
        //   30: getfield 17	com/yelp/android/bj/b$a$a:a	Landroid/os/IBinder;
        //   33: bipush 10
        //   35: aload_2
        //   36: aload_3
        //   37: iconst_0
        //   38: invokeinterface 39 5 0
        //   43: pop
        //   44: aload_3
        //   45: invokevirtual 42	android/os/Parcel:readException	()V
        //   48: aload_3
        //   49: invokevirtual 76	android/os/Parcel:readStrongBinder	()Landroid/os/IBinder;
        //   52: invokestatic 117	com/yelp/android/bk/g$a:a	(Landroid/os/IBinder;)Lcom/yelp/android/bk/g;
        //   55: astore_1
        //   56: aload_3
        //   57: invokevirtual 60	android/os/Parcel:recycle	()V
        //   60: aload_2
        //   61: invokevirtual 60	android/os/Parcel:recycle	()V
        //   64: aload_1
        //   65: areturn
        //   66: aload_2
        //   67: iconst_0
        //   68: invokevirtual 66	android/os/Parcel:writeInt	(I)V
        //   71: goto -42 -> 29
        //   74: astore_1
        //   75: aload_3
        //   76: invokevirtual 60	android/os/Parcel:recycle	()V
        //   79: aload_2
        //   80: invokevirtual 60	android/os/Parcel:recycle	()V
        //   83: aload_1
        //   84: athrow
        // Local variable table:
        //   start	length	slot	name	signature
        //   0	85	0	this	a
        //   0	85	1	paramPolygonOptions	PolygonOptions
        //   3	77	2	localParcel1	Parcel
        //   7	69	3	localParcel2	Parcel
        // Exception table:
        //   from	to	target	type
        //   8	14	74	finally
        //   18	29	74	finally
        //   29	56	74	finally
        //   66	71	74	finally
      }
      
      /* Error */
      public h a(TileOverlayOptions paramTileOverlayOptions)
        throws RemoteException
      {
        // Byte code:
        //   0: invokestatic 27	android/os/Parcel:obtain	()Landroid/os/Parcel;
        //   3: astore_2
        //   4: invokestatic 27	android/os/Parcel:obtain	()Landroid/os/Parcel;
        //   7: astore_3
        //   8: aload_2
        //   9: ldc 29
        //   11: invokevirtual 33	android/os/Parcel:writeInterfaceToken	(Ljava/lang/String;)V
        //   14: aload_1
        //   15: ifnull +51 -> 66
        //   18: aload_2
        //   19: iconst_1
        //   20: invokevirtual 66	android/os/Parcel:writeInt	(I)V
        //   23: aload_1
        //   24: aload_2
        //   25: iconst_0
        //   26: invokevirtual 121	com/google/android/gms/maps/model/TileOverlayOptions:writeToParcel	(Landroid/os/Parcel;I)V
        //   29: aload_0
        //   30: getfield 17	com/yelp/android/bj/b$a$a:a	Landroid/os/IBinder;
        //   33: bipush 13
        //   35: aload_2
        //   36: aload_3
        //   37: iconst_0
        //   38: invokeinterface 39 5 0
        //   43: pop
        //   44: aload_3
        //   45: invokevirtual 42	android/os/Parcel:readException	()V
        //   48: aload_3
        //   49: invokevirtual 76	android/os/Parcel:readStrongBinder	()Landroid/os/IBinder;
        //   52: invokestatic 126	com/yelp/android/bk/h$a:a	(Landroid/os/IBinder;)Lcom/yelp/android/bk/h;
        //   55: astore_1
        //   56: aload_3
        //   57: invokevirtual 60	android/os/Parcel:recycle	()V
        //   60: aload_2
        //   61: invokevirtual 60	android/os/Parcel:recycle	()V
        //   64: aload_1
        //   65: areturn
        //   66: aload_2
        //   67: iconst_0
        //   68: invokevirtual 66	android/os/Parcel:writeInt	(I)V
        //   71: goto -42 -> 29
        //   74: astore_1
        //   75: aload_3
        //   76: invokevirtual 60	android/os/Parcel:recycle	()V
        //   79: aload_2
        //   80: invokevirtual 60	android/os/Parcel:recycle	()V
        //   83: aload_1
        //   84: athrow
        // Local variable table:
        //   start	length	slot	name	signature
        //   0	85	0	this	a
        //   0	85	1	paramTileOverlayOptions	TileOverlayOptions
        //   3	77	2	localParcel1	Parcel
        //   7	69	3	localParcel2	Parcel
        // Exception table:
        //   from	to	target	type
        //   8	14	74	finally
        //   18	29	74	finally
        //   29	56	74	finally
        //   66	71	74	finally
      }
      
      public void a(int paramInt)
        throws RemoteException
      {
        Parcel localParcel1 = Parcel.obtain();
        Parcel localParcel2 = Parcel.obtain();
        try
        {
          localParcel1.writeInterfaceToken("com.google.android.gms.maps.internal.IGoogleMapDelegate");
          localParcel1.writeInt(paramInt);
          a.transact(16, localParcel1, localParcel2, 0);
          localParcel2.readException();
          return;
        }
        finally
        {
          localParcel2.recycle();
          localParcel1.recycle();
        }
      }
      
      public void a(int paramInt1, int paramInt2, int paramInt3, int paramInt4)
        throws RemoteException
      {
        Parcel localParcel1 = Parcel.obtain();
        Parcel localParcel2 = Parcel.obtain();
        try
        {
          localParcel1.writeInterfaceToken("com.google.android.gms.maps.internal.IGoogleMapDelegate");
          localParcel1.writeInt(paramInt1);
          localParcel1.writeInt(paramInt2);
          localParcel1.writeInt(paramInt3);
          localParcel1.writeInt(paramInt4);
          a.transact(39, localParcel1, localParcel2, 0);
          localParcel2.readException();
          return;
        }
        finally
        {
          localParcel2.recycle();
          localParcel1.recycle();
        }
      }
      
      /* Error */
      public void a(Bundle paramBundle)
        throws RemoteException
      {
        // Byte code:
        //   0: invokestatic 27	android/os/Parcel:obtain	()Landroid/os/Parcel;
        //   3: astore_2
        //   4: invokestatic 27	android/os/Parcel:obtain	()Landroid/os/Parcel;
        //   7: astore_3
        //   8: aload_2
        //   9: ldc 29
        //   11: invokevirtual 33	android/os/Parcel:writeInterfaceToken	(Ljava/lang/String;)V
        //   14: aload_1
        //   15: ifnull +42 -> 57
        //   18: aload_2
        //   19: iconst_1
        //   20: invokevirtual 66	android/os/Parcel:writeInt	(I)V
        //   23: aload_1
        //   24: aload_2
        //   25: iconst_0
        //   26: invokevirtual 131	android/os/Bundle:writeToParcel	(Landroid/os/Parcel;I)V
        //   29: aload_0
        //   30: getfield 17	com/yelp/android/bj/b$a$a:a	Landroid/os/IBinder;
        //   33: bipush 54
        //   35: aload_2
        //   36: aload_3
        //   37: iconst_0
        //   38: invokeinterface 39 5 0
        //   43: pop
        //   44: aload_3
        //   45: invokevirtual 42	android/os/Parcel:readException	()V
        //   48: aload_3
        //   49: invokevirtual 60	android/os/Parcel:recycle	()V
        //   52: aload_2
        //   53: invokevirtual 60	android/os/Parcel:recycle	()V
        //   56: return
        //   57: aload_2
        //   58: iconst_0
        //   59: invokevirtual 66	android/os/Parcel:writeInt	(I)V
        //   62: goto -33 -> 29
        //   65: astore_1
        //   66: aload_3
        //   67: invokevirtual 60	android/os/Parcel:recycle	()V
        //   70: aload_2
        //   71: invokevirtual 60	android/os/Parcel:recycle	()V
        //   74: aload_1
        //   75: athrow
        // Local variable table:
        //   start	length	slot	name	signature
        //   0	76	0	this	a
        //   0	76	1	paramBundle	Bundle
        //   3	68	2	localParcel1	Parcel
        //   7	60	3	localParcel2	Parcel
        // Exception table:
        //   from	to	target	type
        //   8	14	65	finally
        //   18	29	65	finally
        //   29	48	65	finally
        //   57	62	65	finally
      }
      
      /* Error */
      public void a(com.google.android.gms.dynamic.c paramc)
        throws RemoteException
      {
        // Byte code:
        //   0: invokestatic 27	android/os/Parcel:obtain	()Landroid/os/Parcel;
        //   3: astore_2
        //   4: invokestatic 27	android/os/Parcel:obtain	()Landroid/os/Parcel;
        //   7: astore_3
        //   8: aload_2
        //   9: ldc 29
        //   11: invokevirtual 33	android/os/Parcel:writeInterfaceToken	(Ljava/lang/String;)V
        //   14: aload_1
        //   15: ifnull +42 -> 57
        //   18: aload_1
        //   19: invokeinterface 137 1 0
        //   24: astore_1
        //   25: aload_2
        //   26: aload_1
        //   27: invokevirtual 140	android/os/Parcel:writeStrongBinder	(Landroid/os/IBinder;)V
        //   30: aload_0
        //   31: getfield 17	com/yelp/android/bj/b$a$a:a	Landroid/os/IBinder;
        //   34: iconst_4
        //   35: aload_2
        //   36: aload_3
        //   37: iconst_0
        //   38: invokeinterface 39 5 0
        //   43: pop
        //   44: aload_3
        //   45: invokevirtual 42	android/os/Parcel:readException	()V
        //   48: aload_3
        //   49: invokevirtual 60	android/os/Parcel:recycle	()V
        //   52: aload_2
        //   53: invokevirtual 60	android/os/Parcel:recycle	()V
        //   56: return
        //   57: aconst_null
        //   58: astore_1
        //   59: goto -34 -> 25
        //   62: astore_1
        //   63: aload_3
        //   64: invokevirtual 60	android/os/Parcel:recycle	()V
        //   67: aload_2
        //   68: invokevirtual 60	android/os/Parcel:recycle	()V
        //   71: aload_1
        //   72: athrow
        // Local variable table:
        //   start	length	slot	name	signature
        //   0	73	0	this	a
        //   0	73	1	paramc	com.google.android.gms.dynamic.c
        //   3	65	2	localParcel1	Parcel
        //   7	57	3	localParcel2	Parcel
        // Exception table:
        //   from	to	target	type
        //   8	14	62	finally
        //   18	25	62	finally
        //   25	48	62	finally
      }
      
      /* Error */
      public void a(com.google.android.gms.dynamic.c paramc, int paramInt, r paramr)
        throws RemoteException
      {
        // Byte code:
        //   0: aconst_null
        //   1: astore 4
        //   3: invokestatic 27	android/os/Parcel:obtain	()Landroid/os/Parcel;
        //   6: astore 5
        //   8: invokestatic 27	android/os/Parcel:obtain	()Landroid/os/Parcel;
        //   11: astore 6
        //   13: aload 5
        //   15: ldc 29
        //   17: invokevirtual 33	android/os/Parcel:writeInterfaceToken	(Ljava/lang/String;)V
        //   20: aload_1
        //   21: ifnull +75 -> 96
        //   24: aload_1
        //   25: invokeinterface 137 1 0
        //   30: astore_1
        //   31: aload 5
        //   33: aload_1
        //   34: invokevirtual 140	android/os/Parcel:writeStrongBinder	(Landroid/os/IBinder;)V
        //   37: aload 5
        //   39: iload_2
        //   40: invokevirtual 66	android/os/Parcel:writeInt	(I)V
        //   43: aload 4
        //   45: astore_1
        //   46: aload_3
        //   47: ifnull +10 -> 57
        //   50: aload_3
        //   51: invokeinterface 144 1 0
        //   56: astore_1
        //   57: aload 5
        //   59: aload_1
        //   60: invokevirtual 140	android/os/Parcel:writeStrongBinder	(Landroid/os/IBinder;)V
        //   63: aload_0
        //   64: getfield 17	com/yelp/android/bj/b$a$a:a	Landroid/os/IBinder;
        //   67: bipush 7
        //   69: aload 5
        //   71: aload 6
        //   73: iconst_0
        //   74: invokeinterface 39 5 0
        //   79: pop
        //   80: aload 6
        //   82: invokevirtual 42	android/os/Parcel:readException	()V
        //   85: aload 6
        //   87: invokevirtual 60	android/os/Parcel:recycle	()V
        //   90: aload 5
        //   92: invokevirtual 60	android/os/Parcel:recycle	()V
        //   95: return
        //   96: aconst_null
        //   97: astore_1
        //   98: goto -67 -> 31
        //   101: astore_1
        //   102: aload 6
        //   104: invokevirtual 60	android/os/Parcel:recycle	()V
        //   107: aload 5
        //   109: invokevirtual 60	android/os/Parcel:recycle	()V
        //   112: aload_1
        //   113: athrow
        // Local variable table:
        //   start	length	slot	name	signature
        //   0	114	0	this	a
        //   0	114	1	paramc	com.google.android.gms.dynamic.c
        //   0	114	2	paramInt	int
        //   0	114	3	paramr	r
        //   1	43	4	localObject	Object
        //   6	102	5	localParcel1	Parcel
        //   11	92	6	localParcel2	Parcel
        // Exception table:
        //   from	to	target	type
        //   13	20	101	finally
        //   24	31	101	finally
        //   31	43	101	finally
        //   50	57	101	finally
        //   57	85	101	finally
      }
      
      /* Error */
      public void a(com.google.android.gms.dynamic.c paramc, r paramr)
        throws RemoteException
      {
        // Byte code:
        //   0: aconst_null
        //   1: astore_3
        //   2: invokestatic 27	android/os/Parcel:obtain	()Landroid/os/Parcel;
        //   5: astore 4
        //   7: invokestatic 27	android/os/Parcel:obtain	()Landroid/os/Parcel;
        //   10: astore 5
        //   12: aload 4
        //   14: ldc 29
        //   16: invokevirtual 33	android/os/Parcel:writeInterfaceToken	(Ljava/lang/String;)V
        //   19: aload_1
        //   20: ifnull +68 -> 88
        //   23: aload_1
        //   24: invokeinterface 137 1 0
        //   29: astore_1
        //   30: aload 4
        //   32: aload_1
        //   33: invokevirtual 140	android/os/Parcel:writeStrongBinder	(Landroid/os/IBinder;)V
        //   36: aload_3
        //   37: astore_1
        //   38: aload_2
        //   39: ifnull +10 -> 49
        //   42: aload_2
        //   43: invokeinterface 144 1 0
        //   48: astore_1
        //   49: aload 4
        //   51: aload_1
        //   52: invokevirtual 140	android/os/Parcel:writeStrongBinder	(Landroid/os/IBinder;)V
        //   55: aload_0
        //   56: getfield 17	com/yelp/android/bj/b$a$a:a	Landroid/os/IBinder;
        //   59: bipush 6
        //   61: aload 4
        //   63: aload 5
        //   65: iconst_0
        //   66: invokeinterface 39 5 0
        //   71: pop
        //   72: aload 5
        //   74: invokevirtual 42	android/os/Parcel:readException	()V
        //   77: aload 5
        //   79: invokevirtual 60	android/os/Parcel:recycle	()V
        //   82: aload 4
        //   84: invokevirtual 60	android/os/Parcel:recycle	()V
        //   87: return
        //   88: aconst_null
        //   89: astore_1
        //   90: goto -60 -> 30
        //   93: astore_1
        //   94: aload 5
        //   96: invokevirtual 60	android/os/Parcel:recycle	()V
        //   99: aload 4
        //   101: invokevirtual 60	android/os/Parcel:recycle	()V
        //   104: aload_1
        //   105: athrow
        // Local variable table:
        //   start	length	slot	name	signature
        //   0	106	0	this	a
        //   0	106	1	paramc	com.google.android.gms.dynamic.c
        //   0	106	2	paramr	r
        //   1	36	3	localObject	Object
        //   5	95	4	localParcel1	Parcel
        //   10	85	5	localParcel2	Parcel
        // Exception table:
        //   from	to	target	type
        //   12	19	93	finally
        //   23	30	93	finally
        //   30	36	93	finally
        //   42	49	93	finally
        //   49	77	93	finally
      }
      
      /* Error */
      public void a(ab paramab)
        throws RemoteException
      {
        // Byte code:
        //   0: invokestatic 27	android/os/Parcel:obtain	()Landroid/os/Parcel;
        //   3: astore_2
        //   4: invokestatic 27	android/os/Parcel:obtain	()Landroid/os/Parcel;
        //   7: astore_3
        //   8: aload_2
        //   9: ldc 29
        //   11: invokevirtual 33	android/os/Parcel:writeInterfaceToken	(Ljava/lang/String;)V
        //   14: aload_1
        //   15: ifnull +43 -> 58
        //   18: aload_1
        //   19: invokeinterface 149 1 0
        //   24: astore_1
        //   25: aload_2
        //   26: aload_1
        //   27: invokevirtual 140	android/os/Parcel:writeStrongBinder	(Landroid/os/IBinder;)V
        //   30: aload_0
        //   31: getfield 17	com/yelp/android/bj/b$a$a:a	Landroid/os/IBinder;
        //   34: bipush 28
        //   36: aload_2
        //   37: aload_3
        //   38: iconst_0
        //   39: invokeinterface 39 5 0
        //   44: pop
        //   45: aload_3
        //   46: invokevirtual 42	android/os/Parcel:readException	()V
        //   49: aload_3
        //   50: invokevirtual 60	android/os/Parcel:recycle	()V
        //   53: aload_2
        //   54: invokevirtual 60	android/os/Parcel:recycle	()V
        //   57: return
        //   58: aconst_null
        //   59: astore_1
        //   60: goto -35 -> 25
        //   63: astore_1
        //   64: aload_3
        //   65: invokevirtual 60	android/os/Parcel:recycle	()V
        //   68: aload_2
        //   69: invokevirtual 60	android/os/Parcel:recycle	()V
        //   72: aload_1
        //   73: athrow
        // Local variable table:
        //   start	length	slot	name	signature
        //   0	74	0	this	a
        //   0	74	1	paramab	ab
        //   3	66	2	localParcel1	Parcel
        //   7	58	3	localParcel2	Parcel
        // Exception table:
        //   from	to	target	type
        //   8	14	63	finally
        //   18	25	63	finally
        //   25	49	63	finally
      }
      
      /* Error */
      public void a(ac paramac)
        throws RemoteException
      {
        // Byte code:
        //   0: invokestatic 27	android/os/Parcel:obtain	()Landroid/os/Parcel;
        //   3: astore_2
        //   4: invokestatic 27	android/os/Parcel:obtain	()Landroid/os/Parcel;
        //   7: astore_3
        //   8: aload_2
        //   9: ldc 29
        //   11: invokevirtual 33	android/os/Parcel:writeInterfaceToken	(Ljava/lang/String;)V
        //   14: aload_1
        //   15: ifnull +43 -> 58
        //   18: aload_1
        //   19: invokeinterface 153 1 0
        //   24: astore_1
        //   25: aload_2
        //   26: aload_1
        //   27: invokevirtual 140	android/os/Parcel:writeStrongBinder	(Landroid/os/IBinder;)V
        //   30: aload_0
        //   31: getfield 17	com/yelp/android/bj/b$a$a:a	Landroid/os/IBinder;
        //   34: bipush 42
        //   36: aload_2
        //   37: aload_3
        //   38: iconst_0
        //   39: invokeinterface 39 5 0
        //   44: pop
        //   45: aload_3
        //   46: invokevirtual 42	android/os/Parcel:readException	()V
        //   49: aload_3
        //   50: invokevirtual 60	android/os/Parcel:recycle	()V
        //   53: aload_2
        //   54: invokevirtual 60	android/os/Parcel:recycle	()V
        //   57: return
        //   58: aconst_null
        //   59: astore_1
        //   60: goto -35 -> 25
        //   63: astore_1
        //   64: aload_3
        //   65: invokevirtual 60	android/os/Parcel:recycle	()V
        //   68: aload_2
        //   69: invokevirtual 60	android/os/Parcel:recycle	()V
        //   72: aload_1
        //   73: athrow
        // Local variable table:
        //   start	length	slot	name	signature
        //   0	74	0	this	a
        //   0	74	1	paramac	ac
        //   3	66	2	localParcel1	Parcel
        //   7	58	3	localParcel2	Parcel
        // Exception table:
        //   from	to	target	type
        //   8	14	63	finally
        //   18	25	63	finally
        //   25	49	63	finally
      }
      
      /* Error */
      public void a(ad paramad)
        throws RemoteException
      {
        // Byte code:
        //   0: invokestatic 27	android/os/Parcel:obtain	()Landroid/os/Parcel;
        //   3: astore_2
        //   4: invokestatic 27	android/os/Parcel:obtain	()Landroid/os/Parcel;
        //   7: astore_3
        //   8: aload_2
        //   9: ldc 29
        //   11: invokevirtual 33	android/os/Parcel:writeInterfaceToken	(Ljava/lang/String;)V
        //   14: aload_1
        //   15: ifnull +43 -> 58
        //   18: aload_1
        //   19: invokeinterface 157 1 0
        //   24: astore_1
        //   25: aload_2
        //   26: aload_1
        //   27: invokevirtual 140	android/os/Parcel:writeStrongBinder	(Landroid/os/IBinder;)V
        //   30: aload_0
        //   31: getfield 17	com/yelp/android/bj/b$a$a:a	Landroid/os/IBinder;
        //   34: bipush 29
        //   36: aload_2
        //   37: aload_3
        //   38: iconst_0
        //   39: invokeinterface 39 5 0
        //   44: pop
        //   45: aload_3
        //   46: invokevirtual 42	android/os/Parcel:readException	()V
        //   49: aload_3
        //   50: invokevirtual 60	android/os/Parcel:recycle	()V
        //   53: aload_2
        //   54: invokevirtual 60	android/os/Parcel:recycle	()V
        //   57: return
        //   58: aconst_null
        //   59: astore_1
        //   60: goto -35 -> 25
        //   63: astore_1
        //   64: aload_3
        //   65: invokevirtual 60	android/os/Parcel:recycle	()V
        //   68: aload_2
        //   69: invokevirtual 60	android/os/Parcel:recycle	()V
        //   72: aload_1
        //   73: athrow
        // Local variable table:
        //   start	length	slot	name	signature
        //   0	74	0	this	a
        //   0	74	1	paramad	ad
        //   3	66	2	localParcel1	Parcel
        //   7	58	3	localParcel2	Parcel
        // Exception table:
        //   from	to	target	type
        //   8	14	63	finally
        //   18	25	63	finally
        //   25	49	63	finally
      }
      
      /* Error */
      public void a(ae paramae)
        throws RemoteException
      {
        // Byte code:
        //   0: invokestatic 27	android/os/Parcel:obtain	()Landroid/os/Parcel;
        //   3: astore_2
        //   4: invokestatic 27	android/os/Parcel:obtain	()Landroid/os/Parcel;
        //   7: astore_3
        //   8: aload_2
        //   9: ldc 29
        //   11: invokevirtual 33	android/os/Parcel:writeInterfaceToken	(Ljava/lang/String;)V
        //   14: aload_1
        //   15: ifnull +43 -> 58
        //   18: aload_1
        //   19: invokeinterface 161 1 0
        //   24: astore_1
        //   25: aload_2
        //   26: aload_1
        //   27: invokevirtual 140	android/os/Parcel:writeStrongBinder	(Landroid/os/IBinder;)V
        //   30: aload_0
        //   31: getfield 17	com/yelp/android/bj/b$a$a:a	Landroid/os/IBinder;
        //   34: bipush 53
        //   36: aload_2
        //   37: aload_3
        //   38: iconst_0
        //   39: invokeinterface 39 5 0
        //   44: pop
        //   45: aload_3
        //   46: invokevirtual 42	android/os/Parcel:readException	()V
        //   49: aload_3
        //   50: invokevirtual 60	android/os/Parcel:recycle	()V
        //   53: aload_2
        //   54: invokevirtual 60	android/os/Parcel:recycle	()V
        //   57: return
        //   58: aconst_null
        //   59: astore_1
        //   60: goto -35 -> 25
        //   63: astore_1
        //   64: aload_3
        //   65: invokevirtual 60	android/os/Parcel:recycle	()V
        //   68: aload_2
        //   69: invokevirtual 60	android/os/Parcel:recycle	()V
        //   72: aload_1
        //   73: athrow
        // Local variable table:
        //   start	length	slot	name	signature
        //   0	74	0	this	a
        //   0	74	1	paramae	ae
        //   3	66	2	localParcel1	Parcel
        //   7	58	3	localParcel2	Parcel
        // Exception table:
        //   from	to	target	type
        //   8	14	63	finally
        //   18	25	63	finally
        //   25	49	63	finally
      }
      
      /* Error */
      public void a(af paramaf)
        throws RemoteException
      {
        // Byte code:
        //   0: invokestatic 27	android/os/Parcel:obtain	()Landroid/os/Parcel;
        //   3: astore_2
        //   4: invokestatic 27	android/os/Parcel:obtain	()Landroid/os/Parcel;
        //   7: astore_3
        //   8: aload_2
        //   9: ldc 29
        //   11: invokevirtual 33	android/os/Parcel:writeInterfaceToken	(Ljava/lang/String;)V
        //   14: aload_1
        //   15: ifnull +43 -> 58
        //   18: aload_1
        //   19: invokeinterface 165 1 0
        //   24: astore_1
        //   25: aload_2
        //   26: aload_1
        //   27: invokevirtual 140	android/os/Parcel:writeStrongBinder	(Landroid/os/IBinder;)V
        //   30: aload_0
        //   31: getfield 17	com/yelp/android/bj/b$a$a:a	Landroid/os/IBinder;
        //   34: bipush 30
        //   36: aload_2
        //   37: aload_3
        //   38: iconst_0
        //   39: invokeinterface 39 5 0
        //   44: pop
        //   45: aload_3
        //   46: invokevirtual 42	android/os/Parcel:readException	()V
        //   49: aload_3
        //   50: invokevirtual 60	android/os/Parcel:recycle	()V
        //   53: aload_2
        //   54: invokevirtual 60	android/os/Parcel:recycle	()V
        //   57: return
        //   58: aconst_null
        //   59: astore_1
        //   60: goto -35 -> 25
        //   63: astore_1
        //   64: aload_3
        //   65: invokevirtual 60	android/os/Parcel:recycle	()V
        //   68: aload_2
        //   69: invokevirtual 60	android/os/Parcel:recycle	()V
        //   72: aload_1
        //   73: athrow
        // Local variable table:
        //   start	length	slot	name	signature
        //   0	74	0	this	a
        //   0	74	1	paramaf	af
        //   3	66	2	localParcel1	Parcel
        //   7	58	3	localParcel2	Parcel
        // Exception table:
        //   from	to	target	type
        //   8	14	63	finally
        //   18	25	63	finally
        //   25	49	63	finally
      }
      
      /* Error */
      public void a(ag paramag)
        throws RemoteException
      {
        // Byte code:
        //   0: invokestatic 27	android/os/Parcel:obtain	()Landroid/os/Parcel;
        //   3: astore_2
        //   4: invokestatic 27	android/os/Parcel:obtain	()Landroid/os/Parcel;
        //   7: astore_3
        //   8: aload_2
        //   9: ldc 29
        //   11: invokevirtual 33	android/os/Parcel:writeInterfaceToken	(Ljava/lang/String;)V
        //   14: aload_1
        //   15: ifnull +43 -> 58
        //   18: aload_1
        //   19: invokeinterface 169 1 0
        //   24: astore_1
        //   25: aload_2
        //   26: aload_1
        //   27: invokevirtual 140	android/os/Parcel:writeStrongBinder	(Landroid/os/IBinder;)V
        //   30: aload_0
        //   31: getfield 17	com/yelp/android/bj/b$a$a:a	Landroid/os/IBinder;
        //   34: bipush 31
        //   36: aload_2
        //   37: aload_3
        //   38: iconst_0
        //   39: invokeinterface 39 5 0
        //   44: pop
        //   45: aload_3
        //   46: invokevirtual 42	android/os/Parcel:readException	()V
        //   49: aload_3
        //   50: invokevirtual 60	android/os/Parcel:recycle	()V
        //   53: aload_2
        //   54: invokevirtual 60	android/os/Parcel:recycle	()V
        //   57: return
        //   58: aconst_null
        //   59: astore_1
        //   60: goto -35 -> 25
        //   63: astore_1
        //   64: aload_3
        //   65: invokevirtual 60	android/os/Parcel:recycle	()V
        //   68: aload_2
        //   69: invokevirtual 60	android/os/Parcel:recycle	()V
        //   72: aload_1
        //   73: athrow
        // Local variable table:
        //   start	length	slot	name	signature
        //   0	74	0	this	a
        //   0	74	1	paramag	ag
        //   3	66	2	localParcel1	Parcel
        //   7	58	3	localParcel2	Parcel
        // Exception table:
        //   from	to	target	type
        //   8	14	63	finally
        //   18	25	63	finally
        //   25	49	63	finally
      }
      
      /* Error */
      public void a(ah paramah)
        throws RemoteException
      {
        // Byte code:
        //   0: invokestatic 27	android/os/Parcel:obtain	()Landroid/os/Parcel;
        //   3: astore_2
        //   4: invokestatic 27	android/os/Parcel:obtain	()Landroid/os/Parcel;
        //   7: astore_3
        //   8: aload_2
        //   9: ldc 29
        //   11: invokevirtual 33	android/os/Parcel:writeInterfaceToken	(Ljava/lang/String;)V
        //   14: aload_1
        //   15: ifnull +43 -> 58
        //   18: aload_1
        //   19: invokeinterface 173 1 0
        //   24: astore_1
        //   25: aload_2
        //   26: aload_1
        //   27: invokevirtual 140	android/os/Parcel:writeStrongBinder	(Landroid/os/IBinder;)V
        //   30: aload_0
        //   31: getfield 17	com/yelp/android/bj/b$a$a:a	Landroid/os/IBinder;
        //   34: bipush 37
        //   36: aload_2
        //   37: aload_3
        //   38: iconst_0
        //   39: invokeinterface 39 5 0
        //   44: pop
        //   45: aload_3
        //   46: invokevirtual 42	android/os/Parcel:readException	()V
        //   49: aload_3
        //   50: invokevirtual 60	android/os/Parcel:recycle	()V
        //   53: aload_2
        //   54: invokevirtual 60	android/os/Parcel:recycle	()V
        //   57: return
        //   58: aconst_null
        //   59: astore_1
        //   60: goto -35 -> 25
        //   63: astore_1
        //   64: aload_3
        //   65: invokevirtual 60	android/os/Parcel:recycle	()V
        //   68: aload_2
        //   69: invokevirtual 60	android/os/Parcel:recycle	()V
        //   72: aload_1
        //   73: athrow
        // Local variable table:
        //   start	length	slot	name	signature
        //   0	74	0	this	a
        //   0	74	1	paramah	ah
        //   3	66	2	localParcel1	Parcel
        //   7	58	3	localParcel2	Parcel
        // Exception table:
        //   from	to	target	type
        //   8	14	63	finally
        //   18	25	63	finally
        //   25	49	63	finally
      }
      
      /* Error */
      public void a(ai paramai)
        throws RemoteException
      {
        // Byte code:
        //   0: invokestatic 27	android/os/Parcel:obtain	()Landroid/os/Parcel;
        //   3: astore_2
        //   4: invokestatic 27	android/os/Parcel:obtain	()Landroid/os/Parcel;
        //   7: astore_3
        //   8: aload_2
        //   9: ldc 29
        //   11: invokevirtual 33	android/os/Parcel:writeInterfaceToken	(Ljava/lang/String;)V
        //   14: aload_1
        //   15: ifnull +43 -> 58
        //   18: aload_1
        //   19: invokeinterface 177 1 0
        //   24: astore_1
        //   25: aload_2
        //   26: aload_1
        //   27: invokevirtual 140	android/os/Parcel:writeStrongBinder	(Landroid/os/IBinder;)V
        //   30: aload_0
        //   31: getfield 17	com/yelp/android/bj/b$a$a:a	Landroid/os/IBinder;
        //   34: bipush 36
        //   36: aload_2
        //   37: aload_3
        //   38: iconst_0
        //   39: invokeinterface 39 5 0
        //   44: pop
        //   45: aload_3
        //   46: invokevirtual 42	android/os/Parcel:readException	()V
        //   49: aload_3
        //   50: invokevirtual 60	android/os/Parcel:recycle	()V
        //   53: aload_2
        //   54: invokevirtual 60	android/os/Parcel:recycle	()V
        //   57: return
        //   58: aconst_null
        //   59: astore_1
        //   60: goto -35 -> 25
        //   63: astore_1
        //   64: aload_3
        //   65: invokevirtual 60	android/os/Parcel:recycle	()V
        //   68: aload_2
        //   69: invokevirtual 60	android/os/Parcel:recycle	()V
        //   72: aload_1
        //   73: athrow
        // Local variable table:
        //   start	length	slot	name	signature
        //   0	74	0	this	a
        //   0	74	1	paramai	ai
        //   3	66	2	localParcel1	Parcel
        //   7	58	3	localParcel2	Parcel
        // Exception table:
        //   from	to	target	type
        //   8	14	63	finally
        //   18	25	63	finally
        //   25	49	63	finally
      }
      
      /* Error */
      public void a(aj paramaj)
        throws RemoteException
      {
        // Byte code:
        //   0: invokestatic 27	android/os/Parcel:obtain	()Landroid/os/Parcel;
        //   3: astore_2
        //   4: invokestatic 27	android/os/Parcel:obtain	()Landroid/os/Parcel;
        //   7: astore_3
        //   8: aload_2
        //   9: ldc 29
        //   11: invokevirtual 33	android/os/Parcel:writeInterfaceToken	(Ljava/lang/String;)V
        //   14: aload_1
        //   15: ifnull +43 -> 58
        //   18: aload_1
        //   19: invokeinterface 181 1 0
        //   24: astore_1
        //   25: aload_2
        //   26: aload_1
        //   27: invokevirtual 140	android/os/Parcel:writeStrongBinder	(Landroid/os/IBinder;)V
        //   30: aload_0
        //   31: getfield 17	com/yelp/android/bj/b$a$a:a	Landroid/os/IBinder;
        //   34: bipush 80
        //   36: aload_2
        //   37: aload_3
        //   38: iconst_0
        //   39: invokeinterface 39 5 0
        //   44: pop
        //   45: aload_3
        //   46: invokevirtual 42	android/os/Parcel:readException	()V
        //   49: aload_3
        //   50: invokevirtual 60	android/os/Parcel:recycle	()V
        //   53: aload_2
        //   54: invokevirtual 60	android/os/Parcel:recycle	()V
        //   57: return
        //   58: aconst_null
        //   59: astore_1
        //   60: goto -35 -> 25
        //   63: astore_1
        //   64: aload_3
        //   65: invokevirtual 60	android/os/Parcel:recycle	()V
        //   68: aload_2
        //   69: invokevirtual 60	android/os/Parcel:recycle	()V
        //   72: aload_1
        //   73: athrow
        // Local variable table:
        //   start	length	slot	name	signature
        //   0	74	0	this	a
        //   0	74	1	paramaj	aj
        //   3	66	2	localParcel1	Parcel
        //   7	58	3	localParcel2	Parcel
        // Exception table:
        //   from	to	target	type
        //   8	14	63	finally
        //   18	25	63	finally
        //   25	49	63	finally
      }
      
      /* Error */
      public void a(ak paramak)
        throws RemoteException
      {
        // Byte code:
        //   0: invokestatic 27	android/os/Parcel:obtain	()Landroid/os/Parcel;
        //   3: astore_2
        //   4: invokestatic 27	android/os/Parcel:obtain	()Landroid/os/Parcel;
        //   7: astore_3
        //   8: aload_2
        //   9: ldc 29
        //   11: invokevirtual 33	android/os/Parcel:writeInterfaceToken	(Ljava/lang/String;)V
        //   14: aload_1
        //   15: ifnull +43 -> 58
        //   18: aload_1
        //   19: invokeinterface 185 1 0
        //   24: astore_1
        //   25: aload_2
        //   26: aload_1
        //   27: invokevirtual 140	android/os/Parcel:writeStrongBinder	(Landroid/os/IBinder;)V
        //   30: aload_0
        //   31: getfield 17	com/yelp/android/bj/b$a$a:a	Landroid/os/IBinder;
        //   34: bipush 85
        //   36: aload_2
        //   37: aload_3
        //   38: iconst_0
        //   39: invokeinterface 39 5 0
        //   44: pop
        //   45: aload_3
        //   46: invokevirtual 42	android/os/Parcel:readException	()V
        //   49: aload_3
        //   50: invokevirtual 60	android/os/Parcel:recycle	()V
        //   53: aload_2
        //   54: invokevirtual 60	android/os/Parcel:recycle	()V
        //   57: return
        //   58: aconst_null
        //   59: astore_1
        //   60: goto -35 -> 25
        //   63: astore_1
        //   64: aload_3
        //   65: invokevirtual 60	android/os/Parcel:recycle	()V
        //   68: aload_2
        //   69: invokevirtual 60	android/os/Parcel:recycle	()V
        //   72: aload_1
        //   73: athrow
        // Local variable table:
        //   start	length	slot	name	signature
        //   0	74	0	this	a
        //   0	74	1	paramak	ak
        //   3	66	2	localParcel1	Parcel
        //   7	58	3	localParcel2	Parcel
        // Exception table:
        //   from	to	target	type
        //   8	14	63	finally
        //   18	25	63	finally
        //   25	49	63	finally
      }
      
      /* Error */
      public void a(al paramal)
        throws RemoteException
      {
        // Byte code:
        //   0: invokestatic 27	android/os/Parcel:obtain	()Landroid/os/Parcel;
        //   3: astore_2
        //   4: invokestatic 27	android/os/Parcel:obtain	()Landroid/os/Parcel;
        //   7: astore_3
        //   8: aload_2
        //   9: ldc 29
        //   11: invokevirtual 33	android/os/Parcel:writeInterfaceToken	(Ljava/lang/String;)V
        //   14: aload_1
        //   15: ifnull +43 -> 58
        //   18: aload_1
        //   19: invokeinterface 189 1 0
        //   24: astore_1
        //   25: aload_2
        //   26: aload_1
        //   27: invokevirtual 140	android/os/Parcel:writeStrongBinder	(Landroid/os/IBinder;)V
        //   30: aload_0
        //   31: getfield 17	com/yelp/android/bj/b$a$a:a	Landroid/os/IBinder;
        //   34: bipush 87
        //   36: aload_2
        //   37: aload_3
        //   38: iconst_0
        //   39: invokeinterface 39 5 0
        //   44: pop
        //   45: aload_3
        //   46: invokevirtual 42	android/os/Parcel:readException	()V
        //   49: aload_3
        //   50: invokevirtual 60	android/os/Parcel:recycle	()V
        //   53: aload_2
        //   54: invokevirtual 60	android/os/Parcel:recycle	()V
        //   57: return
        //   58: aconst_null
        //   59: astore_1
        //   60: goto -35 -> 25
        //   63: astore_1
        //   64: aload_3
        //   65: invokevirtual 60	android/os/Parcel:recycle	()V
        //   68: aload_2
        //   69: invokevirtual 60	android/os/Parcel:recycle	()V
        //   72: aload_1
        //   73: athrow
        // Local variable table:
        //   start	length	slot	name	signature
        //   0	74	0	this	a
        //   0	74	1	paramal	al
        //   3	66	2	localParcel1	Parcel
        //   7	58	3	localParcel2	Parcel
        // Exception table:
        //   from	to	target	type
        //   8	14	63	finally
        //   18	25	63	finally
        //   25	49	63	finally
      }
      
      /* Error */
      public void a(c paramc)
        throws RemoteException
      {
        // Byte code:
        //   0: invokestatic 27	android/os/Parcel:obtain	()Landroid/os/Parcel;
        //   3: astore_2
        //   4: invokestatic 27	android/os/Parcel:obtain	()Landroid/os/Parcel;
        //   7: astore_3
        //   8: aload_2
        //   9: ldc 29
        //   11: invokevirtual 33	android/os/Parcel:writeInterfaceToken	(Ljava/lang/String;)V
        //   14: aload_1
        //   15: ifnull +43 -> 58
        //   18: aload_1
        //   19: invokeinterface 193 1 0
        //   24: astore_1
        //   25: aload_2
        //   26: aload_1
        //   27: invokevirtual 140	android/os/Parcel:writeStrongBinder	(Landroid/os/IBinder;)V
        //   30: aload_0
        //   31: getfield 17	com/yelp/android/bj/b$a$a:a	Landroid/os/IBinder;
        //   34: bipush 24
        //   36: aload_2
        //   37: aload_3
        //   38: iconst_0
        //   39: invokeinterface 39 5 0
        //   44: pop
        //   45: aload_3
        //   46: invokevirtual 42	android/os/Parcel:readException	()V
        //   49: aload_3
        //   50: invokevirtual 60	android/os/Parcel:recycle	()V
        //   53: aload_2
        //   54: invokevirtual 60	android/os/Parcel:recycle	()V
        //   57: return
        //   58: aconst_null
        //   59: astore_1
        //   60: goto -35 -> 25
        //   63: astore_1
        //   64: aload_3
        //   65: invokevirtual 60	android/os/Parcel:recycle	()V
        //   68: aload_2
        //   69: invokevirtual 60	android/os/Parcel:recycle	()V
        //   72: aload_1
        //   73: athrow
        // Local variable table:
        //   start	length	slot	name	signature
        //   0	74	0	this	a
        //   0	74	1	paramc	c
        //   3	66	2	localParcel1	Parcel
        //   7	58	3	localParcel2	Parcel
        // Exception table:
        //   from	to	target	type
        //   8	14	63	finally
        //   18	25	63	finally
        //   25	49	63	finally
      }
      
      /* Error */
      public void a(o paramo, com.google.android.gms.dynamic.c paramc)
        throws RemoteException
      {
        // Byte code:
        //   0: aconst_null
        //   1: astore_3
        //   2: invokestatic 27	android/os/Parcel:obtain	()Landroid/os/Parcel;
        //   5: astore 4
        //   7: invokestatic 27	android/os/Parcel:obtain	()Landroid/os/Parcel;
        //   10: astore 5
        //   12: aload 4
        //   14: ldc 29
        //   16: invokevirtual 33	android/os/Parcel:writeInterfaceToken	(Ljava/lang/String;)V
        //   19: aload_1
        //   20: ifnull +68 -> 88
        //   23: aload_1
        //   24: invokeinterface 197 1 0
        //   29: astore_1
        //   30: aload 4
        //   32: aload_1
        //   33: invokevirtual 140	android/os/Parcel:writeStrongBinder	(Landroid/os/IBinder;)V
        //   36: aload_3
        //   37: astore_1
        //   38: aload_2
        //   39: ifnull +10 -> 49
        //   42: aload_2
        //   43: invokeinterface 137 1 0
        //   48: astore_1
        //   49: aload 4
        //   51: aload_1
        //   52: invokevirtual 140	android/os/Parcel:writeStrongBinder	(Landroid/os/IBinder;)V
        //   55: aload_0
        //   56: getfield 17	com/yelp/android/bj/b$a$a:a	Landroid/os/IBinder;
        //   59: bipush 38
        //   61: aload 4
        //   63: aload 5
        //   65: iconst_0
        //   66: invokeinterface 39 5 0
        //   71: pop
        //   72: aload 5
        //   74: invokevirtual 42	android/os/Parcel:readException	()V
        //   77: aload 5
        //   79: invokevirtual 60	android/os/Parcel:recycle	()V
        //   82: aload 4
        //   84: invokevirtual 60	android/os/Parcel:recycle	()V
        //   87: return
        //   88: aconst_null
        //   89: astore_1
        //   90: goto -60 -> 30
        //   93: astore_1
        //   94: aload 5
        //   96: invokevirtual 60	android/os/Parcel:recycle	()V
        //   99: aload 4
        //   101: invokevirtual 60	android/os/Parcel:recycle	()V
        //   104: aload_1
        //   105: athrow
        // Local variable table:
        //   start	length	slot	name	signature
        //   0	106	0	this	a
        //   0	106	1	paramo	o
        //   0	106	2	paramc	com.google.android.gms.dynamic.c
        //   1	36	3	localObject	Object
        //   5	95	4	localParcel1	Parcel
        //   10	85	5	localParcel2	Parcel
        // Exception table:
        //   from	to	target	type
        //   12	19	93	finally
        //   23	30	93	finally
        //   30	36	93	finally
        //   42	49	93	finally
        //   49	77	93	finally
      }
      
      /* Error */
      public void a(t paramt)
        throws RemoteException
      {
        // Byte code:
        //   0: invokestatic 27	android/os/Parcel:obtain	()Landroid/os/Parcel;
        //   3: astore_2
        //   4: invokestatic 27	android/os/Parcel:obtain	()Landroid/os/Parcel;
        //   7: astore_3
        //   8: aload_2
        //   9: ldc 29
        //   11: invokevirtual 33	android/os/Parcel:writeInterfaceToken	(Ljava/lang/String;)V
        //   14: aload_1
        //   15: ifnull +43 -> 58
        //   18: aload_1
        //   19: invokeinterface 201 1 0
        //   24: astore_1
        //   25: aload_2
        //   26: aload_1
        //   27: invokevirtual 140	android/os/Parcel:writeStrongBinder	(Landroid/os/IBinder;)V
        //   30: aload_0
        //   31: getfield 17	com/yelp/android/bj/b$a$a:a	Landroid/os/IBinder;
        //   34: bipush 33
        //   36: aload_2
        //   37: aload_3
        //   38: iconst_0
        //   39: invokeinterface 39 5 0
        //   44: pop
        //   45: aload_3
        //   46: invokevirtual 42	android/os/Parcel:readException	()V
        //   49: aload_3
        //   50: invokevirtual 60	android/os/Parcel:recycle	()V
        //   53: aload_2
        //   54: invokevirtual 60	android/os/Parcel:recycle	()V
        //   57: return
        //   58: aconst_null
        //   59: astore_1
        //   60: goto -35 -> 25
        //   63: astore_1
        //   64: aload_3
        //   65: invokevirtual 60	android/os/Parcel:recycle	()V
        //   68: aload_2
        //   69: invokevirtual 60	android/os/Parcel:recycle	()V
        //   72: aload_1
        //   73: athrow
        // Local variable table:
        //   start	length	slot	name	signature
        //   0	74	0	this	a
        //   0	74	1	paramt	t
        //   3	66	2	localParcel1	Parcel
        //   7	58	3	localParcel2	Parcel
        // Exception table:
        //   from	to	target	type
        //   8	14	63	finally
        //   18	25	63	finally
        //   25	49	63	finally
      }
      
      /* Error */
      public void a(u paramu)
        throws RemoteException
      {
        // Byte code:
        //   0: invokestatic 27	android/os/Parcel:obtain	()Landroid/os/Parcel;
        //   3: astore_2
        //   4: invokestatic 27	android/os/Parcel:obtain	()Landroid/os/Parcel;
        //   7: astore_3
        //   8: aload_2
        //   9: ldc 29
        //   11: invokevirtual 33	android/os/Parcel:writeInterfaceToken	(Ljava/lang/String;)V
        //   14: aload_1
        //   15: ifnull +43 -> 58
        //   18: aload_1
        //   19: invokeinterface 205 1 0
        //   24: astore_1
        //   25: aload_2
        //   26: aload_1
        //   27: invokevirtual 140	android/os/Parcel:writeStrongBinder	(Landroid/os/IBinder;)V
        //   30: aload_0
        //   31: getfield 17	com/yelp/android/bj/b$a$a:a	Landroid/os/IBinder;
        //   34: bipush 27
        //   36: aload_2
        //   37: aload_3
        //   38: iconst_0
        //   39: invokeinterface 39 5 0
        //   44: pop
        //   45: aload_3
        //   46: invokevirtual 42	android/os/Parcel:readException	()V
        //   49: aload_3
        //   50: invokevirtual 60	android/os/Parcel:recycle	()V
        //   53: aload_2
        //   54: invokevirtual 60	android/os/Parcel:recycle	()V
        //   57: return
        //   58: aconst_null
        //   59: astore_1
        //   60: goto -35 -> 25
        //   63: astore_1
        //   64: aload_3
        //   65: invokevirtual 60	android/os/Parcel:recycle	()V
        //   68: aload_2
        //   69: invokevirtual 60	android/os/Parcel:recycle	()V
        //   72: aload_1
        //   73: athrow
        // Local variable table:
        //   start	length	slot	name	signature
        //   0	74	0	this	a
        //   0	74	1	paramu	u
        //   3	66	2	localParcel1	Parcel
        //   7	58	3	localParcel2	Parcel
        // Exception table:
        //   from	to	target	type
        //   8	14	63	finally
        //   18	25	63	finally
        //   25	49	63	finally
      }
      
      /* Error */
      public void a(v paramv)
        throws RemoteException
      {
        // Byte code:
        //   0: invokestatic 27	android/os/Parcel:obtain	()Landroid/os/Parcel;
        //   3: astore_2
        //   4: invokestatic 27	android/os/Parcel:obtain	()Landroid/os/Parcel;
        //   7: astore_3
        //   8: aload_2
        //   9: ldc 29
        //   11: invokevirtual 33	android/os/Parcel:writeInterfaceToken	(Ljava/lang/String;)V
        //   14: aload_1
        //   15: ifnull +43 -> 58
        //   18: aload_1
        //   19: invokeinterface 209 1 0
        //   24: astore_1
        //   25: aload_2
        //   26: aload_1
        //   27: invokevirtual 140	android/os/Parcel:writeStrongBinder	(Landroid/os/IBinder;)V
        //   30: aload_0
        //   31: getfield 17	com/yelp/android/bj/b$a$a:a	Landroid/os/IBinder;
        //   34: bipush 83
        //   36: aload_2
        //   37: aload_3
        //   38: iconst_0
        //   39: invokeinterface 39 5 0
        //   44: pop
        //   45: aload_3
        //   46: invokevirtual 42	android/os/Parcel:readException	()V
        //   49: aload_3
        //   50: invokevirtual 60	android/os/Parcel:recycle	()V
        //   53: aload_2
        //   54: invokevirtual 60	android/os/Parcel:recycle	()V
        //   57: return
        //   58: aconst_null
        //   59: astore_1
        //   60: goto -35 -> 25
        //   63: astore_1
        //   64: aload_3
        //   65: invokevirtual 60	android/os/Parcel:recycle	()V
        //   68: aload_2
        //   69: invokevirtual 60	android/os/Parcel:recycle	()V
        //   72: aload_1
        //   73: athrow
        // Local variable table:
        //   start	length	slot	name	signature
        //   0	74	0	this	a
        //   0	74	1	paramv	v
        //   3	66	2	localParcel1	Parcel
        //   7	58	3	localParcel2	Parcel
        // Exception table:
        //   from	to	target	type
        //   8	14	63	finally
        //   18	25	63	finally
        //   25	49	63	finally
      }
      
      /* Error */
      public void a(w paramw)
        throws RemoteException
      {
        // Byte code:
        //   0: invokestatic 27	android/os/Parcel:obtain	()Landroid/os/Parcel;
        //   3: astore_2
        //   4: invokestatic 27	android/os/Parcel:obtain	()Landroid/os/Parcel;
        //   7: astore_3
        //   8: aload_2
        //   9: ldc 29
        //   11: invokevirtual 33	android/os/Parcel:writeInterfaceToken	(Ljava/lang/String;)V
        //   14: aload_1
        //   15: ifnull +43 -> 58
        //   18: aload_1
        //   19: invokeinterface 213 1 0
        //   24: astore_1
        //   25: aload_2
        //   26: aload_1
        //   27: invokevirtual 140	android/os/Parcel:writeStrongBinder	(Landroid/os/IBinder;)V
        //   30: aload_0
        //   31: getfield 17	com/yelp/android/bj/b$a$a:a	Landroid/os/IBinder;
        //   34: bipush 45
        //   36: aload_2
        //   37: aload_3
        //   38: iconst_0
        //   39: invokeinterface 39 5 0
        //   44: pop
        //   45: aload_3
        //   46: invokevirtual 42	android/os/Parcel:readException	()V
        //   49: aload_3
        //   50: invokevirtual 60	android/os/Parcel:recycle	()V
        //   53: aload_2
        //   54: invokevirtual 60	android/os/Parcel:recycle	()V
        //   57: return
        //   58: aconst_null
        //   59: astore_1
        //   60: goto -35 -> 25
        //   63: astore_1
        //   64: aload_3
        //   65: invokevirtual 60	android/os/Parcel:recycle	()V
        //   68: aload_2
        //   69: invokevirtual 60	android/os/Parcel:recycle	()V
        //   72: aload_1
        //   73: athrow
        // Local variable table:
        //   start	length	slot	name	signature
        //   0	74	0	this	a
        //   0	74	1	paramw	w
        //   3	66	2	localParcel1	Parcel
        //   7	58	3	localParcel2	Parcel
        // Exception table:
        //   from	to	target	type
        //   8	14	63	finally
        //   18	25	63	finally
        //   25	49	63	finally
      }
      
      /* Error */
      public void a(x paramx)
        throws RemoteException
      {
        // Byte code:
        //   0: invokestatic 27	android/os/Parcel:obtain	()Landroid/os/Parcel;
        //   3: astore_2
        //   4: invokestatic 27	android/os/Parcel:obtain	()Landroid/os/Parcel;
        //   7: astore_3
        //   8: aload_2
        //   9: ldc 29
        //   11: invokevirtual 33	android/os/Parcel:writeInterfaceToken	(Ljava/lang/String;)V
        //   14: aload_1
        //   15: ifnull +43 -> 58
        //   18: aload_1
        //   19: invokeinterface 217 1 0
        //   24: astore_1
        //   25: aload_2
        //   26: aload_1
        //   27: invokevirtual 140	android/os/Parcel:writeStrongBinder	(Landroid/os/IBinder;)V
        //   30: aload_0
        //   31: getfield 17	com/yelp/android/bj/b$a$a:a	Landroid/os/IBinder;
        //   34: bipush 32
        //   36: aload_2
        //   37: aload_3
        //   38: iconst_0
        //   39: invokeinterface 39 5 0
        //   44: pop
        //   45: aload_3
        //   46: invokevirtual 42	android/os/Parcel:readException	()V
        //   49: aload_3
        //   50: invokevirtual 60	android/os/Parcel:recycle	()V
        //   53: aload_2
        //   54: invokevirtual 60	android/os/Parcel:recycle	()V
        //   57: return
        //   58: aconst_null
        //   59: astore_1
        //   60: goto -35 -> 25
        //   63: astore_1
        //   64: aload_3
        //   65: invokevirtual 60	android/os/Parcel:recycle	()V
        //   68: aload_2
        //   69: invokevirtual 60	android/os/Parcel:recycle	()V
        //   72: aload_1
        //   73: athrow
        // Local variable table:
        //   start	length	slot	name	signature
        //   0	74	0	this	a
        //   0	74	1	paramx	x
        //   3	66	2	localParcel1	Parcel
        //   7	58	3	localParcel2	Parcel
        // Exception table:
        //   from	to	target	type
        //   8	14	63	finally
        //   18	25	63	finally
        //   25	49	63	finally
      }
      
      /* Error */
      public void a(y paramy)
        throws RemoteException
      {
        // Byte code:
        //   0: invokestatic 27	android/os/Parcel:obtain	()Landroid/os/Parcel;
        //   3: astore_2
        //   4: invokestatic 27	android/os/Parcel:obtain	()Landroid/os/Parcel;
        //   7: astore_3
        //   8: aload_2
        //   9: ldc 29
        //   11: invokevirtual 33	android/os/Parcel:writeInterfaceToken	(Ljava/lang/String;)V
        //   14: aload_1
        //   15: ifnull +43 -> 58
        //   18: aload_1
        //   19: invokeinterface 221 1 0
        //   24: astore_1
        //   25: aload_2
        //   26: aload_1
        //   27: invokevirtual 140	android/os/Parcel:writeStrongBinder	(Landroid/os/IBinder;)V
        //   30: aload_0
        //   31: getfield 17	com/yelp/android/bj/b$a$a:a	Landroid/os/IBinder;
        //   34: bipush 86
        //   36: aload_2
        //   37: aload_3
        //   38: iconst_0
        //   39: invokeinterface 39 5 0
        //   44: pop
        //   45: aload_3
        //   46: invokevirtual 42	android/os/Parcel:readException	()V
        //   49: aload_3
        //   50: invokevirtual 60	android/os/Parcel:recycle	()V
        //   53: aload_2
        //   54: invokevirtual 60	android/os/Parcel:recycle	()V
        //   57: return
        //   58: aconst_null
        //   59: astore_1
        //   60: goto -35 -> 25
        //   63: astore_1
        //   64: aload_3
        //   65: invokevirtual 60	android/os/Parcel:recycle	()V
        //   68: aload_2
        //   69: invokevirtual 60	android/os/Parcel:recycle	()V
        //   72: aload_1
        //   73: athrow
        // Local variable table:
        //   start	length	slot	name	signature
        //   0	74	0	this	a
        //   0	74	1	paramy	y
        //   3	66	2	localParcel1	Parcel
        //   7	58	3	localParcel2	Parcel
        // Exception table:
        //   from	to	target	type
        //   8	14	63	finally
        //   18	25	63	finally
        //   25	49	63	finally
      }
      
      /* Error */
      public void a(z paramz)
        throws RemoteException
      {
        // Byte code:
        //   0: invokestatic 27	android/os/Parcel:obtain	()Landroid/os/Parcel;
        //   3: astore_2
        //   4: invokestatic 27	android/os/Parcel:obtain	()Landroid/os/Parcel;
        //   7: astore_3
        //   8: aload_2
        //   9: ldc 29
        //   11: invokevirtual 33	android/os/Parcel:writeInterfaceToken	(Ljava/lang/String;)V
        //   14: aload_1
        //   15: ifnull +43 -> 58
        //   18: aload_1
        //   19: invokeinterface 225 1 0
        //   24: astore_1
        //   25: aload_2
        //   26: aload_1
        //   27: invokevirtual 140	android/os/Parcel:writeStrongBinder	(Landroid/os/IBinder;)V
        //   30: aload_0
        //   31: getfield 17	com/yelp/android/bj/b$a$a:a	Landroid/os/IBinder;
        //   34: bipush 84
        //   36: aload_2
        //   37: aload_3
        //   38: iconst_0
        //   39: invokeinterface 39 5 0
        //   44: pop
        //   45: aload_3
        //   46: invokevirtual 42	android/os/Parcel:readException	()V
        //   49: aload_3
        //   50: invokevirtual 60	android/os/Parcel:recycle	()V
        //   53: aload_2
        //   54: invokevirtual 60	android/os/Parcel:recycle	()V
        //   57: return
        //   58: aconst_null
        //   59: astore_1
        //   60: goto -35 -> 25
        //   63: astore_1
        //   64: aload_3
        //   65: invokevirtual 60	android/os/Parcel:recycle	()V
        //   68: aload_2
        //   69: invokevirtual 60	android/os/Parcel:recycle	()V
        //   72: aload_1
        //   73: athrow
        // Local variable table:
        //   start	length	slot	name	signature
        //   0	74	0	this	a
        //   0	74	1	paramz	z
        //   3	66	2	localParcel1	Parcel
        //   7	58	3	localParcel2	Parcel
        // Exception table:
        //   from	to	target	type
        //   8	14	63	finally
        //   18	25	63	finally
        //   25	49	63	finally
      }
      
      public void a(String paramString)
        throws RemoteException
      {
        Parcel localParcel1 = Parcel.obtain();
        Parcel localParcel2 = Parcel.obtain();
        try
        {
          localParcel1.writeInterfaceToken("com.google.android.gms.maps.internal.IGoogleMapDelegate");
          localParcel1.writeString(paramString);
          a.transact(61, localParcel1, localParcel2, 0);
          localParcel2.readException();
          return;
        }
        finally
        {
          localParcel2.recycle();
          localParcel1.recycle();
        }
      }
      
      public void a(boolean paramBoolean)
        throws RemoteException
      {
        int i = 0;
        Parcel localParcel1 = Parcel.obtain();
        Parcel localParcel2 = Parcel.obtain();
        try
        {
          localParcel1.writeInterfaceToken("com.google.android.gms.maps.internal.IGoogleMapDelegate");
          if (paramBoolean) {
            i = 1;
          }
          localParcel1.writeInt(i);
          a.transact(18, localParcel1, localParcel2, 0);
          localParcel2.readException();
          return;
        }
        finally
        {
          localParcel2.recycle();
          localParcel1.recycle();
        }
      }
      
      public IBinder asBinder()
      {
        return a;
      }
      
      public float b()
        throws RemoteException
      {
        Parcel localParcel1 = Parcel.obtain();
        Parcel localParcel2 = Parcel.obtain();
        try
        {
          localParcel1.writeInterfaceToken("com.google.android.gms.maps.internal.IGoogleMapDelegate");
          a.transact(2, localParcel1, localParcel2, 0);
          localParcel2.readException();
          float f = localParcel2.readFloat();
          return f;
        }
        finally
        {
          localParcel2.recycle();
          localParcel1.recycle();
        }
      }
      
      /* Error */
      public void b(Bundle paramBundle)
        throws RemoteException
      {
        // Byte code:
        //   0: invokestatic 27	android/os/Parcel:obtain	()Landroid/os/Parcel;
        //   3: astore_2
        //   4: invokestatic 27	android/os/Parcel:obtain	()Landroid/os/Parcel;
        //   7: astore_3
        //   8: aload_2
        //   9: ldc 29
        //   11: invokevirtual 33	android/os/Parcel:writeInterfaceToken	(Ljava/lang/String;)V
        //   14: aload_1
        //   15: ifnull +54 -> 69
        //   18: aload_2
        //   19: iconst_1
        //   20: invokevirtual 66	android/os/Parcel:writeInt	(I)V
        //   23: aload_1
        //   24: aload_2
        //   25: iconst_0
        //   26: invokevirtual 131	android/os/Bundle:writeToParcel	(Landroid/os/Parcel;I)V
        //   29: aload_0
        //   30: getfield 17	com/yelp/android/bj/b$a$a:a	Landroid/os/IBinder;
        //   33: bipush 60
        //   35: aload_2
        //   36: aload_3
        //   37: iconst_0
        //   38: invokeinterface 39 5 0
        //   43: pop
        //   44: aload_3
        //   45: invokevirtual 42	android/os/Parcel:readException	()V
        //   48: aload_3
        //   49: invokevirtual 46	android/os/Parcel:readInt	()I
        //   52: ifeq +8 -> 60
        //   55: aload_1
        //   56: aload_3
        //   57: invokevirtual 238	android/os/Bundle:readFromParcel	(Landroid/os/Parcel;)V
        //   60: aload_3
        //   61: invokevirtual 60	android/os/Parcel:recycle	()V
        //   64: aload_2
        //   65: invokevirtual 60	android/os/Parcel:recycle	()V
        //   68: return
        //   69: aload_2
        //   70: iconst_0
        //   71: invokevirtual 66	android/os/Parcel:writeInt	(I)V
        //   74: goto -45 -> 29
        //   77: astore_1
        //   78: aload_3
        //   79: invokevirtual 60	android/os/Parcel:recycle	()V
        //   82: aload_2
        //   83: invokevirtual 60	android/os/Parcel:recycle	()V
        //   86: aload_1
        //   87: athrow
        // Local variable table:
        //   start	length	slot	name	signature
        //   0	88	0	this	a
        //   0	88	1	paramBundle	Bundle
        //   3	80	2	localParcel1	Parcel
        //   7	72	3	localParcel2	Parcel
        // Exception table:
        //   from	to	target	type
        //   8	14	77	finally
        //   18	29	77	finally
        //   29	60	77	finally
        //   69	74	77	finally
      }
      
      /* Error */
      public void b(com.google.android.gms.dynamic.c paramc)
        throws RemoteException
      {
        // Byte code:
        //   0: invokestatic 27	android/os/Parcel:obtain	()Landroid/os/Parcel;
        //   3: astore_2
        //   4: invokestatic 27	android/os/Parcel:obtain	()Landroid/os/Parcel;
        //   7: astore_3
        //   8: aload_2
        //   9: ldc 29
        //   11: invokevirtual 33	android/os/Parcel:writeInterfaceToken	(Ljava/lang/String;)V
        //   14: aload_1
        //   15: ifnull +42 -> 57
        //   18: aload_1
        //   19: invokeinterface 137 1 0
        //   24: astore_1
        //   25: aload_2
        //   26: aload_1
        //   27: invokevirtual 140	android/os/Parcel:writeStrongBinder	(Landroid/os/IBinder;)V
        //   30: aload_0
        //   31: getfield 17	com/yelp/android/bj/b$a$a:a	Landroid/os/IBinder;
        //   34: iconst_5
        //   35: aload_2
        //   36: aload_3
        //   37: iconst_0
        //   38: invokeinterface 39 5 0
        //   43: pop
        //   44: aload_3
        //   45: invokevirtual 42	android/os/Parcel:readException	()V
        //   48: aload_3
        //   49: invokevirtual 60	android/os/Parcel:recycle	()V
        //   52: aload_2
        //   53: invokevirtual 60	android/os/Parcel:recycle	()V
        //   56: return
        //   57: aconst_null
        //   58: astore_1
        //   59: goto -34 -> 25
        //   62: astore_1
        //   63: aload_3
        //   64: invokevirtual 60	android/os/Parcel:recycle	()V
        //   67: aload_2
        //   68: invokevirtual 60	android/os/Parcel:recycle	()V
        //   71: aload_1
        //   72: athrow
        // Local variable table:
        //   start	length	slot	name	signature
        //   0	73	0	this	a
        //   0	73	1	paramc	com.google.android.gms.dynamic.c
        //   3	65	2	localParcel1	Parcel
        //   7	57	3	localParcel2	Parcel
        // Exception table:
        //   from	to	target	type
        //   8	14	62	finally
        //   18	25	62	finally
        //   25	48	62	finally
      }
      
      /* Error */
      public boolean b(boolean paramBoolean)
        throws RemoteException
      {
        // Byte code:
        //   0: iconst_1
        //   1: istore_3
        //   2: invokestatic 27	android/os/Parcel:obtain	()Landroid/os/Parcel;
        //   5: astore 4
        //   7: invokestatic 27	android/os/Parcel:obtain	()Landroid/os/Parcel;
        //   10: astore 5
        //   12: aload 4
        //   14: ldc 29
        //   16: invokevirtual 33	android/os/Parcel:writeInterfaceToken	(Ljava/lang/String;)V
        //   19: iload_1
        //   20: ifeq +57 -> 77
        //   23: iconst_1
        //   24: istore_2
        //   25: aload 4
        //   27: iload_2
        //   28: invokevirtual 66	android/os/Parcel:writeInt	(I)V
        //   31: aload_0
        //   32: getfield 17	com/yelp/android/bj/b$a$a:a	Landroid/os/IBinder;
        //   35: bipush 20
        //   37: aload 4
        //   39: aload 5
        //   41: iconst_0
        //   42: invokeinterface 39 5 0
        //   47: pop
        //   48: aload 5
        //   50: invokevirtual 42	android/os/Parcel:readException	()V
        //   53: aload 5
        //   55: invokevirtual 46	android/os/Parcel:readInt	()I
        //   58: istore_2
        //   59: iload_2
        //   60: ifeq +22 -> 82
        //   63: iload_3
        //   64: istore_1
        //   65: aload 5
        //   67: invokevirtual 60	android/os/Parcel:recycle	()V
        //   70: aload 4
        //   72: invokevirtual 60	android/os/Parcel:recycle	()V
        //   75: iload_1
        //   76: ireturn
        //   77: iconst_0
        //   78: istore_2
        //   79: goto -54 -> 25
        //   82: iconst_0
        //   83: istore_1
        //   84: goto -19 -> 65
        //   87: astore 6
        //   89: aload 5
        //   91: invokevirtual 60	android/os/Parcel:recycle	()V
        //   94: aload 4
        //   96: invokevirtual 60	android/os/Parcel:recycle	()V
        //   99: aload 6
        //   101: athrow
        // Local variable table:
        //   start	length	slot	name	signature
        //   0	102	0	this	a
        //   0	102	1	paramBoolean	boolean
        //   24	55	2	i	int
        //   1	63	3	bool	boolean
        //   5	90	4	localParcel1	Parcel
        //   10	80	5	localParcel2	Parcel
        //   87	13	6	localObject	Object
        // Exception table:
        //   from	to	target	type
        //   12	19	87	finally
        //   25	59	87	finally
      }
      
      public float c()
        throws RemoteException
      {
        Parcel localParcel1 = Parcel.obtain();
        Parcel localParcel2 = Parcel.obtain();
        try
        {
          localParcel1.writeInterfaceToken("com.google.android.gms.maps.internal.IGoogleMapDelegate");
          a.transact(3, localParcel1, localParcel2, 0);
          localParcel2.readException();
          float f = localParcel2.readFloat();
          return f;
        }
        finally
        {
          localParcel2.recycle();
          localParcel1.recycle();
        }
      }
      
      /* Error */
      public void c(Bundle paramBundle)
        throws RemoteException
      {
        // Byte code:
        //   0: invokestatic 27	android/os/Parcel:obtain	()Landroid/os/Parcel;
        //   3: astore_2
        //   4: invokestatic 27	android/os/Parcel:obtain	()Landroid/os/Parcel;
        //   7: astore_3
        //   8: aload_2
        //   9: ldc 29
        //   11: invokevirtual 33	android/os/Parcel:writeInterfaceToken	(Ljava/lang/String;)V
        //   14: aload_1
        //   15: ifnull +42 -> 57
        //   18: aload_2
        //   19: iconst_1
        //   20: invokevirtual 66	android/os/Parcel:writeInt	(I)V
        //   23: aload_1
        //   24: aload_2
        //   25: iconst_0
        //   26: invokevirtual 131	android/os/Bundle:writeToParcel	(Landroid/os/Parcel;I)V
        //   29: aload_0
        //   30: getfield 17	com/yelp/android/bj/b$a$a:a	Landroid/os/IBinder;
        //   33: bipush 81
        //   35: aload_2
        //   36: aload_3
        //   37: iconst_0
        //   38: invokeinterface 39 5 0
        //   43: pop
        //   44: aload_3
        //   45: invokevirtual 42	android/os/Parcel:readException	()V
        //   48: aload_3
        //   49: invokevirtual 60	android/os/Parcel:recycle	()V
        //   52: aload_2
        //   53: invokevirtual 60	android/os/Parcel:recycle	()V
        //   56: return
        //   57: aload_2
        //   58: iconst_0
        //   59: invokevirtual 66	android/os/Parcel:writeInt	(I)V
        //   62: goto -33 -> 29
        //   65: astore_1
        //   66: aload_3
        //   67: invokevirtual 60	android/os/Parcel:recycle	()V
        //   70: aload_2
        //   71: invokevirtual 60	android/os/Parcel:recycle	()V
        //   74: aload_1
        //   75: athrow
        // Local variable table:
        //   start	length	slot	name	signature
        //   0	76	0	this	a
        //   0	76	1	paramBundle	Bundle
        //   3	68	2	localParcel1	Parcel
        //   7	60	3	localParcel2	Parcel
        // Exception table:
        //   from	to	target	type
        //   8	14	65	finally
        //   18	29	65	finally
        //   29	48	65	finally
        //   57	62	65	finally
      }
      
      public void c(boolean paramBoolean)
        throws RemoteException
      {
        int i = 0;
        Parcel localParcel1 = Parcel.obtain();
        Parcel localParcel2 = Parcel.obtain();
        try
        {
          localParcel1.writeInterfaceToken("com.google.android.gms.maps.internal.IGoogleMapDelegate");
          if (paramBoolean) {
            i = 1;
          }
          localParcel1.writeInt(i);
          a.transact(22, localParcel1, localParcel2, 0);
          localParcel2.readException();
          return;
        }
        finally
        {
          localParcel2.recycle();
          localParcel1.recycle();
        }
      }
      
      public void d()
        throws RemoteException
      {
        Parcel localParcel1 = Parcel.obtain();
        Parcel localParcel2 = Parcel.obtain();
        try
        {
          localParcel1.writeInterfaceToken("com.google.android.gms.maps.internal.IGoogleMapDelegate");
          a.transact(8, localParcel1, localParcel2, 0);
          localParcel2.readException();
          return;
        }
        finally
        {
          localParcel2.recycle();
          localParcel1.recycle();
        }
      }
      
      public void d(boolean paramBoolean)
        throws RemoteException
      {
        int i = 0;
        Parcel localParcel1 = Parcel.obtain();
        Parcel localParcel2 = Parcel.obtain();
        try
        {
          localParcel1.writeInterfaceToken("com.google.android.gms.maps.internal.IGoogleMapDelegate");
          if (paramBoolean) {
            i = 1;
          }
          localParcel1.writeInt(i);
          a.transact(41, localParcel1, localParcel2, 0);
          localParcel2.readException();
          return;
        }
        finally
        {
          localParcel2.recycle();
          localParcel1.recycle();
        }
      }
      
      public void e()
        throws RemoteException
      {
        Parcel localParcel1 = Parcel.obtain();
        Parcel localParcel2 = Parcel.obtain();
        try
        {
          localParcel1.writeInterfaceToken("com.google.android.gms.maps.internal.IGoogleMapDelegate");
          a.transact(14, localParcel1, localParcel2, 0);
          localParcel2.readException();
          return;
        }
        finally
        {
          localParcel2.recycle();
          localParcel1.recycle();
        }
      }
      
      public int f()
        throws RemoteException
      {
        Parcel localParcel1 = Parcel.obtain();
        Parcel localParcel2 = Parcel.obtain();
        try
        {
          localParcel1.writeInterfaceToken("com.google.android.gms.maps.internal.IGoogleMapDelegate");
          a.transact(15, localParcel1, localParcel2, 0);
          localParcel2.readException();
          int i = localParcel2.readInt();
          return i;
        }
        finally
        {
          localParcel2.recycle();
          localParcel1.recycle();
        }
      }
      
      public boolean g()
        throws RemoteException
      {
        boolean bool = false;
        Parcel localParcel1 = Parcel.obtain();
        Parcel localParcel2 = Parcel.obtain();
        try
        {
          localParcel1.writeInterfaceToken("com.google.android.gms.maps.internal.IGoogleMapDelegate");
          a.transact(17, localParcel1, localParcel2, 0);
          localParcel2.readException();
          int i = localParcel2.readInt();
          if (i != 0) {
            bool = true;
          }
          return bool;
        }
        finally
        {
          localParcel2.recycle();
          localParcel1.recycle();
        }
      }
      
      public boolean h()
        throws RemoteException
      {
        boolean bool = false;
        Parcel localParcel1 = Parcel.obtain();
        Parcel localParcel2 = Parcel.obtain();
        try
        {
          localParcel1.writeInterfaceToken("com.google.android.gms.maps.internal.IGoogleMapDelegate");
          a.transact(19, localParcel1, localParcel2, 0);
          localParcel2.readException();
          int i = localParcel2.readInt();
          if (i != 0) {
            bool = true;
          }
          return bool;
        }
        finally
        {
          localParcel2.recycle();
          localParcel1.recycle();
        }
      }
      
      public boolean i()
        throws RemoteException
      {
        boolean bool = false;
        Parcel localParcel1 = Parcel.obtain();
        Parcel localParcel2 = Parcel.obtain();
        try
        {
          localParcel1.writeInterfaceToken("com.google.android.gms.maps.internal.IGoogleMapDelegate");
          a.transact(21, localParcel1, localParcel2, 0);
          localParcel2.readException();
          int i = localParcel2.readInt();
          if (i != 0) {
            bool = true;
          }
          return bool;
        }
        finally
        {
          localParcel2.recycle();
          localParcel1.recycle();
        }
      }
      
      /* Error */
      public Location j()
        throws RemoteException
      {
        // Byte code:
        //   0: invokestatic 27	android/os/Parcel:obtain	()Landroid/os/Parcel;
        //   3: astore_2
        //   4: invokestatic 27	android/os/Parcel:obtain	()Landroid/os/Parcel;
        //   7: astore_3
        //   8: aload_2
        //   9: ldc 29
        //   11: invokevirtual 33	android/os/Parcel:writeInterfaceToken	(Ljava/lang/String;)V
        //   14: aload_0
        //   15: getfield 17	com/yelp/android/bj/b$a$a:a	Landroid/os/IBinder;
        //   18: bipush 23
        //   20: aload_2
        //   21: aload_3
        //   22: iconst_0
        //   23: invokeinterface 39 5 0
        //   28: pop
        //   29: aload_3
        //   30: invokevirtual 42	android/os/Parcel:readException	()V
        //   33: aload_3
        //   34: invokevirtual 46	android/os/Parcel:readInt	()I
        //   37: ifeq +26 -> 63
        //   40: getstatic 254	android/location/Location:CREATOR	Landroid/os/Parcelable$Creator;
        //   43: aload_3
        //   44: invokeinterface 260 2 0
        //   49: checkcast 251	android/location/Location
        //   52: astore_1
        //   53: aload_3
        //   54: invokevirtual 60	android/os/Parcel:recycle	()V
        //   57: aload_2
        //   58: invokevirtual 60	android/os/Parcel:recycle	()V
        //   61: aload_1
        //   62: areturn
        //   63: aconst_null
        //   64: astore_1
        //   65: goto -12 -> 53
        //   68: astore_1
        //   69: aload_3
        //   70: invokevirtual 60	android/os/Parcel:recycle	()V
        //   73: aload_2
        //   74: invokevirtual 60	android/os/Parcel:recycle	()V
        //   77: aload_1
        //   78: athrow
        // Local variable table:
        //   start	length	slot	name	signature
        //   0	79	0	this	a
        //   52	13	1	localLocation	Location
        //   68	10	1	localObject	Object
        //   3	71	2	localParcel1	Parcel
        //   7	63	3	localParcel2	Parcel
        // Exception table:
        //   from	to	target	type
        //   8	53	68	finally
      }
      
      public j k()
        throws RemoteException
      {
        Parcel localParcel1 = Parcel.obtain();
        Parcel localParcel2 = Parcel.obtain();
        try
        {
          localParcel1.writeInterfaceToken("com.google.android.gms.maps.internal.IGoogleMapDelegate");
          a.transact(25, localParcel1, localParcel2, 0);
          localParcel2.readException();
          j localj = j.a.a(localParcel2.readStrongBinder());
          return localj;
        }
        finally
        {
          localParcel2.recycle();
          localParcel1.recycle();
        }
      }
      
      public f l()
        throws RemoteException
      {
        Parcel localParcel1 = Parcel.obtain();
        Parcel localParcel2 = Parcel.obtain();
        try
        {
          localParcel1.writeInterfaceToken("com.google.android.gms.maps.internal.IGoogleMapDelegate");
          a.transact(26, localParcel1, localParcel2, 0);
          localParcel2.readException();
          f localf = f.a.a(localParcel2.readStrongBinder());
          return localf;
        }
        finally
        {
          localParcel2.recycle();
          localParcel1.recycle();
        }
      }
      
      public boolean m()
        throws RemoteException
      {
        boolean bool = false;
        Parcel localParcel1 = Parcel.obtain();
        Parcel localParcel2 = Parcel.obtain();
        try
        {
          localParcel1.writeInterfaceToken("com.google.android.gms.maps.internal.IGoogleMapDelegate");
          a.transact(40, localParcel1, localParcel2, 0);
          localParcel2.readException();
          int i = localParcel2.readInt();
          if (i != 0) {
            bool = true;
          }
          return bool;
        }
        finally
        {
          localParcel2.recycle();
          localParcel1.recycle();
        }
      }
      
      public e n()
        throws RemoteException
      {
        Parcel localParcel1 = Parcel.obtain();
        Parcel localParcel2 = Parcel.obtain();
        try
        {
          localParcel1.writeInterfaceToken("com.google.android.gms.maps.internal.IGoogleMapDelegate");
          a.transact(44, localParcel1, localParcel2, 0);
          localParcel2.readException();
          e locale = e.a.a(localParcel2.readStrongBinder());
          return locale;
        }
        finally
        {
          localParcel2.recycle();
          localParcel1.recycle();
        }
      }
      
      public void o()
        throws RemoteException
      {
        Parcel localParcel1 = Parcel.obtain();
        Parcel localParcel2 = Parcel.obtain();
        try
        {
          localParcel1.writeInterfaceToken("com.google.android.gms.maps.internal.IGoogleMapDelegate");
          a.transact(55, localParcel1, localParcel2, 0);
          localParcel2.readException();
          return;
        }
        finally
        {
          localParcel2.recycle();
          localParcel1.recycle();
        }
      }
      
      public void p()
        throws RemoteException
      {
        Parcel localParcel1 = Parcel.obtain();
        Parcel localParcel2 = Parcel.obtain();
        try
        {
          localParcel1.writeInterfaceToken("com.google.android.gms.maps.internal.IGoogleMapDelegate");
          a.transact(56, localParcel1, localParcel2, 0);
          localParcel2.readException();
          return;
        }
        finally
        {
          localParcel2.recycle();
          localParcel1.recycle();
        }
      }
      
      public void q()
        throws RemoteException
      {
        Parcel localParcel1 = Parcel.obtain();
        Parcel localParcel2 = Parcel.obtain();
        try
        {
          localParcel1.writeInterfaceToken("com.google.android.gms.maps.internal.IGoogleMapDelegate");
          a.transact(57, localParcel1, localParcel2, 0);
          localParcel2.readException();
          return;
        }
        finally
        {
          localParcel2.recycle();
          localParcel1.recycle();
        }
      }
      
      public void r()
        throws RemoteException
      {
        Parcel localParcel1 = Parcel.obtain();
        Parcel localParcel2 = Parcel.obtain();
        try
        {
          localParcel1.writeInterfaceToken("com.google.android.gms.maps.internal.IGoogleMapDelegate");
          a.transact(58, localParcel1, localParcel2, 0);
          localParcel2.readException();
          return;
        }
        finally
        {
          localParcel2.recycle();
          localParcel1.recycle();
        }
      }
      
      public boolean s()
        throws RemoteException
      {
        boolean bool = false;
        Parcel localParcel1 = Parcel.obtain();
        Parcel localParcel2 = Parcel.obtain();
        try
        {
          localParcel1.writeInterfaceToken("com.google.android.gms.maps.internal.IGoogleMapDelegate");
          a.transact(59, localParcel1, localParcel2, 0);
          localParcel2.readException();
          int i = localParcel2.readInt();
          if (i != 0) {
            bool = true;
          }
          return bool;
        }
        finally
        {
          localParcel2.recycle();
          localParcel1.recycle();
        }
      }
      
      public void t()
        throws RemoteException
      {
        Parcel localParcel1 = Parcel.obtain();
        Parcel localParcel2 = Parcel.obtain();
        try
        {
          localParcel1.writeInterfaceToken("com.google.android.gms.maps.internal.IGoogleMapDelegate");
          a.transact(82, localParcel1, localParcel2, 0);
          localParcel2.readException();
          return;
        }
        finally
        {
          localParcel2.recycle();
          localParcel1.recycle();
        }
      }
    }
  }
}

/* Location:
 * Qualified Name:     com.yelp.android.bj.b
 * Java Class Version: 6 (50.0)
 * JD-Core Version:    0.7.1
 */