package com.yelp.android.bj;

import android.os.Binder;
import android.os.Bundle;
import android.os.IBinder;
import android.os.IInterface;
import android.os.Parcel;
import android.os.Parcelable.Creator;
import android.os.RemoteException;
import com.google.android.gms.dynamic.c;
import com.google.android.gms.dynamic.c.a;

public abstract interface e
  extends IInterface
{
  public abstract b a()
    throws RemoteException;
  
  public abstract void a(Bundle paramBundle)
    throws RemoteException;
  
  public abstract void a(ae paramae)
    throws RemoteException;
  
  public abstract void b()
    throws RemoteException;
  
  public abstract void b(Bundle paramBundle)
    throws RemoteException;
  
  public abstract void c()
    throws RemoteException;
  
  public abstract void c(Bundle paramBundle)
    throws RemoteException;
  
  public abstract void d()
    throws RemoteException;
  
  public abstract void e()
    throws RemoteException;
  
  public abstract c f()
    throws RemoteException;
  
  public abstract void g()
    throws RemoteException;
  
  public static abstract class a
    extends Binder
    implements e
  {
    public static e a(IBinder paramIBinder)
    {
      if (paramIBinder == null) {
        return null;
      }
      IInterface localIInterface = paramIBinder.queryLocalInterface("com.google.android.gms.maps.internal.IMapViewDelegate");
      if ((localIInterface != null) && ((localIInterface instanceof e))) {
        return (e)localIInterface;
      }
      return new a(paramIBinder);
    }
    
    public boolean onTransact(int paramInt1, Parcel paramParcel1, Parcel paramParcel2, int paramInt2)
      throws RemoteException
    {
      Object localObject2 = null;
      Object localObject3 = null;
      b localb = null;
      Object localObject4 = null;
      Object localObject1 = null;
      switch (paramInt1)
      {
      default: 
        return super.onTransact(paramInt1, paramParcel1, paramParcel2, paramInt2);
      case 1598968902: 
        paramParcel2.writeString("com.google.android.gms.maps.internal.IMapViewDelegate");
        return true;
      case 1: 
        paramParcel1.enforceInterface("com.google.android.gms.maps.internal.IMapViewDelegate");
        localb = a();
        paramParcel2.writeNoException();
        paramParcel1 = (Parcel)localObject1;
        if (localb != null) {
          paramParcel1 = localb.asBinder();
        }
        paramParcel2.writeStrongBinder(paramParcel1);
        return true;
      case 2: 
        paramParcel1.enforceInterface("com.google.android.gms.maps.internal.IMapViewDelegate");
        localObject1 = localObject2;
        if (paramParcel1.readInt() != 0) {
          localObject1 = (Bundle)Bundle.CREATOR.createFromParcel(paramParcel1);
        }
        a((Bundle)localObject1);
        paramParcel2.writeNoException();
        return true;
      case 3: 
        paramParcel1.enforceInterface("com.google.android.gms.maps.internal.IMapViewDelegate");
        b();
        paramParcel2.writeNoException();
        return true;
      case 4: 
        paramParcel1.enforceInterface("com.google.android.gms.maps.internal.IMapViewDelegate");
        c();
        paramParcel2.writeNoException();
        return true;
      case 5: 
        paramParcel1.enforceInterface("com.google.android.gms.maps.internal.IMapViewDelegate");
        d();
        paramParcel2.writeNoException();
        return true;
      case 6: 
        paramParcel1.enforceInterface("com.google.android.gms.maps.internal.IMapViewDelegate");
        e();
        paramParcel2.writeNoException();
        return true;
      case 7: 
        paramParcel1.enforceInterface("com.google.android.gms.maps.internal.IMapViewDelegate");
        localObject1 = localObject3;
        if (paramParcel1.readInt() != 0) {
          localObject1 = (Bundle)Bundle.CREATOR.createFromParcel(paramParcel1);
        }
        b((Bundle)localObject1);
        paramParcel2.writeNoException();
        if (localObject1 != null)
        {
          paramParcel2.writeInt(1);
          ((Bundle)localObject1).writeToParcel(paramParcel2, 1);
        }
        for (;;)
        {
          return true;
          paramParcel2.writeInt(0);
        }
      case 8: 
        paramParcel1.enforceInterface("com.google.android.gms.maps.internal.IMapViewDelegate");
        localObject1 = f();
        paramParcel2.writeNoException();
        paramParcel1 = localb;
        if (localObject1 != null) {
          paramParcel1 = ((c)localObject1).asBinder();
        }
        paramParcel2.writeStrongBinder(paramParcel1);
        return true;
      case 9: 
        paramParcel1.enforceInterface("com.google.android.gms.maps.internal.IMapViewDelegate");
        a(ae.a.a(paramParcel1.readStrongBinder()));
        paramParcel2.writeNoException();
        return true;
      case 10: 
        paramParcel1.enforceInterface("com.google.android.gms.maps.internal.IMapViewDelegate");
        localObject1 = localObject4;
        if (paramParcel1.readInt() != 0) {
          localObject1 = (Bundle)Bundle.CREATOR.createFromParcel(paramParcel1);
        }
        c((Bundle)localObject1);
        paramParcel2.writeNoException();
        return true;
      }
      paramParcel1.enforceInterface("com.google.android.gms.maps.internal.IMapViewDelegate");
      g();
      paramParcel2.writeNoException();
      return true;
    }
    
    private static class a
      implements e
    {
      private IBinder a;
      
      a(IBinder paramIBinder)
      {
        a = paramIBinder;
      }
      
      public b a()
        throws RemoteException
      {
        Parcel localParcel1 = Parcel.obtain();
        Parcel localParcel2 = Parcel.obtain();
        try
        {
          localParcel1.writeInterfaceToken("com.google.android.gms.maps.internal.IMapViewDelegate");
          a.transact(1, localParcel1, localParcel2, 0);
          localParcel2.readException();
          b localb = b.a.a(localParcel2.readStrongBinder());
          return localb;
        }
        finally
        {
          localParcel2.recycle();
          localParcel1.recycle();
        }
      }
      
      /* Error */
      public void a(Bundle paramBundle)
        throws RemoteException
      {
        // Byte code:
        //   0: invokestatic 27	android/os/Parcel:obtain	()Landroid/os/Parcel;
        //   3: astore_2
        //   4: invokestatic 27	android/os/Parcel:obtain	()Landroid/os/Parcel;
        //   7: astore_3
        //   8: aload_2
        //   9: ldc 29
        //   11: invokevirtual 33	android/os/Parcel:writeInterfaceToken	(Ljava/lang/String;)V
        //   14: aload_1
        //   15: ifnull +41 -> 56
        //   18: aload_2
        //   19: iconst_1
        //   20: invokevirtual 60	android/os/Parcel:writeInt	(I)V
        //   23: aload_1
        //   24: aload_2
        //   25: iconst_0
        //   26: invokevirtual 66	android/os/Bundle:writeToParcel	(Landroid/os/Parcel;I)V
        //   29: aload_0
        //   30: getfield 17	com/yelp/android/bj/e$a$a:a	Landroid/os/IBinder;
        //   33: iconst_2
        //   34: aload_2
        //   35: aload_3
        //   36: iconst_0
        //   37: invokeinterface 39 5 0
        //   42: pop
        //   43: aload_3
        //   44: invokevirtual 42	android/os/Parcel:readException	()V
        //   47: aload_3
        //   48: invokevirtual 54	android/os/Parcel:recycle	()V
        //   51: aload_2
        //   52: invokevirtual 54	android/os/Parcel:recycle	()V
        //   55: return
        //   56: aload_2
        //   57: iconst_0
        //   58: invokevirtual 60	android/os/Parcel:writeInt	(I)V
        //   61: goto -32 -> 29
        //   64: astore_1
        //   65: aload_3
        //   66: invokevirtual 54	android/os/Parcel:recycle	()V
        //   69: aload_2
        //   70: invokevirtual 54	android/os/Parcel:recycle	()V
        //   73: aload_1
        //   74: athrow
        // Local variable table:
        //   start	length	slot	name	signature
        //   0	75	0	this	a
        //   0	75	1	paramBundle	Bundle
        //   3	67	2	localParcel1	Parcel
        //   7	59	3	localParcel2	Parcel
        // Exception table:
        //   from	to	target	type
        //   8	14	64	finally
        //   18	29	64	finally
        //   29	47	64	finally
        //   56	61	64	finally
      }
      
      /* Error */
      public void a(ae paramae)
        throws RemoteException
      {
        // Byte code:
        //   0: invokestatic 27	android/os/Parcel:obtain	()Landroid/os/Parcel;
        //   3: astore_2
        //   4: invokestatic 27	android/os/Parcel:obtain	()Landroid/os/Parcel;
        //   7: astore_3
        //   8: aload_2
        //   9: ldc 29
        //   11: invokevirtual 33	android/os/Parcel:writeInterfaceToken	(Ljava/lang/String;)V
        //   14: aload_1
        //   15: ifnull +43 -> 58
        //   18: aload_1
        //   19: invokeinterface 72 1 0
        //   24: astore_1
        //   25: aload_2
        //   26: aload_1
        //   27: invokevirtual 75	android/os/Parcel:writeStrongBinder	(Landroid/os/IBinder;)V
        //   30: aload_0
        //   31: getfield 17	com/yelp/android/bj/e$a$a:a	Landroid/os/IBinder;
        //   34: bipush 9
        //   36: aload_2
        //   37: aload_3
        //   38: iconst_0
        //   39: invokeinterface 39 5 0
        //   44: pop
        //   45: aload_3
        //   46: invokevirtual 42	android/os/Parcel:readException	()V
        //   49: aload_3
        //   50: invokevirtual 54	android/os/Parcel:recycle	()V
        //   53: aload_2
        //   54: invokevirtual 54	android/os/Parcel:recycle	()V
        //   57: return
        //   58: aconst_null
        //   59: astore_1
        //   60: goto -35 -> 25
        //   63: astore_1
        //   64: aload_3
        //   65: invokevirtual 54	android/os/Parcel:recycle	()V
        //   68: aload_2
        //   69: invokevirtual 54	android/os/Parcel:recycle	()V
        //   72: aload_1
        //   73: athrow
        // Local variable table:
        //   start	length	slot	name	signature
        //   0	74	0	this	a
        //   0	74	1	paramae	ae
        //   3	66	2	localParcel1	Parcel
        //   7	58	3	localParcel2	Parcel
        // Exception table:
        //   from	to	target	type
        //   8	14	63	finally
        //   18	25	63	finally
        //   25	49	63	finally
      }
      
      public IBinder asBinder()
      {
        return a;
      }
      
      public void b()
        throws RemoteException
      {
        Parcel localParcel1 = Parcel.obtain();
        Parcel localParcel2 = Parcel.obtain();
        try
        {
          localParcel1.writeInterfaceToken("com.google.android.gms.maps.internal.IMapViewDelegate");
          a.transact(3, localParcel1, localParcel2, 0);
          localParcel2.readException();
          return;
        }
        finally
        {
          localParcel2.recycle();
          localParcel1.recycle();
        }
      }
      
      /* Error */
      public void b(Bundle paramBundle)
        throws RemoteException
      {
        // Byte code:
        //   0: invokestatic 27	android/os/Parcel:obtain	()Landroid/os/Parcel;
        //   3: astore_2
        //   4: invokestatic 27	android/os/Parcel:obtain	()Landroid/os/Parcel;
        //   7: astore_3
        //   8: aload_2
        //   9: ldc 29
        //   11: invokevirtual 33	android/os/Parcel:writeInterfaceToken	(Ljava/lang/String;)V
        //   14: aload_1
        //   15: ifnull +54 -> 69
        //   18: aload_2
        //   19: iconst_1
        //   20: invokevirtual 60	android/os/Parcel:writeInt	(I)V
        //   23: aload_1
        //   24: aload_2
        //   25: iconst_0
        //   26: invokevirtual 66	android/os/Bundle:writeToParcel	(Landroid/os/Parcel;I)V
        //   29: aload_0
        //   30: getfield 17	com/yelp/android/bj/e$a$a:a	Landroid/os/IBinder;
        //   33: bipush 7
        //   35: aload_2
        //   36: aload_3
        //   37: iconst_0
        //   38: invokeinterface 39 5 0
        //   43: pop
        //   44: aload_3
        //   45: invokevirtual 42	android/os/Parcel:readException	()V
        //   48: aload_3
        //   49: invokevirtual 80	android/os/Parcel:readInt	()I
        //   52: ifeq +8 -> 60
        //   55: aload_1
        //   56: aload_3
        //   57: invokevirtual 84	android/os/Bundle:readFromParcel	(Landroid/os/Parcel;)V
        //   60: aload_3
        //   61: invokevirtual 54	android/os/Parcel:recycle	()V
        //   64: aload_2
        //   65: invokevirtual 54	android/os/Parcel:recycle	()V
        //   68: return
        //   69: aload_2
        //   70: iconst_0
        //   71: invokevirtual 60	android/os/Parcel:writeInt	(I)V
        //   74: goto -45 -> 29
        //   77: astore_1
        //   78: aload_3
        //   79: invokevirtual 54	android/os/Parcel:recycle	()V
        //   82: aload_2
        //   83: invokevirtual 54	android/os/Parcel:recycle	()V
        //   86: aload_1
        //   87: athrow
        // Local variable table:
        //   start	length	slot	name	signature
        //   0	88	0	this	a
        //   0	88	1	paramBundle	Bundle
        //   3	80	2	localParcel1	Parcel
        //   7	72	3	localParcel2	Parcel
        // Exception table:
        //   from	to	target	type
        //   8	14	77	finally
        //   18	29	77	finally
        //   29	60	77	finally
        //   69	74	77	finally
      }
      
      public void c()
        throws RemoteException
      {
        Parcel localParcel1 = Parcel.obtain();
        Parcel localParcel2 = Parcel.obtain();
        try
        {
          localParcel1.writeInterfaceToken("com.google.android.gms.maps.internal.IMapViewDelegate");
          a.transact(4, localParcel1, localParcel2, 0);
          localParcel2.readException();
          return;
        }
        finally
        {
          localParcel2.recycle();
          localParcel1.recycle();
        }
      }
      
      /* Error */
      public void c(Bundle paramBundle)
        throws RemoteException
      {
        // Byte code:
        //   0: invokestatic 27	android/os/Parcel:obtain	()Landroid/os/Parcel;
        //   3: astore_2
        //   4: invokestatic 27	android/os/Parcel:obtain	()Landroid/os/Parcel;
        //   7: astore_3
        //   8: aload_2
        //   9: ldc 29
        //   11: invokevirtual 33	android/os/Parcel:writeInterfaceToken	(Ljava/lang/String;)V
        //   14: aload_1
        //   15: ifnull +42 -> 57
        //   18: aload_2
        //   19: iconst_1
        //   20: invokevirtual 60	android/os/Parcel:writeInt	(I)V
        //   23: aload_1
        //   24: aload_2
        //   25: iconst_0
        //   26: invokevirtual 66	android/os/Bundle:writeToParcel	(Landroid/os/Parcel;I)V
        //   29: aload_0
        //   30: getfield 17	com/yelp/android/bj/e$a$a:a	Landroid/os/IBinder;
        //   33: bipush 10
        //   35: aload_2
        //   36: aload_3
        //   37: iconst_0
        //   38: invokeinterface 39 5 0
        //   43: pop
        //   44: aload_3
        //   45: invokevirtual 42	android/os/Parcel:readException	()V
        //   48: aload_3
        //   49: invokevirtual 54	android/os/Parcel:recycle	()V
        //   52: aload_2
        //   53: invokevirtual 54	android/os/Parcel:recycle	()V
        //   56: return
        //   57: aload_2
        //   58: iconst_0
        //   59: invokevirtual 60	android/os/Parcel:writeInt	(I)V
        //   62: goto -33 -> 29
        //   65: astore_1
        //   66: aload_3
        //   67: invokevirtual 54	android/os/Parcel:recycle	()V
        //   70: aload_2
        //   71: invokevirtual 54	android/os/Parcel:recycle	()V
        //   74: aload_1
        //   75: athrow
        // Local variable table:
        //   start	length	slot	name	signature
        //   0	76	0	this	a
        //   0	76	1	paramBundle	Bundle
        //   3	68	2	localParcel1	Parcel
        //   7	60	3	localParcel2	Parcel
        // Exception table:
        //   from	to	target	type
        //   8	14	65	finally
        //   18	29	65	finally
        //   29	48	65	finally
        //   57	62	65	finally
      }
      
      public void d()
        throws RemoteException
      {
        Parcel localParcel1 = Parcel.obtain();
        Parcel localParcel2 = Parcel.obtain();
        try
        {
          localParcel1.writeInterfaceToken("com.google.android.gms.maps.internal.IMapViewDelegate");
          a.transact(5, localParcel1, localParcel2, 0);
          localParcel2.readException();
          return;
        }
        finally
        {
          localParcel2.recycle();
          localParcel1.recycle();
        }
      }
      
      public void e()
        throws RemoteException
      {
        Parcel localParcel1 = Parcel.obtain();
        Parcel localParcel2 = Parcel.obtain();
        try
        {
          localParcel1.writeInterfaceToken("com.google.android.gms.maps.internal.IMapViewDelegate");
          a.transact(6, localParcel1, localParcel2, 0);
          localParcel2.readException();
          return;
        }
        finally
        {
          localParcel2.recycle();
          localParcel1.recycle();
        }
      }
      
      public c f()
        throws RemoteException
      {
        Parcel localParcel1 = Parcel.obtain();
        Parcel localParcel2 = Parcel.obtain();
        try
        {
          localParcel1.writeInterfaceToken("com.google.android.gms.maps.internal.IMapViewDelegate");
          a.transact(8, localParcel1, localParcel2, 0);
          localParcel2.readException();
          c localc = c.a.a(localParcel2.readStrongBinder());
          return localc;
        }
        finally
        {
          localParcel2.recycle();
          localParcel1.recycle();
        }
      }
      
      public void g()
        throws RemoteException
      {
        Parcel localParcel1 = Parcel.obtain();
        Parcel localParcel2 = Parcel.obtain();
        try
        {
          localParcel1.writeInterfaceToken("com.google.android.gms.maps.internal.IMapViewDelegate");
          a.transact(11, localParcel1, localParcel2, 0);
          localParcel2.readException();
          return;
        }
        finally
        {
          localParcel2.recycle();
          localParcel1.recycle();
        }
      }
    }
  }
}

/* Location:
 * Qualified Name:     com.yelp.android.bj.e
 * Java Class Version: 6 (50.0)
 * JD-Core Version:    0.7.1
 */