package com.yelp.android.bj;

import android.os.Binder;
import android.os.IBinder;
import android.os.IInterface;
import android.os.Parcel;
import android.os.RemoteException;

public abstract class j$a
  extends Binder
  implements j
{
  public static j a(IBinder paramIBinder)
  {
    if (paramIBinder == null) {
      return null;
    }
    IInterface localIInterface = paramIBinder.queryLocalInterface("com.google.android.gms.maps.internal.IUiSettingsDelegate");
    if ((localIInterface != null) && ((localIInterface instanceof j))) {
      return (j)localIInterface;
    }
    return new a(paramIBinder);
  }
  
  public boolean onTransact(int paramInt1, Parcel paramParcel1, Parcel paramParcel2, int paramInt2)
    throws RemoteException
  {
    boolean bool2 = false;
    boolean bool3 = false;
    boolean bool4 = false;
    boolean bool5 = false;
    boolean bool6 = false;
    boolean bool7 = false;
    boolean bool8 = false;
    int i = 0;
    int j = 0;
    int k = 0;
    int m = 0;
    int n = 0;
    int i1 = 0;
    int i2 = 0;
    boolean bool9 = false;
    int i3 = 0;
    boolean bool10 = false;
    int i4 = 0;
    boolean bool1 = false;
    switch (paramInt1)
    {
    default: 
      return super.onTransact(paramInt1, paramParcel1, paramParcel2, paramInt2);
    case 1598968902: 
      paramParcel2.writeString("com.google.android.gms.maps.internal.IUiSettingsDelegate");
      return true;
    case 1: 
      paramParcel1.enforceInterface("com.google.android.gms.maps.internal.IUiSettingsDelegate");
      if (paramParcel1.readInt() != 0) {
        bool1 = true;
      }
      a(bool1);
      paramParcel2.writeNoException();
      return true;
    case 2: 
      paramParcel1.enforceInterface("com.google.android.gms.maps.internal.IUiSettingsDelegate");
      bool1 = bool2;
      if (paramParcel1.readInt() != 0) {
        bool1 = true;
      }
      b(bool1);
      paramParcel2.writeNoException();
      return true;
    case 3: 
      paramParcel1.enforceInterface("com.google.android.gms.maps.internal.IUiSettingsDelegate");
      bool1 = bool3;
      if (paramParcel1.readInt() != 0) {
        bool1 = true;
      }
      c(bool1);
      paramParcel2.writeNoException();
      return true;
    case 4: 
      paramParcel1.enforceInterface("com.google.android.gms.maps.internal.IUiSettingsDelegate");
      bool1 = bool4;
      if (paramParcel1.readInt() != 0) {
        bool1 = true;
      }
      d(bool1);
      paramParcel2.writeNoException();
      return true;
    case 5: 
      paramParcel1.enforceInterface("com.google.android.gms.maps.internal.IUiSettingsDelegate");
      bool1 = bool5;
      if (paramParcel1.readInt() != 0) {
        bool1 = true;
      }
      e(bool1);
      paramParcel2.writeNoException();
      return true;
    case 6: 
      paramParcel1.enforceInterface("com.google.android.gms.maps.internal.IUiSettingsDelegate");
      bool1 = bool6;
      if (paramParcel1.readInt() != 0) {
        bool1 = true;
      }
      f(bool1);
      paramParcel2.writeNoException();
      return true;
    case 7: 
      paramParcel1.enforceInterface("com.google.android.gms.maps.internal.IUiSettingsDelegate");
      bool1 = bool7;
      if (paramParcel1.readInt() != 0) {
        bool1 = true;
      }
      g(bool1);
      paramParcel2.writeNoException();
      return true;
    case 8: 
      paramParcel1.enforceInterface("com.google.android.gms.maps.internal.IUiSettingsDelegate");
      bool1 = bool8;
      if (paramParcel1.readInt() != 0) {
        bool1 = true;
      }
      h(bool1);
      paramParcel2.writeNoException();
      return true;
    case 9: 
      paramParcel1.enforceInterface("com.google.android.gms.maps.internal.IUiSettingsDelegate");
      bool1 = a();
      paramParcel2.writeNoException();
      paramInt1 = i;
      if (bool1) {
        paramInt1 = 1;
      }
      paramParcel2.writeInt(paramInt1);
      return true;
    case 10: 
      paramParcel1.enforceInterface("com.google.android.gms.maps.internal.IUiSettingsDelegate");
      bool1 = b();
      paramParcel2.writeNoException();
      paramInt1 = j;
      if (bool1) {
        paramInt1 = 1;
      }
      paramParcel2.writeInt(paramInt1);
      return true;
    case 11: 
      paramParcel1.enforceInterface("com.google.android.gms.maps.internal.IUiSettingsDelegate");
      bool1 = c();
      paramParcel2.writeNoException();
      paramInt1 = k;
      if (bool1) {
        paramInt1 = 1;
      }
      paramParcel2.writeInt(paramInt1);
      return true;
    case 12: 
      paramParcel1.enforceInterface("com.google.android.gms.maps.internal.IUiSettingsDelegate");
      bool1 = d();
      paramParcel2.writeNoException();
      paramInt1 = m;
      if (bool1) {
        paramInt1 = 1;
      }
      paramParcel2.writeInt(paramInt1);
      return true;
    case 13: 
      paramParcel1.enforceInterface("com.google.android.gms.maps.internal.IUiSettingsDelegate");
      bool1 = e();
      paramParcel2.writeNoException();
      paramInt1 = n;
      if (bool1) {
        paramInt1 = 1;
      }
      paramParcel2.writeInt(paramInt1);
      return true;
    case 14: 
      paramParcel1.enforceInterface("com.google.android.gms.maps.internal.IUiSettingsDelegate");
      bool1 = f();
      paramParcel2.writeNoException();
      paramInt1 = i1;
      if (bool1) {
        paramInt1 = 1;
      }
      paramParcel2.writeInt(paramInt1);
      return true;
    case 15: 
      paramParcel1.enforceInterface("com.google.android.gms.maps.internal.IUiSettingsDelegate");
      bool1 = g();
      paramParcel2.writeNoException();
      paramInt1 = i2;
      if (bool1) {
        paramInt1 = 1;
      }
      paramParcel2.writeInt(paramInt1);
      return true;
    case 16: 
      paramParcel1.enforceInterface("com.google.android.gms.maps.internal.IUiSettingsDelegate");
      bool1 = bool9;
      if (paramParcel1.readInt() != 0) {
        bool1 = true;
      }
      i(bool1);
      paramParcel2.writeNoException();
      return true;
    case 17: 
      paramParcel1.enforceInterface("com.google.android.gms.maps.internal.IUiSettingsDelegate");
      bool1 = h();
      paramParcel2.writeNoException();
      paramInt1 = i3;
      if (bool1) {
        paramInt1 = 1;
      }
      paramParcel2.writeInt(paramInt1);
      return true;
    case 18: 
      paramParcel1.enforceInterface("com.google.android.gms.maps.internal.IUiSettingsDelegate");
      bool1 = bool10;
      if (paramParcel1.readInt() != 0) {
        bool1 = true;
      }
      j(bool1);
      paramParcel2.writeNoException();
      return true;
    }
    paramParcel1.enforceInterface("com.google.android.gms.maps.internal.IUiSettingsDelegate");
    bool1 = i();
    paramParcel2.writeNoException();
    paramInt1 = i4;
    if (bool1) {
      paramInt1 = 1;
    }
    paramParcel2.writeInt(paramInt1);
    return true;
  }
  
  private static class a
    implements j
  {
    private IBinder a;
    
    a(IBinder paramIBinder)
    {
      a = paramIBinder;
    }
    
    /* Error */
    public void a(boolean paramBoolean)
      throws RemoteException
    {
      // Byte code:
      //   0: iconst_1
      //   1: istore_2
      //   2: invokestatic 27	android/os/Parcel:obtain	()Landroid/os/Parcel;
      //   5: astore_3
      //   6: invokestatic 27	android/os/Parcel:obtain	()Landroid/os/Parcel;
      //   9: astore 4
      //   11: aload_3
      //   12: ldc 29
      //   14: invokevirtual 33	android/os/Parcel:writeInterfaceToken	(Ljava/lang/String;)V
      //   17: iload_1
      //   18: ifeq +38 -> 56
      //   21: aload_3
      //   22: iload_2
      //   23: invokevirtual 37	android/os/Parcel:writeInt	(I)V
      //   26: aload_0
      //   27: getfield 17	com/yelp/android/bj/j$a$a:a	Landroid/os/IBinder;
      //   30: iconst_1
      //   31: aload_3
      //   32: aload 4
      //   34: iconst_0
      //   35: invokeinterface 43 5 0
      //   40: pop
      //   41: aload 4
      //   43: invokevirtual 46	android/os/Parcel:readException	()V
      //   46: aload 4
      //   48: invokevirtual 49	android/os/Parcel:recycle	()V
      //   51: aload_3
      //   52: invokevirtual 49	android/os/Parcel:recycle	()V
      //   55: return
      //   56: iconst_0
      //   57: istore_2
      //   58: goto -37 -> 21
      //   61: astore 5
      //   63: aload 4
      //   65: invokevirtual 49	android/os/Parcel:recycle	()V
      //   68: aload_3
      //   69: invokevirtual 49	android/os/Parcel:recycle	()V
      //   72: aload 5
      //   74: athrow
      // Local variable table:
      //   start	length	slot	name	signature
      //   0	75	0	this	a
      //   0	75	1	paramBoolean	boolean
      //   1	57	2	i	int
      //   5	64	3	localParcel1	Parcel
      //   9	55	4	localParcel2	Parcel
      //   61	12	5	localObject	Object
      // Exception table:
      //   from	to	target	type
      //   11	17	61	finally
      //   21	46	61	finally
    }
    
    public boolean a()
      throws RemoteException
    {
      boolean bool = false;
      Parcel localParcel1 = Parcel.obtain();
      Parcel localParcel2 = Parcel.obtain();
      try
      {
        localParcel1.writeInterfaceToken("com.google.android.gms.maps.internal.IUiSettingsDelegate");
        a.transact(9, localParcel1, localParcel2, 0);
        localParcel2.readException();
        int i = localParcel2.readInt();
        if (i != 0) {
          bool = true;
        }
        return bool;
      }
      finally
      {
        localParcel2.recycle();
        localParcel1.recycle();
      }
    }
    
    public IBinder asBinder()
    {
      return a;
    }
    
    public void b(boolean paramBoolean)
      throws RemoteException
    {
      int i = 0;
      Parcel localParcel1 = Parcel.obtain();
      Parcel localParcel2 = Parcel.obtain();
      try
      {
        localParcel1.writeInterfaceToken("com.google.android.gms.maps.internal.IUiSettingsDelegate");
        if (paramBoolean) {
          i = 1;
        }
        localParcel1.writeInt(i);
        a.transact(2, localParcel1, localParcel2, 0);
        localParcel2.readException();
        return;
      }
      finally
      {
        localParcel2.recycle();
        localParcel1.recycle();
      }
    }
    
    public boolean b()
      throws RemoteException
    {
      boolean bool = false;
      Parcel localParcel1 = Parcel.obtain();
      Parcel localParcel2 = Parcel.obtain();
      try
      {
        localParcel1.writeInterfaceToken("com.google.android.gms.maps.internal.IUiSettingsDelegate");
        a.transact(10, localParcel1, localParcel2, 0);
        localParcel2.readException();
        int i = localParcel2.readInt();
        if (i != 0) {
          bool = true;
        }
        return bool;
      }
      finally
      {
        localParcel2.recycle();
        localParcel1.recycle();
      }
    }
    
    public void c(boolean paramBoolean)
      throws RemoteException
    {
      int i = 0;
      Parcel localParcel1 = Parcel.obtain();
      Parcel localParcel2 = Parcel.obtain();
      try
      {
        localParcel1.writeInterfaceToken("com.google.android.gms.maps.internal.IUiSettingsDelegate");
        if (paramBoolean) {
          i = 1;
        }
        localParcel1.writeInt(i);
        a.transact(3, localParcel1, localParcel2, 0);
        localParcel2.readException();
        return;
      }
      finally
      {
        localParcel2.recycle();
        localParcel1.recycle();
      }
    }
    
    public boolean c()
      throws RemoteException
    {
      boolean bool = false;
      Parcel localParcel1 = Parcel.obtain();
      Parcel localParcel2 = Parcel.obtain();
      try
      {
        localParcel1.writeInterfaceToken("com.google.android.gms.maps.internal.IUiSettingsDelegate");
        a.transact(11, localParcel1, localParcel2, 0);
        localParcel2.readException();
        int i = localParcel2.readInt();
        if (i != 0) {
          bool = true;
        }
        return bool;
      }
      finally
      {
        localParcel2.recycle();
        localParcel1.recycle();
      }
    }
    
    public void d(boolean paramBoolean)
      throws RemoteException
    {
      int i = 0;
      Parcel localParcel1 = Parcel.obtain();
      Parcel localParcel2 = Parcel.obtain();
      try
      {
        localParcel1.writeInterfaceToken("com.google.android.gms.maps.internal.IUiSettingsDelegate");
        if (paramBoolean) {
          i = 1;
        }
        localParcel1.writeInt(i);
        a.transact(4, localParcel1, localParcel2, 0);
        localParcel2.readException();
        return;
      }
      finally
      {
        localParcel2.recycle();
        localParcel1.recycle();
      }
    }
    
    public boolean d()
      throws RemoteException
    {
      boolean bool = false;
      Parcel localParcel1 = Parcel.obtain();
      Parcel localParcel2 = Parcel.obtain();
      try
      {
        localParcel1.writeInterfaceToken("com.google.android.gms.maps.internal.IUiSettingsDelegate");
        a.transact(12, localParcel1, localParcel2, 0);
        localParcel2.readException();
        int i = localParcel2.readInt();
        if (i != 0) {
          bool = true;
        }
        return bool;
      }
      finally
      {
        localParcel2.recycle();
        localParcel1.recycle();
      }
    }
    
    public void e(boolean paramBoolean)
      throws RemoteException
    {
      int i = 0;
      Parcel localParcel1 = Parcel.obtain();
      Parcel localParcel2 = Parcel.obtain();
      try
      {
        localParcel1.writeInterfaceToken("com.google.android.gms.maps.internal.IUiSettingsDelegate");
        if (paramBoolean) {
          i = 1;
        }
        localParcel1.writeInt(i);
        a.transact(5, localParcel1, localParcel2, 0);
        localParcel2.readException();
        return;
      }
      finally
      {
        localParcel2.recycle();
        localParcel1.recycle();
      }
    }
    
    public boolean e()
      throws RemoteException
    {
      boolean bool = false;
      Parcel localParcel1 = Parcel.obtain();
      Parcel localParcel2 = Parcel.obtain();
      try
      {
        localParcel1.writeInterfaceToken("com.google.android.gms.maps.internal.IUiSettingsDelegate");
        a.transact(13, localParcel1, localParcel2, 0);
        localParcel2.readException();
        int i = localParcel2.readInt();
        if (i != 0) {
          bool = true;
        }
        return bool;
      }
      finally
      {
        localParcel2.recycle();
        localParcel1.recycle();
      }
    }
    
    public void f(boolean paramBoolean)
      throws RemoteException
    {
      int i = 0;
      Parcel localParcel1 = Parcel.obtain();
      Parcel localParcel2 = Parcel.obtain();
      try
      {
        localParcel1.writeInterfaceToken("com.google.android.gms.maps.internal.IUiSettingsDelegate");
        if (paramBoolean) {
          i = 1;
        }
        localParcel1.writeInt(i);
        a.transact(6, localParcel1, localParcel2, 0);
        localParcel2.readException();
        return;
      }
      finally
      {
        localParcel2.recycle();
        localParcel1.recycle();
      }
    }
    
    public boolean f()
      throws RemoteException
    {
      boolean bool = false;
      Parcel localParcel1 = Parcel.obtain();
      Parcel localParcel2 = Parcel.obtain();
      try
      {
        localParcel1.writeInterfaceToken("com.google.android.gms.maps.internal.IUiSettingsDelegate");
        a.transact(14, localParcel1, localParcel2, 0);
        localParcel2.readException();
        int i = localParcel2.readInt();
        if (i != 0) {
          bool = true;
        }
        return bool;
      }
      finally
      {
        localParcel2.recycle();
        localParcel1.recycle();
      }
    }
    
    public void g(boolean paramBoolean)
      throws RemoteException
    {
      int i = 0;
      Parcel localParcel1 = Parcel.obtain();
      Parcel localParcel2 = Parcel.obtain();
      try
      {
        localParcel1.writeInterfaceToken("com.google.android.gms.maps.internal.IUiSettingsDelegate");
        if (paramBoolean) {
          i = 1;
        }
        localParcel1.writeInt(i);
        a.transact(7, localParcel1, localParcel2, 0);
        localParcel2.readException();
        return;
      }
      finally
      {
        localParcel2.recycle();
        localParcel1.recycle();
      }
    }
    
    public boolean g()
      throws RemoteException
    {
      boolean bool = false;
      Parcel localParcel1 = Parcel.obtain();
      Parcel localParcel2 = Parcel.obtain();
      try
      {
        localParcel1.writeInterfaceToken("com.google.android.gms.maps.internal.IUiSettingsDelegate");
        a.transact(15, localParcel1, localParcel2, 0);
        localParcel2.readException();
        int i = localParcel2.readInt();
        if (i != 0) {
          bool = true;
        }
        return bool;
      }
      finally
      {
        localParcel2.recycle();
        localParcel1.recycle();
      }
    }
    
    public void h(boolean paramBoolean)
      throws RemoteException
    {
      int i = 0;
      Parcel localParcel1 = Parcel.obtain();
      Parcel localParcel2 = Parcel.obtain();
      try
      {
        localParcel1.writeInterfaceToken("com.google.android.gms.maps.internal.IUiSettingsDelegate");
        if (paramBoolean) {
          i = 1;
        }
        localParcel1.writeInt(i);
        a.transact(8, localParcel1, localParcel2, 0);
        localParcel2.readException();
        return;
      }
      finally
      {
        localParcel2.recycle();
        localParcel1.recycle();
      }
    }
    
    public boolean h()
      throws RemoteException
    {
      boolean bool = false;
      Parcel localParcel1 = Parcel.obtain();
      Parcel localParcel2 = Parcel.obtain();
      try
      {
        localParcel1.writeInterfaceToken("com.google.android.gms.maps.internal.IUiSettingsDelegate");
        a.transact(17, localParcel1, localParcel2, 0);
        localParcel2.readException();
        int i = localParcel2.readInt();
        if (i != 0) {
          bool = true;
        }
        return bool;
      }
      finally
      {
        localParcel2.recycle();
        localParcel1.recycle();
      }
    }
    
    public void i(boolean paramBoolean)
      throws RemoteException
    {
      int i = 0;
      Parcel localParcel1 = Parcel.obtain();
      Parcel localParcel2 = Parcel.obtain();
      try
      {
        localParcel1.writeInterfaceToken("com.google.android.gms.maps.internal.IUiSettingsDelegate");
        if (paramBoolean) {
          i = 1;
        }
        localParcel1.writeInt(i);
        a.transact(16, localParcel1, localParcel2, 0);
        localParcel2.readException();
        return;
      }
      finally
      {
        localParcel2.recycle();
        localParcel1.recycle();
      }
    }
    
    public boolean i()
      throws RemoteException
    {
      boolean bool = false;
      Parcel localParcel1 = Parcel.obtain();
      Parcel localParcel2 = Parcel.obtain();
      try
      {
        localParcel1.writeInterfaceToken("com.google.android.gms.maps.internal.IUiSettingsDelegate");
        a.transact(19, localParcel1, localParcel2, 0);
        localParcel2.readException();
        int i = localParcel2.readInt();
        if (i != 0) {
          bool = true;
        }
        return bool;
      }
      finally
      {
        localParcel2.recycle();
        localParcel1.recycle();
      }
    }
    
    public void j(boolean paramBoolean)
      throws RemoteException
    {
      int i = 0;
      Parcel localParcel1 = Parcel.obtain();
      Parcel localParcel2 = Parcel.obtain();
      try
      {
        localParcel1.writeInterfaceToken("com.google.android.gms.maps.internal.IUiSettingsDelegate");
        if (paramBoolean) {
          i = 1;
        }
        localParcel1.writeInt(i);
        a.transact(18, localParcel1, localParcel2, 0);
        localParcel2.readException();
        return;
      }
      finally
      {
        localParcel2.recycle();
        localParcel1.recycle();
      }
    }
  }
}

/* Location:
 * Qualified Name:     com.yelp.android.bj.j.a
 * Java Class Version: 6 (50.0)
 * JD-Core Version:    0.7.1
 */