package com.yelp.android.cz;

public final class a
{
  /* Error */
  public static final a a(android.net.Uri paramUri)
  {
    // Byte code:
    //   0: aload_0
    //   1: invokevirtual 16	android/net/Uri:getQuery	()Ljava/lang/String;
    //   4: ldc 18
    //   6: invokevirtual 24	java/lang/String:split	(Ljava/lang/String;)[Ljava/lang/String;
    //   9: astore 9
    //   11: aload 9
    //   13: arraylength
    //   14: istore 4
    //   16: iconst_0
    //   17: istore_3
    //   18: aconst_null
    //   19: astore_0
    //   20: iconst_m1
    //   21: istore_1
    //   22: aconst_null
    //   23: astore 6
    //   25: aload 6
    //   27: astore 7
    //   29: aload_0
    //   30: astore 8
    //   32: iload_1
    //   33: istore_2
    //   34: iload_3
    //   35: iload 4
    //   37: if_icmpge +165 -> 202
    //   40: aload 9
    //   42: iload_3
    //   43: aaload
    //   44: astore 7
    //   46: aload 7
    //   48: ldc 26
    //   50: invokevirtual 30	java/lang/String:indexOf	(Ljava/lang/String;)I
    //   53: istore_2
    //   54: aload 7
    //   56: iconst_0
    //   57: iload_2
    //   58: invokevirtual 34	java/lang/String:substring	(II)Ljava/lang/String;
    //   61: astore 8
    //   63: aload 8
    //   65: ifnull +155 -> 220
    //   68: aload 7
    //   70: invokevirtual 38	java/lang/String:length	()I
    //   73: iload_2
    //   74: iconst_1
    //   75: iadd
    //   76: if_icmpgt +33 -> 109
    //   79: aconst_null
    //   80: astore 7
    //   82: aload 8
    //   84: ldc 40
    //   86: invokevirtual 44	java/lang/String:equals	(Ljava/lang/Object;)Z
    //   89: istore 5
    //   91: iload 5
    //   93: ifeq +29 -> 122
    //   96: aload 7
    //   98: invokestatic 49	java/lang/Integer:parseInt	(Ljava/lang/String;)I
    //   101: istore_1
    //   102: iload_3
    //   103: iconst_1
    //   104: iadd
    //   105: istore_3
    //   106: goto -81 -> 25
    //   109: aload 7
    //   111: iload_2
    //   112: iconst_1
    //   113: iadd
    //   114: invokevirtual 52	java/lang/String:substring	(I)Ljava/lang/String;
    //   117: astore 7
    //   119: goto -37 -> 82
    //   122: aload 8
    //   124: ldc 54
    //   126: invokevirtual 44	java/lang/String:equals	(Ljava/lang/Object;)Z
    //   129: ifeq +10 -> 139
    //   132: aload 7
    //   134: astore 6
    //   136: goto -34 -> 102
    //   139: aload 8
    //   141: ldc 56
    //   143: invokevirtual 44	java/lang/String:equals	(Ljava/lang/Object;)Z
    //   146: istore 5
    //   148: iload 5
    //   150: ifeq +70 -> 220
    //   153: aload 7
    //   155: astore_0
    //   156: goto -54 -> 102
    //   159: astore_0
    //   160: aconst_null
    //   161: astore 6
    //   163: aconst_null
    //   164: astore_0
    //   165: iconst_m1
    //   166: istore_1
    //   167: aload 6
    //   169: astore 7
    //   171: aload_0
    //   172: astore 8
    //   174: iload_1
    //   175: istore_2
    //   176: aload_0
    //   177: ifnonnull +25 -> 202
    //   180: aload 6
    //   182: astore 7
    //   184: aload_0
    //   185: astore 8
    //   187: iload_1
    //   188: istore_2
    //   189: iload_1
    //   190: ifne +12 -> 202
    //   193: iconst_m1
    //   194: istore_2
    //   195: aload_0
    //   196: astore 8
    //   198: aload 6
    //   200: astore 7
    //   202: new 6	com/yelp/android/cz/a$a
    //   205: dup
    //   206: iload_2
    //   207: aload 8
    //   209: aload 7
    //   211: invokespecial 60	com/yelp/android/cz/a$a:<init>	(ILjava/lang/String;Ljava/lang/String;)V
    //   214: areturn
    //   215: astore 7
    //   217: goto -50 -> 167
    //   220: goto -118 -> 102
    //   223: astore 7
    //   225: iconst_m1
    //   226: istore_1
    //   227: goto -125 -> 102
    // Local variable table:
    //   start	length	slot	name	signature
    //   0	230	0	paramUri	android.net.Uri
    //   21	206	1	i	int
    //   33	174	2	j	int
    //   17	89	3	k	int
    //   14	24	4	m	int
    //   89	60	5	bool	boolean
    //   23	176	6	localObject1	Object
    //   27	183	7	localObject2	Object
    //   215	1	7	localThrowable1	Throwable
    //   223	1	7	localThrowable2	Throwable
    //   30	178	8	localObject3	Object
    //   9	32	9	arrayOfString	String[]
    // Exception table:
    //   from	to	target	type
    //   0	16	159	java/lang/Throwable
    //   46	63	215	java/lang/Throwable
    //   68	79	215	java/lang/Throwable
    //   82	91	215	java/lang/Throwable
    //   109	119	215	java/lang/Throwable
    //   122	132	215	java/lang/Throwable
    //   139	148	215	java/lang/Throwable
    //   96	102	223	java/lang/Throwable
  }
  
  public static final class a
  {
    public final int a;
    public final String b;
    public final String c;
    
    a(int paramInt, String paramString1, String paramString2)
    {
      a = paramInt;
      b = paramString1;
      c = paramString2;
    }
  }
}

/* Location:
 * Qualified Name:     com.yelp.android.cz.a
 * Java Class Version: 6 (50.0)
 * JD-Core Version:    0.7.1
 */