package com.google.android.gms.location.internal;

import android.app.PendingIntent;
import android.location.Location;
import android.os.Binder;
import android.os.IBinder;
import android.os.IInterface;
import android.os.Parcel;
import android.os.Parcelable.Creator;
import android.os.RemoteException;
import com.google.android.gms.common.api.internal.zzo;
import com.google.android.gms.common.api.internal.zzo.zza;
import com.google.android.gms.location.ActivityRecognitionResult;
import com.google.android.gms.location.GeofencingRequest;
import com.google.android.gms.location.GestureRequest;
import com.google.android.gms.location.LocationAvailability;
import com.google.android.gms.location.LocationRequest;
import com.google.android.gms.location.LocationSettingsRequest;
import com.google.android.gms.location.k;
import com.google.android.gms.location.p;
import com.google.android.gms.location.r;
import com.google.android.gms.location.r.a;
import java.util.List;

public abstract interface i
  extends IInterface
{
  public abstract Location a()
    throws RemoteException;
  
  public abstract ActivityRecognitionResult a(String paramString)
    throws RemoteException;
  
  public abstract void a(long paramLong, boolean paramBoolean, PendingIntent paramPendingIntent)
    throws RemoteException;
  
  public abstract void a(PendingIntent paramPendingIntent)
    throws RemoteException;
  
  public abstract void a(PendingIntent paramPendingIntent, zzo paramzzo)
    throws RemoteException;
  
  public abstract void a(PendingIntent paramPendingIntent, h paramh, String paramString)
    throws RemoteException;
  
  public abstract void a(Location paramLocation)
    throws RemoteException;
  
  public abstract void a(Location paramLocation, int paramInt)
    throws RemoteException;
  
  public abstract void a(GeofencingRequest paramGeofencingRequest, PendingIntent paramPendingIntent, h paramh)
    throws RemoteException;
  
  public abstract void a(GestureRequest paramGestureRequest, PendingIntent paramPendingIntent, zzo paramzzo)
    throws RemoteException;
  
  public abstract void a(LocationRequest paramLocationRequest, PendingIntent paramPendingIntent)
    throws RemoteException;
  
  public abstract void a(LocationRequest paramLocationRequest, r paramr)
    throws RemoteException;
  
  public abstract void a(LocationRequest paramLocationRequest, r paramr, String paramString)
    throws RemoteException;
  
  public abstract void a(LocationSettingsRequest paramLocationSettingsRequest, j paramj, String paramString)
    throws RemoteException;
  
  public abstract void a(LocationRequestInternal paramLocationRequestInternal, PendingIntent paramPendingIntent)
    throws RemoteException;
  
  public abstract void a(LocationRequestInternal paramLocationRequestInternal, r paramr)
    throws RemoteException;
  
  public abstract void a(LocationRequestUpdateData paramLocationRequestUpdateData)
    throws RemoteException;
  
  public abstract void a(g paramg)
    throws RemoteException;
  
  public abstract void a(h paramh, String paramString)
    throws RemoteException;
  
  public abstract void a(r paramr)
    throws RemoteException;
  
  public abstract void a(List<ParcelableGeofence> paramList, PendingIntent paramPendingIntent, h paramh, String paramString)
    throws RemoteException;
  
  public abstract void a(boolean paramBoolean)
    throws RemoteException;
  
  public abstract void a(String[] paramArrayOfString, h paramh, String paramString)
    throws RemoteException;
  
  public abstract Location b(String paramString)
    throws RemoteException;
  
  public abstract void b(PendingIntent paramPendingIntent)
    throws RemoteException;
  
  public abstract void b(PendingIntent paramPendingIntent, zzo paramzzo)
    throws RemoteException;
  
  public abstract LocationAvailability c(String paramString)
    throws RemoteException;
  
  public abstract void c(PendingIntent paramPendingIntent, zzo paramzzo)
    throws RemoteException;
  
  public abstract void d(PendingIntent paramPendingIntent, zzo paramzzo)
    throws RemoteException;
  
  public abstract void e(PendingIntent paramPendingIntent, zzo paramzzo)
    throws RemoteException;
  
  public static abstract class a
    extends Binder
    implements i
  {
    public static i a(IBinder paramIBinder)
    {
      if (paramIBinder == null) {
        return null;
      }
      IInterface localIInterface = paramIBinder.queryLocalInterface("com.google.android.gms.location.internal.IGoogleLocationManagerService");
      if ((localIInterface != null) && ((localIInterface instanceof i))) {
        return (i)localIInterface;
      }
      return new a(paramIBinder);
    }
    
    public boolean onTransact(int paramInt1, Parcel paramParcel1, Parcel paramParcel2, int paramInt2)
      throws RemoteException
    {
      boolean bool = false;
      Object localObject2 = null;
      Object localObject3 = null;
      Object localObject4 = null;
      Object localObject1 = null;
      switch (paramInt1)
      {
      default: 
        return super.onTransact(paramInt1, paramParcel1, paramParcel2, paramInt2);
      case 1598968902: 
        paramParcel2.writeString("com.google.android.gms.location.internal.IGoogleLocationManagerService");
        return true;
      case 1: 
        paramParcel1.enforceInterface("com.google.android.gms.location.internal.IGoogleLocationManagerService");
        localObject2 = paramParcel1.createTypedArrayList(ParcelableGeofence.CREATOR);
        if (paramParcel1.readInt() != 0) {}
        for (localObject1 = (PendingIntent)PendingIntent.CREATOR.createFromParcel(paramParcel1);; localObject1 = null)
        {
          a((List)localObject2, (PendingIntent)localObject1, h.a.a(paramParcel1.readStrongBinder()), paramParcel1.readString());
          paramParcel2.writeNoException();
          return true;
        }
      case 57: 
        paramParcel1.enforceInterface("com.google.android.gms.location.internal.IGoogleLocationManagerService");
        if (paramParcel1.readInt() != 0)
        {
          localObject1 = (GeofencingRequest)GeofencingRequest.CREATOR.createFromParcel(paramParcel1);
          if (paramParcel1.readInt() == 0) {
            break label436;
          }
        }
        for (localObject2 = (PendingIntent)PendingIntent.CREATOR.createFromParcel(paramParcel1);; localObject2 = null)
        {
          a((GeofencingRequest)localObject1, (PendingIntent)localObject2, h.a.a(paramParcel1.readStrongBinder()));
          paramParcel2.writeNoException();
          return true;
          localObject1 = null;
          break;
        }
      case 2: 
        paramParcel1.enforceInterface("com.google.android.gms.location.internal.IGoogleLocationManagerService");
        if (paramParcel1.readInt() != 0) {}
        for (localObject1 = (PendingIntent)PendingIntent.CREATOR.createFromParcel(paramParcel1);; localObject1 = null)
        {
          a((PendingIntent)localObject1, h.a.a(paramParcel1.readStrongBinder()), paramParcel1.readString());
          paramParcel2.writeNoException();
          return true;
        }
      case 3: 
        paramParcel1.enforceInterface("com.google.android.gms.location.internal.IGoogleLocationManagerService");
        a(paramParcel1.createStringArray(), h.a.a(paramParcel1.readStrongBinder()), paramParcel1.readString());
        paramParcel2.writeNoException();
        return true;
      case 4: 
        paramParcel1.enforceInterface("com.google.android.gms.location.internal.IGoogleLocationManagerService");
        a(h.a.a(paramParcel1.readStrongBinder()), paramParcel1.readString());
        paramParcel2.writeNoException();
        return true;
      case 5: 
        paramParcel1.enforceInterface("com.google.android.gms.location.internal.IGoogleLocationManagerService");
        long l = paramParcel1.readLong();
        if (paramParcel1.readInt() != 0)
        {
          bool = true;
          if (paramParcel1.readInt() == 0) {
            break label619;
          }
        }
        for (paramParcel1 = (PendingIntent)PendingIntent.CREATOR.createFromParcel(paramParcel1);; paramParcel1 = null)
        {
          a(l, bool, paramParcel1);
          paramParcel2.writeNoException();
          return true;
          bool = false;
          break;
        }
      case 6: 
        paramParcel1.enforceInterface("com.google.android.gms.location.internal.IGoogleLocationManagerService");
        if (paramParcel1.readInt() != 0) {}
        for (paramParcel1 = (PendingIntent)PendingIntent.CREATOR.createFromParcel(paramParcel1);; paramParcel1 = null)
        {
          a(paramParcel1);
          paramParcel2.writeNoException();
          return true;
        }
      case 64: 
        paramParcel1.enforceInterface("com.google.android.gms.location.internal.IGoogleLocationManagerService");
        paramParcel1 = a(paramParcel1.readString());
        paramParcel2.writeNoException();
        if (paramParcel1 != null)
        {
          paramParcel2.writeInt(1);
          paramParcel1.writeToParcel(paramParcel2, 1);
          return true;
        }
        paramParcel2.writeInt(0);
        return true;
      case 65: 
        paramParcel1.enforceInterface("com.google.android.gms.location.internal.IGoogleLocationManagerService");
        if (paramParcel1.readInt() != 0) {}
        for (localObject1 = (PendingIntent)PendingIntent.CREATOR.createFromParcel(paramParcel1);; localObject1 = null)
        {
          a((PendingIntent)localObject1, zzo.zza.zzaN(paramParcel1.readStrongBinder()));
          paramParcel2.writeNoException();
          return true;
        }
      case 66: 
        paramParcel1.enforceInterface("com.google.android.gms.location.internal.IGoogleLocationManagerService");
        if (paramParcel1.readInt() != 0) {}
        for (localObject1 = (PendingIntent)PendingIntent.CREATOR.createFromParcel(paramParcel1);; localObject1 = null)
        {
          b((PendingIntent)localObject1, zzo.zza.zzaN(paramParcel1.readStrongBinder()));
          paramParcel2.writeNoException();
          return true;
        }
      case 60: 
        paramParcel1.enforceInterface("com.google.android.gms.location.internal.IGoogleLocationManagerService");
        if (paramParcel1.readInt() != 0)
        {
          localObject1 = GestureRequest.CREATOR.a(paramParcel1);
          if (paramParcel1.readInt() == 0) {
            break label883;
          }
        }
        for (localObject2 = (PendingIntent)PendingIntent.CREATOR.createFromParcel(paramParcel1);; localObject2 = null)
        {
          a((GestureRequest)localObject1, (PendingIntent)localObject2, zzo.zza.zzaN(paramParcel1.readStrongBinder()));
          paramParcel2.writeNoException();
          return true;
          localObject1 = null;
          break;
        }
      case 61: 
        paramParcel1.enforceInterface("com.google.android.gms.location.internal.IGoogleLocationManagerService");
        if (paramParcel1.readInt() != 0) {}
        for (localObject1 = (PendingIntent)PendingIntent.CREATOR.createFromParcel(paramParcel1);; localObject1 = null)
        {
          c((PendingIntent)localObject1, zzo.zza.zzaN(paramParcel1.readStrongBinder()));
          paramParcel2.writeNoException();
          return true;
        }
      case 68: 
        paramParcel1.enforceInterface("com.google.android.gms.location.internal.IGoogleLocationManagerService");
        if (paramParcel1.readInt() != 0) {}
        for (localObject1 = (PendingIntent)PendingIntent.CREATOR.createFromParcel(paramParcel1);; localObject1 = null)
        {
          d((PendingIntent)localObject1, zzo.zza.zzaN(paramParcel1.readStrongBinder()));
          paramParcel2.writeNoException();
          return true;
        }
      case 69: 
        paramParcel1.enforceInterface("com.google.android.gms.location.internal.IGoogleLocationManagerService");
        if (paramParcel1.readInt() != 0) {}
        for (localObject1 = (PendingIntent)PendingIntent.CREATOR.createFromParcel(paramParcel1);; localObject1 = null)
        {
          e((PendingIntent)localObject1, zzo.zza.zzaN(paramParcel1.readStrongBinder()));
          paramParcel2.writeNoException();
          return true;
        }
      case 7: 
        paramParcel1.enforceInterface("com.google.android.gms.location.internal.IGoogleLocationManagerService");
        paramParcel1 = a();
        paramParcel2.writeNoException();
        if (paramParcel1 != null)
        {
          paramParcel2.writeInt(1);
          paramParcel1.writeToParcel(paramParcel2, 1);
          return true;
        }
        paramParcel2.writeInt(0);
        return true;
      case 8: 
        paramParcel1.enforceInterface("com.google.android.gms.location.internal.IGoogleLocationManagerService");
        if (paramParcel1.readInt() != 0) {
          localObject1 = LocationRequest.CREATOR.a(paramParcel1);
        }
        a((LocationRequest)localObject1, r.a.a(paramParcel1.readStrongBinder()));
        paramParcel2.writeNoException();
        return true;
      case 20: 
        paramParcel1.enforceInterface("com.google.android.gms.location.internal.IGoogleLocationManagerService");
        localObject1 = localObject2;
        if (paramParcel1.readInt() != 0) {
          localObject1 = LocationRequest.CREATOR.a(paramParcel1);
        }
        a((LocationRequest)localObject1, r.a.a(paramParcel1.readStrongBinder()), paramParcel1.readString());
        paramParcel2.writeNoException();
        return true;
      case 9: 
        paramParcel1.enforceInterface("com.google.android.gms.location.internal.IGoogleLocationManagerService");
        if (paramParcel1.readInt() != 0)
        {
          localObject1 = LocationRequest.CREATOR.a(paramParcel1);
          if (paramParcel1.readInt() == 0) {
            break label1235;
          }
        }
        for (paramParcel1 = (PendingIntent)PendingIntent.CREATOR.createFromParcel(paramParcel1);; paramParcel1 = null)
        {
          a((LocationRequest)localObject1, paramParcel1);
          paramParcel2.writeNoException();
          return true;
          localObject1 = null;
          break;
        }
      case 52: 
        paramParcel1.enforceInterface("com.google.android.gms.location.internal.IGoogleLocationManagerService");
        localObject1 = localObject3;
        if (paramParcel1.readInt() != 0) {
          localObject1 = LocationRequestInternal.CREATOR.a(paramParcel1);
        }
        a((LocationRequestInternal)localObject1, r.a.a(paramParcel1.readStrongBinder()));
        paramParcel2.writeNoException();
        return true;
      case 53: 
        paramParcel1.enforceInterface("com.google.android.gms.location.internal.IGoogleLocationManagerService");
        if (paramParcel1.readInt() != 0)
        {
          localObject1 = LocationRequestInternal.CREATOR.a(paramParcel1);
          if (paramParcel1.readInt() == 0) {
            break label1346;
          }
        }
        for (paramParcel1 = (PendingIntent)PendingIntent.CREATOR.createFromParcel(paramParcel1);; paramParcel1 = null)
        {
          a((LocationRequestInternal)localObject1, paramParcel1);
          paramParcel2.writeNoException();
          return true;
          localObject1 = null;
          break;
        }
      case 10: 
        paramParcel1.enforceInterface("com.google.android.gms.location.internal.IGoogleLocationManagerService");
        a(r.a.a(paramParcel1.readStrongBinder()));
        paramParcel2.writeNoException();
        return true;
      case 11: 
        paramParcel1.enforceInterface("com.google.android.gms.location.internal.IGoogleLocationManagerService");
        if (paramParcel1.readInt() != 0) {}
        for (paramParcel1 = (PendingIntent)PendingIntent.CREATOR.createFromParcel(paramParcel1);; paramParcel1 = null)
        {
          b(paramParcel1);
          paramParcel2.writeNoException();
          return true;
        }
      case 59: 
        paramParcel1.enforceInterface("com.google.android.gms.location.internal.IGoogleLocationManagerService");
        localObject1 = localObject4;
        if (paramParcel1.readInt() != 0) {
          localObject1 = LocationRequestUpdateData.CREATOR.a(paramParcel1);
        }
        a((LocationRequestUpdateData)localObject1);
        paramParcel2.writeNoException();
        return true;
      case 12: 
        paramParcel1.enforceInterface("com.google.android.gms.location.internal.IGoogleLocationManagerService");
        if (paramParcel1.readInt() != 0) {
          bool = true;
        }
        a(bool);
        paramParcel2.writeNoException();
        return true;
      case 13: 
        paramParcel1.enforceInterface("com.google.android.gms.location.internal.IGoogleLocationManagerService");
        if (paramParcel1.readInt() != 0) {}
        for (paramParcel1 = (Location)Location.CREATOR.createFromParcel(paramParcel1);; paramParcel1 = null)
        {
          a(paramParcel1);
          paramParcel2.writeNoException();
          return true;
        }
      case 21: 
        paramParcel1.enforceInterface("com.google.android.gms.location.internal.IGoogleLocationManagerService");
        paramParcel1 = b(paramParcel1.readString());
        paramParcel2.writeNoException();
        if (paramParcel1 != null)
        {
          paramParcel2.writeInt(1);
          paramParcel1.writeToParcel(paramParcel2, 1);
          return true;
        }
        paramParcel2.writeInt(0);
        return true;
      case 26: 
        paramParcel1.enforceInterface("com.google.android.gms.location.internal.IGoogleLocationManagerService");
        if (paramParcel1.readInt() != 0) {}
        for (localObject1 = (Location)Location.CREATOR.createFromParcel(paramParcel1);; localObject1 = null)
        {
          a((Location)localObject1, paramParcel1.readInt());
          paramParcel2.writeNoException();
          return true;
        }
      case 67: 
        paramParcel1.enforceInterface("com.google.android.gms.location.internal.IGoogleLocationManagerService");
        a(g.a.a(paramParcel1.readStrongBinder()));
        paramParcel2.writeNoException();
        return true;
      case 34: 
        label436:
        label619:
        label883:
        label1235:
        label1346:
        paramParcel1.enforceInterface("com.google.android.gms.location.internal.IGoogleLocationManagerService");
        paramParcel1 = c(paramParcel1.readString());
        paramParcel2.writeNoException();
        if (paramParcel1 != null)
        {
          paramParcel2.writeInt(1);
          paramParcel1.writeToParcel(paramParcel2, 1);
          return true;
        }
        paramParcel2.writeInt(0);
        return true;
      }
      paramParcel1.enforceInterface("com.google.android.gms.location.internal.IGoogleLocationManagerService");
      if (paramParcel1.readInt() != 0) {}
      for (localObject1 = (LocationSettingsRequest)LocationSettingsRequest.CREATOR.createFromParcel(paramParcel1);; localObject1 = null)
      {
        a((LocationSettingsRequest)localObject1, j.a.a(paramParcel1.readStrongBinder()), paramParcel1.readString());
        paramParcel2.writeNoException();
        return true;
      }
    }
    
    private static class a
      implements i
    {
      private IBinder a;
      
      a(IBinder paramIBinder)
      {
        a = paramIBinder;
      }
      
      /* Error */
      public Location a()
        throws RemoteException
      {
        // Byte code:
        //   0: invokestatic 27	android/os/Parcel:obtain	()Landroid/os/Parcel;
        //   3: astore_2
        //   4: invokestatic 27	android/os/Parcel:obtain	()Landroid/os/Parcel;
        //   7: astore_3
        //   8: aload_2
        //   9: ldc 29
        //   11: invokevirtual 33	android/os/Parcel:writeInterfaceToken	(Ljava/lang/String;)V
        //   14: aload_0
        //   15: getfield 17	com/google/android/gms/location/internal/i$a$a:a	Landroid/os/IBinder;
        //   18: bipush 7
        //   20: aload_2
        //   21: aload_3
        //   22: iconst_0
        //   23: invokeinterface 39 5 0
        //   28: pop
        //   29: aload_3
        //   30: invokevirtual 42	android/os/Parcel:readException	()V
        //   33: aload_3
        //   34: invokevirtual 46	android/os/Parcel:readInt	()I
        //   37: ifeq +26 -> 63
        //   40: getstatic 52	android/location/Location:CREATOR	Landroid/os/Parcelable$Creator;
        //   43: aload_3
        //   44: invokeinterface 58 2 0
        //   49: checkcast 48	android/location/Location
        //   52: astore_1
        //   53: aload_3
        //   54: invokevirtual 61	android/os/Parcel:recycle	()V
        //   57: aload_2
        //   58: invokevirtual 61	android/os/Parcel:recycle	()V
        //   61: aload_1
        //   62: areturn
        //   63: aconst_null
        //   64: astore_1
        //   65: goto -12 -> 53
        //   68: astore_1
        //   69: aload_3
        //   70: invokevirtual 61	android/os/Parcel:recycle	()V
        //   73: aload_2
        //   74: invokevirtual 61	android/os/Parcel:recycle	()V
        //   77: aload_1
        //   78: athrow
        // Local variable table:
        //   start	length	slot	name	signature
        //   0	79	0	this	a
        //   52	13	1	localLocation	Location
        //   68	10	1	localObject	Object
        //   3	71	2	localParcel1	Parcel
        //   7	63	3	localParcel2	Parcel
        // Exception table:
        //   from	to	target	type
        //   8	53	68	finally
      }
      
      /* Error */
      public ActivityRecognitionResult a(String paramString)
        throws RemoteException
      {
        // Byte code:
        //   0: invokestatic 27	android/os/Parcel:obtain	()Landroid/os/Parcel;
        //   3: astore_2
        //   4: invokestatic 27	android/os/Parcel:obtain	()Landroid/os/Parcel;
        //   7: astore_3
        //   8: aload_2
        //   9: ldc 29
        //   11: invokevirtual 33	android/os/Parcel:writeInterfaceToken	(Ljava/lang/String;)V
        //   14: aload_2
        //   15: aload_1
        //   16: invokevirtual 66	android/os/Parcel:writeString	(Ljava/lang/String;)V
        //   19: aload_0
        //   20: getfield 17	com/google/android/gms/location/internal/i$a$a:a	Landroid/os/IBinder;
        //   23: bipush 64
        //   25: aload_2
        //   26: aload_3
        //   27: iconst_0
        //   28: invokeinterface 39 5 0
        //   33: pop
        //   34: aload_3
        //   35: invokevirtual 42	android/os/Parcel:readException	()V
        //   38: aload_3
        //   39: invokevirtual 46	android/os/Parcel:readInt	()I
        //   42: ifeq +21 -> 63
        //   45: getstatic 71	com/google/android/gms/location/ActivityRecognitionResult:CREATOR	Lcom/google/android/gms/location/c;
        //   48: aload_3
        //   49: invokevirtual 76	com/google/android/gms/location/c:a	(Landroid/os/Parcel;)Lcom/google/android/gms/location/ActivityRecognitionResult;
        //   52: astore_1
        //   53: aload_3
        //   54: invokevirtual 61	android/os/Parcel:recycle	()V
        //   57: aload_2
        //   58: invokevirtual 61	android/os/Parcel:recycle	()V
        //   61: aload_1
        //   62: areturn
        //   63: aconst_null
        //   64: astore_1
        //   65: goto -12 -> 53
        //   68: astore_1
        //   69: aload_3
        //   70: invokevirtual 61	android/os/Parcel:recycle	()V
        //   73: aload_2
        //   74: invokevirtual 61	android/os/Parcel:recycle	()V
        //   77: aload_1
        //   78: athrow
        // Local variable table:
        //   start	length	slot	name	signature
        //   0	79	0	this	a
        //   0	79	1	paramString	String
        //   3	71	2	localParcel1	Parcel
        //   7	63	3	localParcel2	Parcel
        // Exception table:
        //   from	to	target	type
        //   8	53	68	finally
      }
      
      /* Error */
      public void a(long paramLong, boolean paramBoolean, PendingIntent paramPendingIntent)
        throws RemoteException
      {
        // Byte code:
        //   0: iconst_1
        //   1: istore 5
        //   3: invokestatic 27	android/os/Parcel:obtain	()Landroid/os/Parcel;
        //   6: astore 6
        //   8: invokestatic 27	android/os/Parcel:obtain	()Landroid/os/Parcel;
        //   11: astore 7
        //   13: aload 6
        //   15: ldc 29
        //   17: invokevirtual 33	android/os/Parcel:writeInterfaceToken	(Ljava/lang/String;)V
        //   20: aload 6
        //   22: lload_1
        //   23: invokevirtual 81	android/os/Parcel:writeLong	(J)V
        //   26: iload_3
        //   27: ifeq +61 -> 88
        //   30: aload 6
        //   32: iload 5
        //   34: invokevirtual 85	android/os/Parcel:writeInt	(I)V
        //   37: aload 4
        //   39: ifnull +55 -> 94
        //   42: aload 6
        //   44: iconst_1
        //   45: invokevirtual 85	android/os/Parcel:writeInt	(I)V
        //   48: aload 4
        //   50: aload 6
        //   52: iconst_0
        //   53: invokevirtual 91	android/app/PendingIntent:writeToParcel	(Landroid/os/Parcel;I)V
        //   56: aload_0
        //   57: getfield 17	com/google/android/gms/location/internal/i$a$a:a	Landroid/os/IBinder;
        //   60: iconst_5
        //   61: aload 6
        //   63: aload 7
        //   65: iconst_0
        //   66: invokeinterface 39 5 0
        //   71: pop
        //   72: aload 7
        //   74: invokevirtual 42	android/os/Parcel:readException	()V
        //   77: aload 7
        //   79: invokevirtual 61	android/os/Parcel:recycle	()V
        //   82: aload 6
        //   84: invokevirtual 61	android/os/Parcel:recycle	()V
        //   87: return
        //   88: iconst_0
        //   89: istore 5
        //   91: goto -61 -> 30
        //   94: aload 6
        //   96: iconst_0
        //   97: invokevirtual 85	android/os/Parcel:writeInt	(I)V
        //   100: goto -44 -> 56
        //   103: astore 4
        //   105: aload 7
        //   107: invokevirtual 61	android/os/Parcel:recycle	()V
        //   110: aload 6
        //   112: invokevirtual 61	android/os/Parcel:recycle	()V
        //   115: aload 4
        //   117: athrow
        // Local variable table:
        //   start	length	slot	name	signature
        //   0	118	0	this	a
        //   0	118	1	paramLong	long
        //   0	118	3	paramBoolean	boolean
        //   0	118	4	paramPendingIntent	PendingIntent
        //   1	89	5	i	int
        //   6	105	6	localParcel1	Parcel
        //   11	95	7	localParcel2	Parcel
        // Exception table:
        //   from	to	target	type
        //   13	26	103	finally
        //   30	37	103	finally
        //   42	56	103	finally
        //   56	77	103	finally
        //   94	100	103	finally
      }
      
      /* Error */
      public void a(PendingIntent paramPendingIntent)
        throws RemoteException
      {
        // Byte code:
        //   0: invokestatic 27	android/os/Parcel:obtain	()Landroid/os/Parcel;
        //   3: astore_2
        //   4: invokestatic 27	android/os/Parcel:obtain	()Landroid/os/Parcel;
        //   7: astore_3
        //   8: aload_2
        //   9: ldc 29
        //   11: invokevirtual 33	android/os/Parcel:writeInterfaceToken	(Ljava/lang/String;)V
        //   14: aload_1
        //   15: ifnull +42 -> 57
        //   18: aload_2
        //   19: iconst_1
        //   20: invokevirtual 85	android/os/Parcel:writeInt	(I)V
        //   23: aload_1
        //   24: aload_2
        //   25: iconst_0
        //   26: invokevirtual 91	android/app/PendingIntent:writeToParcel	(Landroid/os/Parcel;I)V
        //   29: aload_0
        //   30: getfield 17	com/google/android/gms/location/internal/i$a$a:a	Landroid/os/IBinder;
        //   33: bipush 6
        //   35: aload_2
        //   36: aload_3
        //   37: iconst_0
        //   38: invokeinterface 39 5 0
        //   43: pop
        //   44: aload_3
        //   45: invokevirtual 42	android/os/Parcel:readException	()V
        //   48: aload_3
        //   49: invokevirtual 61	android/os/Parcel:recycle	()V
        //   52: aload_2
        //   53: invokevirtual 61	android/os/Parcel:recycle	()V
        //   56: return
        //   57: aload_2
        //   58: iconst_0
        //   59: invokevirtual 85	android/os/Parcel:writeInt	(I)V
        //   62: goto -33 -> 29
        //   65: astore_1
        //   66: aload_3
        //   67: invokevirtual 61	android/os/Parcel:recycle	()V
        //   70: aload_2
        //   71: invokevirtual 61	android/os/Parcel:recycle	()V
        //   74: aload_1
        //   75: athrow
        // Local variable table:
        //   start	length	slot	name	signature
        //   0	76	0	this	a
        //   0	76	1	paramPendingIntent	PendingIntent
        //   3	68	2	localParcel1	Parcel
        //   7	60	3	localParcel2	Parcel
        // Exception table:
        //   from	to	target	type
        //   8	14	65	finally
        //   18	29	65	finally
        //   29	48	65	finally
        //   57	62	65	finally
      }
      
      public void a(PendingIntent paramPendingIntent, zzo paramzzo)
        throws RemoteException
      {
        Parcel localParcel1 = Parcel.obtain();
        Parcel localParcel2 = Parcel.obtain();
        for (;;)
        {
          try
          {
            localParcel1.writeInterfaceToken("com.google.android.gms.location.internal.IGoogleLocationManagerService");
            if (paramPendingIntent != null)
            {
              localParcel1.writeInt(1);
              paramPendingIntent.writeToParcel(localParcel1, 0);
              if (paramzzo != null)
              {
                paramPendingIntent = paramzzo.asBinder();
                localParcel1.writeStrongBinder(paramPendingIntent);
                a.transact(65, localParcel1, localParcel2, 0);
                localParcel2.readException();
              }
            }
            else
            {
              localParcel1.writeInt(0);
              continue;
            }
            paramPendingIntent = null;
          }
          finally
          {
            localParcel2.recycle();
            localParcel1.recycle();
          }
        }
      }
      
      public void a(PendingIntent paramPendingIntent, h paramh, String paramString)
        throws RemoteException
      {
        Parcel localParcel1 = Parcel.obtain();
        Parcel localParcel2 = Parcel.obtain();
        for (;;)
        {
          try
          {
            localParcel1.writeInterfaceToken("com.google.android.gms.location.internal.IGoogleLocationManagerService");
            if (paramPendingIntent != null)
            {
              localParcel1.writeInt(1);
              paramPendingIntent.writeToParcel(localParcel1, 0);
              if (paramh != null)
              {
                paramPendingIntent = paramh.asBinder();
                localParcel1.writeStrongBinder(paramPendingIntent);
                localParcel1.writeString(paramString);
                a.transact(2, localParcel1, localParcel2, 0);
                localParcel2.readException();
              }
            }
            else
            {
              localParcel1.writeInt(0);
              continue;
            }
            paramPendingIntent = null;
          }
          finally
          {
            localParcel2.recycle();
            localParcel1.recycle();
          }
        }
      }
      
      /* Error */
      public void a(Location paramLocation)
        throws RemoteException
      {
        // Byte code:
        //   0: invokestatic 27	android/os/Parcel:obtain	()Landroid/os/Parcel;
        //   3: astore_2
        //   4: invokestatic 27	android/os/Parcel:obtain	()Landroid/os/Parcel;
        //   7: astore_3
        //   8: aload_2
        //   9: ldc 29
        //   11: invokevirtual 33	android/os/Parcel:writeInterfaceToken	(Ljava/lang/String;)V
        //   14: aload_1
        //   15: ifnull +42 -> 57
        //   18: aload_2
        //   19: iconst_1
        //   20: invokevirtual 85	android/os/Parcel:writeInt	(I)V
        //   23: aload_1
        //   24: aload_2
        //   25: iconst_0
        //   26: invokevirtual 108	android/location/Location:writeToParcel	(Landroid/os/Parcel;I)V
        //   29: aload_0
        //   30: getfield 17	com/google/android/gms/location/internal/i$a$a:a	Landroid/os/IBinder;
        //   33: bipush 13
        //   35: aload_2
        //   36: aload_3
        //   37: iconst_0
        //   38: invokeinterface 39 5 0
        //   43: pop
        //   44: aload_3
        //   45: invokevirtual 42	android/os/Parcel:readException	()V
        //   48: aload_3
        //   49: invokevirtual 61	android/os/Parcel:recycle	()V
        //   52: aload_2
        //   53: invokevirtual 61	android/os/Parcel:recycle	()V
        //   56: return
        //   57: aload_2
        //   58: iconst_0
        //   59: invokevirtual 85	android/os/Parcel:writeInt	(I)V
        //   62: goto -33 -> 29
        //   65: astore_1
        //   66: aload_3
        //   67: invokevirtual 61	android/os/Parcel:recycle	()V
        //   70: aload_2
        //   71: invokevirtual 61	android/os/Parcel:recycle	()V
        //   74: aload_1
        //   75: athrow
        // Local variable table:
        //   start	length	slot	name	signature
        //   0	76	0	this	a
        //   0	76	1	paramLocation	Location
        //   3	68	2	localParcel1	Parcel
        //   7	60	3	localParcel2	Parcel
        // Exception table:
        //   from	to	target	type
        //   8	14	65	finally
        //   18	29	65	finally
        //   29	48	65	finally
        //   57	62	65	finally
      }
      
      /* Error */
      public void a(Location paramLocation, int paramInt)
        throws RemoteException
      {
        // Byte code:
        //   0: invokestatic 27	android/os/Parcel:obtain	()Landroid/os/Parcel;
        //   3: astore_3
        //   4: invokestatic 27	android/os/Parcel:obtain	()Landroid/os/Parcel;
        //   7: astore 4
        //   9: aload_3
        //   10: ldc 29
        //   12: invokevirtual 33	android/os/Parcel:writeInterfaceToken	(Ljava/lang/String;)V
        //   15: aload_1
        //   16: ifnull +50 -> 66
        //   19: aload_3
        //   20: iconst_1
        //   21: invokevirtual 85	android/os/Parcel:writeInt	(I)V
        //   24: aload_1
        //   25: aload_3
        //   26: iconst_0
        //   27: invokevirtual 108	android/location/Location:writeToParcel	(Landroid/os/Parcel;I)V
        //   30: aload_3
        //   31: iload_2
        //   32: invokevirtual 85	android/os/Parcel:writeInt	(I)V
        //   35: aload_0
        //   36: getfield 17	com/google/android/gms/location/internal/i$a$a:a	Landroid/os/IBinder;
        //   39: bipush 26
        //   41: aload_3
        //   42: aload 4
        //   44: iconst_0
        //   45: invokeinterface 39 5 0
        //   50: pop
        //   51: aload 4
        //   53: invokevirtual 42	android/os/Parcel:readException	()V
        //   56: aload 4
        //   58: invokevirtual 61	android/os/Parcel:recycle	()V
        //   61: aload_3
        //   62: invokevirtual 61	android/os/Parcel:recycle	()V
        //   65: return
        //   66: aload_3
        //   67: iconst_0
        //   68: invokevirtual 85	android/os/Parcel:writeInt	(I)V
        //   71: goto -41 -> 30
        //   74: astore_1
        //   75: aload 4
        //   77: invokevirtual 61	android/os/Parcel:recycle	()V
        //   80: aload_3
        //   81: invokevirtual 61	android/os/Parcel:recycle	()V
        //   84: aload_1
        //   85: athrow
        // Local variable table:
        //   start	length	slot	name	signature
        //   0	86	0	this	a
        //   0	86	1	paramLocation	Location
        //   0	86	2	paramInt	int
        //   3	78	3	localParcel1	Parcel
        //   7	69	4	localParcel2	Parcel
        // Exception table:
        //   from	to	target	type
        //   9	15	74	finally
        //   19	30	74	finally
        //   30	56	74	finally
        //   66	71	74	finally
      }
      
      public void a(GeofencingRequest paramGeofencingRequest, PendingIntent paramPendingIntent, h paramh)
        throws RemoteException
      {
        Parcel localParcel1 = Parcel.obtain();
        Parcel localParcel2 = Parcel.obtain();
        for (;;)
        {
          try
          {
            localParcel1.writeInterfaceToken("com.google.android.gms.location.internal.IGoogleLocationManagerService");
            if (paramGeofencingRequest != null)
            {
              localParcel1.writeInt(1);
              paramGeofencingRequest.writeToParcel(localParcel1, 0);
              if (paramPendingIntent != null)
              {
                localParcel1.writeInt(1);
                paramPendingIntent.writeToParcel(localParcel1, 0);
                if (paramh == null) {
                  break label132;
                }
                paramGeofencingRequest = paramh.asBinder();
                localParcel1.writeStrongBinder(paramGeofencingRequest);
                a.transact(57, localParcel1, localParcel2, 0);
                localParcel2.readException();
              }
            }
            else
            {
              localParcel1.writeInt(0);
              continue;
            }
            localParcel1.writeInt(0);
          }
          finally
          {
            localParcel2.recycle();
            localParcel1.recycle();
          }
          continue;
          label132:
          paramGeofencingRequest = null;
        }
      }
      
      public void a(GestureRequest paramGestureRequest, PendingIntent paramPendingIntent, zzo paramzzo)
        throws RemoteException
      {
        Parcel localParcel1 = Parcel.obtain();
        Parcel localParcel2 = Parcel.obtain();
        for (;;)
        {
          try
          {
            localParcel1.writeInterfaceToken("com.google.android.gms.location.internal.IGoogleLocationManagerService");
            if (paramGestureRequest != null)
            {
              localParcel1.writeInt(1);
              paramGestureRequest.writeToParcel(localParcel1, 0);
              if (paramPendingIntent != null)
              {
                localParcel1.writeInt(1);
                paramPendingIntent.writeToParcel(localParcel1, 0);
                if (paramzzo == null) {
                  break label132;
                }
                paramGestureRequest = paramzzo.asBinder();
                localParcel1.writeStrongBinder(paramGestureRequest);
                a.transact(60, localParcel1, localParcel2, 0);
                localParcel2.readException();
              }
            }
            else
            {
              localParcel1.writeInt(0);
              continue;
            }
            localParcel1.writeInt(0);
          }
          finally
          {
            localParcel2.recycle();
            localParcel1.recycle();
          }
          continue;
          label132:
          paramGestureRequest = null;
        }
      }
      
      public void a(LocationRequest paramLocationRequest, PendingIntent paramPendingIntent)
        throws RemoteException
      {
        Parcel localParcel1 = Parcel.obtain();
        Parcel localParcel2 = Parcel.obtain();
        for (;;)
        {
          try
          {
            localParcel1.writeInterfaceToken("com.google.android.gms.location.internal.IGoogleLocationManagerService");
            if (paramLocationRequest != null)
            {
              localParcel1.writeInt(1);
              paramLocationRequest.writeToParcel(localParcel1, 0);
              if (paramPendingIntent != null)
              {
                localParcel1.writeInt(1);
                paramPendingIntent.writeToParcel(localParcel1, 0);
                a.transact(9, localParcel1, localParcel2, 0);
                localParcel2.readException();
              }
            }
            else
            {
              localParcel1.writeInt(0);
              continue;
            }
            localParcel1.writeInt(0);
          }
          finally
          {
            localParcel2.recycle();
            localParcel1.recycle();
          }
        }
      }
      
      public void a(LocationRequest paramLocationRequest, r paramr)
        throws RemoteException
      {
        Parcel localParcel1 = Parcel.obtain();
        Parcel localParcel2 = Parcel.obtain();
        for (;;)
        {
          try
          {
            localParcel1.writeInterfaceToken("com.google.android.gms.location.internal.IGoogleLocationManagerService");
            if (paramLocationRequest != null)
            {
              localParcel1.writeInt(1);
              paramLocationRequest.writeToParcel(localParcel1, 0);
              if (paramr != null)
              {
                paramLocationRequest = paramr.asBinder();
                localParcel1.writeStrongBinder(paramLocationRequest);
                a.transact(8, localParcel1, localParcel2, 0);
                localParcel2.readException();
              }
            }
            else
            {
              localParcel1.writeInt(0);
              continue;
            }
            paramLocationRequest = null;
          }
          finally
          {
            localParcel2.recycle();
            localParcel1.recycle();
          }
        }
      }
      
      public void a(LocationRequest paramLocationRequest, r paramr, String paramString)
        throws RemoteException
      {
        Parcel localParcel1 = Parcel.obtain();
        Parcel localParcel2 = Parcel.obtain();
        for (;;)
        {
          try
          {
            localParcel1.writeInterfaceToken("com.google.android.gms.location.internal.IGoogleLocationManagerService");
            if (paramLocationRequest != null)
            {
              localParcel1.writeInt(1);
              paramLocationRequest.writeToParcel(localParcel1, 0);
              if (paramr != null)
              {
                paramLocationRequest = paramr.asBinder();
                localParcel1.writeStrongBinder(paramLocationRequest);
                localParcel1.writeString(paramString);
                a.transact(20, localParcel1, localParcel2, 0);
                localParcel2.readException();
              }
            }
            else
            {
              localParcel1.writeInt(0);
              continue;
            }
            paramLocationRequest = null;
          }
          finally
          {
            localParcel2.recycle();
            localParcel1.recycle();
          }
        }
      }
      
      public void a(LocationSettingsRequest paramLocationSettingsRequest, j paramj, String paramString)
        throws RemoteException
      {
        Parcel localParcel1 = Parcel.obtain();
        Parcel localParcel2 = Parcel.obtain();
        for (;;)
        {
          try
          {
            localParcel1.writeInterfaceToken("com.google.android.gms.location.internal.IGoogleLocationManagerService");
            if (paramLocationSettingsRequest != null)
            {
              localParcel1.writeInt(1);
              paramLocationSettingsRequest.writeToParcel(localParcel1, 0);
              if (paramj != null)
              {
                paramLocationSettingsRequest = paramj.asBinder();
                localParcel1.writeStrongBinder(paramLocationSettingsRequest);
                localParcel1.writeString(paramString);
                a.transact(63, localParcel1, localParcel2, 0);
                localParcel2.readException();
              }
            }
            else
            {
              localParcel1.writeInt(0);
              continue;
            }
            paramLocationSettingsRequest = null;
          }
          finally
          {
            localParcel2.recycle();
            localParcel1.recycle();
          }
        }
      }
      
      public void a(LocationRequestInternal paramLocationRequestInternal, PendingIntent paramPendingIntent)
        throws RemoteException
      {
        Parcel localParcel1 = Parcel.obtain();
        Parcel localParcel2 = Parcel.obtain();
        for (;;)
        {
          try
          {
            localParcel1.writeInterfaceToken("com.google.android.gms.location.internal.IGoogleLocationManagerService");
            if (paramLocationRequestInternal != null)
            {
              localParcel1.writeInt(1);
              paramLocationRequestInternal.writeToParcel(localParcel1, 0);
              if (paramPendingIntent != null)
              {
                localParcel1.writeInt(1);
                paramPendingIntent.writeToParcel(localParcel1, 0);
                a.transact(53, localParcel1, localParcel2, 0);
                localParcel2.readException();
              }
            }
            else
            {
              localParcel1.writeInt(0);
              continue;
            }
            localParcel1.writeInt(0);
          }
          finally
          {
            localParcel2.recycle();
            localParcel1.recycle();
          }
        }
      }
      
      public void a(LocationRequestInternal paramLocationRequestInternal, r paramr)
        throws RemoteException
      {
        Parcel localParcel1 = Parcel.obtain();
        Parcel localParcel2 = Parcel.obtain();
        for (;;)
        {
          try
          {
            localParcel1.writeInterfaceToken("com.google.android.gms.location.internal.IGoogleLocationManagerService");
            if (paramLocationRequestInternal != null)
            {
              localParcel1.writeInt(1);
              paramLocationRequestInternal.writeToParcel(localParcel1, 0);
              if (paramr != null)
              {
                paramLocationRequestInternal = paramr.asBinder();
                localParcel1.writeStrongBinder(paramLocationRequestInternal);
                a.transact(52, localParcel1, localParcel2, 0);
                localParcel2.readException();
              }
            }
            else
            {
              localParcel1.writeInt(0);
              continue;
            }
            paramLocationRequestInternal = null;
          }
          finally
          {
            localParcel2.recycle();
            localParcel1.recycle();
          }
        }
      }
      
      /* Error */
      public void a(LocationRequestUpdateData paramLocationRequestUpdateData)
        throws RemoteException
      {
        // Byte code:
        //   0: invokestatic 27	android/os/Parcel:obtain	()Landroid/os/Parcel;
        //   3: astore_2
        //   4: invokestatic 27	android/os/Parcel:obtain	()Landroid/os/Parcel;
        //   7: astore_3
        //   8: aload_2
        //   9: ldc 29
        //   11: invokevirtual 33	android/os/Parcel:writeInterfaceToken	(Ljava/lang/String;)V
        //   14: aload_1
        //   15: ifnull +42 -> 57
        //   18: aload_2
        //   19: iconst_1
        //   20: invokevirtual 85	android/os/Parcel:writeInt	(I)V
        //   23: aload_1
        //   24: aload_2
        //   25: iconst_0
        //   26: invokevirtual 142	com/google/android/gms/location/internal/LocationRequestUpdateData:writeToParcel	(Landroid/os/Parcel;I)V
        //   29: aload_0
        //   30: getfield 17	com/google/android/gms/location/internal/i$a$a:a	Landroid/os/IBinder;
        //   33: bipush 59
        //   35: aload_2
        //   36: aload_3
        //   37: iconst_0
        //   38: invokeinterface 39 5 0
        //   43: pop
        //   44: aload_3
        //   45: invokevirtual 42	android/os/Parcel:readException	()V
        //   48: aload_3
        //   49: invokevirtual 61	android/os/Parcel:recycle	()V
        //   52: aload_2
        //   53: invokevirtual 61	android/os/Parcel:recycle	()V
        //   56: return
        //   57: aload_2
        //   58: iconst_0
        //   59: invokevirtual 85	android/os/Parcel:writeInt	(I)V
        //   62: goto -33 -> 29
        //   65: astore_1
        //   66: aload_3
        //   67: invokevirtual 61	android/os/Parcel:recycle	()V
        //   70: aload_2
        //   71: invokevirtual 61	android/os/Parcel:recycle	()V
        //   74: aload_1
        //   75: athrow
        // Local variable table:
        //   start	length	slot	name	signature
        //   0	76	0	this	a
        //   0	76	1	paramLocationRequestUpdateData	LocationRequestUpdateData
        //   3	68	2	localParcel1	Parcel
        //   7	60	3	localParcel2	Parcel
        // Exception table:
        //   from	to	target	type
        //   8	14	65	finally
        //   18	29	65	finally
        //   29	48	65	finally
        //   57	62	65	finally
      }
      
      /* Error */
      public void a(g paramg)
        throws RemoteException
      {
        // Byte code:
        //   0: invokestatic 27	android/os/Parcel:obtain	()Landroid/os/Parcel;
        //   3: astore_2
        //   4: invokestatic 27	android/os/Parcel:obtain	()Landroid/os/Parcel;
        //   7: astore_3
        //   8: aload_2
        //   9: ldc 29
        //   11: invokevirtual 33	android/os/Parcel:writeInterfaceToken	(Ljava/lang/String;)V
        //   14: aload_1
        //   15: ifnull +43 -> 58
        //   18: aload_1
        //   19: invokeinterface 146 1 0
        //   24: astore_1
        //   25: aload_2
        //   26: aload_1
        //   27: invokevirtual 102	android/os/Parcel:writeStrongBinder	(Landroid/os/IBinder;)V
        //   30: aload_0
        //   31: getfield 17	com/google/android/gms/location/internal/i$a$a:a	Landroid/os/IBinder;
        //   34: bipush 67
        //   36: aload_2
        //   37: aload_3
        //   38: iconst_0
        //   39: invokeinterface 39 5 0
        //   44: pop
        //   45: aload_3
        //   46: invokevirtual 42	android/os/Parcel:readException	()V
        //   49: aload_3
        //   50: invokevirtual 61	android/os/Parcel:recycle	()V
        //   53: aload_2
        //   54: invokevirtual 61	android/os/Parcel:recycle	()V
        //   57: return
        //   58: aconst_null
        //   59: astore_1
        //   60: goto -35 -> 25
        //   63: astore_1
        //   64: aload_3
        //   65: invokevirtual 61	android/os/Parcel:recycle	()V
        //   68: aload_2
        //   69: invokevirtual 61	android/os/Parcel:recycle	()V
        //   72: aload_1
        //   73: athrow
        // Local variable table:
        //   start	length	slot	name	signature
        //   0	74	0	this	a
        //   0	74	1	paramg	g
        //   3	66	2	localParcel1	Parcel
        //   7	58	3	localParcel2	Parcel
        // Exception table:
        //   from	to	target	type
        //   8	14	63	finally
        //   18	25	63	finally
        //   25	49	63	finally
      }
      
      /* Error */
      public void a(h paramh, String paramString)
        throws RemoteException
      {
        // Byte code:
        //   0: invokestatic 27	android/os/Parcel:obtain	()Landroid/os/Parcel;
        //   3: astore_3
        //   4: invokestatic 27	android/os/Parcel:obtain	()Landroid/os/Parcel;
        //   7: astore 4
        //   9: aload_3
        //   10: ldc 29
        //   12: invokevirtual 33	android/os/Parcel:writeInterfaceToken	(Ljava/lang/String;)V
        //   15: aload_1
        //   16: ifnull +50 -> 66
        //   19: aload_1
        //   20: invokeinterface 106 1 0
        //   25: astore_1
        //   26: aload_3
        //   27: aload_1
        //   28: invokevirtual 102	android/os/Parcel:writeStrongBinder	(Landroid/os/IBinder;)V
        //   31: aload_3
        //   32: aload_2
        //   33: invokevirtual 66	android/os/Parcel:writeString	(Ljava/lang/String;)V
        //   36: aload_0
        //   37: getfield 17	com/google/android/gms/location/internal/i$a$a:a	Landroid/os/IBinder;
        //   40: iconst_4
        //   41: aload_3
        //   42: aload 4
        //   44: iconst_0
        //   45: invokeinterface 39 5 0
        //   50: pop
        //   51: aload 4
        //   53: invokevirtual 42	android/os/Parcel:readException	()V
        //   56: aload 4
        //   58: invokevirtual 61	android/os/Parcel:recycle	()V
        //   61: aload_3
        //   62: invokevirtual 61	android/os/Parcel:recycle	()V
        //   65: return
        //   66: aconst_null
        //   67: astore_1
        //   68: goto -42 -> 26
        //   71: astore_1
        //   72: aload 4
        //   74: invokevirtual 61	android/os/Parcel:recycle	()V
        //   77: aload_3
        //   78: invokevirtual 61	android/os/Parcel:recycle	()V
        //   81: aload_1
        //   82: athrow
        // Local variable table:
        //   start	length	slot	name	signature
        //   0	83	0	this	a
        //   0	83	1	paramh	h
        //   0	83	2	paramString	String
        //   3	75	3	localParcel1	Parcel
        //   7	66	4	localParcel2	Parcel
        // Exception table:
        //   from	to	target	type
        //   9	15	71	finally
        //   19	26	71	finally
        //   26	56	71	finally
      }
      
      /* Error */
      public void a(r paramr)
        throws RemoteException
      {
        // Byte code:
        //   0: invokestatic 27	android/os/Parcel:obtain	()Landroid/os/Parcel;
        //   3: astore_2
        //   4: invokestatic 27	android/os/Parcel:obtain	()Landroid/os/Parcel;
        //   7: astore_3
        //   8: aload_2
        //   9: ldc 29
        //   11: invokevirtual 33	android/os/Parcel:writeInterfaceToken	(Ljava/lang/String;)V
        //   14: aload_1
        //   15: ifnull +43 -> 58
        //   18: aload_1
        //   19: invokeinterface 125 1 0
        //   24: astore_1
        //   25: aload_2
        //   26: aload_1
        //   27: invokevirtual 102	android/os/Parcel:writeStrongBinder	(Landroid/os/IBinder;)V
        //   30: aload_0
        //   31: getfield 17	com/google/android/gms/location/internal/i$a$a:a	Landroid/os/IBinder;
        //   34: bipush 10
        //   36: aload_2
        //   37: aload_3
        //   38: iconst_0
        //   39: invokeinterface 39 5 0
        //   44: pop
        //   45: aload_3
        //   46: invokevirtual 42	android/os/Parcel:readException	()V
        //   49: aload_3
        //   50: invokevirtual 61	android/os/Parcel:recycle	()V
        //   53: aload_2
        //   54: invokevirtual 61	android/os/Parcel:recycle	()V
        //   57: return
        //   58: aconst_null
        //   59: astore_1
        //   60: goto -35 -> 25
        //   63: astore_1
        //   64: aload_3
        //   65: invokevirtual 61	android/os/Parcel:recycle	()V
        //   68: aload_2
        //   69: invokevirtual 61	android/os/Parcel:recycle	()V
        //   72: aload_1
        //   73: athrow
        // Local variable table:
        //   start	length	slot	name	signature
        //   0	74	0	this	a
        //   0	74	1	paramr	r
        //   3	66	2	localParcel1	Parcel
        //   7	58	3	localParcel2	Parcel
        // Exception table:
        //   from	to	target	type
        //   8	14	63	finally
        //   18	25	63	finally
        //   25	49	63	finally
      }
      
      public void a(List<ParcelableGeofence> paramList, PendingIntent paramPendingIntent, h paramh, String paramString)
        throws RemoteException
      {
        Parcel localParcel1 = Parcel.obtain();
        Parcel localParcel2 = Parcel.obtain();
        for (;;)
        {
          try
          {
            localParcel1.writeInterfaceToken("com.google.android.gms.location.internal.IGoogleLocationManagerService");
            localParcel1.writeTypedList(paramList);
            if (paramPendingIntent != null)
            {
              localParcel1.writeInt(1);
              paramPendingIntent.writeToParcel(localParcel1, 0);
              if (paramh != null)
              {
                paramList = paramh.asBinder();
                localParcel1.writeStrongBinder(paramList);
                localParcel1.writeString(paramString);
                a.transact(1, localParcel1, localParcel2, 0);
                localParcel2.readException();
              }
            }
            else
            {
              localParcel1.writeInt(0);
              continue;
            }
            paramList = null;
          }
          finally
          {
            localParcel2.recycle();
            localParcel1.recycle();
          }
        }
      }
      
      public void a(boolean paramBoolean)
        throws RemoteException
      {
        int i = 0;
        Parcel localParcel1 = Parcel.obtain();
        Parcel localParcel2 = Parcel.obtain();
        try
        {
          localParcel1.writeInterfaceToken("com.google.android.gms.location.internal.IGoogleLocationManagerService");
          if (paramBoolean) {
            i = 1;
          }
          localParcel1.writeInt(i);
          a.transact(12, localParcel1, localParcel2, 0);
          localParcel2.readException();
          return;
        }
        finally
        {
          localParcel2.recycle();
          localParcel1.recycle();
        }
      }
      
      /* Error */
      public void a(String[] paramArrayOfString, h paramh, String paramString)
        throws RemoteException
      {
        // Byte code:
        //   0: invokestatic 27	android/os/Parcel:obtain	()Landroid/os/Parcel;
        //   3: astore 4
        //   5: invokestatic 27	android/os/Parcel:obtain	()Landroid/os/Parcel;
        //   8: astore 5
        //   10: aload 4
        //   12: ldc 29
        //   14: invokevirtual 33	android/os/Parcel:writeInterfaceToken	(Ljava/lang/String;)V
        //   17: aload 4
        //   19: aload_1
        //   20: invokevirtual 161	android/os/Parcel:writeStringArray	([Ljava/lang/String;)V
        //   23: aload_2
        //   24: ifnull +54 -> 78
        //   27: aload_2
        //   28: invokeinterface 106 1 0
        //   33: astore_1
        //   34: aload 4
        //   36: aload_1
        //   37: invokevirtual 102	android/os/Parcel:writeStrongBinder	(Landroid/os/IBinder;)V
        //   40: aload 4
        //   42: aload_3
        //   43: invokevirtual 66	android/os/Parcel:writeString	(Ljava/lang/String;)V
        //   46: aload_0
        //   47: getfield 17	com/google/android/gms/location/internal/i$a$a:a	Landroid/os/IBinder;
        //   50: iconst_3
        //   51: aload 4
        //   53: aload 5
        //   55: iconst_0
        //   56: invokeinterface 39 5 0
        //   61: pop
        //   62: aload 5
        //   64: invokevirtual 42	android/os/Parcel:readException	()V
        //   67: aload 5
        //   69: invokevirtual 61	android/os/Parcel:recycle	()V
        //   72: aload 4
        //   74: invokevirtual 61	android/os/Parcel:recycle	()V
        //   77: return
        //   78: aconst_null
        //   79: astore_1
        //   80: goto -46 -> 34
        //   83: astore_1
        //   84: aload 5
        //   86: invokevirtual 61	android/os/Parcel:recycle	()V
        //   89: aload 4
        //   91: invokevirtual 61	android/os/Parcel:recycle	()V
        //   94: aload_1
        //   95: athrow
        // Local variable table:
        //   start	length	slot	name	signature
        //   0	96	0	this	a
        //   0	96	1	paramArrayOfString	String[]
        //   0	96	2	paramh	h
        //   0	96	3	paramString	String
        //   3	87	4	localParcel1	Parcel
        //   8	77	5	localParcel2	Parcel
        // Exception table:
        //   from	to	target	type
        //   10	23	83	finally
        //   27	34	83	finally
        //   34	67	83	finally
      }
      
      public IBinder asBinder()
      {
        return a;
      }
      
      /* Error */
      public Location b(String paramString)
        throws RemoteException
      {
        // Byte code:
        //   0: invokestatic 27	android/os/Parcel:obtain	()Landroid/os/Parcel;
        //   3: astore_2
        //   4: invokestatic 27	android/os/Parcel:obtain	()Landroid/os/Parcel;
        //   7: astore_3
        //   8: aload_2
        //   9: ldc 29
        //   11: invokevirtual 33	android/os/Parcel:writeInterfaceToken	(Ljava/lang/String;)V
        //   14: aload_2
        //   15: aload_1
        //   16: invokevirtual 66	android/os/Parcel:writeString	(Ljava/lang/String;)V
        //   19: aload_0
        //   20: getfield 17	com/google/android/gms/location/internal/i$a$a:a	Landroid/os/IBinder;
        //   23: bipush 21
        //   25: aload_2
        //   26: aload_3
        //   27: iconst_0
        //   28: invokeinterface 39 5 0
        //   33: pop
        //   34: aload_3
        //   35: invokevirtual 42	android/os/Parcel:readException	()V
        //   38: aload_3
        //   39: invokevirtual 46	android/os/Parcel:readInt	()I
        //   42: ifeq +26 -> 68
        //   45: getstatic 52	android/location/Location:CREATOR	Landroid/os/Parcelable$Creator;
        //   48: aload_3
        //   49: invokeinterface 58 2 0
        //   54: checkcast 48	android/location/Location
        //   57: astore_1
        //   58: aload_3
        //   59: invokevirtual 61	android/os/Parcel:recycle	()V
        //   62: aload_2
        //   63: invokevirtual 61	android/os/Parcel:recycle	()V
        //   66: aload_1
        //   67: areturn
        //   68: aconst_null
        //   69: astore_1
        //   70: goto -12 -> 58
        //   73: astore_1
        //   74: aload_3
        //   75: invokevirtual 61	android/os/Parcel:recycle	()V
        //   78: aload_2
        //   79: invokevirtual 61	android/os/Parcel:recycle	()V
        //   82: aload_1
        //   83: athrow
        // Local variable table:
        //   start	length	slot	name	signature
        //   0	84	0	this	a
        //   0	84	1	paramString	String
        //   3	76	2	localParcel1	Parcel
        //   7	68	3	localParcel2	Parcel
        // Exception table:
        //   from	to	target	type
        //   8	58	73	finally
      }
      
      /* Error */
      public void b(PendingIntent paramPendingIntent)
        throws RemoteException
      {
        // Byte code:
        //   0: invokestatic 27	android/os/Parcel:obtain	()Landroid/os/Parcel;
        //   3: astore_2
        //   4: invokestatic 27	android/os/Parcel:obtain	()Landroid/os/Parcel;
        //   7: astore_3
        //   8: aload_2
        //   9: ldc 29
        //   11: invokevirtual 33	android/os/Parcel:writeInterfaceToken	(Ljava/lang/String;)V
        //   14: aload_1
        //   15: ifnull +42 -> 57
        //   18: aload_2
        //   19: iconst_1
        //   20: invokevirtual 85	android/os/Parcel:writeInt	(I)V
        //   23: aload_1
        //   24: aload_2
        //   25: iconst_0
        //   26: invokevirtual 91	android/app/PendingIntent:writeToParcel	(Landroid/os/Parcel;I)V
        //   29: aload_0
        //   30: getfield 17	com/google/android/gms/location/internal/i$a$a:a	Landroid/os/IBinder;
        //   33: bipush 11
        //   35: aload_2
        //   36: aload_3
        //   37: iconst_0
        //   38: invokeinterface 39 5 0
        //   43: pop
        //   44: aload_3
        //   45: invokevirtual 42	android/os/Parcel:readException	()V
        //   48: aload_3
        //   49: invokevirtual 61	android/os/Parcel:recycle	()V
        //   52: aload_2
        //   53: invokevirtual 61	android/os/Parcel:recycle	()V
        //   56: return
        //   57: aload_2
        //   58: iconst_0
        //   59: invokevirtual 85	android/os/Parcel:writeInt	(I)V
        //   62: goto -33 -> 29
        //   65: astore_1
        //   66: aload_3
        //   67: invokevirtual 61	android/os/Parcel:recycle	()V
        //   70: aload_2
        //   71: invokevirtual 61	android/os/Parcel:recycle	()V
        //   74: aload_1
        //   75: athrow
        // Local variable table:
        //   start	length	slot	name	signature
        //   0	76	0	this	a
        //   0	76	1	paramPendingIntent	PendingIntent
        //   3	68	2	localParcel1	Parcel
        //   7	60	3	localParcel2	Parcel
        // Exception table:
        //   from	to	target	type
        //   8	14	65	finally
        //   18	29	65	finally
        //   29	48	65	finally
        //   57	62	65	finally
      }
      
      public void b(PendingIntent paramPendingIntent, zzo paramzzo)
        throws RemoteException
      {
        Parcel localParcel1 = Parcel.obtain();
        Parcel localParcel2 = Parcel.obtain();
        for (;;)
        {
          try
          {
            localParcel1.writeInterfaceToken("com.google.android.gms.location.internal.IGoogleLocationManagerService");
            if (paramPendingIntent != null)
            {
              localParcel1.writeInt(1);
              paramPendingIntent.writeToParcel(localParcel1, 0);
              if (paramzzo != null)
              {
                paramPendingIntent = paramzzo.asBinder();
                localParcel1.writeStrongBinder(paramPendingIntent);
                a.transact(66, localParcel1, localParcel2, 0);
                localParcel2.readException();
              }
            }
            else
            {
              localParcel1.writeInt(0);
              continue;
            }
            paramPendingIntent = null;
          }
          finally
          {
            localParcel2.recycle();
            localParcel1.recycle();
          }
        }
      }
      
      /* Error */
      public LocationAvailability c(String paramString)
        throws RemoteException
      {
        // Byte code:
        //   0: invokestatic 27	android/os/Parcel:obtain	()Landroid/os/Parcel;
        //   3: astore_2
        //   4: invokestatic 27	android/os/Parcel:obtain	()Landroid/os/Parcel;
        //   7: astore_3
        //   8: aload_2
        //   9: ldc 29
        //   11: invokevirtual 33	android/os/Parcel:writeInterfaceToken	(Ljava/lang/String;)V
        //   14: aload_2
        //   15: aload_1
        //   16: invokevirtual 66	android/os/Parcel:writeString	(Ljava/lang/String;)V
        //   19: aload_0
        //   20: getfield 17	com/google/android/gms/location/internal/i$a$a:a	Landroid/os/IBinder;
        //   23: bipush 34
        //   25: aload_2
        //   26: aload_3
        //   27: iconst_0
        //   28: invokeinterface 39 5 0
        //   33: pop
        //   34: aload_3
        //   35: invokevirtual 42	android/os/Parcel:readException	()V
        //   38: aload_3
        //   39: invokevirtual 46	android/os/Parcel:readInt	()I
        //   42: ifeq +21 -> 63
        //   45: getstatic 170	com/google/android/gms/location/LocationAvailability:CREATOR	Lcom/google/android/gms/location/i;
        //   48: aload_3
        //   49: invokevirtual 175	com/google/android/gms/location/i:a	(Landroid/os/Parcel;)Lcom/google/android/gms/location/LocationAvailability;
        //   52: astore_1
        //   53: aload_3
        //   54: invokevirtual 61	android/os/Parcel:recycle	()V
        //   57: aload_2
        //   58: invokevirtual 61	android/os/Parcel:recycle	()V
        //   61: aload_1
        //   62: areturn
        //   63: aconst_null
        //   64: astore_1
        //   65: goto -12 -> 53
        //   68: astore_1
        //   69: aload_3
        //   70: invokevirtual 61	android/os/Parcel:recycle	()V
        //   73: aload_2
        //   74: invokevirtual 61	android/os/Parcel:recycle	()V
        //   77: aload_1
        //   78: athrow
        // Local variable table:
        //   start	length	slot	name	signature
        //   0	79	0	this	a
        //   0	79	1	paramString	String
        //   3	71	2	localParcel1	Parcel
        //   7	63	3	localParcel2	Parcel
        // Exception table:
        //   from	to	target	type
        //   8	53	68	finally
      }
      
      public void c(PendingIntent paramPendingIntent, zzo paramzzo)
        throws RemoteException
      {
        Parcel localParcel1 = Parcel.obtain();
        Parcel localParcel2 = Parcel.obtain();
        for (;;)
        {
          try
          {
            localParcel1.writeInterfaceToken("com.google.android.gms.location.internal.IGoogleLocationManagerService");
            if (paramPendingIntent != null)
            {
              localParcel1.writeInt(1);
              paramPendingIntent.writeToParcel(localParcel1, 0);
              if (paramzzo != null)
              {
                paramPendingIntent = paramzzo.asBinder();
                localParcel1.writeStrongBinder(paramPendingIntent);
                a.transact(61, localParcel1, localParcel2, 0);
                localParcel2.readException();
              }
            }
            else
            {
              localParcel1.writeInt(0);
              continue;
            }
            paramPendingIntent = null;
          }
          finally
          {
            localParcel2.recycle();
            localParcel1.recycle();
          }
        }
      }
      
      public void d(PendingIntent paramPendingIntent, zzo paramzzo)
        throws RemoteException
      {
        Parcel localParcel1 = Parcel.obtain();
        Parcel localParcel2 = Parcel.obtain();
        for (;;)
        {
          try
          {
            localParcel1.writeInterfaceToken("com.google.android.gms.location.internal.IGoogleLocationManagerService");
            if (paramPendingIntent != null)
            {
              localParcel1.writeInt(1);
              paramPendingIntent.writeToParcel(localParcel1, 0);
              if (paramzzo != null)
              {
                paramPendingIntent = paramzzo.asBinder();
                localParcel1.writeStrongBinder(paramPendingIntent);
                a.transact(68, localParcel1, localParcel2, 0);
                localParcel2.readException();
              }
            }
            else
            {
              localParcel1.writeInt(0);
              continue;
            }
            paramPendingIntent = null;
          }
          finally
          {
            localParcel2.recycle();
            localParcel1.recycle();
          }
        }
      }
      
      public void e(PendingIntent paramPendingIntent, zzo paramzzo)
        throws RemoteException
      {
        Parcel localParcel1 = Parcel.obtain();
        Parcel localParcel2 = Parcel.obtain();
        for (;;)
        {
          try
          {
            localParcel1.writeInterfaceToken("com.google.android.gms.location.internal.IGoogleLocationManagerService");
            if (paramPendingIntent != null)
            {
              localParcel1.writeInt(1);
              paramPendingIntent.writeToParcel(localParcel1, 0);
              if (paramzzo != null)
              {
                paramPendingIntent = paramzzo.asBinder();
                localParcel1.writeStrongBinder(paramPendingIntent);
                a.transact(69, localParcel1, localParcel2, 0);
                localParcel2.readException();
              }
            }
            else
            {
              localParcel1.writeInt(0);
              continue;
            }
            paramPendingIntent = null;
          }
          finally
          {
            localParcel2.recycle();
            localParcel1.recycle();
          }
        }
      }
    }
  }
}

/* Location:
 * Qualified Name:     com.google.android.gms.location.internal.i
 * Java Class Version: 6 (50.0)
 * JD-Core Version:    0.7.1
 */