package com.kahuna.sdk;

import android.content.Context;

final class i
  implements Runnable
{
  i(Context paramContext) {}
  
  /* Error */
  public void run()
  {
    // Byte code:
    //   0: invokestatic 24	com/kahuna/sdk/h:a	()Lcom/kahuna/sdk/h;
    //   3: astore_1
    //   4: aload_1
    //   5: invokestatic 27	com/kahuna/sdk/h:a	(Lcom/kahuna/sdk/h;)Landroid/content/Context;
    //   8: invokestatic 31	com/kahuna/sdk/ai:a	(Landroid/content/Context;)V
    //   11: aload_1
    //   12: invokestatic 35	com/kahuna/sdk/h:b	(Lcom/kahuna/sdk/h;)Z
    //   15: ifne +7 -> 22
    //   18: aload_1
    //   19: invokestatic 39	com/kahuna/sdk/h:c	(Lcom/kahuna/sdk/h;)V
    //   22: aload_1
    //   23: invokestatic 27	com/kahuna/sdk/h:a	(Lcom/kahuna/sdk/h;)Landroid/content/Context;
    //   26: invokestatic 42	com/kahuna/sdk/aa:a	(Landroid/content/Context;)V
    //   29: aload_0
    //   30: getfield 12	com/kahuna/sdk/i:a	Landroid/content/Context;
    //   33: invokestatic 45	com/kahuna/sdk/f:a	(Landroid/content/Context;)V
    //   36: aload_0
    //   37: getfield 12	com/kahuna/sdk/i:a	Landroid/content/Context;
    //   40: invokestatic 48	com/kahuna/sdk/ak:a	(Landroid/content/Context;)V
    //   43: aload_1
    //   44: aload_1
    //   45: invokestatic 27	com/kahuna/sdk/h:a	(Lcom/kahuna/sdk/h;)Landroid/content/Context;
    //   48: invokestatic 53	com/kahuna/sdk/location/m:a	(Lcom/kahuna/sdk/h;Landroid/content/Context;)V
    //   51: aload_1
    //   52: invokestatic 27	com/kahuna/sdk/h:a	(Lcom/kahuna/sdk/h;)Landroid/content/Context;
    //   55: iconst_0
    //   56: invokestatic 58	com/kahuna/sdk/ag:a	(Landroid/content/Context;Z)Lcom/kahuna/sdk/a;
    //   59: astore_2
    //   60: aload_1
    //   61: invokestatic 62	com/kahuna/sdk/h:d	(Lcom/kahuna/sdk/h;)Ljava/lang/Object;
    //   64: astore_3
    //   65: aload_3
    //   66: monitorenter
    //   67: aload_1
    //   68: aload_2
    //   69: invokevirtual 67	com/kahuna/sdk/a:a	()Ljava/util/List;
    //   72: invokestatic 70	com/kahuna/sdk/h:a	(Lcom/kahuna/sdk/h;Ljava/util/List;)Ljava/util/List;
    //   75: pop
    //   76: aload_3
    //   77: monitorexit
    //   78: aload_1
    //   79: invokestatic 74	com/kahuna/sdk/h:e	(Lcom/kahuna/sdk/h;)Ljava/util/List;
    //   82: invokestatic 79	com/kahuna/sdk/b:a	(Ljava/util/List;)V
    //   85: aload_1
    //   86: invokestatic 82	com/kahuna/sdk/h:f	(Lcom/kahuna/sdk/h;)Ljava/lang/Object;
    //   89: astore_3
    //   90: aload_3
    //   91: monitorenter
    //   92: aload_1
    //   93: invokestatic 86	com/kahuna/sdk/h:g	(Lcom/kahuna/sdk/h;)Ljava/util/Set;
    //   96: aload_1
    //   97: invokestatic 27	com/kahuna/sdk/h:a	(Lcom/kahuna/sdk/h;)Landroid/content/Context;
    //   100: invokestatic 89	com/kahuna/sdk/ag:g	(Landroid/content/Context;)Ljava/util/Set;
    //   103: invokeinterface 95 2 0
    //   108: pop
    //   109: aload_3
    //   110: monitorexit
    //   111: aload_1
    //   112: aload_2
    //   113: invokevirtual 98	com/kahuna/sdk/a:b	()Ljava/lang/String;
    //   116: invokestatic 101	com/kahuna/sdk/h:a	(Lcom/kahuna/sdk/h;Ljava/lang/String;)Ljava/lang/String;
    //   119: pop
    //   120: aload_1
    //   121: aload_2
    //   122: invokevirtual 104	com/kahuna/sdk/a:c	()Lorg/json/JSONArray;
    //   125: invokestatic 107	com/kahuna/sdk/h:a	(Lcom/kahuna/sdk/h;Lorg/json/JSONArray;)Lorg/json/JSONArray;
    //   128: pop
    //   129: return
    //   130: astore_2
    //   131: getstatic 110	com/kahuna/sdk/h:a	Z
    //   134: ifeq -83 -> 51
    //   137: ldc 112
    //   139: ldc 114
    //   141: invokestatic 120	android/util/Log:w	(Ljava/lang/String;Ljava/lang/String;)I
    //   144: pop
    //   145: ldc 112
    //   147: aload_2
    //   148: invokestatic 123	android/util/Log:w	(Ljava/lang/String;Ljava/lang/Throwable;)I
    //   151: pop
    //   152: goto -101 -> 51
    //   155: astore_1
    //   156: aload_3
    //   157: monitorexit
    //   158: aload_1
    //   159: athrow
    //   160: astore_1
    //   161: aload_3
    //   162: monitorexit
    //   163: aload_1
    //   164: athrow
    // Local variable table:
    //   start	length	slot	name	signature
    //   0	165	0	this	i
    //   3	118	1	localh	h
    //   155	4	1	localObject1	Object
    //   160	4	1	localObject2	Object
    //   59	63	2	locala	a
    //   130	18	2	localThrowable	Throwable
    // Exception table:
    //   from	to	target	type
    //   43	51	130	java/lang/Throwable
    //   67	78	155	finally
    //   156	158	155	finally
    //   92	111	160	finally
    //   161	163	160	finally
  }
}

/* Location:
 * Qualified Name:     com.kahuna.sdk.i
 * Java Class Version: 6 (50.0)
 * JD-Core Version:    0.7.1
 */