package com.kahuna.sdk;

import java.util.TimerTask;

class v
  extends TimerTask
{
  private v(h paramh) {}
  
  /* Error */
  public void run()
  {
    // Byte code:
    //   0: aconst_null
    //   1: astore 4
    //   3: aload_0
    //   4: getfield 10	com/kahuna/sdk/v:a	Lcom/kahuna/sdk/h;
    //   7: invokestatic 28	com/kahuna/sdk/h:t	(Lcom/kahuna/sdk/h;)Ljava/lang/Object;
    //   10: astore_3
    //   11: aload_3
    //   12: monitorenter
    //   13: aload_0
    //   14: getfield 10	com/kahuna/sdk/v:a	Lcom/kahuna/sdk/h;
    //   17: iconst_1
    //   18: invokestatic 32	com/kahuna/sdk/h:b	(Lcom/kahuna/sdk/h;Z)Z
    //   21: pop
    //   22: aload_3
    //   23: monitorexit
    //   24: new 34	com/yelp/android/ao/i
    //   27: dup
    //   28: invokespecial 35	com/yelp/android/ao/i:<init>	()V
    //   31: astore 5
    //   33: aload 5
    //   35: ldc 37
    //   37: aload_0
    //   38: getfield 10	com/kahuna/sdk/v:a	Lcom/kahuna/sdk/h;
    //   41: invokestatic 41	com/kahuna/sdk/h:i	(Lcom/kahuna/sdk/h;)Ljava/lang/String;
    //   44: invokevirtual 44	com/yelp/android/ao/i:a	(Ljava/lang/String;Ljava/lang/String;)V
    //   47: aload 5
    //   49: ldc 46
    //   51: aload_0
    //   52: getfield 10	com/kahuna/sdk/v:a	Lcom/kahuna/sdk/h;
    //   55: invokestatic 49	com/kahuna/sdk/h:j	(Lcom/kahuna/sdk/h;)Ljava/lang/String;
    //   58: invokevirtual 44	com/yelp/android/ao/i:a	(Ljava/lang/String;Ljava/lang/String;)V
    //   61: aload 5
    //   63: ldc 51
    //   65: aload_0
    //   66: getfield 10	com/kahuna/sdk/v:a	Lcom/kahuna/sdk/h;
    //   69: invokestatic 54	com/kahuna/sdk/h:u	(Lcom/kahuna/sdk/h;)Ljava/lang/String;
    //   72: invokevirtual 44	com/yelp/android/ao/i:a	(Ljava/lang/String;Ljava/lang/String;)V
    //   75: aload 5
    //   77: ldc 56
    //   79: aload_0
    //   80: getfield 10	com/kahuna/sdk/v:a	Lcom/kahuna/sdk/h;
    //   83: invokestatic 59	com/kahuna/sdk/h:v	(Lcom/kahuna/sdk/h;)Ljava/lang/String;
    //   86: invokevirtual 44	com/yelp/android/ao/i:a	(Ljava/lang/String;Ljava/lang/String;)V
    //   89: aload 5
    //   91: ldc 61
    //   93: aload_0
    //   94: getfield 10	com/kahuna/sdk/v:a	Lcom/kahuna/sdk/h;
    //   97: invokestatic 64	com/kahuna/sdk/h:w	(Lcom/kahuna/sdk/h;)Ljava/lang/String;
    //   100: invokevirtual 44	com/yelp/android/ao/i:a	(Ljava/lang/String;Ljava/lang/String;)V
    //   103: aload 5
    //   105: ldc 66
    //   107: aload_0
    //   108: getfield 10	com/kahuna/sdk/v:a	Lcom/kahuna/sdk/h;
    //   111: invokestatic 69	com/kahuna/sdk/h:x	(Lcom/kahuna/sdk/h;)Ljava/lang/String;
    //   114: invokevirtual 44	com/yelp/android/ao/i:a	(Ljava/lang/String;Ljava/lang/String;)V
    //   117: aload 5
    //   119: ldc 71
    //   121: aload_0
    //   122: getfield 10	com/kahuna/sdk/v:a	Lcom/kahuna/sdk/h;
    //   125: invokestatic 74	com/kahuna/sdk/h:y	(Lcom/kahuna/sdk/h;)Ljava/lang/String;
    //   128: invokevirtual 44	com/yelp/android/ao/i:a	(Ljava/lang/String;Ljava/lang/String;)V
    //   131: aload 5
    //   133: ldc 76
    //   135: new 78	java/lang/StringBuilder
    //   138: dup
    //   139: invokespecial 79	java/lang/StringBuilder:<init>	()V
    //   142: ldc 81
    //   144: invokevirtual 85	java/lang/StringBuilder:append	(Ljava/lang/String;)Ljava/lang/StringBuilder;
    //   147: invokestatic 91	java/lang/System:currentTimeMillis	()J
    //   150: ldc2_w 92
    //   153: ldiv
    //   154: invokevirtual 96	java/lang/StringBuilder:append	(J)Ljava/lang/StringBuilder;
    //   157: invokevirtual 100	java/lang/StringBuilder:toString	()Ljava/lang/String;
    //   160: invokevirtual 44	com/yelp/android/ao/i:a	(Ljava/lang/String;Ljava/lang/String;)V
    //   163: aload 5
    //   165: ldc 102
    //   167: ldc 104
    //   169: invokevirtual 44	com/yelp/android/ao/i:a	(Ljava/lang/String;Ljava/lang/String;)V
    //   172: aload_0
    //   173: getfield 10	com/kahuna/sdk/v:a	Lcom/kahuna/sdk/h;
    //   176: invokestatic 107	com/kahuna/sdk/h:z	(Lcom/kahuna/sdk/h;)Ljava/lang/String;
    //   179: invokestatic 112	com/kahuna/sdk/aj:a	(Ljava/lang/String;)Z
    //   182: ifne +17 -> 199
    //   185: aload 5
    //   187: ldc 114
    //   189: aload_0
    //   190: getfield 10	com/kahuna/sdk/v:a	Lcom/kahuna/sdk/h;
    //   193: invokestatic 107	com/kahuna/sdk/h:z	(Lcom/kahuna/sdk/h;)Ljava/lang/String;
    //   196: invokevirtual 44	com/yelp/android/ao/i:a	(Ljava/lang/String;Ljava/lang/String;)V
    //   199: aload_0
    //   200: getfield 10	com/kahuna/sdk/v:a	Lcom/kahuna/sdk/h;
    //   203: invokestatic 117	com/kahuna/sdk/h:A	(Lcom/kahuna/sdk/h;)Ljava/lang/String;
    //   206: invokestatic 112	com/kahuna/sdk/aj:a	(Ljava/lang/String;)Z
    //   209: ifne +35 -> 244
    //   212: aload_0
    //   213: getfield 10	com/kahuna/sdk/v:a	Lcom/kahuna/sdk/h;
    //   216: invokestatic 120	com/kahuna/sdk/h:B	(Lcom/kahuna/sdk/h;)Ljava/lang/String;
    //   219: invokestatic 112	com/kahuna/sdk/aj:a	(Ljava/lang/String;)Z
    //   222: ifne +22 -> 244
    //   225: aload 5
    //   227: aload_0
    //   228: getfield 10	com/kahuna/sdk/v:a	Lcom/kahuna/sdk/h;
    //   231: invokestatic 117	com/kahuna/sdk/h:A	(Lcom/kahuna/sdk/h;)Ljava/lang/String;
    //   234: aload_0
    //   235: getfield 10	com/kahuna/sdk/v:a	Lcom/kahuna/sdk/h;
    //   238: invokestatic 120	com/kahuna/sdk/h:B	(Lcom/kahuna/sdk/h;)Ljava/lang/String;
    //   241: invokevirtual 44	com/yelp/android/ao/i:a	(Ljava/lang/String;Ljava/lang/String;)V
    //   244: aload_0
    //   245: getfield 10	com/kahuna/sdk/v:a	Lcom/kahuna/sdk/h;
    //   248: invokestatic 124	com/kahuna/sdk/h:k	(Lcom/kahuna/sdk/h;)Z
    //   251: ifeq +405 -> 656
    //   254: ldc 126
    //   256: astore_3
    //   257: aload 5
    //   259: ldc -128
    //   261: aload_3
    //   262: invokevirtual 44	com/yelp/android/ao/i:a	(Ljava/lang/String;Ljava/lang/String;)V
    //   265: aload 5
    //   267: ldc -126
    //   269: new 78	java/lang/StringBuilder
    //   272: dup
    //   273: invokespecial 79	java/lang/StringBuilder:<init>	()V
    //   276: ldc 81
    //   278: invokevirtual 85	java/lang/StringBuilder:append	(Ljava/lang/String;)Ljava/lang/StringBuilder;
    //   281: aload_0
    //   282: getfield 10	com/kahuna/sdk/v:a	Lcom/kahuna/sdk/h;
    //   285: invokestatic 134	com/kahuna/sdk/h:C	(Lcom/kahuna/sdk/h;)Lcom/kahuna/sdk/ah;
    //   288: invokevirtual 138	com/kahuna/sdk/ah:a	()J
    //   291: invokevirtual 96	java/lang/StringBuilder:append	(J)Ljava/lang/StringBuilder;
    //   294: invokevirtual 100	java/lang/StringBuilder:toString	()Ljava/lang/String;
    //   297: invokevirtual 44	com/yelp/android/ao/i:a	(Ljava/lang/String;Ljava/lang/String;)V
    //   300: new 140	org/json/JSONArray
    //   303: dup
    //   304: invokespecial 141	org/json/JSONArray:<init>	()V
    //   307: astore_3
    //   308: invokestatic 145	com/kahuna/sdk/h:r	()Z
    //   311: ifeq +10 -> 321
    //   314: aload_3
    //   315: ldc -109
    //   317: invokevirtual 151	org/json/JSONArray:put	(Ljava/lang/Object;)Lorg/json/JSONArray;
    //   320: pop
    //   321: invokestatic 153	com/kahuna/sdk/h:s	()Z
    //   324: ifeq +351 -> 675
    //   327: invokestatic 157	com/kahuna/sdk/location/m:a	()Z
    //   330: ifeq +345 -> 675
    //   333: aload_3
    //   334: ldc -97
    //   336: invokevirtual 151	org/json/JSONArray:put	(Ljava/lang/Object;)Lorg/json/JSONArray;
    //   339: pop
    //   340: aload_0
    //   341: getfield 10	com/kahuna/sdk/v:a	Lcom/kahuna/sdk/h;
    //   344: invokestatic 162	com/kahuna/sdk/location/m:a	(Lcom/kahuna/sdk/h;)Ljava/util/Set;
    //   347: astore 7
    //   349: aload 7
    //   351: invokeinterface 168 1 0
    //   356: ifle +319 -> 675
    //   359: new 140	org/json/JSONArray
    //   362: dup
    //   363: invokespecial 141	org/json/JSONArray:<init>	()V
    //   366: astore 6
    //   368: aload 7
    //   370: invokeinterface 172 1 0
    //   375: astore 7
    //   377: aload 7
    //   379: invokeinterface 177 1 0
    //   384: ifeq +279 -> 663
    //   387: aload 6
    //   389: aload 7
    //   391: invokeinterface 181 1 0
    //   396: checkcast 183	java/lang/String
    //   399: invokevirtual 151	org/json/JSONArray:put	(Ljava/lang/Object;)Lorg/json/JSONArray;
    //   402: pop
    //   403: goto -26 -> 377
    //   406: astore 6
    //   408: aload_3
    //   409: invokestatic 186	com/kahuna/sdk/aj:a	(Lorg/json/JSONArray;)Z
    //   412: ifne +14 -> 426
    //   415: aload 5
    //   417: ldc -68
    //   419: aload_3
    //   420: invokevirtual 189	org/json/JSONArray:toString	()Ljava/lang/String;
    //   423: invokevirtual 44	com/yelp/android/ao/i:a	(Ljava/lang/String;Ljava/lang/String;)V
    //   426: new 140	org/json/JSONArray
    //   429: dup
    //   430: invokespecial 141	org/json/JSONArray:<init>	()V
    //   433: astore 6
    //   435: aload_0
    //   436: getfield 10	com/kahuna/sdk/v:a	Lcom/kahuna/sdk/h;
    //   439: new 191	java/util/ArrayList
    //   442: dup
    //   443: invokespecial 192	java/util/ArrayList:<init>	()V
    //   446: invokestatic 195	com/kahuna/sdk/h:b	(Lcom/kahuna/sdk/h;Ljava/util/List;)Ljava/util/List;
    //   449: pop
    //   450: aload_0
    //   451: getfield 10	com/kahuna/sdk/v:a	Lcom/kahuna/sdk/h;
    //   454: invokestatic 198	com/kahuna/sdk/h:f	(Lcom/kahuna/sdk/h;)Ljava/lang/Object;
    //   457: astore 7
    //   459: aload 7
    //   461: monitorenter
    //   462: aload 4
    //   464: astore_3
    //   465: aload_0
    //   466: getfield 10	com/kahuna/sdk/v:a	Lcom/kahuna/sdk/h;
    //   469: invokestatic 201	com/kahuna/sdk/h:g	(Lcom/kahuna/sdk/h;)Ljava/util/Set;
    //   472: invokeinterface 204 1 0
    //   477: ifne +345 -> 822
    //   480: invokestatic 207	com/kahuna/sdk/h:a	()Lcom/kahuna/sdk/h;
    //   483: invokestatic 210	com/kahuna/sdk/h:s	(Lcom/kahuna/sdk/h;)Ljava/util/Map;
    //   486: astore 4
    //   488: new 212	java/util/HashMap
    //   491: dup
    //   492: invokespecial 213	java/util/HashMap:<init>	()V
    //   495: astore_3
    //   496: aload_0
    //   497: getfield 10	com/kahuna/sdk/v:a	Lcom/kahuna/sdk/h;
    //   500: invokestatic 201	com/kahuna/sdk/h:g	(Lcom/kahuna/sdk/h;)Ljava/util/Set;
    //   503: invokeinterface 172 1 0
    //   508: astore 8
    //   510: aload 8
    //   512: invokeinterface 177 1 0
    //   517: ifeq +276 -> 793
    //   520: aload 8
    //   522: invokeinterface 181 1 0
    //   527: checkcast 183	java/lang/String
    //   530: astore 9
    //   532: aload 4
    //   534: aload 9
    //   536: invokeinterface 219 2 0
    //   541: ifeq -31 -> 510
    //   544: aload_3
    //   545: aload 9
    //   547: aload 4
    //   549: aload 9
    //   551: invokeinterface 223 2 0
    //   556: invokeinterface 226 3 0
    //   561: pop
    //   562: goto -52 -> 510
    //   565: astore_3
    //   566: aload 7
    //   568: monitorexit
    //   569: aload_3
    //   570: athrow
    //   571: astore_3
    //   572: getstatic 229	com/kahuna/sdk/h:a	Z
    //   575: ifeq +32 -> 607
    //   578: ldc -25
    //   580: new 78	java/lang/StringBuilder
    //   583: dup
    //   584: invokespecial 79	java/lang/StringBuilder:<init>	()V
    //   587: ldc -23
    //   589: invokevirtual 85	java/lang/StringBuilder:append	(Ljava/lang/String;)Ljava/lang/StringBuilder;
    //   592: aload_3
    //   593: invokevirtual 236	java/lang/StringBuilder:append	(Ljava/lang/Object;)Ljava/lang/StringBuilder;
    //   596: invokevirtual 100	java/lang/StringBuilder:toString	()Ljava/lang/String;
    //   599: invokestatic 242	android/util/Log:d	(Ljava/lang/String;Ljava/lang/String;)I
    //   602: pop
    //   603: aload_3
    //   604: invokevirtual 245	java/lang/Exception:printStackTrace	()V
    //   607: aload_0
    //   608: getfield 10	com/kahuna/sdk/v:a	Lcom/kahuna/sdk/h;
    //   611: invokestatic 248	com/kahuna/sdk/h:p	(Lcom/kahuna/sdk/h;)Ljava/lang/Object;
    //   614: astore_3
    //   615: aload_3
    //   616: monitorenter
    //   617: aload_0
    //   618: getfield 10	com/kahuna/sdk/v:a	Lcom/kahuna/sdk/h;
    //   621: invokestatic 252	com/kahuna/sdk/h:q	(Lcom/kahuna/sdk/h;)Lcom/kahuna/sdk/u;
    //   624: ifnull +22 -> 646
    //   627: aload_0
    //   628: getfield 10	com/kahuna/sdk/v:a	Lcom/kahuna/sdk/h;
    //   631: invokestatic 252	com/kahuna/sdk/h:q	(Lcom/kahuna/sdk/h;)Lcom/kahuna/sdk/u;
    //   634: invokevirtual 257	com/kahuna/sdk/u:cancel	()V
    //   637: aload_0
    //   638: getfield 10	com/kahuna/sdk/v:a	Lcom/kahuna/sdk/h;
    //   641: aconst_null
    //   642: invokestatic 260	com/kahuna/sdk/h:a	(Lcom/kahuna/sdk/h;Lcom/kahuna/sdk/u;)Lcom/kahuna/sdk/u;
    //   645: pop
    //   646: aload_3
    //   647: monitorexit
    //   648: return
    //   649: astore 4
    //   651: aload_3
    //   652: monitorexit
    //   653: aload 4
    //   655: athrow
    //   656: ldc_w 261
    //   659: astore_3
    //   660: goto -403 -> 257
    //   663: aload 5
    //   665: ldc -97
    //   667: aload 6
    //   669: invokevirtual 189	org/json/JSONArray:toString	()Ljava/lang/String;
    //   672: invokevirtual 44	com/yelp/android/ao/i:a	(Ljava/lang/String;Ljava/lang/String;)V
    //   675: getstatic 267	android/os/Build$VERSION:SDK_INT	I
    //   678: bipush 18
    //   680: if_icmplt -272 -> 408
    //   683: invokestatic 269	com/kahuna/sdk/h:t	()Z
    //   686: ifeq -278 -> 408
    //   689: invokestatic 272	com/kahuna/sdk/location/c:a	()Z
    //   692: ifeq -284 -> 408
    //   695: invokestatic 207	com/kahuna/sdk/h:a	()Lcom/kahuna/sdk/h;
    //   698: invokestatic 276	com/kahuna/sdk/location/KahunaIBeaconManager:a	(Lcom/kahuna/sdk/h;)Z
    //   701: ifeq -293 -> 408
    //   704: aload_3
    //   705: ldc_w 278
    //   708: invokevirtual 151	org/json/JSONArray:put	(Ljava/lang/Object;)Lorg/json/JSONArray;
    //   711: pop
    //   712: invokestatic 207	com/kahuna/sdk/h:a	()Lcom/kahuna/sdk/h;
    //   715: invokestatic 280	com/kahuna/sdk/location/KahunaIBeaconManager:d	(Lcom/kahuna/sdk/h;)Ljava/util/Set;
    //   718: astore 7
    //   720: aload 7
    //   722: invokeinterface 168 1 0
    //   727: ifle -319 -> 408
    //   730: new 140	org/json/JSONArray
    //   733: dup
    //   734: invokespecial 141	org/json/JSONArray:<init>	()V
    //   737: astore 6
    //   739: aload 7
    //   741: invokeinterface 172 1 0
    //   746: astore 7
    //   748: aload 7
    //   750: invokeinterface 177 1 0
    //   755: ifeq +22 -> 777
    //   758: aload 6
    //   760: aload 7
    //   762: invokeinterface 181 1 0
    //   767: checkcast 183	java/lang/String
    //   770: invokevirtual 151	org/json/JSONArray:put	(Ljava/lang/Object;)Lorg/json/JSONArray;
    //   773: pop
    //   774: goto -26 -> 748
    //   777: aload 5
    //   779: ldc_w 278
    //   782: aload 6
    //   784: invokevirtual 189	org/json/JSONArray:toString	()Ljava/lang/String;
    //   787: invokevirtual 44	com/yelp/android/ao/i:a	(Ljava/lang/String;Ljava/lang/String;)V
    //   790: goto -382 -> 408
    //   793: aload_0
    //   794: getfield 10	com/kahuna/sdk/v:a	Lcom/kahuna/sdk/h;
    //   797: invokestatic 201	com/kahuna/sdk/h:g	(Lcom/kahuna/sdk/h;)Ljava/util/Set;
    //   800: invokeinterface 283 1 0
    //   805: aload_0
    //   806: getfield 10	com/kahuna/sdk/v:a	Lcom/kahuna/sdk/h;
    //   809: invokestatic 201	com/kahuna/sdk/h:g	(Lcom/kahuna/sdk/h;)Ljava/util/Set;
    //   812: aload_0
    //   813: getfield 10	com/kahuna/sdk/v:a	Lcom/kahuna/sdk/h;
    //   816: invokestatic 286	com/kahuna/sdk/h:a	(Lcom/kahuna/sdk/h;)Landroid/content/Context;
    //   819: invokestatic 291	com/kahuna/sdk/ag:a	(Ljava/util/Set;Landroid/content/Context;)V
    //   822: aload 7
    //   824: monitorexit
    //   825: aload_0
    //   826: getfield 10	com/kahuna/sdk/v:a	Lcom/kahuna/sdk/h;
    //   829: invokestatic 293	com/kahuna/sdk/h:d	(Lcom/kahuna/sdk/h;)Ljava/lang/Object;
    //   832: astore 4
    //   834: aload 4
    //   836: monitorenter
    //   837: aload_3
    //   838: ifnull +39 -> 877
    //   841: new 295	com/kahuna/sdk/Event
    //   844: dup
    //   845: ldc_w 297
    //   848: invokestatic 91	java/lang/System:currentTimeMillis	()J
    //   851: ldc2_w 92
    //   854: ldiv
    //   855: aconst_null
    //   856: aload_3
    //   857: aconst_null
    //   858: aconst_null
    //   859: invokespecial 300	com/kahuna/sdk/Event:<init>	(Ljava/lang/String;JLjava/util/Map;Ljava/util/Map;Ljava/util/Map;Ljava/lang/String;)V
    //   862: astore_3
    //   863: aload_0
    //   864: getfield 10	com/kahuna/sdk/v:a	Lcom/kahuna/sdk/h;
    //   867: invokestatic 304	com/kahuna/sdk/h:e	(Lcom/kahuna/sdk/h;)Ljava/util/List;
    //   870: aload_3
    //   871: invokeinterface 309 2 0
    //   876: pop
    //   877: aload_0
    //   878: getfield 10	com/kahuna/sdk/v:a	Lcom/kahuna/sdk/h;
    //   881: invokestatic 313	com/kahuna/sdk/h:D	(Lcom/kahuna/sdk/h;)Ljava/util/concurrent/atomic/AtomicInteger;
    //   884: invokevirtual 317	java/util/concurrent/atomic/AtomicInteger:get	()I
    //   887: ifgt +25 -> 912
    //   890: aload_0
    //   891: getfield 10	com/kahuna/sdk/v:a	Lcom/kahuna/sdk/h;
    //   894: invokestatic 313	com/kahuna/sdk/h:D	(Lcom/kahuna/sdk/h;)Ljava/util/concurrent/atomic/AtomicInteger;
    //   897: aload_0
    //   898: getfield 10	com/kahuna/sdk/v:a	Lcom/kahuna/sdk/h;
    //   901: invokestatic 304	com/kahuna/sdk/h:e	(Lcom/kahuna/sdk/h;)Ljava/util/List;
    //   904: invokeinterface 318 1 0
    //   909: invokevirtual 322	java/util/concurrent/atomic/AtomicInteger:set	(I)V
    //   912: aload_0
    //   913: getfield 10	com/kahuna/sdk/v:a	Lcom/kahuna/sdk/h;
    //   916: invokestatic 134	com/kahuna/sdk/h:C	(Lcom/kahuna/sdk/h;)Lcom/kahuna/sdk/ah;
    //   919: invokevirtual 325	com/kahuna/sdk/ah:n	()I
    //   922: istore_1
    //   923: iload_1
    //   924: aload_0
    //   925: getfield 10	com/kahuna/sdk/v:a	Lcom/kahuna/sdk/h;
    //   928: invokestatic 304	com/kahuna/sdk/h:e	(Lcom/kahuna/sdk/h;)Ljava/util/List;
    //   931: invokeinterface 318 1 0
    //   936: if_icmpge +61 -> 997
    //   939: goto +707 -> 1646
    //   942: iload_2
    //   943: iload_1
    //   944: if_icmpge +69 -> 1013
    //   947: aload_0
    //   948: getfield 10	com/kahuna/sdk/v:a	Lcom/kahuna/sdk/h;
    //   951: invokestatic 304	com/kahuna/sdk/h:e	(Lcom/kahuna/sdk/h;)Ljava/util/List;
    //   954: iload_2
    //   955: invokeinterface 328 2 0
    //   960: checkcast 295	com/kahuna/sdk/Event
    //   963: astore_3
    //   964: aload_0
    //   965: getfield 10	com/kahuna/sdk/v:a	Lcom/kahuna/sdk/h;
    //   968: invokestatic 331	com/kahuna/sdk/h:E	(Lcom/kahuna/sdk/h;)Ljava/util/List;
    //   971: aload_3
    //   972: invokeinterface 309 2 0
    //   977: pop
    //   978: aload_3
    //   979: invokevirtual 335	com/kahuna/sdk/Event:h	()Lorg/json/JSONObject;
    //   982: astore_3
    //   983: aload_3
    //   984: ifnull +667 -> 1651
    //   987: aload 6
    //   989: aload_3
    //   990: invokevirtual 151	org/json/JSONArray:put	(Ljava/lang/Object;)Lorg/json/JSONArray;
    //   993: pop
    //   994: goto +657 -> 1651
    //   997: aload_0
    //   998: getfield 10	com/kahuna/sdk/v:a	Lcom/kahuna/sdk/h;
    //   1001: invokestatic 304	com/kahuna/sdk/h:e	(Lcom/kahuna/sdk/h;)Ljava/util/List;
    //   1004: invokeinterface 318 1 0
    //   1009: istore_1
    //   1010: goto +636 -> 1646
    //   1013: aload 4
    //   1015: monitorexit
    //   1016: invokestatic 339	com/kahuna/sdk/b:a	()V
    //   1019: aload_0
    //   1020: getfield 10	com/kahuna/sdk/v:a	Lcom/kahuna/sdk/h;
    //   1023: invokestatic 331	com/kahuna/sdk/h:E	(Lcom/kahuna/sdk/h;)Ljava/util/List;
    //   1026: invokeinterface 318 1 0
    //   1031: ifne +86 -> 1117
    //   1034: aload_0
    //   1035: getfield 10	com/kahuna/sdk/v:a	Lcom/kahuna/sdk/h;
    //   1038: invokestatic 28	com/kahuna/sdk/h:t	(Lcom/kahuna/sdk/h;)Ljava/lang/Object;
    //   1041: astore_3
    //   1042: aload_3
    //   1043: monitorenter
    //   1044: aload_0
    //   1045: getfield 10	com/kahuna/sdk/v:a	Lcom/kahuna/sdk/h;
    //   1048: iconst_0
    //   1049: invokestatic 32	com/kahuna/sdk/h:b	(Lcom/kahuna/sdk/h;Z)Z
    //   1052: pop
    //   1053: aload_3
    //   1054: monitorexit
    //   1055: aload_0
    //   1056: getfield 10	com/kahuna/sdk/v:a	Lcom/kahuna/sdk/h;
    //   1059: invokestatic 248	com/kahuna/sdk/h:p	(Lcom/kahuna/sdk/h;)Ljava/lang/Object;
    //   1062: astore_3
    //   1063: aload_3
    //   1064: monitorenter
    //   1065: aload_0
    //   1066: getfield 10	com/kahuna/sdk/v:a	Lcom/kahuna/sdk/h;
    //   1069: invokestatic 252	com/kahuna/sdk/h:q	(Lcom/kahuna/sdk/h;)Lcom/kahuna/sdk/u;
    //   1072: ifnull +22 -> 1094
    //   1075: aload_0
    //   1076: getfield 10	com/kahuna/sdk/v:a	Lcom/kahuna/sdk/h;
    //   1079: invokestatic 252	com/kahuna/sdk/h:q	(Lcom/kahuna/sdk/h;)Lcom/kahuna/sdk/u;
    //   1082: invokevirtual 257	com/kahuna/sdk/u:cancel	()V
    //   1085: aload_0
    //   1086: getfield 10	com/kahuna/sdk/v:a	Lcom/kahuna/sdk/h;
    //   1089: aconst_null
    //   1090: invokestatic 260	com/kahuna/sdk/h:a	(Lcom/kahuna/sdk/h;Lcom/kahuna/sdk/u;)Lcom/kahuna/sdk/u;
    //   1093: pop
    //   1094: aload_3
    //   1095: monitorexit
    //   1096: return
    //   1097: astore 4
    //   1099: aload_3
    //   1100: monitorexit
    //   1101: aload 4
    //   1103: athrow
    //   1104: astore_3
    //   1105: aload 4
    //   1107: monitorexit
    //   1108: aload_3
    //   1109: athrow
    //   1110: astore 4
    //   1112: aload_3
    //   1113: monitorexit
    //   1114: aload 4
    //   1116: athrow
    //   1117: aload 6
    //   1119: invokevirtual 189	org/json/JSONArray:toString	()Ljava/lang/String;
    //   1122: astore_3
    //   1123: aload 5
    //   1125: ldc_w 341
    //   1128: aload_3
    //   1129: ldc_w 343
    //   1132: iconst_0
    //   1133: invokestatic 346	com/kahuna/sdk/aj:a	(Ljava/lang/String;Ljava/lang/String;Z)Ljava/lang/String;
    //   1136: invokevirtual 44	com/yelp/android/ao/i:a	(Ljava/lang/String;Ljava/lang/String;)V
    //   1139: aload 5
    //   1141: ldc_w 348
    //   1144: aload_3
    //   1145: invokevirtual 44	com/yelp/android/ao/i:a	(Ljava/lang/String;Ljava/lang/String;)V
    //   1148: aload_0
    //   1149: getfield 10	com/kahuna/sdk/v:a	Lcom/kahuna/sdk/h;
    //   1152: invokestatic 351	com/kahuna/sdk/h:F	(Lcom/kahuna/sdk/h;)Ljava/lang/String;
    //   1155: invokestatic 112	com/kahuna/sdk/aj:a	(Ljava/lang/String;)Z
    //   1158: ifne +18 -> 1176
    //   1161: aload 5
    //   1163: ldc_w 353
    //   1166: aload_0
    //   1167: getfield 10	com/kahuna/sdk/v:a	Lcom/kahuna/sdk/h;
    //   1170: invokestatic 351	com/kahuna/sdk/h:F	(Lcom/kahuna/sdk/h;)Ljava/lang/String;
    //   1173: invokevirtual 44	com/yelp/android/ao/i:a	(Ljava/lang/String;Ljava/lang/String;)V
    //   1176: aload_0
    //   1177: getfield 10	com/kahuna/sdk/v:a	Lcom/kahuna/sdk/h;
    //   1180: invokestatic 357	com/kahuna/sdk/h:G	(Lcom/kahuna/sdk/h;)Lorg/json/JSONArray;
    //   1183: invokestatic 186	com/kahuna/sdk/aj:a	(Lorg/json/JSONArray;)Z
    //   1186: ifne +21 -> 1207
    //   1189: aload 5
    //   1191: ldc_w 359
    //   1194: aload_0
    //   1195: getfield 10	com/kahuna/sdk/v:a	Lcom/kahuna/sdk/h;
    //   1198: invokestatic 357	com/kahuna/sdk/h:G	(Lcom/kahuna/sdk/h;)Lorg/json/JSONArray;
    //   1201: invokevirtual 189	org/json/JSONArray:toString	()Ljava/lang/String;
    //   1204: invokevirtual 44	com/yelp/android/ao/i:a	(Ljava/lang/String;Ljava/lang/String;)V
    //   1207: aload 5
    //   1209: invokevirtual 362	com/yelp/android/ao/i:b	()Lorg/apache/http/HttpEntity;
    //   1212: ldc_w 364
    //   1215: invokestatic 369	org/apache/http/util/EntityUtils:toString	(Lorg/apache/http/HttpEntity;Ljava/lang/String;)Ljava/lang/String;
    //   1218: ldc_w 343
    //   1221: iconst_0
    //   1222: invokestatic 346	com/kahuna/sdk/aj:a	(Ljava/lang/String;Ljava/lang/String;Z)Ljava/lang/String;
    //   1225: astore_3
    //   1226: getstatic 229	com/kahuna/sdk/h:a	Z
    //   1229: ifeq +29 -> 1258
    //   1232: ldc -25
    //   1234: new 78	java/lang/StringBuilder
    //   1237: dup
    //   1238: invokespecial 79	java/lang/StringBuilder:<init>	()V
    //   1241: ldc_w 371
    //   1244: invokevirtual 85	java/lang/StringBuilder:append	(Ljava/lang/String;)Ljava/lang/StringBuilder;
    //   1247: aload_3
    //   1248: invokevirtual 85	java/lang/StringBuilder:append	(Ljava/lang/String;)Ljava/lang/StringBuilder;
    //   1251: invokevirtual 100	java/lang/StringBuilder:toString	()Ljava/lang/String;
    //   1254: invokestatic 242	android/util/Log:d	(Ljava/lang/String;Ljava/lang/String;)I
    //   1257: pop
    //   1258: new 373	org/apache/http/message/BasicHeader
    //   1261: dup
    //   1262: ldc_w 375
    //   1265: aload_3
    //   1266: invokespecial 377	org/apache/http/message/BasicHeader:<init>	(Ljava/lang/String;Ljava/lang/String;)V
    //   1269: astore_3
    //   1270: aload_0
    //   1271: getfield 10	com/kahuna/sdk/v:a	Lcom/kahuna/sdk/h;
    //   1274: invokestatic 381	com/kahuna/sdk/h:K	(Lcom/kahuna/sdk/h;)Lcom/yelp/android/ao/a;
    //   1277: astore 4
    //   1279: new 383	com/kahuna/sdk/w
    //   1282: dup
    //   1283: aload_0
    //   1284: invokespecial 386	com/kahuna/sdk/w:<init>	(Lcom/kahuna/sdk/v;)V
    //   1287: astore 6
    //   1289: aload 4
    //   1291: aconst_null
    //   1292: ldc_w 388
    //   1295: iconst_1
    //   1296: anewarray 390	org/apache/http/Header
    //   1299: dup
    //   1300: iconst_0
    //   1301: aload_3
    //   1302: aastore
    //   1303: aload 5
    //   1305: ldc_w 392
    //   1308: aload 6
    //   1310: invokevirtual 397	com/yelp/android/ao/a:a	(Landroid/content/Context;Ljava/lang/String;[Lorg/apache/http/Header;Lcom/yelp/android/ao/i;Ljava/lang/String;Lcom/yelp/android/ao/f;)V
    //   1313: getstatic 229	com/kahuna/sdk/h:a	Z
    //   1316: ifeq -668 -> 648
    //   1319: aload_0
    //   1320: getfield 10	com/kahuna/sdk/v:a	Lcom/kahuna/sdk/h;
    //   1323: invokestatic 286	com/kahuna/sdk/h:a	(Lcom/kahuna/sdk/h;)Landroid/content/Context;
    //   1326: invokestatic 402	com/kahuna/sdk/aa:b	(Landroid/content/Context;)Z
    //   1329: ifeq +282 -> 1611
    //   1332: ldc -25
    //   1334: ldc_w 404
    //   1337: invokestatic 242	android/util/Log:d	(Ljava/lang/String;Ljava/lang/String;)I
    //   1340: pop
    //   1341: aload 5
    //   1343: invokevirtual 407	com/yelp/android/ao/i:a	()Ljava/util/Map;
    //   1346: astore_3
    //   1347: new 78	java/lang/StringBuilder
    //   1350: dup
    //   1351: invokespecial 79	java/lang/StringBuilder:<init>	()V
    //   1354: astore 4
    //   1356: aload_3
    //   1357: invokeinterface 411 1 0
    //   1362: invokeinterface 172 1 0
    //   1367: astore 5
    //   1369: aload 5
    //   1371: invokeinterface 177 1 0
    //   1376: ifeq +204 -> 1580
    //   1379: aload 5
    //   1381: invokeinterface 181 1 0
    //   1386: checkcast 183	java/lang/String
    //   1389: astore 6
    //   1391: ldc 37
    //   1393: aload 6
    //   1395: invokevirtual 414	java/lang/String:equals	(Ljava/lang/Object;)Z
    //   1398: ifne -29 -> 1369
    //   1401: aload 4
    //   1403: invokevirtual 417	java/lang/StringBuilder:length	()I
    //   1406: ifle +12 -> 1418
    //   1409: aload 4
    //   1411: ldc_w 419
    //   1414: invokevirtual 85	java/lang/StringBuilder:append	(Ljava/lang/String;)Ljava/lang/StringBuilder;
    //   1417: pop
    //   1418: ldc_w 348
    //   1421: aload 6
    //   1423: invokevirtual 414	java/lang/String:equals	(Ljava/lang/Object;)Z
    //   1426: ifeq +110 -> 1536
    //   1429: aload 4
    //   1431: new 78	java/lang/StringBuilder
    //   1434: dup
    //   1435: invokespecial 79	java/lang/StringBuilder:<init>	()V
    //   1438: aload 6
    //   1440: invokevirtual 85	java/lang/StringBuilder:append	(Ljava/lang/String;)Ljava/lang/StringBuilder;
    //   1443: ldc_w 421
    //   1446: invokevirtual 85	java/lang/StringBuilder:append	(Ljava/lang/String;)Ljava/lang/StringBuilder;
    //   1449: invokevirtual 100	java/lang/StringBuilder:toString	()Ljava/lang/String;
    //   1452: invokevirtual 85	java/lang/StringBuilder:append	(Ljava/lang/String;)Ljava/lang/StringBuilder;
    //   1455: pop
    //   1456: aload_0
    //   1457: getfield 10	com/kahuna/sdk/v:a	Lcom/kahuna/sdk/h;
    //   1460: invokestatic 331	com/kahuna/sdk/h:E	(Lcom/kahuna/sdk/h;)Ljava/util/List;
    //   1463: invokeinterface 318 1 0
    //   1468: istore_2
    //   1469: iconst_0
    //   1470: istore_1
    //   1471: iload_1
    //   1472: iload_2
    //   1473: if_icmpge +51 -> 1524
    //   1476: aload_0
    //   1477: getfield 10	com/kahuna/sdk/v:a	Lcom/kahuna/sdk/h;
    //   1480: invokestatic 331	com/kahuna/sdk/h:E	(Lcom/kahuna/sdk/h;)Ljava/util/List;
    //   1483: iload_1
    //   1484: invokeinterface 328 2 0
    //   1489: checkcast 295	com/kahuna/sdk/Event
    //   1492: invokevirtual 335	com/kahuna/sdk/Event:h	()Lorg/json/JSONObject;
    //   1495: astore 6
    //   1497: aload 6
    //   1499: ldc_w 423
    //   1502: invokevirtual 429	org/json/JSONObject:remove	(Ljava/lang/String;)Ljava/lang/Object;
    //   1505: pop
    //   1506: aload 4
    //   1508: aload 6
    //   1510: invokevirtual 430	org/json/JSONObject:toString	()Ljava/lang/String;
    //   1513: invokevirtual 85	java/lang/StringBuilder:append	(Ljava/lang/String;)Ljava/lang/StringBuilder;
    //   1516: pop
    //   1517: iload_1
    //   1518: iconst_1
    //   1519: iadd
    //   1520: istore_1
    //   1521: goto -50 -> 1471
    //   1524: aload 4
    //   1526: ldc_w 432
    //   1529: invokevirtual 85	java/lang/StringBuilder:append	(Ljava/lang/String;)Ljava/lang/StringBuilder;
    //   1532: pop
    //   1533: goto -164 -> 1369
    //   1536: aload 4
    //   1538: new 78	java/lang/StringBuilder
    //   1541: dup
    //   1542: invokespecial 79	java/lang/StringBuilder:<init>	()V
    //   1545: aload 6
    //   1547: invokevirtual 85	java/lang/StringBuilder:append	(Ljava/lang/String;)Ljava/lang/StringBuilder;
    //   1550: ldc_w 434
    //   1553: invokevirtual 85	java/lang/StringBuilder:append	(Ljava/lang/String;)Ljava/lang/StringBuilder;
    //   1556: aload_3
    //   1557: aload 6
    //   1559: invokeinterface 223 2 0
    //   1564: checkcast 183	java/lang/String
    //   1567: invokevirtual 85	java/lang/StringBuilder:append	(Ljava/lang/String;)Ljava/lang/StringBuilder;
    //   1570: invokevirtual 100	java/lang/StringBuilder:toString	()Ljava/lang/String;
    //   1573: invokevirtual 85	java/lang/StringBuilder:append	(Ljava/lang/String;)Ljava/lang/StringBuilder;
    //   1576: pop
    //   1577: goto -208 -> 1369
    //   1580: ldc -25
    //   1582: new 78	java/lang/StringBuilder
    //   1585: dup
    //   1586: invokespecial 79	java/lang/StringBuilder:<init>	()V
    //   1589: ldc_w 436
    //   1592: invokevirtual 85	java/lang/StringBuilder:append	(Ljava/lang/String;)Ljava/lang/StringBuilder;
    //   1595: aload 4
    //   1597: invokevirtual 100	java/lang/StringBuilder:toString	()Ljava/lang/String;
    //   1600: invokevirtual 85	java/lang/StringBuilder:append	(Ljava/lang/String;)Ljava/lang/StringBuilder;
    //   1603: invokevirtual 100	java/lang/StringBuilder:toString	()Ljava/lang/String;
    //   1606: invokestatic 242	android/util/Log:d	(Ljava/lang/String;Ljava/lang/String;)I
    //   1609: pop
    //   1610: return
    //   1611: ldc -25
    //   1613: new 78	java/lang/StringBuilder
    //   1616: dup
    //   1617: invokespecial 79	java/lang/StringBuilder:<init>	()V
    //   1620: ldc_w 436
    //   1623: invokevirtual 85	java/lang/StringBuilder:append	(Ljava/lang/String;)Ljava/lang/StringBuilder;
    //   1626: aload 5
    //   1628: invokevirtual 236	java/lang/StringBuilder:append	(Ljava/lang/Object;)Ljava/lang/StringBuilder;
    //   1631: invokevirtual 100	java/lang/StringBuilder:toString	()Ljava/lang/String;
    //   1634: invokestatic 242	android/util/Log:d	(Ljava/lang/String;Ljava/lang/String;)I
    //   1637: pop
    //   1638: return
    //   1639: astore 4
    //   1641: aload_3
    //   1642: monitorexit
    //   1643: aload 4
    //   1645: athrow
    //   1646: iconst_0
    //   1647: istore_2
    //   1648: goto -706 -> 942
    //   1651: iload_2
    //   1652: iconst_1
    //   1653: iadd
    //   1654: istore_2
    //   1655: goto -713 -> 942
    // Local variable table:
    //   start	length	slot	name	signature
    //   0	1658	0	this	v
    //   922	599	1	i	int
    //   942	713	2	j	int
    //   10	535	3	localObject1	Object
    //   565	5	3	localObject2	Object
    //   571	33	3	localException	Exception
    //   1104	9	3	localObject4	Object
    //   1122	520	3	localObject5	Object
    //   1	547	4	localMap	java.util.Map
    //   649	5	4	localObject6	Object
    //   832	182	4	localObject7	Object
    //   1097	9	4	localObject8	Object
    //   1110	5	4	localObject9	Object
    //   1277	319	4	localObject10	Object
    //   1639	5	4	localObject11	Object
    //   31	1596	5	localObject12	Object
    //   366	22	6	localJSONArray	org.json.JSONArray
    //   406	1	6	localThrowable	Throwable
    //   433	1125	6	localObject13	Object
    //   347	476	7	localObject14	Object
    //   508	13	8	localIterator	java.util.Iterator
    //   530	20	9	str	String
    // Exception table:
    //   from	to	target	type
    //   321	377	406	java/lang/Throwable
    //   377	403	406	java/lang/Throwable
    //   663	675	406	java/lang/Throwable
    //   675	748	406	java/lang/Throwable
    //   748	774	406	java/lang/Throwable
    //   777	790	406	java/lang/Throwable
    //   465	510	565	finally
    //   510	562	565	finally
    //   566	569	565	finally
    //   793	822	565	finally
    //   822	825	565	finally
    //   3	13	571	java/lang/Exception
    //   24	199	571	java/lang/Exception
    //   199	244	571	java/lang/Exception
    //   244	254	571	java/lang/Exception
    //   257	321	571	java/lang/Exception
    //   321	377	571	java/lang/Exception
    //   377	403	571	java/lang/Exception
    //   408	426	571	java/lang/Exception
    //   426	462	571	java/lang/Exception
    //   569	571	571	java/lang/Exception
    //   653	656	571	java/lang/Exception
    //   663	675	571	java/lang/Exception
    //   675	748	571	java/lang/Exception
    //   748	774	571	java/lang/Exception
    //   777	790	571	java/lang/Exception
    //   825	837	571	java/lang/Exception
    //   1016	1044	571	java/lang/Exception
    //   1055	1065	571	java/lang/Exception
    //   1101	1104	571	java/lang/Exception
    //   1108	1110	571	java/lang/Exception
    //   1114	1117	571	java/lang/Exception
    //   1117	1176	571	java/lang/Exception
    //   1176	1207	571	java/lang/Exception
    //   1207	1258	571	java/lang/Exception
    //   1258	1369	571	java/lang/Exception
    //   1369	1418	571	java/lang/Exception
    //   1418	1469	571	java/lang/Exception
    //   1476	1517	571	java/lang/Exception
    //   1524	1533	571	java/lang/Exception
    //   1536	1577	571	java/lang/Exception
    //   1580	1610	571	java/lang/Exception
    //   1611	1638	571	java/lang/Exception
    //   13	24	649	finally
    //   651	653	649	finally
    //   1065	1094	1097	finally
    //   1094	1096	1097	finally
    //   1099	1101	1097	finally
    //   841	877	1104	finally
    //   877	912	1104	finally
    //   912	939	1104	finally
    //   947	983	1104	finally
    //   987	994	1104	finally
    //   997	1010	1104	finally
    //   1013	1016	1104	finally
    //   1105	1108	1104	finally
    //   1044	1055	1110	finally
    //   1112	1114	1110	finally
    //   617	646	1639	finally
    //   646	648	1639	finally
    //   1641	1643	1639	finally
  }
}

/* Location:
 * Qualified Name:     com.kahuna.sdk.v
 * Java Class Version: 6 (50.0)
 * JD-Core Version:    0.7.1
 */