package com.google.android.gms.ads.internal.client;

import android.os.Binder;
import android.os.IBinder;
import android.os.IInterface;
import android.os.Parcel;
import android.os.RemoteException;

public abstract class z$a
  extends Binder
  implements z
{
  public z$a()
  {
    attachInterface(this, "com.google.android.gms.ads.internal.client.IAdLoader");
  }
  
  public static z a(IBinder paramIBinder)
  {
    if (paramIBinder == null) {
      return null;
    }
    IInterface localIInterface = paramIBinder.queryLocalInterface("com.google.android.gms.ads.internal.client.IAdLoader");
    if ((localIInterface != null) && ((localIInterface instanceof z))) {
      return (z)localIInterface;
    }
    return new a(paramIBinder);
  }
  
  public IBinder asBinder()
  {
    return this;
  }
  
  public boolean onTransact(int paramInt1, Parcel paramParcel1, Parcel paramParcel2, int paramInt2)
    throws RemoteException
  {
    switch (paramInt1)
    {
    default: 
      return super.onTransact(paramInt1, paramParcel1, paramParcel2, paramInt2);
    case 1598968902: 
      paramParcel2.writeString("com.google.android.gms.ads.internal.client.IAdLoader");
      return true;
    case 1: 
      paramParcel1.enforceInterface("com.google.android.gms.ads.internal.client.IAdLoader");
      if (paramParcel1.readInt() != 0) {}
      for (paramParcel1 = AdRequestParcel.CREATOR.a(paramParcel1);; paramParcel1 = null)
      {
        a(paramParcel1);
        paramParcel2.writeNoException();
        return true;
      }
    case 2: 
      paramParcel1.enforceInterface("com.google.android.gms.ads.internal.client.IAdLoader");
      paramParcel1 = b();
      paramParcel2.writeNoException();
      paramParcel2.writeString(paramParcel1);
      return true;
    }
    paramParcel1.enforceInterface("com.google.android.gms.ads.internal.client.IAdLoader");
    boolean bool = a();
    paramParcel2.writeNoException();
    if (bool) {}
    for (paramInt1 = 1;; paramInt1 = 0)
    {
      paramParcel2.writeInt(paramInt1);
      return true;
    }
  }
  
  private static class a
    implements z
  {
    private IBinder a;
    
    a(IBinder paramIBinder)
    {
      a = paramIBinder;
    }
    
    /* Error */
    public void a(AdRequestParcel paramAdRequestParcel)
      throws RemoteException
    {
      // Byte code:
      //   0: invokestatic 27	android/os/Parcel:obtain	()Landroid/os/Parcel;
      //   3: astore_2
      //   4: invokestatic 27	android/os/Parcel:obtain	()Landroid/os/Parcel;
      //   7: astore_3
      //   8: aload_2
      //   9: ldc 29
      //   11: invokevirtual 33	android/os/Parcel:writeInterfaceToken	(Ljava/lang/String;)V
      //   14: aload_1
      //   15: ifnull +41 -> 56
      //   18: aload_2
      //   19: iconst_1
      //   20: invokevirtual 37	android/os/Parcel:writeInt	(I)V
      //   23: aload_1
      //   24: aload_2
      //   25: iconst_0
      //   26: invokevirtual 43	com/google/android/gms/ads/internal/client/AdRequestParcel:writeToParcel	(Landroid/os/Parcel;I)V
      //   29: aload_0
      //   30: getfield 17	com/google/android/gms/ads/internal/client/z$a$a:a	Landroid/os/IBinder;
      //   33: iconst_1
      //   34: aload_2
      //   35: aload_3
      //   36: iconst_0
      //   37: invokeinterface 49 5 0
      //   42: pop
      //   43: aload_3
      //   44: invokevirtual 52	android/os/Parcel:readException	()V
      //   47: aload_3
      //   48: invokevirtual 55	android/os/Parcel:recycle	()V
      //   51: aload_2
      //   52: invokevirtual 55	android/os/Parcel:recycle	()V
      //   55: return
      //   56: aload_2
      //   57: iconst_0
      //   58: invokevirtual 37	android/os/Parcel:writeInt	(I)V
      //   61: goto -32 -> 29
      //   64: astore_1
      //   65: aload_3
      //   66: invokevirtual 55	android/os/Parcel:recycle	()V
      //   69: aload_2
      //   70: invokevirtual 55	android/os/Parcel:recycle	()V
      //   73: aload_1
      //   74: athrow
      // Local variable table:
      //   start	length	slot	name	signature
      //   0	75	0	this	a
      //   0	75	1	paramAdRequestParcel	AdRequestParcel
      //   3	67	2	localParcel1	Parcel
      //   7	59	3	localParcel2	Parcel
      // Exception table:
      //   from	to	target	type
      //   8	14	64	finally
      //   18	29	64	finally
      //   29	47	64	finally
      //   56	61	64	finally
    }
    
    public boolean a()
      throws RemoteException
    {
      boolean bool = false;
      Parcel localParcel1 = Parcel.obtain();
      Parcel localParcel2 = Parcel.obtain();
      try
      {
        localParcel1.writeInterfaceToken("com.google.android.gms.ads.internal.client.IAdLoader");
        a.transact(3, localParcel1, localParcel2, 0);
        localParcel2.readException();
        int i = localParcel2.readInt();
        if (i != 0) {
          bool = true;
        }
        return bool;
      }
      finally
      {
        localParcel2.recycle();
        localParcel1.recycle();
      }
    }
    
    public IBinder asBinder()
    {
      return a;
    }
    
    public String b()
      throws RemoteException
    {
      Parcel localParcel1 = Parcel.obtain();
      Parcel localParcel2 = Parcel.obtain();
      try
      {
        localParcel1.writeInterfaceToken("com.google.android.gms.ads.internal.client.IAdLoader");
        a.transact(2, localParcel1, localParcel2, 0);
        localParcel2.readException();
        String str = localParcel2.readString();
        return str;
      }
      finally
      {
        localParcel2.recycle();
        localParcel1.recycle();
      }
    }
  }
}

/* Location:
 * Qualified Name:     com.google.android.gms.ads.internal.client.z.a
 * Java Class Version: 6 (50.0)
 * JD-Core Version:    0.7.1
 */