package com.google.android.gms.internal;

import android.os.Binder;
import android.os.IBinder;
import android.os.IInterface;
import android.os.Parcel;
import android.os.RemoteException;
import com.google.android.gms.dynamic.c.a;

public abstract class ba$a
  extends Binder
  implements ba
{
  public ba$a()
  {
    attachInterface(this, "com.google.android.gms.ads.internal.customrenderedad.client.ICustomRenderedAd");
  }
  
  public static ba a(IBinder paramIBinder)
  {
    if (paramIBinder == null) {
      return null;
    }
    IInterface localIInterface = paramIBinder.queryLocalInterface("com.google.android.gms.ads.internal.customrenderedad.client.ICustomRenderedAd");
    if ((localIInterface != null) && ((localIInterface instanceof ba))) {
      return (ba)localIInterface;
    }
    return new a(paramIBinder);
  }
  
  public IBinder asBinder()
  {
    return this;
  }
  
  public boolean onTransact(int paramInt1, Parcel paramParcel1, Parcel paramParcel2, int paramInt2)
    throws RemoteException
  {
    switch (paramInt1)
    {
    default: 
      return super.onTransact(paramInt1, paramParcel1, paramParcel2, paramInt2);
    case 1598968902: 
      paramParcel2.writeString("com.google.android.gms.ads.internal.customrenderedad.client.ICustomRenderedAd");
      return true;
    case 1: 
      paramParcel1.enforceInterface("com.google.android.gms.ads.internal.customrenderedad.client.ICustomRenderedAd");
      paramParcel1 = a();
      paramParcel2.writeNoException();
      paramParcel2.writeString(paramParcel1);
      return true;
    case 2: 
      paramParcel1.enforceInterface("com.google.android.gms.ads.internal.customrenderedad.client.ICustomRenderedAd");
      paramParcel1 = b();
      paramParcel2.writeNoException();
      paramParcel2.writeString(paramParcel1);
      return true;
    case 3: 
      paramParcel1.enforceInterface("com.google.android.gms.ads.internal.customrenderedad.client.ICustomRenderedAd");
      a(c.a.a(paramParcel1.readStrongBinder()));
      paramParcel2.writeNoException();
      return true;
    case 4: 
      paramParcel1.enforceInterface("com.google.android.gms.ads.internal.customrenderedad.client.ICustomRenderedAd");
      c();
      paramParcel2.writeNoException();
      return true;
    }
    paramParcel1.enforceInterface("com.google.android.gms.ads.internal.customrenderedad.client.ICustomRenderedAd");
    d();
    paramParcel2.writeNoException();
    return true;
  }
  
  private static class a
    implements ba
  {
    private IBinder a;
    
    a(IBinder paramIBinder)
    {
      a = paramIBinder;
    }
    
    public String a()
      throws RemoteException
    {
      Parcel localParcel1 = Parcel.obtain();
      Parcel localParcel2 = Parcel.obtain();
      try
      {
        localParcel1.writeInterfaceToken("com.google.android.gms.ads.internal.customrenderedad.client.ICustomRenderedAd");
        a.transact(1, localParcel1, localParcel2, 0);
        localParcel2.readException();
        String str = localParcel2.readString();
        return str;
      }
      finally
      {
        localParcel2.recycle();
        localParcel1.recycle();
      }
    }
    
    /* Error */
    public void a(com.google.android.gms.dynamic.c paramc)
      throws RemoteException
    {
      // Byte code:
      //   0: invokestatic 27	android/os/Parcel:obtain	()Landroid/os/Parcel;
      //   3: astore_2
      //   4: invokestatic 27	android/os/Parcel:obtain	()Landroid/os/Parcel;
      //   7: astore_3
      //   8: aload_2
      //   9: ldc 29
      //   11: invokevirtual 33	android/os/Parcel:writeInterfaceToken	(Ljava/lang/String;)V
      //   14: aload_1
      //   15: ifnull +42 -> 57
      //   18: aload_1
      //   19: invokeinterface 56 1 0
      //   24: astore_1
      //   25: aload_2
      //   26: aload_1
      //   27: invokevirtual 59	android/os/Parcel:writeStrongBinder	(Landroid/os/IBinder;)V
      //   30: aload_0
      //   31: getfield 17	com/google/android/gms/internal/ba$a$a:a	Landroid/os/IBinder;
      //   34: iconst_3
      //   35: aload_2
      //   36: aload_3
      //   37: iconst_0
      //   38: invokeinterface 39 5 0
      //   43: pop
      //   44: aload_3
      //   45: invokevirtual 42	android/os/Parcel:readException	()V
      //   48: aload_3
      //   49: invokevirtual 48	android/os/Parcel:recycle	()V
      //   52: aload_2
      //   53: invokevirtual 48	android/os/Parcel:recycle	()V
      //   56: return
      //   57: aconst_null
      //   58: astore_1
      //   59: goto -34 -> 25
      //   62: astore_1
      //   63: aload_3
      //   64: invokevirtual 48	android/os/Parcel:recycle	()V
      //   67: aload_2
      //   68: invokevirtual 48	android/os/Parcel:recycle	()V
      //   71: aload_1
      //   72: athrow
      // Local variable table:
      //   start	length	slot	name	signature
      //   0	73	0	this	a
      //   0	73	1	paramc	com.google.android.gms.dynamic.c
      //   3	65	2	localParcel1	Parcel
      //   7	57	3	localParcel2	Parcel
      // Exception table:
      //   from	to	target	type
      //   8	14	62	finally
      //   18	25	62	finally
      //   25	48	62	finally
    }
    
    public IBinder asBinder()
    {
      return a;
    }
    
    public String b()
      throws RemoteException
    {
      Parcel localParcel1 = Parcel.obtain();
      Parcel localParcel2 = Parcel.obtain();
      try
      {
        localParcel1.writeInterfaceToken("com.google.android.gms.ads.internal.customrenderedad.client.ICustomRenderedAd");
        a.transact(2, localParcel1, localParcel2, 0);
        localParcel2.readException();
        String str = localParcel2.readString();
        return str;
      }
      finally
      {
        localParcel2.recycle();
        localParcel1.recycle();
      }
    }
    
    public void c()
      throws RemoteException
    {
      Parcel localParcel1 = Parcel.obtain();
      Parcel localParcel2 = Parcel.obtain();
      try
      {
        localParcel1.writeInterfaceToken("com.google.android.gms.ads.internal.customrenderedad.client.ICustomRenderedAd");
        a.transact(4, localParcel1, localParcel2, 0);
        localParcel2.readException();
        return;
      }
      finally
      {
        localParcel2.recycle();
        localParcel1.recycle();
      }
    }
    
    public void d()
      throws RemoteException
    {
      Parcel localParcel1 = Parcel.obtain();
      Parcel localParcel2 = Parcel.obtain();
      try
      {
        localParcel1.writeInterfaceToken("com.google.android.gms.ads.internal.customrenderedad.client.ICustomRenderedAd");
        a.transact(5, localParcel1, localParcel2, 0);
        localParcel2.readException();
        return;
      }
      finally
      {
        localParcel2.recycle();
        localParcel1.recycle();
      }
    }
  }
}

/* Location:
 * Qualified Name:     com.google.android.gms.internal.ba.a
 * Java Class Version: 6 (50.0)
 * JD-Core Version:    0.7.1
 */