package com.google.android.gms.internal;

import android.os.IBinder;
import android.os.Parcel;
import android.os.RemoteException;
import java.util.ArrayList;
import java.util.List;

class dx$a$a
  implements dx
{
  private IBinder a;
  
  dx$a$a(IBinder paramIBinder)
  {
    a = paramIBinder;
  }
  
  public String a()
    throws RemoteException
  {
    Parcel localParcel1 = Parcel.obtain();
    Parcel localParcel2 = Parcel.obtain();
    try
    {
      localParcel1.writeInterfaceToken("com.google.android.gms.ads.internal.mediation.client.INativeAppInstallAdMapper");
      a.transact(2, localParcel1, localParcel2, 0);
      localParcel2.readException();
      String str = localParcel2.readString();
      return str;
    }
    finally
    {
      localParcel2.recycle();
      localParcel1.recycle();
    }
  }
  
  /* Error */
  public void a(com.google.android.gms.dynamic.c paramc)
    throws RemoteException
  {
    // Byte code:
    //   0: invokestatic 27	android/os/Parcel:obtain	()Landroid/os/Parcel;
    //   3: astore_2
    //   4: invokestatic 27	android/os/Parcel:obtain	()Landroid/os/Parcel;
    //   7: astore_3
    //   8: aload_2
    //   9: ldc 29
    //   11: invokevirtual 33	android/os/Parcel:writeInterfaceToken	(Ljava/lang/String;)V
    //   14: aload_1
    //   15: ifnull +43 -> 58
    //   18: aload_1
    //   19: invokeinterface 56 1 0
    //   24: astore_1
    //   25: aload_2
    //   26: aload_1
    //   27: invokevirtual 59	android/os/Parcel:writeStrongBinder	(Landroid/os/IBinder;)V
    //   30: aload_0
    //   31: getfield 17	com/google/android/gms/internal/dx$a$a:a	Landroid/os/IBinder;
    //   34: bipush 11
    //   36: aload_2
    //   37: aload_3
    //   38: iconst_0
    //   39: invokeinterface 39 5 0
    //   44: pop
    //   45: aload_3
    //   46: invokevirtual 42	android/os/Parcel:readException	()V
    //   49: aload_3
    //   50: invokevirtual 48	android/os/Parcel:recycle	()V
    //   53: aload_2
    //   54: invokevirtual 48	android/os/Parcel:recycle	()V
    //   57: return
    //   58: aconst_null
    //   59: astore_1
    //   60: goto -35 -> 25
    //   63: astore_1
    //   64: aload_3
    //   65: invokevirtual 48	android/os/Parcel:recycle	()V
    //   68: aload_2
    //   69: invokevirtual 48	android/os/Parcel:recycle	()V
    //   72: aload_1
    //   73: athrow
    // Local variable table:
    //   start	length	slot	name	signature
    //   0	74	0	this	a
    //   0	74	1	paramc	com.google.android.gms.dynamic.c
    //   3	66	2	localParcel1	Parcel
    //   7	58	3	localParcel2	Parcel
    // Exception table:
    //   from	to	target	type
    //   8	14	63	finally
    //   18	25	63	finally
    //   25	49	63	finally
  }
  
  public IBinder asBinder()
  {
    return a;
  }
  
  public List b()
    throws RemoteException
  {
    Parcel localParcel1 = Parcel.obtain();
    Parcel localParcel2 = Parcel.obtain();
    try
    {
      localParcel1.writeInterfaceToken("com.google.android.gms.ads.internal.mediation.client.INativeAppInstallAdMapper");
      a.transact(3, localParcel1, localParcel2, 0);
      localParcel2.readException();
      ArrayList localArrayList = localParcel2.readArrayList(getClass().getClassLoader());
      return localArrayList;
    }
    finally
    {
      localParcel2.recycle();
      localParcel1.recycle();
    }
  }
  
  /* Error */
  public void b(com.google.android.gms.dynamic.c paramc)
    throws RemoteException
  {
    // Byte code:
    //   0: invokestatic 27	android/os/Parcel:obtain	()Landroid/os/Parcel;
    //   3: astore_2
    //   4: invokestatic 27	android/os/Parcel:obtain	()Landroid/os/Parcel;
    //   7: astore_3
    //   8: aload_2
    //   9: ldc 29
    //   11: invokevirtual 33	android/os/Parcel:writeInterfaceToken	(Ljava/lang/String;)V
    //   14: aload_1
    //   15: ifnull +43 -> 58
    //   18: aload_1
    //   19: invokeinterface 56 1 0
    //   24: astore_1
    //   25: aload_2
    //   26: aload_1
    //   27: invokevirtual 59	android/os/Parcel:writeStrongBinder	(Landroid/os/IBinder;)V
    //   30: aload_0
    //   31: getfield 17	com/google/android/gms/internal/dx$a$a:a	Landroid/os/IBinder;
    //   34: bipush 12
    //   36: aload_2
    //   37: aload_3
    //   38: iconst_0
    //   39: invokeinterface 39 5 0
    //   44: pop
    //   45: aload_3
    //   46: invokevirtual 42	android/os/Parcel:readException	()V
    //   49: aload_3
    //   50: invokevirtual 48	android/os/Parcel:recycle	()V
    //   53: aload_2
    //   54: invokevirtual 48	android/os/Parcel:recycle	()V
    //   57: return
    //   58: aconst_null
    //   59: astore_1
    //   60: goto -35 -> 25
    //   63: astore_1
    //   64: aload_3
    //   65: invokevirtual 48	android/os/Parcel:recycle	()V
    //   68: aload_2
    //   69: invokevirtual 48	android/os/Parcel:recycle	()V
    //   72: aload_1
    //   73: athrow
    // Local variable table:
    //   start	length	slot	name	signature
    //   0	74	0	this	a
    //   0	74	1	paramc	com.google.android.gms.dynamic.c
    //   3	66	2	localParcel1	Parcel
    //   7	58	3	localParcel2	Parcel
    // Exception table:
    //   from	to	target	type
    //   8	14	63	finally
    //   18	25	63	finally
    //   25	49	63	finally
  }
  
  public String c()
    throws RemoteException
  {
    Parcel localParcel1 = Parcel.obtain();
    Parcel localParcel2 = Parcel.obtain();
    try
    {
      localParcel1.writeInterfaceToken("com.google.android.gms.ads.internal.mediation.client.INativeAppInstallAdMapper");
      a.transact(4, localParcel1, localParcel2, 0);
      localParcel2.readException();
      String str = localParcel2.readString();
      return str;
    }
    finally
    {
      localParcel2.recycle();
      localParcel1.recycle();
    }
  }
  
  public bd d()
    throws RemoteException
  {
    Parcel localParcel1 = Parcel.obtain();
    Parcel localParcel2 = Parcel.obtain();
    try
    {
      localParcel1.writeInterfaceToken("com.google.android.gms.ads.internal.mediation.client.INativeAppInstallAdMapper");
      a.transact(5, localParcel1, localParcel2, 0);
      localParcel2.readException();
      bd localbd = bd.a.a(localParcel2.readStrongBinder());
      return localbd;
    }
    finally
    {
      localParcel2.recycle();
      localParcel1.recycle();
    }
  }
  
  public String e()
    throws RemoteException
  {
    Parcel localParcel1 = Parcel.obtain();
    Parcel localParcel2 = Parcel.obtain();
    try
    {
      localParcel1.writeInterfaceToken("com.google.android.gms.ads.internal.mediation.client.INativeAppInstallAdMapper");
      a.transact(6, localParcel1, localParcel2, 0);
      localParcel2.readException();
      String str = localParcel2.readString();
      return str;
    }
    finally
    {
      localParcel2.recycle();
      localParcel1.recycle();
    }
  }
  
  public double f()
    throws RemoteException
  {
    Parcel localParcel1 = Parcel.obtain();
    Parcel localParcel2 = Parcel.obtain();
    try
    {
      localParcel1.writeInterfaceToken("com.google.android.gms.ads.internal.mediation.client.INativeAppInstallAdMapper");
      a.transact(7, localParcel1, localParcel2, 0);
      localParcel2.readException();
      double d = localParcel2.readDouble();
      return d;
    }
    finally
    {
      localParcel2.recycle();
      localParcel1.recycle();
    }
  }
  
  public String g()
    throws RemoteException
  {
    Parcel localParcel1 = Parcel.obtain();
    Parcel localParcel2 = Parcel.obtain();
    try
    {
      localParcel1.writeInterfaceToken("com.google.android.gms.ads.internal.mediation.client.INativeAppInstallAdMapper");
      a.transact(8, localParcel1, localParcel2, 0);
      localParcel2.readException();
      String str = localParcel2.readString();
      return str;
    }
    finally
    {
      localParcel2.recycle();
      localParcel1.recycle();
    }
  }
  
  public String h()
    throws RemoteException
  {
    Parcel localParcel1 = Parcel.obtain();
    Parcel localParcel2 = Parcel.obtain();
    try
    {
      localParcel1.writeInterfaceToken("com.google.android.gms.ads.internal.mediation.client.INativeAppInstallAdMapper");
      a.transact(9, localParcel1, localParcel2, 0);
      localParcel2.readException();
      String str = localParcel2.readString();
      return str;
    }
    finally
    {
      localParcel2.recycle();
      localParcel1.recycle();
    }
  }
  
  public void i()
    throws RemoteException
  {
    Parcel localParcel1 = Parcel.obtain();
    Parcel localParcel2 = Parcel.obtain();
    try
    {
      localParcel1.writeInterfaceToken("com.google.android.gms.ads.internal.mediation.client.INativeAppInstallAdMapper");
      a.transact(10, localParcel1, localParcel2, 0);
      localParcel2.readException();
      return;
    }
    finally
    {
      localParcel2.recycle();
      localParcel1.recycle();
    }
  }
  
  public boolean j()
    throws RemoteException
  {
    boolean bool = false;
    Parcel localParcel1 = Parcel.obtain();
    Parcel localParcel2 = Parcel.obtain();
    try
    {
      localParcel1.writeInterfaceToken("com.google.android.gms.ads.internal.mediation.client.INativeAppInstallAdMapper");
      a.transact(13, localParcel1, localParcel2, 0);
      localParcel2.readException();
      int i = localParcel2.readInt();
      if (i != 0) {
        bool = true;
      }
      return bool;
    }
    finally
    {
      localParcel2.recycle();
      localParcel1.recycle();
    }
  }
  
  public boolean k()
    throws RemoteException
  {
    boolean bool = false;
    Parcel localParcel1 = Parcel.obtain();
    Parcel localParcel2 = Parcel.obtain();
    try
    {
      localParcel1.writeInterfaceToken("com.google.android.gms.ads.internal.mediation.client.INativeAppInstallAdMapper");
      a.transact(14, localParcel1, localParcel2, 0);
      localParcel2.readException();
      int i = localParcel2.readInt();
      if (i != 0) {
        bool = true;
      }
      return bool;
    }
    finally
    {
      localParcel2.recycle();
      localParcel1.recycle();
    }
  }
  
  /* Error */
  public android.os.Bundle l()
    throws RemoteException
  {
    // Byte code:
    //   0: invokestatic 27	android/os/Parcel:obtain	()Landroid/os/Parcel;
    //   3: astore_2
    //   4: invokestatic 27	android/os/Parcel:obtain	()Landroid/os/Parcel;
    //   7: astore_3
    //   8: aload_2
    //   9: ldc 29
    //   11: invokevirtual 33	android/os/Parcel:writeInterfaceToken	(Ljava/lang/String;)V
    //   14: aload_0
    //   15: getfield 17	com/google/android/gms/internal/dx$a$a:a	Landroid/os/IBinder;
    //   18: bipush 15
    //   20: aload_2
    //   21: aload_3
    //   22: iconst_0
    //   23: invokeinterface 39 5 0
    //   28: pop
    //   29: aload_3
    //   30: invokevirtual 42	android/os/Parcel:readException	()V
    //   33: aload_3
    //   34: invokevirtual 101	android/os/Parcel:readInt	()I
    //   37: ifeq +26 -> 63
    //   40: getstatic 110	android/os/Bundle:CREATOR	Landroid/os/Parcelable$Creator;
    //   43: aload_3
    //   44: invokeinterface 116 2 0
    //   49: checkcast 106	android/os/Bundle
    //   52: astore_1
    //   53: aload_3
    //   54: invokevirtual 48	android/os/Parcel:recycle	()V
    //   57: aload_2
    //   58: invokevirtual 48	android/os/Parcel:recycle	()V
    //   61: aload_1
    //   62: areturn
    //   63: aconst_null
    //   64: astore_1
    //   65: goto -12 -> 53
    //   68: astore_1
    //   69: aload_3
    //   70: invokevirtual 48	android/os/Parcel:recycle	()V
    //   73: aload_2
    //   74: invokevirtual 48	android/os/Parcel:recycle	()V
    //   77: aload_1
    //   78: athrow
    // Local variable table:
    //   start	length	slot	name	signature
    //   0	79	0	this	a
    //   52	13	1	localBundle	android.os.Bundle
    //   68	10	1	localObject	Object
    //   3	71	2	localParcel1	Parcel
    //   7	63	3	localParcel2	Parcel
    // Exception table:
    //   from	to	target	type
    //   8	53	68	finally
  }
}

/* Location:
 * Qualified Name:     com.google.android.gms.internal.dx.a.a
 * Java Class Version: 6 (50.0)
 * JD-Core Version:    0.7.1
 */