package com.google.android.gms.internal;

import android.os.Binder;
import android.os.Bundle;
import android.os.IBinder;
import android.os.IInterface;
import android.os.Parcel;
import android.os.RemoteException;
import com.google.android.gms.dynamic.c;
import com.google.android.gms.dynamic.c.a;
import java.util.ArrayList;
import java.util.List;

public abstract interface dx
  extends IInterface
{
  public abstract String a()
    throws RemoteException;
  
  public abstract void a(c paramc)
    throws RemoteException;
  
  public abstract List b()
    throws RemoteException;
  
  public abstract void b(c paramc)
    throws RemoteException;
  
  public abstract String c()
    throws RemoteException;
  
  public abstract bd d()
    throws RemoteException;
  
  public abstract String e()
    throws RemoteException;
  
  public abstract double f()
    throws RemoteException;
  
  public abstract String g()
    throws RemoteException;
  
  public abstract String h()
    throws RemoteException;
  
  public abstract void i()
    throws RemoteException;
  
  public abstract boolean j()
    throws RemoteException;
  
  public abstract boolean k()
    throws RemoteException;
  
  public abstract Bundle l()
    throws RemoteException;
  
  public static abstract class a
    extends Binder
    implements dx
  {
    public a()
    {
      attachInterface(this, "com.google.android.gms.ads.internal.mediation.client.INativeAppInstallAdMapper");
    }
    
    public static dx a(IBinder paramIBinder)
    {
      if (paramIBinder == null) {
        return null;
      }
      IInterface localIInterface = paramIBinder.queryLocalInterface("com.google.android.gms.ads.internal.mediation.client.INativeAppInstallAdMapper");
      if ((localIInterface != null) && ((localIInterface instanceof dx))) {
        return (dx)localIInterface;
      }
      return new a(paramIBinder);
    }
    
    public IBinder asBinder()
    {
      return this;
    }
    
    public boolean onTransact(int paramInt1, Parcel paramParcel1, Parcel paramParcel2, int paramInt2)
      throws RemoteException
    {
      int j = 0;
      int i = 0;
      boolean bool;
      switch (paramInt1)
      {
      default: 
        return super.onTransact(paramInt1, paramParcel1, paramParcel2, paramInt2);
      case 1598968902: 
        paramParcel2.writeString("com.google.android.gms.ads.internal.mediation.client.INativeAppInstallAdMapper");
        return true;
      case 2: 
        paramParcel1.enforceInterface("com.google.android.gms.ads.internal.mediation.client.INativeAppInstallAdMapper");
        paramParcel1 = a();
        paramParcel2.writeNoException();
        paramParcel2.writeString(paramParcel1);
        return true;
      case 3: 
        paramParcel1.enforceInterface("com.google.android.gms.ads.internal.mediation.client.INativeAppInstallAdMapper");
        paramParcel1 = b();
        paramParcel2.writeNoException();
        paramParcel2.writeList(paramParcel1);
        return true;
      case 4: 
        paramParcel1.enforceInterface("com.google.android.gms.ads.internal.mediation.client.INativeAppInstallAdMapper");
        paramParcel1 = c();
        paramParcel2.writeNoException();
        paramParcel2.writeString(paramParcel1);
        return true;
      case 5: 
        paramParcel1.enforceInterface("com.google.android.gms.ads.internal.mediation.client.INativeAppInstallAdMapper");
        paramParcel1 = d();
        paramParcel2.writeNoException();
        if (paramParcel1 != null) {}
        for (paramParcel1 = paramParcel1.asBinder();; paramParcel1 = null)
        {
          paramParcel2.writeStrongBinder(paramParcel1);
          return true;
        }
      case 6: 
        paramParcel1.enforceInterface("com.google.android.gms.ads.internal.mediation.client.INativeAppInstallAdMapper");
        paramParcel1 = e();
        paramParcel2.writeNoException();
        paramParcel2.writeString(paramParcel1);
        return true;
      case 7: 
        paramParcel1.enforceInterface("com.google.android.gms.ads.internal.mediation.client.INativeAppInstallAdMapper");
        double d = f();
        paramParcel2.writeNoException();
        paramParcel2.writeDouble(d);
        return true;
      case 8: 
        paramParcel1.enforceInterface("com.google.android.gms.ads.internal.mediation.client.INativeAppInstallAdMapper");
        paramParcel1 = g();
        paramParcel2.writeNoException();
        paramParcel2.writeString(paramParcel1);
        return true;
      case 9: 
        paramParcel1.enforceInterface("com.google.android.gms.ads.internal.mediation.client.INativeAppInstallAdMapper");
        paramParcel1 = h();
        paramParcel2.writeNoException();
        paramParcel2.writeString(paramParcel1);
        return true;
      case 10: 
        paramParcel1.enforceInterface("com.google.android.gms.ads.internal.mediation.client.INativeAppInstallAdMapper");
        i();
        paramParcel2.writeNoException();
        return true;
      case 11: 
        paramParcel1.enforceInterface("com.google.android.gms.ads.internal.mediation.client.INativeAppInstallAdMapper");
        a(c.a.a(paramParcel1.readStrongBinder()));
        paramParcel2.writeNoException();
        return true;
      case 12: 
        paramParcel1.enforceInterface("com.google.android.gms.ads.internal.mediation.client.INativeAppInstallAdMapper");
        b(c.a.a(paramParcel1.readStrongBinder()));
        paramParcel2.writeNoException();
        return true;
      case 13: 
        paramParcel1.enforceInterface("com.google.android.gms.ads.internal.mediation.client.INativeAppInstallAdMapper");
        bool = j();
        paramParcel2.writeNoException();
        paramInt1 = i;
        if (bool) {
          paramInt1 = 1;
        }
        paramParcel2.writeInt(paramInt1);
        return true;
      case 14: 
        paramParcel1.enforceInterface("com.google.android.gms.ads.internal.mediation.client.INativeAppInstallAdMapper");
        bool = k();
        paramParcel2.writeNoException();
        paramInt1 = j;
        if (bool) {
          paramInt1 = 1;
        }
        paramParcel2.writeInt(paramInt1);
        return true;
      }
      paramParcel1.enforceInterface("com.google.android.gms.ads.internal.mediation.client.INativeAppInstallAdMapper");
      paramParcel1 = l();
      paramParcel2.writeNoException();
      if (paramParcel1 != null)
      {
        paramParcel2.writeInt(1);
        paramParcel1.writeToParcel(paramParcel2, 1);
        return true;
      }
      paramParcel2.writeInt(0);
      return true;
    }
    
    private static class a
      implements dx
    {
      private IBinder a;
      
      a(IBinder paramIBinder)
      {
        a = paramIBinder;
      }
      
      public String a()
        throws RemoteException
      {
        Parcel localParcel1 = Parcel.obtain();
        Parcel localParcel2 = Parcel.obtain();
        try
        {
          localParcel1.writeInterfaceToken("com.google.android.gms.ads.internal.mediation.client.INativeAppInstallAdMapper");
          a.transact(2, localParcel1, localParcel2, 0);
          localParcel2.readException();
          String str = localParcel2.readString();
          return str;
        }
        finally
        {
          localParcel2.recycle();
          localParcel1.recycle();
        }
      }
      
      /* Error */
      public void a(c paramc)
        throws RemoteException
      {
        // Byte code:
        //   0: invokestatic 27	android/os/Parcel:obtain	()Landroid/os/Parcel;
        //   3: astore_2
        //   4: invokestatic 27	android/os/Parcel:obtain	()Landroid/os/Parcel;
        //   7: astore_3
        //   8: aload_2
        //   9: ldc 29
        //   11: invokevirtual 33	android/os/Parcel:writeInterfaceToken	(Ljava/lang/String;)V
        //   14: aload_1
        //   15: ifnull +43 -> 58
        //   18: aload_1
        //   19: invokeinterface 56 1 0
        //   24: astore_1
        //   25: aload_2
        //   26: aload_1
        //   27: invokevirtual 59	android/os/Parcel:writeStrongBinder	(Landroid/os/IBinder;)V
        //   30: aload_0
        //   31: getfield 17	com/google/android/gms/internal/dx$a$a:a	Landroid/os/IBinder;
        //   34: bipush 11
        //   36: aload_2
        //   37: aload_3
        //   38: iconst_0
        //   39: invokeinterface 39 5 0
        //   44: pop
        //   45: aload_3
        //   46: invokevirtual 42	android/os/Parcel:readException	()V
        //   49: aload_3
        //   50: invokevirtual 48	android/os/Parcel:recycle	()V
        //   53: aload_2
        //   54: invokevirtual 48	android/os/Parcel:recycle	()V
        //   57: return
        //   58: aconst_null
        //   59: astore_1
        //   60: goto -35 -> 25
        //   63: astore_1
        //   64: aload_3
        //   65: invokevirtual 48	android/os/Parcel:recycle	()V
        //   68: aload_2
        //   69: invokevirtual 48	android/os/Parcel:recycle	()V
        //   72: aload_1
        //   73: athrow
        // Local variable table:
        //   start	length	slot	name	signature
        //   0	74	0	this	a
        //   0	74	1	paramc	c
        //   3	66	2	localParcel1	Parcel
        //   7	58	3	localParcel2	Parcel
        // Exception table:
        //   from	to	target	type
        //   8	14	63	finally
        //   18	25	63	finally
        //   25	49	63	finally
      }
      
      public IBinder asBinder()
      {
        return a;
      }
      
      public List b()
        throws RemoteException
      {
        Parcel localParcel1 = Parcel.obtain();
        Parcel localParcel2 = Parcel.obtain();
        try
        {
          localParcel1.writeInterfaceToken("com.google.android.gms.ads.internal.mediation.client.INativeAppInstallAdMapper");
          a.transact(3, localParcel1, localParcel2, 0);
          localParcel2.readException();
          ArrayList localArrayList = localParcel2.readArrayList(getClass().getClassLoader());
          return localArrayList;
        }
        finally
        {
          localParcel2.recycle();
          localParcel1.recycle();
        }
      }
      
      /* Error */
      public void b(c paramc)
        throws RemoteException
      {
        // Byte code:
        //   0: invokestatic 27	android/os/Parcel:obtain	()Landroid/os/Parcel;
        //   3: astore_2
        //   4: invokestatic 27	android/os/Parcel:obtain	()Landroid/os/Parcel;
        //   7: astore_3
        //   8: aload_2
        //   9: ldc 29
        //   11: invokevirtual 33	android/os/Parcel:writeInterfaceToken	(Ljava/lang/String;)V
        //   14: aload_1
        //   15: ifnull +43 -> 58
        //   18: aload_1
        //   19: invokeinterface 56 1 0
        //   24: astore_1
        //   25: aload_2
        //   26: aload_1
        //   27: invokevirtual 59	android/os/Parcel:writeStrongBinder	(Landroid/os/IBinder;)V
        //   30: aload_0
        //   31: getfield 17	com/google/android/gms/internal/dx$a$a:a	Landroid/os/IBinder;
        //   34: bipush 12
        //   36: aload_2
        //   37: aload_3
        //   38: iconst_0
        //   39: invokeinterface 39 5 0
        //   44: pop
        //   45: aload_3
        //   46: invokevirtual 42	android/os/Parcel:readException	()V
        //   49: aload_3
        //   50: invokevirtual 48	android/os/Parcel:recycle	()V
        //   53: aload_2
        //   54: invokevirtual 48	android/os/Parcel:recycle	()V
        //   57: return
        //   58: aconst_null
        //   59: astore_1
        //   60: goto -35 -> 25
        //   63: astore_1
        //   64: aload_3
        //   65: invokevirtual 48	android/os/Parcel:recycle	()V
        //   68: aload_2
        //   69: invokevirtual 48	android/os/Parcel:recycle	()V
        //   72: aload_1
        //   73: athrow
        // Local variable table:
        //   start	length	slot	name	signature
        //   0	74	0	this	a
        //   0	74	1	paramc	c
        //   3	66	2	localParcel1	Parcel
        //   7	58	3	localParcel2	Parcel
        // Exception table:
        //   from	to	target	type
        //   8	14	63	finally
        //   18	25	63	finally
        //   25	49	63	finally
      }
      
      public String c()
        throws RemoteException
      {
        Parcel localParcel1 = Parcel.obtain();
        Parcel localParcel2 = Parcel.obtain();
        try
        {
          localParcel1.writeInterfaceToken("com.google.android.gms.ads.internal.mediation.client.INativeAppInstallAdMapper");
          a.transact(4, localParcel1, localParcel2, 0);
          localParcel2.readException();
          String str = localParcel2.readString();
          return str;
        }
        finally
        {
          localParcel2.recycle();
          localParcel1.recycle();
        }
      }
      
      public bd d()
        throws RemoteException
      {
        Parcel localParcel1 = Parcel.obtain();
        Parcel localParcel2 = Parcel.obtain();
        try
        {
          localParcel1.writeInterfaceToken("com.google.android.gms.ads.internal.mediation.client.INativeAppInstallAdMapper");
          a.transact(5, localParcel1, localParcel2, 0);
          localParcel2.readException();
          bd localbd = bd.a.a(localParcel2.readStrongBinder());
          return localbd;
        }
        finally
        {
          localParcel2.recycle();
          localParcel1.recycle();
        }
      }
      
      public String e()
        throws RemoteException
      {
        Parcel localParcel1 = Parcel.obtain();
        Parcel localParcel2 = Parcel.obtain();
        try
        {
          localParcel1.writeInterfaceToken("com.google.android.gms.ads.internal.mediation.client.INativeAppInstallAdMapper");
          a.transact(6, localParcel1, localParcel2, 0);
          localParcel2.readException();
          String str = localParcel2.readString();
          return str;
        }
        finally
        {
          localParcel2.recycle();
          localParcel1.recycle();
        }
      }
      
      public double f()
        throws RemoteException
      {
        Parcel localParcel1 = Parcel.obtain();
        Parcel localParcel2 = Parcel.obtain();
        try
        {
          localParcel1.writeInterfaceToken("com.google.android.gms.ads.internal.mediation.client.INativeAppInstallAdMapper");
          a.transact(7, localParcel1, localParcel2, 0);
          localParcel2.readException();
          double d = localParcel2.readDouble();
          return d;
        }
        finally
        {
          localParcel2.recycle();
          localParcel1.recycle();
        }
      }
      
      public String g()
        throws RemoteException
      {
        Parcel localParcel1 = Parcel.obtain();
        Parcel localParcel2 = Parcel.obtain();
        try
        {
          localParcel1.writeInterfaceToken("com.google.android.gms.ads.internal.mediation.client.INativeAppInstallAdMapper");
          a.transact(8, localParcel1, localParcel2, 0);
          localParcel2.readException();
          String str = localParcel2.readString();
          return str;
        }
        finally
        {
          localParcel2.recycle();
          localParcel1.recycle();
        }
      }
      
      public String h()
        throws RemoteException
      {
        Parcel localParcel1 = Parcel.obtain();
        Parcel localParcel2 = Parcel.obtain();
        try
        {
          localParcel1.writeInterfaceToken("com.google.android.gms.ads.internal.mediation.client.INativeAppInstallAdMapper");
          a.transact(9, localParcel1, localParcel2, 0);
          localParcel2.readException();
          String str = localParcel2.readString();
          return str;
        }
        finally
        {
          localParcel2.recycle();
          localParcel1.recycle();
        }
      }
      
      public void i()
        throws RemoteException
      {
        Parcel localParcel1 = Parcel.obtain();
        Parcel localParcel2 = Parcel.obtain();
        try
        {
          localParcel1.writeInterfaceToken("com.google.android.gms.ads.internal.mediation.client.INativeAppInstallAdMapper");
          a.transact(10, localParcel1, localParcel2, 0);
          localParcel2.readException();
          return;
        }
        finally
        {
          localParcel2.recycle();
          localParcel1.recycle();
        }
      }
      
      public boolean j()
        throws RemoteException
      {
        boolean bool = false;
        Parcel localParcel1 = Parcel.obtain();
        Parcel localParcel2 = Parcel.obtain();
        try
        {
          localParcel1.writeInterfaceToken("com.google.android.gms.ads.internal.mediation.client.INativeAppInstallAdMapper");
          a.transact(13, localParcel1, localParcel2, 0);
          localParcel2.readException();
          int i = localParcel2.readInt();
          if (i != 0) {
            bool = true;
          }
          return bool;
        }
        finally
        {
          localParcel2.recycle();
          localParcel1.recycle();
        }
      }
      
      public boolean k()
        throws RemoteException
      {
        boolean bool = false;
        Parcel localParcel1 = Parcel.obtain();
        Parcel localParcel2 = Parcel.obtain();
        try
        {
          localParcel1.writeInterfaceToken("com.google.android.gms.ads.internal.mediation.client.INativeAppInstallAdMapper");
          a.transact(14, localParcel1, localParcel2, 0);
          localParcel2.readException();
          int i = localParcel2.readInt();
          if (i != 0) {
            bool = true;
          }
          return bool;
        }
        finally
        {
          localParcel2.recycle();
          localParcel1.recycle();
        }
      }
      
      /* Error */
      public Bundle l()
        throws RemoteException
      {
        // Byte code:
        //   0: invokestatic 27	android/os/Parcel:obtain	()Landroid/os/Parcel;
        //   3: astore_2
        //   4: invokestatic 27	android/os/Parcel:obtain	()Landroid/os/Parcel;
        //   7: astore_3
        //   8: aload_2
        //   9: ldc 29
        //   11: invokevirtual 33	android/os/Parcel:writeInterfaceToken	(Ljava/lang/String;)V
        //   14: aload_0
        //   15: getfield 17	com/google/android/gms/internal/dx$a$a:a	Landroid/os/IBinder;
        //   18: bipush 15
        //   20: aload_2
        //   21: aload_3
        //   22: iconst_0
        //   23: invokeinterface 39 5 0
        //   28: pop
        //   29: aload_3
        //   30: invokevirtual 42	android/os/Parcel:readException	()V
        //   33: aload_3
        //   34: invokevirtual 101	android/os/Parcel:readInt	()I
        //   37: ifeq +26 -> 63
        //   40: getstatic 110	android/os/Bundle:CREATOR	Landroid/os/Parcelable$Creator;
        //   43: aload_3
        //   44: invokeinterface 116 2 0
        //   49: checkcast 106	android/os/Bundle
        //   52: astore_1
        //   53: aload_3
        //   54: invokevirtual 48	android/os/Parcel:recycle	()V
        //   57: aload_2
        //   58: invokevirtual 48	android/os/Parcel:recycle	()V
        //   61: aload_1
        //   62: areturn
        //   63: aconst_null
        //   64: astore_1
        //   65: goto -12 -> 53
        //   68: astore_1
        //   69: aload_3
        //   70: invokevirtual 48	android/os/Parcel:recycle	()V
        //   73: aload_2
        //   74: invokevirtual 48	android/os/Parcel:recycle	()V
        //   77: aload_1
        //   78: athrow
        // Local variable table:
        //   start	length	slot	name	signature
        //   0	79	0	this	a
        //   52	13	1	localBundle	Bundle
        //   68	10	1	localObject	Object
        //   3	71	2	localParcel1	Parcel
        //   7	63	3	localParcel2	Parcel
        // Exception table:
        //   from	to	target	type
        //   8	53	68	finally
      }
    }
  }
}

/* Location:
 * Qualified Name:     com.google.android.gms.internal.dx
 * Java Class Version: 6 (50.0)
 * JD-Core Version:    0.7.1
 */