package com.google.android.gms.internal;

import android.content.Context;
import android.util.DisplayMetrics;
import android.view.MotionEvent;
import com.google.android.gms.clearcut.b;
import com.google.android.gms.clearcut.b.a;
import com.google.android.gms.common.api.GoogleApiClient;
import com.google.android.gms.common.api.GoogleApiClient.Builder;
import com.google.android.gms.common.zzc;
import com.yelp.android.az.a.a;
import dalvik.system.DexClassLoader;
import java.io.File;
import java.io.FileNotFoundException;
import java.io.FileOutputStream;
import java.io.IOException;
import java.io.UnsupportedEncodingException;
import java.lang.reflect.InvocationTargetException;
import java.lang.reflect.Method;
import java.nio.ByteBuffer;
import java.util.ArrayList;
import java.util.Random;
import java.util.concurrent.TimeUnit;

public abstract class zzal
  extends h
{
  private static Method A;
  private static Method B;
  private static Method C;
  private static Method D;
  private static String E;
  private static String F;
  private static String G;
  private static long H = 0L;
  private static zzaq I;
  private static Random J;
  private static zzc K;
  private static boolean L;
  private static boolean M = false;
  static boolean j = false;
  protected static b k = null;
  protected static a.a l;
  protected static int m;
  protected static boolean n;
  protected static boolean o;
  protected static boolean p;
  protected static boolean q;
  private static Method r;
  private static Method s;
  private static Method t;
  private static Method u;
  private static Method v;
  private static Method w;
  private static Method x;
  private static Method y;
  private static Method z;
  
  static
  {
    J = new Random();
    K = zzc.zzoK();
    n = false;
    o = false;
    p = false;
    q = false;
  }
  
  protected zzal(Context paramContext, k paramk)
  {
    super(paramContext, paramk);
    l = new a.a();
    la = paramContext.getPackageName();
  }
  
  static String a(Context paramContext, k paramk)
    throws zzal.zza
  {
    if (F != null) {
      return F;
    }
    if (u == null) {
      throw new zza();
    }
    try
    {
      paramContext = (ByteBuffer)u.invoke(null, new Object[] { paramContext });
      if (paramContext == null) {
        throw new zza();
      }
    }
    catch (IllegalAccessException paramContext)
    {
      throw new zza(paramContext);
      F = paramk.a(paramContext.array(), true);
      paramContext = F;
      return paramContext;
    }
    catch (InvocationTargetException paramContext)
    {
      throw new zza(paramContext);
    }
  }
  
  static ArrayList<Long> a(MotionEvent paramMotionEvent, DisplayMetrics paramDisplayMetrics)
    throws zzal.zza
  {
    if ((v == null) || (paramMotionEvent == null)) {
      throw new zza();
    }
    try
    {
      paramMotionEvent = (ArrayList)v.invoke(null, new Object[] { paramMotionEvent, paramDisplayMetrics });
      return paramMotionEvent;
    }
    catch (IllegalAccessException paramMotionEvent)
    {
      throw new zza(paramMotionEvent);
    }
    catch (InvocationTargetException paramMotionEvent)
    {
      throw new zza(paramMotionEvent);
    }
  }
  
  protected static void a(int paramInt1, int paramInt2)
    throws IOException
  {
    if ((q) && (n) && (k != null))
    {
      b.a locala = k.a(lq.a(l));
      locala.b(paramInt2);
      locala.a(paramInt1);
      locala.a(i);
    }
  }
  
  protected static void a(String paramString, Context paramContext, k paramk)
  {
    for (;;)
    {
      boolean bool;
      try
      {
        bool = j;
        if (bool) {}
      }
      finally {}
      try
      {
        I = new zzaq(paramk, null);
        E = paramString;
        ao.a(paramContext);
        l(paramContext);
        H = c().longValue();
        J = new Random();
      }
      catch (UnsupportedOperationException paramString)
      {
        continue;
      }
      catch (zza paramString)
      {
        continue;
      }
      try
      {
        i = new GoogleApiClient.Builder(paramContext).addApi(b.c).build();
        K = zzc.zzoK();
        if (K.isGooglePlayServicesAvailable(paramContext) != 0) {
          continue;
        }
        bool = true;
        L = bool;
        ao.a(paramContext);
        n = ((Boolean)ao.az.c()).booleanValue();
        k = new b(paramContext, "ADSHIELD", null, null);
      }
      catch (NoClassDefFoundError paramString) {}
    }
    if (K.zzaj(paramContext) > 0) {}
    for (bool = true;; bool = false)
    {
      M = bool;
      j = true;
      return;
      bool = false;
      break;
    }
  }
  
  static String b()
    throws zzal.zza
  {
    if (E == null) {
      throw new zza();
    }
    return E;
  }
  
  static String b(Context paramContext, k paramk)
    throws zzal.zza
  {
    if (G != null) {
      return G;
    }
    if (x == null) {
      throw new zza();
    }
    try
    {
      paramContext = (ByteBuffer)x.invoke(null, new Object[] { paramContext });
      if (paramContext == null) {
        throw new zza();
      }
    }
    catch (IllegalAccessException paramContext)
    {
      throw new zza(paramContext);
      G = paramk.a(paramContext.array(), true);
      paramContext = G;
      return paramContext;
    }
    catch (InvocationTargetException paramContext)
    {
      throw new zza(paramContext);
    }
  }
  
  private static String b(byte[] paramArrayOfByte, String paramString)
    throws zzal.zza
  {
    try
    {
      paramArrayOfByte = new String(I.a(paramArrayOfByte, paramString), "UTF-8");
      return paramArrayOfByte;
    }
    catch (zzaq.zza paramArrayOfByte)
    {
      throw new zza(paramArrayOfByte);
    }
    catch (UnsupportedEncodingException paramArrayOfByte)
    {
      throw new zza(paramArrayOfByte);
    }
  }
  
  static Long c()
    throws zzal.zza
  {
    if (r == null) {
      throw new zza();
    }
    try
    {
      Long localLong = (Long)r.invoke(null, new Object[0]);
      return localLong;
    }
    catch (IllegalAccessException localIllegalAccessException)
    {
      throw new zza(localIllegalAccessException);
    }
    catch (InvocationTargetException localInvocationTargetException)
    {
      throw new zza(localInvocationTargetException);
    }
  }
  
  static String d()
    throws zzal.zza
  {
    if (t == null) {
      throw new zza();
    }
    try
    {
      String str = (String)t.invoke(null, new Object[0]);
      return str;
    }
    catch (IllegalAccessException localIllegalAccessException)
    {
      throw new zza(localIllegalAccessException);
    }
    catch (InvocationTargetException localInvocationTargetException)
    {
      throw new zza(localInvocationTargetException);
    }
  }
  
  static String d(Context paramContext)
    throws zzal.zza
  {
    if (w == null) {
      throw new zza();
    }
    try
    {
      paramContext = (String)w.invoke(null, new Object[] { paramContext });
      if (paramContext == null) {
        throw new zza();
      }
    }
    catch (IllegalAccessException paramContext)
    {
      throw new zza(paramContext);
    }
    catch (InvocationTargetException paramContext)
    {
      throw new zza(paramContext);
    }
    return paramContext;
  }
  
  static Long e()
    throws zzal.zza
  {
    if (s == null) {
      throw new zza();
    }
    try
    {
      Long localLong = (Long)s.invoke(null, new Object[0]);
      return localLong;
    }
    catch (IllegalAccessException localIllegalAccessException)
    {
      throw new zza(localIllegalAccessException);
    }
    catch (InvocationTargetException localInvocationTargetException)
    {
      throw new zza(localInvocationTargetException);
    }
  }
  
  static String e(Context paramContext)
    throws zzal.zza
  {
    if (A == null) {
      throw new zza();
    }
    try
    {
      paramContext = (String)A.invoke(null, new Object[] { paramContext });
      return paramContext;
    }
    catch (IllegalAccessException paramContext)
    {
      throw new zza(paramContext);
    }
    catch (InvocationTargetException paramContext)
    {
      throw new zza(paramContext);
    }
  }
  
  static Long f(Context paramContext)
    throws zzal.zza
  {
    if (B == null) {
      throw new zza();
    }
    try
    {
      paramContext = (Long)B.invoke(null, new Object[] { paramContext });
      return paramContext;
    }
    catch (IllegalAccessException paramContext)
    {
      throw new zza(paramContext);
    }
    catch (InvocationTargetException paramContext)
    {
      throw new zza(paramContext);
    }
  }
  
  private void f()
  {
    if ((q) && (k != null))
    {
      k.a(i, 100L, TimeUnit.MILLISECONDS);
      i.disconnect();
    }
  }
  
  static ArrayList<Long> g(Context paramContext)
    throws zzal.zza
  {
    if (y == null) {
      throw new zza();
    }
    try
    {
      paramContext = (ArrayList)y.invoke(null, new Object[] { paramContext });
      if ((paramContext == null) || (paramContext.size() != 2)) {
        throw new zza();
      }
    }
    catch (IllegalAccessException paramContext)
    {
      throw new zza(paramContext);
    }
    catch (InvocationTargetException paramContext)
    {
      throw new zza(paramContext);
    }
    return paramContext;
  }
  
  static int[] h(Context paramContext)
    throws zzal.zza
  {
    if (z == null) {
      throw new zza();
    }
    try
    {
      paramContext = (int[])z.invoke(null, new Object[] { paramContext });
      return paramContext;
    }
    catch (IllegalAccessException paramContext)
    {
      throw new zza(paramContext);
    }
    catch (InvocationTargetException paramContext)
    {
      throw new zza(paramContext);
    }
  }
  
  static int i(Context paramContext)
    throws zzal.zza
  {
    if (C == null) {
      throw new zza();
    }
    try
    {
      int i = ((Integer)C.invoke(null, new Object[] { paramContext })).intValue();
      return i;
    }
    catch (IllegalAccessException paramContext)
    {
      throw new zza(paramContext);
    }
    catch (InvocationTargetException paramContext)
    {
      throw new zza(paramContext);
    }
  }
  
  static int j(Context paramContext)
    throws zzal.zza
  {
    if (D == null) {
      throw new zza();
    }
    try
    {
      int i = ((Integer)D.invoke(null, new Object[] { paramContext })).intValue();
      return i;
    }
    catch (IllegalAccessException paramContext)
    {
      throw new zza(paramContext);
    }
    catch (InvocationTargetException paramContext)
    {
      throw new zza(paramContext);
    }
  }
  
  private void k(Context paramContext)
  {
    if (L)
    {
      i.connect();
      q = true;
      return;
    }
    q = false;
  }
  
  private static void l(Context paramContext)
    throws zzal.zza
  {
    try
    {
      localObject1 = I.a(l.a());
      localObject2 = I.a((byte[])localObject1, l.b());
      localFile2 = paramContext.getCacheDir();
      localFile1 = localFile2;
      if (localFile2 == null)
      {
        localFile2 = paramContext.getDir("dex", 0);
        localFile1 = localFile2;
        if (localFile2 == null) {
          throw new zza();
        }
      }
    }
    catch (FileNotFoundException paramContext)
    {
      Object localObject1;
      Object localObject2;
      File localFile1;
      throw new zza(paramContext);
      File localFile2 = File.createTempFile("ads", ".jar", localFile1);
      Object localObject3 = new FileOutputStream(localFile2);
      ((FileOutputStream)localObject3).write((byte[])localObject2, 0, localObject2.length);
      ((FileOutputStream)localObject3).close();
      try
      {
        Object localObject4 = new DexClassLoader(localFile2.getAbsolutePath(), localFile1.getAbsolutePath(), null, paramContext.getClassLoader());
        paramContext = ((DexClassLoader)localObject4).loadClass(b((byte[])localObject1, l.k()));
        localObject2 = ((DexClassLoader)localObject4).loadClass(b((byte[])localObject1, l.y()));
        localObject3 = ((DexClassLoader)localObject4).loadClass(b((byte[])localObject1, l.s()));
        Class localClass1 = ((DexClassLoader)localObject4).loadClass(b((byte[])localObject1, l.o()));
        Class localClass2 = ((DexClassLoader)localObject4).loadClass(b((byte[])localObject1, l.A()));
        Class localClass3 = ((DexClassLoader)localObject4).loadClass(b((byte[])localObject1, l.m()));
        Class localClass4 = ((DexClassLoader)localObject4).loadClass(b((byte[])localObject1, l.w()));
        Class localClass5 = ((DexClassLoader)localObject4).loadClass(b((byte[])localObject1, l.u()));
        Class localClass6 = ((DexClassLoader)localObject4).loadClass(b((byte[])localObject1, l.i()));
        Class localClass7 = ((DexClassLoader)localObject4).loadClass(b((byte[])localObject1, l.g()));
        Class localClass8 = ((DexClassLoader)localObject4).loadClass(b((byte[])localObject1, l.e()));
        Class localClass9 = ((DexClassLoader)localObject4).loadClass(b((byte[])localObject1, l.q()));
        localObject4 = ((DexClassLoader)localObject4).loadClass(b((byte[])localObject1, l.c()));
        r = paramContext.getMethod(b((byte[])localObject1, l.l()), new Class[0]);
        s = ((Class)localObject2).getMethod(b((byte[])localObject1, l.z()), new Class[0]);
        t = ((Class)localObject3).getMethod(b((byte[])localObject1, l.t()), new Class[0]);
        u = localClass1.getMethod(b((byte[])localObject1, l.p()), new Class[] { Context.class });
        v = localClass2.getMethod(b((byte[])localObject1, l.B()), new Class[] { MotionEvent.class, DisplayMetrics.class });
        w = localClass3.getMethod(b((byte[])localObject1, l.n()), new Class[] { Context.class });
        x = localClass4.getMethod(b((byte[])localObject1, l.x()), new Class[] { Context.class });
        y = localClass5.getMethod(b((byte[])localObject1, l.v()), new Class[] { Context.class });
        z = localClass6.getMethod(b((byte[])localObject1, l.j()), new Class[] { Context.class });
        A = localClass7.getMethod(b((byte[])localObject1, l.h()), new Class[] { Context.class });
        B = localClass8.getMethod(b((byte[])localObject1, l.f()), new Class[] { Context.class });
        C = localClass9.getMethod(b((byte[])localObject1, l.r()), new Class[] { Context.class });
        D = ((Class)localObject4).getMethod(b((byte[])localObject1, l.d()), new Class[] { Context.class });
        return;
      }
      finally
      {
        localObject1 = localFile2.getName();
        localFile2.delete();
        new File(localFile1, ((String)localObject1).replace(".jar", ".dex")).delete();
      }
    }
    catch (IOException paramContext)
    {
      throw new zza(paramContext);
    }
    catch (ClassNotFoundException paramContext)
    {
      throw new zza(paramContext);
    }
    catch (zzaq.zza paramContext)
    {
      throw new zza(paramContext);
    }
    catch (NoSuchMethodException paramContext)
    {
      throw new zza(paramContext);
    }
    catch (NullPointerException paramContext)
    {
      throw new zza(paramContext);
    }
  }
  
  protected boolean a()
  {
    return M;
  }
  
  /* Error */
  protected com.yelp.android.az.b.a b(Context paramContext)
  {
    // Byte code:
    //   0: new 465	com/yelp/android/az/b$a
    //   3: dup
    //   4: invokespecial 466	com/yelp/android/az/b$a:<init>	()V
    //   7: astore 5
    //   9: aload_0
    //   10: aload_1
    //   11: invokespecial 468	com/google/android/gms/internal/zzal:k	(Landroid/content/Context;)V
    //   14: getstatic 60	com/google/android/gms/internal/zzal:J	Ljava/util/Random;
    //   17: invokevirtual 471	java/util/Random:nextInt	()I
    //   20: putstatic 473	com/google/android/gms/internal/zzal:m	I
    //   23: iconst_0
    //   24: getstatic 473	com/google/android/gms/internal/zzal:m	I
    //   27: invokestatic 475	com/google/android/gms/internal/zzal:a	(II)V
    //   30: aload 5
    //   32: invokestatic 476	com/google/android/gms/internal/zzal:d	()Ljava/lang/String;
    //   35: putfield 477	com/yelp/android/az/b$a:a	Ljava/lang/String;
    //   38: iconst_1
    //   39: getstatic 473	com/google/android/gms/internal/zzal:m	I
    //   42: invokestatic 475	com/google/android/gms/internal/zzal:a	(II)V
    //   45: aload 5
    //   47: invokestatic 478	com/google/android/gms/internal/zzal:b	()Ljava/lang/String;
    //   50: putfield 480	com/yelp/android/az/b$a:b	Ljava/lang/String;
    //   53: iconst_2
    //   54: getstatic 473	com/google/android/gms/internal/zzal:m	I
    //   57: invokestatic 475	com/google/android/gms/internal/zzal:a	(II)V
    //   60: invokestatic 189	com/google/android/gms/internal/zzal:c	()Ljava/lang/Long;
    //   63: invokevirtual 195	java/lang/Long:longValue	()J
    //   66: lstore_2
    //   67: aload 5
    //   69: lload_2
    //   70: invokestatic 484	java/lang/Long:valueOf	(J)Ljava/lang/Long;
    //   73: putfield 488	com/yelp/android/az/b$a:Q	Ljava/lang/Long;
    //   76: getstatic 49	com/google/android/gms/internal/zzal:H	J
    //   79: lconst_0
    //   80: lcmp
    //   81: ifeq +27 -> 108
    //   84: aload 5
    //   86: lload_2
    //   87: getstatic 49	com/google/android/gms/internal/zzal:H	J
    //   90: lsub
    //   91: invokestatic 484	java/lang/Long:valueOf	(J)Ljava/lang/Long;
    //   94: putfield 490	com/yelp/android/az/b$a:q	Ljava/lang/Long;
    //   97: aload 5
    //   99: getstatic 49	com/google/android/gms/internal/zzal:H	J
    //   102: invokestatic 484	java/lang/Long:valueOf	(J)Ljava/lang/Long;
    //   105: putfield 492	com/yelp/android/az/b$a:v	Ljava/lang/Long;
    //   108: bipush 25
    //   110: getstatic 473	com/google/android/gms/internal/zzal:m	I
    //   113: invokestatic 475	com/google/android/gms/internal/zzal:a	(II)V
    //   116: aload_1
    //   117: invokestatic 494	com/google/android/gms/internal/zzal:g	(Landroid/content/Context;)Ljava/util/ArrayList;
    //   120: astore 6
    //   122: aload 5
    //   124: aload 6
    //   126: iconst_0
    //   127: invokevirtual 498	java/util/ArrayList:get	(I)Ljava/lang/Object;
    //   130: checkcast 191	java/lang/Long
    //   133: invokevirtual 195	java/lang/Long:longValue	()J
    //   136: invokestatic 484	java/lang/Long:valueOf	(J)Ljava/lang/Long;
    //   139: putfield 500	com/yelp/android/az/b$a:y	Ljava/lang/Long;
    //   142: aload 5
    //   144: aload 6
    //   146: iconst_1
    //   147: invokevirtual 498	java/util/ArrayList:get	(I)Ljava/lang/Object;
    //   150: checkcast 191	java/lang/Long
    //   153: invokevirtual 195	java/lang/Long:longValue	()J
    //   156: invokestatic 484	java/lang/Long:valueOf	(J)Ljava/lang/Long;
    //   159: putfield 502	com/yelp/android/az/b$a:z	Ljava/lang/Long;
    //   162: bipush 31
    //   164: getstatic 473	com/google/android/gms/internal/zzal:m	I
    //   167: invokestatic 475	com/google/android/gms/internal/zzal:a	(II)V
    //   170: aload 5
    //   172: invokestatic 504	com/google/android/gms/internal/zzal:e	()Ljava/lang/Long;
    //   175: putfield 506	com/yelp/android/az/b$a:A	Ljava/lang/Long;
    //   178: bipush 33
    //   180: getstatic 473	com/google/android/gms/internal/zzal:m	I
    //   183: invokestatic 475	com/google/android/gms/internal/zzal:a	(II)V
    //   186: getstatic 72	com/google/android/gms/internal/zzal:o	Z
    //   189: ifeq +155 -> 344
    //   192: getstatic 74	com/google/android/gms/internal/zzal:p	Z
    //   195: istore 4
    //   197: iload 4
    //   199: ifeq +145 -> 344
    //   202: aload 5
    //   204: aload_1
    //   205: aload_0
    //   206: getfield 509	com/google/android/gms/internal/zzal:h	Lcom/google/android/gms/internal/k;
    //   209: invokestatic 511	com/google/android/gms/internal/zzal:b	(Landroid/content/Context;Lcom/google/android/gms/internal/k;)Ljava/lang/String;
    //   212: putfield 513	com/yelp/android/az/b$a:x	Ljava/lang/String;
    //   215: bipush 29
    //   217: getstatic 473	com/google/android/gms/internal/zzal:m	I
    //   220: invokestatic 475	com/google/android/gms/internal/zzal:a	(II)V
    //   223: aload_1
    //   224: invokestatic 515	com/google/android/gms/internal/zzal:h	(Landroid/content/Context;)[I
    //   227: astore 6
    //   229: aload 5
    //   231: aload 6
    //   233: iconst_0
    //   234: iaload
    //   235: i2l
    //   236: invokestatic 484	java/lang/Long:valueOf	(J)Ljava/lang/Long;
    //   239: putfield 517	com/yelp/android/az/b$a:e	Ljava/lang/Long;
    //   242: aload 5
    //   244: aload 6
    //   246: iconst_1
    //   247: iaload
    //   248: i2l
    //   249: invokestatic 484	java/lang/Long:valueOf	(J)Ljava/lang/Long;
    //   252: putfield 519	com/yelp/android/az/b$a:f	Ljava/lang/Long;
    //   255: iconst_5
    //   256: getstatic 473	com/google/android/gms/internal/zzal:m	I
    //   259: invokestatic 475	com/google/android/gms/internal/zzal:a	(II)V
    //   262: aload 5
    //   264: aload_1
    //   265: invokestatic 521	com/google/android/gms/internal/zzal:i	(Landroid/content/Context;)I
    //   268: i2l
    //   269: invokestatic 484	java/lang/Long:valueOf	(J)Ljava/lang/Long;
    //   272: putfield 523	com/yelp/android/az/b$a:l	Ljava/lang/Long;
    //   275: bipush 12
    //   277: getstatic 473	com/google/android/gms/internal/zzal:m	I
    //   280: invokestatic 475	com/google/android/gms/internal/zzal:a	(II)V
    //   283: aload 5
    //   285: aload_1
    //   286: invokestatic 525	com/google/android/gms/internal/zzal:j	(Landroid/content/Context;)I
    //   289: i2l
    //   290: invokestatic 484	java/lang/Long:valueOf	(J)Ljava/lang/Long;
    //   293: putfield 527	com/yelp/android/az/b$a:c	Ljava/lang/Long;
    //   296: iconst_3
    //   297: getstatic 473	com/google/android/gms/internal/zzal:m	I
    //   300: invokestatic 475	com/google/android/gms/internal/zzal:a	(II)V
    //   303: aload 5
    //   305: aload_1
    //   306: invokestatic 529	com/google/android/gms/internal/zzal:e	(Landroid/content/Context;)Ljava/lang/String;
    //   309: putfield 531	com/yelp/android/az/b$a:B	Ljava/lang/String;
    //   312: bipush 34
    //   314: getstatic 473	com/google/android/gms/internal/zzal:m	I
    //   317: invokestatic 475	com/google/android/gms/internal/zzal:a	(II)V
    //   320: aload 5
    //   322: aload_1
    //   323: invokestatic 533	com/google/android/gms/internal/zzal:f	(Landroid/content/Context;)Ljava/lang/Long;
    //   326: putfield 535	com/yelp/android/az/b$a:C	Ljava/lang/Long;
    //   329: bipush 35
    //   331: getstatic 473	com/google/android/gms/internal/zzal:m	I
    //   334: invokestatic 475	com/google/android/gms/internal/zzal:a	(II)V
    //   337: aload_0
    //   338: invokespecial 537	com/google/android/gms/internal/zzal:f	()V
    //   341: aload 5
    //   343: areturn
    //   344: aload 5
    //   346: aload_1
    //   347: aload_0
    //   348: getfield 509	com/google/android/gms/internal/zzal:h	Lcom/google/android/gms/internal/k;
    //   351: invokestatic 539	com/google/android/gms/internal/zzal:a	(Landroid/content/Context;Lcom/google/android/gms/internal/k;)Ljava/lang/String;
    //   354: putfield 541	com/yelp/android/az/b$a:w	Ljava/lang/String;
    //   357: bipush 27
    //   359: getstatic 473	com/google/android/gms/internal/zzal:m	I
    //   362: invokestatic 475	com/google/android/gms/internal/zzal:a	(II)V
    //   365: goto -163 -> 202
    //   368: astore 6
    //   370: goto -168 -> 202
    //   373: astore_1
    //   374: aload 5
    //   376: areturn
    //   377: astore_1
    //   378: goto -41 -> 337
    //   381: astore 6
    //   383: goto -63 -> 320
    //   386: astore 6
    //   388: goto -85 -> 303
    //   391: astore 6
    //   393: goto -110 -> 283
    //   396: astore 6
    //   398: goto -136 -> 262
    //   401: astore 6
    //   403: goto -180 -> 223
    //   406: astore 6
    //   408: goto -222 -> 186
    //   411: astore 6
    //   413: goto -243 -> 170
    //   416: astore 6
    //   418: goto -302 -> 116
    //   421: astore 6
    //   423: goto -363 -> 60
    //   426: astore 6
    //   428: goto -383 -> 45
    // Local variable table:
    //   start	length	slot	name	signature
    //   0	431	0	this	zzal
    //   0	431	1	paramContext	Context
    //   66	21	2	l1	long
    //   195	3	4	bool	boolean
    //   7	368	5	locala	com.yelp.android.az.b.a
    //   120	125	6	localObject	Object
    //   368	1	6	localzza1	zza
    //   381	1	6	localzza2	zza
    //   386	1	6	localzza3	zza
    //   391	1	6	localzza4	zza
    //   396	1	6	localzza5	zza
    //   401	1	6	localzza6	zza
    //   406	1	6	localzza7	zza
    //   411	1	6	localzza8	zza
    //   416	1	6	localzza9	zza
    //   421	1	6	localzza10	zza
    //   426	1	6	localzza11	zza
    // Exception table:
    //   from	to	target	type
    //   186	197	368	com/google/android/gms/internal/zzal$zza
    //   344	365	368	com/google/android/gms/internal/zzal$zza
    //   9	30	373	java/io/IOException
    //   30	45	373	java/io/IOException
    //   45	60	373	java/io/IOException
    //   60	108	373	java/io/IOException
    //   108	116	373	java/io/IOException
    //   116	170	373	java/io/IOException
    //   170	186	373	java/io/IOException
    //   186	197	373	java/io/IOException
    //   202	223	373	java/io/IOException
    //   223	262	373	java/io/IOException
    //   262	283	373	java/io/IOException
    //   283	303	373	java/io/IOException
    //   303	320	373	java/io/IOException
    //   320	337	373	java/io/IOException
    //   337	341	373	java/io/IOException
    //   344	365	373	java/io/IOException
    //   320	337	377	com/google/android/gms/internal/zzal$zza
    //   303	320	381	com/google/android/gms/internal/zzal$zza
    //   283	303	386	com/google/android/gms/internal/zzal$zza
    //   262	283	391	com/google/android/gms/internal/zzal$zza
    //   223	262	396	com/google/android/gms/internal/zzal$zza
    //   202	223	401	com/google/android/gms/internal/zzal$zza
    //   170	186	406	com/google/android/gms/internal/zzal$zza
    //   116	170	411	com/google/android/gms/internal/zzal$zza
    //   60	108	416	com/google/android/gms/internal/zzal$zza
    //   108	116	416	com/google/android/gms/internal/zzal$zza
    //   45	60	421	com/google/android/gms/internal/zzal$zza
    //   30	45	426	com/google/android/gms/internal/zzal$zza
  }
  
  /* Error */
  protected com.yelp.android.az.b.a c(Context paramContext)
  {
    // Byte code:
    //   0: iconst_0
    //   1: istore_2
    //   2: new 465	com/yelp/android/az/b$a
    //   5: dup
    //   6: invokespecial 466	com/yelp/android/az/b$a:<init>	()V
    //   9: astore 4
    //   11: aload_0
    //   12: aload_1
    //   13: invokespecial 468	com/google/android/gms/internal/zzal:k	(Landroid/content/Context;)V
    //   16: getstatic 60	com/google/android/gms/internal/zzal:J	Ljava/util/Random;
    //   19: invokevirtual 471	java/util/Random:nextInt	()I
    //   22: putstatic 473	com/google/android/gms/internal/zzal:m	I
    //   25: aload 4
    //   27: invokestatic 478	com/google/android/gms/internal/zzal:b	()Ljava/lang/String;
    //   30: putfield 480	com/yelp/android/az/b$a:b	Ljava/lang/String;
    //   33: aload 4
    //   35: invokestatic 476	com/google/android/gms/internal/zzal:d	()Ljava/lang/String;
    //   38: putfield 477	com/yelp/android/az/b$a:a	Ljava/lang/String;
    //   41: aload 4
    //   43: invokestatic 189	com/google/android/gms/internal/zzal:c	()Ljava/lang/Long;
    //   46: putfield 488	com/yelp/android/az/b$a:Q	Ljava/lang/Long;
    //   49: iconst_0
    //   50: getstatic 473	com/google/android/gms/internal/zzal:m	I
    //   53: invokestatic 475	com/google/android/gms/internal/zzal:a	(II)V
    //   56: aload_0
    //   57: getfield 544	com/google/android/gms/internal/zzal:a	Landroid/view/MotionEvent;
    //   60: aload_0
    //   61: getfield 547	com/google/android/gms/internal/zzal:g	Landroid/util/DisplayMetrics;
    //   64: invokestatic 549	com/google/android/gms/internal/zzal:a	(Landroid/view/MotionEvent;Landroid/util/DisplayMetrics;)Ljava/util/ArrayList;
    //   67: astore 5
    //   69: aload 4
    //   71: aload 5
    //   73: iconst_0
    //   74: invokevirtual 498	java/util/ArrayList:get	(I)Ljava/lang/Object;
    //   77: checkcast 191	java/lang/Long
    //   80: putfield 551	com/yelp/android/az/b$a:n	Ljava/lang/Long;
    //   83: aload 4
    //   85: aload 5
    //   87: iconst_1
    //   88: invokevirtual 498	java/util/ArrayList:get	(I)Ljava/lang/Object;
    //   91: checkcast 191	java/lang/Long
    //   94: putfield 553	com/yelp/android/az/b$a:o	Ljava/lang/Long;
    //   97: aload 5
    //   99: iconst_2
    //   100: invokevirtual 498	java/util/ArrayList:get	(I)Ljava/lang/Object;
    //   103: checkcast 191	java/lang/Long
    //   106: invokevirtual 195	java/lang/Long:longValue	()J
    //   109: lconst_0
    //   110: lcmp
    //   111: iflt +17 -> 128
    //   114: aload 4
    //   116: aload 5
    //   118: iconst_2
    //   119: invokevirtual 498	java/util/ArrayList:get	(I)Ljava/lang/Object;
    //   122: checkcast 191	java/lang/Long
    //   125: putfield 555	com/yelp/android/az/b$a:p	Ljava/lang/Long;
    //   128: aload 4
    //   130: aload 5
    //   132: iconst_3
    //   133: invokevirtual 498	java/util/ArrayList:get	(I)Ljava/lang/Object;
    //   136: checkcast 191	java/lang/Long
    //   139: putfield 557	com/yelp/android/az/b$a:D	Ljava/lang/Long;
    //   142: aload 4
    //   144: aload 5
    //   146: iconst_4
    //   147: invokevirtual 498	java/util/ArrayList:get	(I)Ljava/lang/Object;
    //   150: checkcast 191	java/lang/Long
    //   153: putfield 559	com/yelp/android/az/b$a:E	Ljava/lang/Long;
    //   156: bipush 14
    //   158: getstatic 473	com/google/android/gms/internal/zzal:m	I
    //   161: invokestatic 475	com/google/android/gms/internal/zzal:a	(II)V
    //   164: aload_0
    //   165: getfield 561	com/google/android/gms/internal/zzal:c	J
    //   168: lconst_0
    //   169: lcmp
    //   170: ifle +15 -> 185
    //   173: aload 4
    //   175: aload_0
    //   176: getfield 561	com/google/android/gms/internal/zzal:c	J
    //   179: invokestatic 484	java/lang/Long:valueOf	(J)Ljava/lang/Long;
    //   182: putfield 563	com/yelp/android/az/b$a:I	Ljava/lang/Long;
    //   185: aload_0
    //   186: getfield 565	com/google/android/gms/internal/zzal:d	J
    //   189: lconst_0
    //   190: lcmp
    //   191: ifle +15 -> 206
    //   194: aload 4
    //   196: aload_0
    //   197: getfield 565	com/google/android/gms/internal/zzal:d	J
    //   200: invokestatic 484	java/lang/Long:valueOf	(J)Ljava/lang/Long;
    //   203: putfield 567	com/yelp/android/az/b$a:H	Ljava/lang/Long;
    //   206: aload_0
    //   207: getfield 569	com/google/android/gms/internal/zzal:e	J
    //   210: lconst_0
    //   211: lcmp
    //   212: ifle +15 -> 227
    //   215: aload 4
    //   217: aload_0
    //   218: getfield 569	com/google/android/gms/internal/zzal:e	J
    //   221: invokestatic 484	java/lang/Long:valueOf	(J)Ljava/lang/Long;
    //   224: putfield 571	com/yelp/android/az/b$a:G	Ljava/lang/Long;
    //   227: aload_0
    //   228: getfield 573	com/google/android/gms/internal/zzal:f	J
    //   231: lconst_0
    //   232: lcmp
    //   233: ifle +15 -> 248
    //   236: aload 4
    //   238: aload_0
    //   239: getfield 573	com/google/android/gms/internal/zzal:f	J
    //   242: invokestatic 484	java/lang/Long:valueOf	(J)Ljava/lang/Long;
    //   245: putfield 575	com/yelp/android/az/b$a:J	Ljava/lang/Long;
    //   248: aload_0
    //   249: getfield 578	com/google/android/gms/internal/zzal:b	Ljava/util/LinkedList;
    //   252: invokevirtual 581	java/util/LinkedList:size	()I
    //   255: iconst_1
    //   256: isub
    //   257: istore_3
    //   258: iload_3
    //   259: ifle +98 -> 357
    //   262: aload 4
    //   264: iload_3
    //   265: anewarray 583	com/yelp/android/az/b$a$a
    //   268: putfield 586	com/yelp/android/az/b$a:K	[Lcom/yelp/android/az/b$a$a;
    //   271: iload_2
    //   272: iload_3
    //   273: if_icmpge +84 -> 357
    //   276: aload_0
    //   277: getfield 578	com/google/android/gms/internal/zzal:b	Ljava/util/LinkedList;
    //   280: iload_2
    //   281: invokevirtual 587	java/util/LinkedList:get	(I)Ljava/lang/Object;
    //   284: checkcast 429	android/view/MotionEvent
    //   287: aload_0
    //   288: getfield 547	com/google/android/gms/internal/zzal:g	Landroid/util/DisplayMetrics;
    //   291: invokestatic 549	com/google/android/gms/internal/zzal:a	(Landroid/view/MotionEvent;Landroid/util/DisplayMetrics;)Ljava/util/ArrayList;
    //   294: astore 5
    //   296: new 583	com/yelp/android/az/b$a$a
    //   299: dup
    //   300: invokespecial 588	com/yelp/android/az/b$a$a:<init>	()V
    //   303: astore 6
    //   305: aload 6
    //   307: aload 5
    //   309: iconst_0
    //   310: invokevirtual 498	java/util/ArrayList:get	(I)Ljava/lang/Object;
    //   313: checkcast 191	java/lang/Long
    //   316: putfield 590	com/yelp/android/az/b$a$a:a	Ljava/lang/Long;
    //   319: aload 6
    //   321: aload 5
    //   323: iconst_1
    //   324: invokevirtual 498	java/util/ArrayList:get	(I)Ljava/lang/Object;
    //   327: checkcast 191	java/lang/Long
    //   330: putfield 592	com/yelp/android/az/b$a$a:b	Ljava/lang/Long;
    //   333: aload 4
    //   335: getfield 586	com/yelp/android/az/b$a:K	[Lcom/yelp/android/az/b$a$a;
    //   338: iload_2
    //   339: aload 6
    //   341: aastore
    //   342: iload_2
    //   343: iconst_1
    //   344: iadd
    //   345: istore_2
    //   346: goto -75 -> 271
    //   349: astore 5
    //   351: aload 4
    //   353: aconst_null
    //   354: putfield 586	com/yelp/android/az/b$a:K	[Lcom/yelp/android/az/b$a$a;
    //   357: aload 4
    //   359: aload_1
    //   360: invokestatic 529	com/google/android/gms/internal/zzal:e	(Landroid/content/Context;)Ljava/lang/String;
    //   363: putfield 531	com/yelp/android/az/b$a:B	Ljava/lang/String;
    //   366: aload 4
    //   368: aload_1
    //   369: invokestatic 533	com/google/android/gms/internal/zzal:f	(Landroid/content/Context;)Ljava/lang/Long;
    //   372: putfield 535	com/yelp/android/az/b$a:C	Ljava/lang/Long;
    //   375: aload_0
    //   376: invokespecial 537	com/google/android/gms/internal/zzal:f	()V
    //   379: aload 4
    //   381: areturn
    //   382: astore_1
    //   383: aload 4
    //   385: areturn
    //   386: astore_1
    //   387: goto -12 -> 375
    //   390: astore 5
    //   392: goto -26 -> 366
    //   395: astore 5
    //   397: goto -233 -> 164
    //   400: astore 5
    //   402: goto -353 -> 49
    //   405: astore 5
    //   407: goto -366 -> 41
    //   410: astore 5
    //   412: goto -379 -> 33
    // Local variable table:
    //   start	length	slot	name	signature
    //   0	415	0	this	zzal
    //   0	415	1	paramContext	Context
    //   1	345	2	i	int
    //   257	17	3	i1	int
    //   9	375	4	locala	com.yelp.android.az.b.a
    //   67	255	5	localArrayList	ArrayList
    //   349	1	5	localzza1	zza
    //   390	1	5	localzza2	zza
    //   395	1	5	localzza3	zza
    //   400	1	5	localzza4	zza
    //   405	1	5	localzza5	zza
    //   410	1	5	localzza6	zza
    //   303	37	6	locala1	com.yelp.android.az.b.a.a
    // Exception table:
    //   from	to	target	type
    //   248	258	349	com/google/android/gms/internal/zzal$zza
    //   262	271	349	com/google/android/gms/internal/zzal$zza
    //   276	342	349	com/google/android/gms/internal/zzal$zza
    //   11	25	382	java/io/IOException
    //   25	33	382	java/io/IOException
    //   33	41	382	java/io/IOException
    //   41	49	382	java/io/IOException
    //   49	56	382	java/io/IOException
    //   56	128	382	java/io/IOException
    //   128	164	382	java/io/IOException
    //   164	185	382	java/io/IOException
    //   185	206	382	java/io/IOException
    //   206	227	382	java/io/IOException
    //   227	248	382	java/io/IOException
    //   248	258	382	java/io/IOException
    //   262	271	382	java/io/IOException
    //   276	342	382	java/io/IOException
    //   351	357	382	java/io/IOException
    //   357	366	382	java/io/IOException
    //   366	375	382	java/io/IOException
    //   375	379	382	java/io/IOException
    //   366	375	386	com/google/android/gms/internal/zzal$zza
    //   357	366	390	com/google/android/gms/internal/zzal$zza
    //   56	128	395	com/google/android/gms/internal/zzal$zza
    //   128	164	395	com/google/android/gms/internal/zzal$zza
    //   41	49	400	com/google/android/gms/internal/zzal$zza
    //   33	41	405	com/google/android/gms/internal/zzal$zza
    //   25	33	410	com/google/android/gms/internal/zzal$zza
  }
  
  static class zza
    extends Exception
  {
    public zza() {}
    
    public zza(Throwable paramThrowable)
    {
      super();
    }
  }
}

/* Location:
 * Qualified Name:     com.google.android.gms.internal.zzal
 * Java Class Version: 6 (50.0)
 * JD-Core Version:    0.7.1
 */